package com.a.a.a;

import com.a.a.l;
import com.a.a.p;
import com.a.a.q;
import com.a.a.s;
import com.a.a.t;
import java.io.IOException;
import java.io.InputStream;
import java.util.Comparator;
import java.util.Map;
import java.util.TreeMap;
import org.apache.http.Header;
import org.apache.http.HttpEntity;

public final class a
  implements com.a.a.f
{
  protected static final boolean a = t.b;
  private static int d = 3000;
  private static int e = 4096;
  protected final f b;
  protected final b c;
  
  public a(f paramf)
  {
    this(paramf, localb);
  }
  
  private a(f paramf, b paramb)
  {
    b = paramf;
    c = paramb;
  }
  
  private static Map a(Header[] paramArrayOfHeader)
  {
    TreeMap localTreeMap = new java/util/TreeMap;
    Comparator localComparator = String.CASE_INSENSITIVE_ORDER;
    localTreeMap.<init>(localComparator);
    int i = 0;
    localComparator = null;
    for (;;)
    {
      int j = paramArrayOfHeader.length;
      if (i >= j) {
        break;
      }
      String str1 = paramArrayOfHeader[i].getName();
      String str2 = paramArrayOfHeader[i].getValue();
      localTreeMap.put(str1, str2);
      i += 1;
    }
    return localTreeMap;
  }
  
  private static void a(String paramString, l paraml, s params)
  {
    int i = 2;
    int j = 1;
    Object localObject1 = j;
    int k = paraml.f();
    try
    {
      ((p)localObject1).a(params);
      Object[] arrayOfObject1 = new Object[i];
      arrayOfObject1[0] = paramString;
      localObject2 = Integer.valueOf(k);
      arrayOfObject1[j] = localObject2;
      localObject1 = String.format("%s-retry [timeout=%s]", arrayOfObject1);
      paraml.a((String)localObject1);
      return;
    }
    catch (s locals)
    {
      Object[] arrayOfObject2 = new Object[i];
      arrayOfObject2[0] = paramString;
      Object localObject2 = Integer.valueOf(k);
      arrayOfObject2[j] = localObject2;
      localObject2 = String.format("%s-timeout-giveup [timeout=%s]", arrayOfObject2);
      paraml.a((String)localObject2);
      throw locals;
    }
  }
  
  private byte[] a(HttpEntity paramHttpEntity)
  {
    k localk = new com/a/a/a/k;
    Object localObject1 = c;
    long l = paramHttpEntity.getContentLength();
    int i = (int)l;
    localk.<init>((b)localObject1, i);
    i = 0;
    byte[] arrayOfByte2 = null;
    try
    {
      localObject1 = paramHttpEntity.getContent();
      if (localObject1 == null)
      {
        localObject1 = new com/a/a/q;
        ((q)localObject1).<init>();
        throw ((Throwable)localObject1);
      }
    }
    finally {}
    try
    {
      paramHttpEntity.consumeContent();
      c.a(arrayOfByte2);
      localk.close();
      throw ((Throwable)localObject2);
      b localb = c;
      int j = 1024;
      arrayOfByte2 = localb.a(j);
      for (;;)
      {
        int k = ((InputStream)localObject2).read(arrayOfByte2);
        j = -1;
        if (k == j) {
          break;
        }
        j = 0;
        arrayOfObject = null;
        localk.write(arrayOfByte2, 0, k);
      }
      byte[] arrayOfByte1 = localk.toByteArray();
      try
      {
        paramHttpEntity.consumeContent();
        c.a(arrayOfByte2);
        localk.close();
        return arrayOfByte1;
      }
      catch (IOException localIOException1)
      {
        for (;;)
        {
          String str1 = "Error occured when calling consumingContent";
          arrayOfObject = new Object[0];
          t.a(str1, arrayOfObject);
        }
      }
    }
    catch (IOException localIOException2)
    {
      for (;;)
      {
        String str2 = "Error occured when calling consumingContent";
        Object[] arrayOfObject = new Object[0];
        t.a(str2, arrayOfObject);
      }
    }
  }
  
  /* Error */
  public final com.a.a.i a(l paraml)
  {
    // Byte code:
    //   0: invokestatic 162	android/os/SystemClock:elapsedRealtime	()J
    //   3: lstore_2
    //   4: iconst_0
    //   5: istore 4
    //   7: aconst_null
    //   8: astore 5
    //   10: invokestatic 168	java/util/Collections:emptyMap	()Ljava/util/Map;
    //   13: astore 6
    //   15: new 170	java/util/HashMap
    //   18: astore 7
    //   20: aload 7
    //   22: invokespecial 171	java/util/HashMap:<init>	()V
    //   25: aload_1
    //   26: getfield 175	com/a/a/l:k	Lcom/a/a/b$a;
    //   29: astore 8
    //   31: aload 8
    //   33: ifnull +102 -> 135
    //   36: aload 8
    //   38: getfield 180	com/a/a/b$a:b	Ljava/lang/String;
    //   41: astore 9
    //   43: aload 9
    //   45: ifnull +26 -> 71
    //   48: ldc -74
    //   50: astore 9
    //   52: aload 8
    //   54: getfield 180	com/a/a/b$a:b	Ljava/lang/String;
    //   57: astore 10
    //   59: aload 7
    //   61: aload 9
    //   63: aload 10
    //   65: invokeinterface 69 3 0
    //   70: pop
    //   71: aload 8
    //   73: getfield 185	com/a/a/b$a:d	J
    //   76: lstore 11
    //   78: lconst_0
    //   79: lstore 13
    //   81: lload 11
    //   83: lload 13
    //   85: lcmp
    //   86: istore 15
    //   88: iload 15
    //   90: ifle +45 -> 135
    //   93: new 187	java/util/Date
    //   96: astore 9
    //   98: aload 8
    //   100: getfield 185	com/a/a/b$a:d	J
    //   103: lstore 11
    //   105: aload 9
    //   107: lload 11
    //   109: invokespecial 190	java/util/Date:<init>	(J)V
    //   112: ldc -64
    //   114: astore 8
    //   116: aload 9
    //   118: invokestatic 198	org/apache/http/impl/cookie/DateUtils:formatDate	(Ljava/util/Date;)Ljava/lang/String;
    //   121: astore 9
    //   123: aload 7
    //   125: aload 8
    //   127: aload 9
    //   129: invokeinterface 69 3 0
    //   134: pop
    //   135: aload_0
    //   136: getfield 41	com/a/a/a/a:b	Lcom/a/a/a/f;
    //   139: astore 8
    //   141: aload 8
    //   143: aload_1
    //   144: aload 7
    //   146: invokeinterface 203 3 0
    //   151: astore 16
    //   153: aload 16
    //   155: invokeinterface 209 1 0
    //   160: astore 5
    //   162: aload 5
    //   164: invokeinterface 214 1 0
    //   169: istore 17
    //   171: aload 16
    //   173: invokeinterface 218 1 0
    //   178: astore 7
    //   180: aload 7
    //   182: invokestatic 221	com/a/a/a/a:a	([Lorg/apache/http/Header;)Ljava/util/Map;
    //   185: astore 6
    //   187: sipush 304
    //   190: istore 18
    //   192: iload 17
    //   194: iload 18
    //   196: if_icmpne +133 -> 329
    //   199: aload_1
    //   200: getfield 175	com/a/a/l:k	Lcom/a/a/b$a;
    //   203: astore 7
    //   205: aload 7
    //   207: ifnonnull +46 -> 253
    //   210: new 224	com/a/a/i
    //   213: astore 5
    //   215: sipush 304
    //   218: istore 17
    //   220: iconst_0
    //   221: istore 15
    //   223: aconst_null
    //   224: astore 9
    //   226: iconst_1
    //   227: istore 19
    //   229: invokestatic 162	android/os/SystemClock:elapsedRealtime	()J
    //   232: lload_2
    //   233: lsub
    //   234: lstore 11
    //   236: aload 5
    //   238: iload 17
    //   240: aconst_null
    //   241: aload 6
    //   243: iload 19
    //   245: lload 11
    //   247: invokespecial 227	com/a/a/i:<init>	(I[BLjava/util/Map;ZJ)V
    //   250: aload 5
    //   252: areturn
    //   253: aload 7
    //   255: getfield 231	com/a/a/b$a:g	Ljava/util/Map;
    //   258: astore 5
    //   260: aload 5
    //   262: aload 6
    //   264: invokeinterface 235 2 0
    //   269: new 224	com/a/a/i
    //   272: astore 10
    //   274: sipush 304
    //   277: istore 20
    //   279: aload 7
    //   281: getfield 238	com/a/a/b$a:a	[B
    //   284: astore 21
    //   286: aload 7
    //   288: getfield 231	com/a/a/b$a:g	Ljava/util/Map;
    //   291: astore 22
    //   293: iconst_1
    //   294: istore 23
    //   296: invokestatic 162	android/os/SystemClock:elapsedRealtime	()J
    //   299: lstore 24
    //   301: lload 24
    //   303: lload_2
    //   304: lsub
    //   305: lstore 26
    //   307: aload 10
    //   309: iload 20
    //   311: aload 21
    //   313: aload 22
    //   315: iload 23
    //   317: lload 26
    //   319: invokespecial 227	com/a/a/i:<init>	(I[BLjava/util/Map;ZJ)V
    //   322: aload 10
    //   324: astore 5
    //   326: goto -76 -> 250
    //   329: aload 16
    //   331: invokeinterface 242 1 0
    //   336: astore 7
    //   338: aload 7
    //   340: ifnull +254 -> 594
    //   343: aload 16
    //   345: invokeinterface 242 1 0
    //   350: astore 7
    //   352: aload_0
    //   353: aload 7
    //   355: invokespecial 245	com/a/a/a/a:a	(Lorg/apache/http/HttpEntity;)[B
    //   358: astore 9
    //   360: invokestatic 162	android/os/SystemClock:elapsedRealtime	()J
    //   363: lload_2
    //   364: lsub
    //   365: lstore 11
    //   367: getstatic 21	com/a/a/a/a:a	Z
    //   370: istore 18
    //   372: iload 18
    //   374: ifne +21 -> 395
    //   377: getstatic 24	com/a/a/a/a:d	I
    //   380: i2l
    //   381: lstore 13
    //   383: lload 11
    //   385: lload 13
    //   387: lcmp
    //   388: istore 18
    //   390: iload 18
    //   392: ifle +137 -> 529
    //   395: ldc -9
    //   397: astore 10
    //   399: iconst_5
    //   400: istore 18
    //   402: iload 18
    //   404: anewarray 4	java/lang/Object
    //   407: astore 22
    //   409: iconst_0
    //   410: istore 18
    //   412: aconst_null
    //   413: astore 7
    //   415: aload 22
    //   417: iconst_0
    //   418: aload_1
    //   419: aastore
    //   420: iconst_1
    //   421: istore 18
    //   423: lload 11
    //   425: invokestatic 253	java/lang/Long:valueOf	(J)Ljava/lang/Long;
    //   428: astore 28
    //   430: aload 22
    //   432: iload 18
    //   434: aload 28
    //   436: aastore
    //   437: iconst_2
    //   438: istore 20
    //   440: aload 9
    //   442: ifnull +166 -> 608
    //   445: aload 9
    //   447: arraylength
    //   448: istore 18
    //   450: iload 18
    //   452: invokestatic 94	java/lang/Integer:valueOf	(I)Ljava/lang/Integer;
    //   455: astore 7
    //   457: aload 22
    //   459: iload 20
    //   461: aload 7
    //   463: aastore
    //   464: iconst_3
    //   465: istore 18
    //   467: aload 5
    //   469: invokeinterface 214 1 0
    //   474: istore 4
    //   476: iload 4
    //   478: invokestatic 94	java/lang/Integer:valueOf	(I)Ljava/lang/Integer;
    //   481: astore 5
    //   483: aload 22
    //   485: iload 18
    //   487: aload 5
    //   489: aastore
    //   490: iconst_4
    //   491: istore 18
    //   493: aload_1
    //   494: getfield 77	com/a/a/l:j	Lcom/a/a/p;
    //   497: astore 5
    //   499: aload 5
    //   501: invokeinterface 257 1 0
    //   506: istore 4
    //   508: iload 4
    //   510: invokestatic 94	java/lang/Integer:valueOf	(I)Ljava/lang/Integer;
    //   513: astore 5
    //   515: aload 22
    //   517: iload 18
    //   519: aload 5
    //   521: aastore
    //   522: aload 10
    //   524: aload 22
    //   526: invokestatic 259	com/a/a/t:b	(Ljava/lang/String;[Ljava/lang/Object;)V
    //   529: sipush 200
    //   532: istore 18
    //   534: iload 17
    //   536: iload 18
    //   538: if_icmplt +15 -> 553
    //   541: sipush 299
    //   544: istore 18
    //   546: iload 17
    //   548: iload 18
    //   550: if_icmple +66 -> 616
    //   553: new 157	java/io/IOException
    //   556: astore 7
    //   558: aload 7
    //   560: invokespecial 262	java/io/IOException:<init>	()V
    //   563: aload 7
    //   565: athrow
    //   566: astore 7
    //   568: ldc_w 264
    //   571: astore 7
    //   573: new 266	com/a/a/r
    //   576: astore 5
    //   578: aload 5
    //   580: invokespecial 267	com/a/a/r:<init>	()V
    //   583: aload 7
    //   585: aload_1
    //   586: aload 5
    //   588: invokestatic 270	com/a/a/a/a:a	(Ljava/lang/String;Lcom/a/a/l;Lcom/a/a/s;)V
    //   591: goto -587 -> 4
    //   594: iconst_0
    //   595: istore 18
    //   597: aconst_null
    //   598: astore 7
    //   600: iconst_0
    //   601: newarray <illegal type>
    //   603: astore 9
    //   605: goto -245 -> 360
    //   608: ldc_w 272
    //   611: astore 7
    //   613: goto -156 -> 457
    //   616: new 224	com/a/a/i
    //   619: astore 5
    //   621: iconst_0
    //   622: istore 19
    //   624: aconst_null
    //   625: astore 10
    //   627: invokestatic 162	android/os/SystemClock:elapsedRealtime	()J
    //   630: lload_2
    //   631: lsub
    //   632: lstore 11
    //   634: aload 5
    //   636: iload 17
    //   638: aload 9
    //   640: aload 6
    //   642: iconst_0
    //   643: lload 11
    //   645: invokespecial 227	com/a/a/i:<init>	(I[BLjava/util/Map;ZJ)V
    //   648: goto -398 -> 250
    //   651: astore 7
    //   653: ldc_w 274
    //   656: astore 7
    //   658: new 266	com/a/a/r
    //   661: astore 5
    //   663: aload 5
    //   665: invokespecial 267	com/a/a/r:<init>	()V
    //   668: aload 7
    //   670: aload_1
    //   671: aload 5
    //   673: invokestatic 270	com/a/a/a/a:a	(Ljava/lang/String;Lcom/a/a/l;Lcom/a/a/s;)V
    //   676: goto -672 -> 4
    //   679: astore 5
    //   681: new 276	java/lang/RuntimeException
    //   684: astore 8
    //   686: ldc_w 278
    //   689: astore 9
    //   691: aload_1
    //   692: getfield 279	com/a/a/l:b	Ljava/lang/String;
    //   695: invokestatic 282	java/lang/String:valueOf	(Ljava/lang/Object;)Ljava/lang/String;
    //   698: astore 7
    //   700: aload 7
    //   702: invokevirtual 285	java/lang/String:length	()I
    //   705: istore 29
    //   707: iload 29
    //   709: ifeq +24 -> 733
    //   712: aload 9
    //   714: aload 7
    //   716: invokevirtual 289	java/lang/String:concat	(Ljava/lang/String;)Ljava/lang/String;
    //   719: astore 7
    //   721: aload 8
    //   723: aload 7
    //   725: aload 5
    //   727: invokespecial 292	java/lang/RuntimeException:<init>	(Ljava/lang/String;Ljava/lang/Throwable;)V
    //   730: aload 8
    //   732: athrow
    //   733: new 47	java/lang/String
    //   736: astore 7
    //   738: aload 7
    //   740: aload 9
    //   742: invokespecial 294	java/lang/String:<init>	(Ljava/lang/String;)V
    //   745: goto -24 -> 721
    //   748: astore 7
    //   750: iconst_0
    //   751: istore 15
    //   753: aconst_null
    //   754: astore 9
    //   756: aload 5
    //   758: ifnull +160 -> 918
    //   761: aload 5
    //   763: invokeinterface 209 1 0
    //   768: invokeinterface 214 1 0
    //   773: istore 17
    //   775: ldc_w 296
    //   778: astore 7
    //   780: iconst_2
    //   781: istore 4
    //   783: iload 4
    //   785: anewarray 4	java/lang/Object
    //   788: astore 5
    //   790: aconst_null
    //   791: astore 10
    //   793: iload 17
    //   795: invokestatic 94	java/lang/Integer:valueOf	(I)Ljava/lang/Integer;
    //   798: astore 28
    //   800: aload 5
    //   802: iconst_0
    //   803: aload 28
    //   805: aastore
    //   806: iconst_1
    //   807: istore 19
    //   809: aload_1
    //   810: getfield 279	com/a/a/l:b	Ljava/lang/String;
    //   813: astore 28
    //   815: aload 5
    //   817: iload 19
    //   819: aload 28
    //   821: aastore
    //   822: aload 7
    //   824: aload 5
    //   826: invokestatic 298	com/a/a/t:c	(Ljava/lang/String;[Ljava/lang/Object;)V
    //   829: aload 9
    //   831: ifnull +117 -> 948
    //   834: new 224	com/a/a/i
    //   837: astore 5
    //   839: iconst_0
    //   840: istore 19
    //   842: aconst_null
    //   843: astore 10
    //   845: invokestatic 162	android/os/SystemClock:elapsedRealtime	()J
    //   848: lload_2
    //   849: lsub
    //   850: lstore 11
    //   852: aload 5
    //   854: iload 17
    //   856: aload 9
    //   858: aload 6
    //   860: iconst_0
    //   861: lload 11
    //   863: invokespecial 227	com/a/a/i:<init>	(I[BLjava/util/Map;ZJ)V
    //   866: sipush 401
    //   869: istore 18
    //   871: iload 17
    //   873: iload 18
    //   875: if_icmpeq +15 -> 890
    //   878: sipush 403
    //   881: istore 18
    //   883: iload 17
    //   885: iload 18
    //   887: if_icmpne +46 -> 933
    //   890: ldc_w 302
    //   893: astore 7
    //   895: new 304	com/a/a/a
    //   898: astore 8
    //   900: aload 8
    //   902: aload 5
    //   904: invokespecial 307	com/a/a/a:<init>	(Lcom/a/a/i;)V
    //   907: aload 7
    //   909: aload_1
    //   910: aload 8
    //   912: invokestatic 270	com/a/a/a/a:a	(Ljava/lang/String;Lcom/a/a/l;Lcom/a/a/s;)V
    //   915: goto -911 -> 4
    //   918: new 309	com/a/a/j
    //   921: astore 5
    //   923: aload 5
    //   925: aload 7
    //   927: invokespecial 312	com/a/a/j:<init>	(Ljava/lang/Throwable;)V
    //   930: aload 5
    //   932: athrow
    //   933: new 122	com/a/a/q
    //   936: astore 7
    //   938: aload 7
    //   940: aload 5
    //   942: invokespecial 313	com/a/a/q:<init>	(Lcom/a/a/i;)V
    //   945: aload 7
    //   947: athrow
    //   948: new 315	com/a/a/h
    //   951: astore 7
    //   953: aload 7
    //   955: iconst_0
    //   956: invokespecial 318	com/a/a/h:<init>	(B)V
    //   959: aload 7
    //   961: athrow
    //   962: astore 7
    //   964: iconst_0
    //   965: istore 15
    //   967: aconst_null
    //   968: astore 9
    //   970: aload 16
    //   972: astore 5
    //   974: goto -218 -> 756
    //   977: astore 7
    //   979: aload 16
    //   981: astore 5
    //   983: goto -227 -> 756
    // Local variable table:
    //   start	length	slot	name	signature
    //   0	986	0	this	a
    //   0	986	1	paraml	l
    //   3	846	2	l1	long
    //   5	779	4	i	int
    //   8	664	5	localObject1	Object
    //   679	83	5	localMalformedURLException	java.net.MalformedURLException
    //   788	194	5	localObject2	Object
    //   13	846	6	localMap	Map
    //   18	546	7	localObject3	Object
    //   566	1	7	localSocketTimeoutException	java.net.SocketTimeoutException
    //   571	41	7	str1	String
    //   651	1	7	localConnectTimeoutException	org.apache.http.conn.ConnectTimeoutException
    //   656	83	7	str2	String
    //   748	1	7	localIOException1	IOException
    //   778	182	7	localObject4	Object
    //   962	1	7	localIOException2	IOException
    //   977	1	7	localIOException3	IOException
    //   29	882	8	localObject5	Object
    //   41	928	9	localObject6	Object
    //   57	787	10	localObject7	Object
    //   76	786	11	l2	long
    //   79	307	13	l3	long
    //   86	880	15	bool1	boolean
    //   151	829	16	localHttpResponse	org.apache.http.HttpResponse
    //   169	719	17	j	int
    //   190	7	18	k	int
    //   370	21	18	bool2	boolean
    //   400	488	18	m	int
    //   227	614	19	bool3	boolean
    //   277	183	20	n	int
    //   284	28	21	arrayOfByte	byte[]
    //   291	234	22	localObject8	Object
    //   294	22	23	bool4	boolean
    //   299	3	24	l4	long
    //   305	13	26	l5	long
    //   428	392	28	localObject9	Object
    //   705	3	29	i1	int
    // Exception table:
    //   from	to	target	type
    //   15	18	566	java/net/SocketTimeoutException
    //   20	25	566	java/net/SocketTimeoutException
    //   25	29	566	java/net/SocketTimeoutException
    //   36	41	566	java/net/SocketTimeoutException
    //   52	57	566	java/net/SocketTimeoutException
    //   63	71	566	java/net/SocketTimeoutException
    //   71	76	566	java/net/SocketTimeoutException
    //   93	96	566	java/net/SocketTimeoutException
    //   98	103	566	java/net/SocketTimeoutException
    //   107	112	566	java/net/SocketTimeoutException
    //   116	121	566	java/net/SocketTimeoutException
    //   127	135	566	java/net/SocketTimeoutException
    //   135	139	566	java/net/SocketTimeoutException
    //   144	151	566	java/net/SocketTimeoutException
    //   153	160	566	java/net/SocketTimeoutException
    //   162	169	566	java/net/SocketTimeoutException
    //   171	178	566	java/net/SocketTimeoutException
    //   180	185	566	java/net/SocketTimeoutException
    //   199	203	566	java/net/SocketTimeoutException
    //   210	213	566	java/net/SocketTimeoutException
    //   229	232	566	java/net/SocketTimeoutException
    //   245	250	566	java/net/SocketTimeoutException
    //   253	258	566	java/net/SocketTimeoutException
    //   262	269	566	java/net/SocketTimeoutException
    //   269	272	566	java/net/SocketTimeoutException
    //   279	284	566	java/net/SocketTimeoutException
    //   286	291	566	java/net/SocketTimeoutException
    //   296	299	566	java/net/SocketTimeoutException
    //   317	322	566	java/net/SocketTimeoutException
    //   329	336	566	java/net/SocketTimeoutException
    //   343	350	566	java/net/SocketTimeoutException
    //   353	358	566	java/net/SocketTimeoutException
    //   360	363	566	java/net/SocketTimeoutException
    //   367	370	566	java/net/SocketTimeoutException
    //   377	380	566	java/net/SocketTimeoutException
    //   402	407	566	java/net/SocketTimeoutException
    //   418	420	566	java/net/SocketTimeoutException
    //   423	428	566	java/net/SocketTimeoutException
    //   434	437	566	java/net/SocketTimeoutException
    //   445	448	566	java/net/SocketTimeoutException
    //   450	455	566	java/net/SocketTimeoutException
    //   461	464	566	java/net/SocketTimeoutException
    //   467	474	566	java/net/SocketTimeoutException
    //   476	481	566	java/net/SocketTimeoutException
    //   487	490	566	java/net/SocketTimeoutException
    //   493	497	566	java/net/SocketTimeoutException
    //   499	506	566	java/net/SocketTimeoutException
    //   508	513	566	java/net/SocketTimeoutException
    //   519	522	566	java/net/SocketTimeoutException
    //   524	529	566	java/net/SocketTimeoutException
    //   553	556	566	java/net/SocketTimeoutException
    //   558	563	566	java/net/SocketTimeoutException
    //   563	566	566	java/net/SocketTimeoutException
    //   600	603	566	java/net/SocketTimeoutException
    //   616	619	566	java/net/SocketTimeoutException
    //   627	630	566	java/net/SocketTimeoutException
    //   643	648	566	java/net/SocketTimeoutException
    //   15	18	651	org/apache/http/conn/ConnectTimeoutException
    //   20	25	651	org/apache/http/conn/ConnectTimeoutException
    //   25	29	651	org/apache/http/conn/ConnectTimeoutException
    //   36	41	651	org/apache/http/conn/ConnectTimeoutException
    //   52	57	651	org/apache/http/conn/ConnectTimeoutException
    //   63	71	651	org/apache/http/conn/ConnectTimeoutException
    //   71	76	651	org/apache/http/conn/ConnectTimeoutException
    //   93	96	651	org/apache/http/conn/ConnectTimeoutException
    //   98	103	651	org/apache/http/conn/ConnectTimeoutException
    //   107	112	651	org/apache/http/conn/ConnectTimeoutException
    //   116	121	651	org/apache/http/conn/ConnectTimeoutException
    //   127	135	651	org/apache/http/conn/ConnectTimeoutException
    //   135	139	651	org/apache/http/conn/ConnectTimeoutException
    //   144	151	651	org/apache/http/conn/ConnectTimeoutException
    //   153	160	651	org/apache/http/conn/ConnectTimeoutException
    //   162	169	651	org/apache/http/conn/ConnectTimeoutException
    //   171	178	651	org/apache/http/conn/ConnectTimeoutException
    //   180	185	651	org/apache/http/conn/ConnectTimeoutException
    //   199	203	651	org/apache/http/conn/ConnectTimeoutException
    //   210	213	651	org/apache/http/conn/ConnectTimeoutException
    //   229	232	651	org/apache/http/conn/ConnectTimeoutException
    //   245	250	651	org/apache/http/conn/ConnectTimeoutException
    //   253	258	651	org/apache/http/conn/ConnectTimeoutException
    //   262	269	651	org/apache/http/conn/ConnectTimeoutException
    //   269	272	651	org/apache/http/conn/ConnectTimeoutException
    //   279	284	651	org/apache/http/conn/ConnectTimeoutException
    //   286	291	651	org/apache/http/conn/ConnectTimeoutException
    //   296	299	651	org/apache/http/conn/ConnectTimeoutException
    //   317	322	651	org/apache/http/conn/ConnectTimeoutException
    //   329	336	651	org/apache/http/conn/ConnectTimeoutException
    //   343	350	651	org/apache/http/conn/ConnectTimeoutException
    //   353	358	651	org/apache/http/conn/ConnectTimeoutException
    //   360	363	651	org/apache/http/conn/ConnectTimeoutException
    //   367	370	651	org/apache/http/conn/ConnectTimeoutException
    //   377	380	651	org/apache/http/conn/ConnectTimeoutException
    //   402	407	651	org/apache/http/conn/ConnectTimeoutException
    //   418	420	651	org/apache/http/conn/ConnectTimeoutException
    //   423	428	651	org/apache/http/conn/ConnectTimeoutException
    //   434	437	651	org/apache/http/conn/ConnectTimeoutException
    //   445	448	651	org/apache/http/conn/ConnectTimeoutException
    //   450	455	651	org/apache/http/conn/ConnectTimeoutException
    //   461	464	651	org/apache/http/conn/ConnectTimeoutException
    //   467	474	651	org/apache/http/conn/ConnectTimeoutException
    //   476	481	651	org/apache/http/conn/ConnectTimeoutException
    //   487	490	651	org/apache/http/conn/ConnectTimeoutException
    //   493	497	651	org/apache/http/conn/ConnectTimeoutException
    //   499	506	651	org/apache/http/conn/ConnectTimeoutException
    //   508	513	651	org/apache/http/conn/ConnectTimeoutException
    //   519	522	651	org/apache/http/conn/ConnectTimeoutException
    //   524	529	651	org/apache/http/conn/ConnectTimeoutException
    //   553	556	651	org/apache/http/conn/ConnectTimeoutException
    //   558	563	651	org/apache/http/conn/ConnectTimeoutException
    //   563	566	651	org/apache/http/conn/ConnectTimeoutException
    //   600	603	651	org/apache/http/conn/ConnectTimeoutException
    //   616	619	651	org/apache/http/conn/ConnectTimeoutException
    //   627	630	651	org/apache/http/conn/ConnectTimeoutException
    //   643	648	651	org/apache/http/conn/ConnectTimeoutException
    //   15	18	679	java/net/MalformedURLException
    //   20	25	679	java/net/MalformedURLException
    //   25	29	679	java/net/MalformedURLException
    //   36	41	679	java/net/MalformedURLException
    //   52	57	679	java/net/MalformedURLException
    //   63	71	679	java/net/MalformedURLException
    //   71	76	679	java/net/MalformedURLException
    //   93	96	679	java/net/MalformedURLException
    //   98	103	679	java/net/MalformedURLException
    //   107	112	679	java/net/MalformedURLException
    //   116	121	679	java/net/MalformedURLException
    //   127	135	679	java/net/MalformedURLException
    //   135	139	679	java/net/MalformedURLException
    //   144	151	679	java/net/MalformedURLException
    //   153	160	679	java/net/MalformedURLException
    //   162	169	679	java/net/MalformedURLException
    //   171	178	679	java/net/MalformedURLException
    //   180	185	679	java/net/MalformedURLException
    //   199	203	679	java/net/MalformedURLException
    //   210	213	679	java/net/MalformedURLException
    //   229	232	679	java/net/MalformedURLException
    //   245	250	679	java/net/MalformedURLException
    //   253	258	679	java/net/MalformedURLException
    //   262	269	679	java/net/MalformedURLException
    //   269	272	679	java/net/MalformedURLException
    //   279	284	679	java/net/MalformedURLException
    //   286	291	679	java/net/MalformedURLException
    //   296	299	679	java/net/MalformedURLException
    //   317	322	679	java/net/MalformedURLException
    //   329	336	679	java/net/MalformedURLException
    //   343	350	679	java/net/MalformedURLException
    //   353	358	679	java/net/MalformedURLException
    //   360	363	679	java/net/MalformedURLException
    //   367	370	679	java/net/MalformedURLException
    //   377	380	679	java/net/MalformedURLException
    //   402	407	679	java/net/MalformedURLException
    //   418	420	679	java/net/MalformedURLException
    //   423	428	679	java/net/MalformedURLException
    //   434	437	679	java/net/MalformedURLException
    //   445	448	679	java/net/MalformedURLException
    //   450	455	679	java/net/MalformedURLException
    //   461	464	679	java/net/MalformedURLException
    //   467	474	679	java/net/MalformedURLException
    //   476	481	679	java/net/MalformedURLException
    //   487	490	679	java/net/MalformedURLException
    //   493	497	679	java/net/MalformedURLException
    //   499	506	679	java/net/MalformedURLException
    //   508	513	679	java/net/MalformedURLException
    //   519	522	679	java/net/MalformedURLException
    //   524	529	679	java/net/MalformedURLException
    //   553	556	679	java/net/MalformedURLException
    //   558	563	679	java/net/MalformedURLException
    //   563	566	679	java/net/MalformedURLException
    //   600	603	679	java/net/MalformedURLException
    //   616	619	679	java/net/MalformedURLException
    //   627	630	679	java/net/MalformedURLException
    //   643	648	679	java/net/MalformedURLException
    //   15	18	748	java/io/IOException
    //   20	25	748	java/io/IOException
    //   25	29	748	java/io/IOException
    //   36	41	748	java/io/IOException
    //   52	57	748	java/io/IOException
    //   63	71	748	java/io/IOException
    //   71	76	748	java/io/IOException
    //   93	96	748	java/io/IOException
    //   98	103	748	java/io/IOException
    //   107	112	748	java/io/IOException
    //   116	121	748	java/io/IOException
    //   127	135	748	java/io/IOException
    //   135	139	748	java/io/IOException
    //   144	151	748	java/io/IOException
    //   153	160	962	java/io/IOException
    //   162	169	962	java/io/IOException
    //   171	178	962	java/io/IOException
    //   180	185	962	java/io/IOException
    //   199	203	962	java/io/IOException
    //   210	213	962	java/io/IOException
    //   229	232	962	java/io/IOException
    //   245	250	962	java/io/IOException
    //   253	258	962	java/io/IOException
    //   262	269	962	java/io/IOException
    //   269	272	962	java/io/IOException
    //   279	284	962	java/io/IOException
    //   286	291	962	java/io/IOException
    //   296	299	962	java/io/IOException
    //   317	322	962	java/io/IOException
    //   329	336	962	java/io/IOException
    //   343	350	962	java/io/IOException
    //   353	358	962	java/io/IOException
    //   600	603	962	java/io/IOException
    //   360	363	977	java/io/IOException
    //   367	370	977	java/io/IOException
    //   377	380	977	java/io/IOException
    //   402	407	977	java/io/IOException
    //   418	420	977	java/io/IOException
    //   423	428	977	java/io/IOException
    //   434	437	977	java/io/IOException
    //   445	448	977	java/io/IOException
    //   450	455	977	java/io/IOException
    //   461	464	977	java/io/IOException
    //   467	474	977	java/io/IOException
    //   476	481	977	java/io/IOException
    //   487	490	977	java/io/IOException
    //   493	497	977	java/io/IOException
    //   499	506	977	java/io/IOException
    //   508	513	977	java/io/IOException
    //   519	522	977	java/io/IOException
    //   524	529	977	java/io/IOException
    //   553	556	977	java/io/IOException
    //   558	563	977	java/io/IOException
    //   563	566	977	java/io/IOException
    //   616	619	977	java/io/IOException
    //   627	630	977	java/io/IOException
    //   643	648	977	java/io/IOException
  }
}


/* Location:              com/a/a/a/a.class
 * Java compiler version: 5 (49.0)
 * JD-Core Version:       0.7.1
 */