package com.google.android.gms.b;

import android.os.Binder;
import android.os.IBinder;
import android.os.IInterface;
import android.os.Parcel;
import android.os.Parcelable.Creator;
import com.google.android.gms.auth.api.signin.GoogleSignInAccount;
import com.google.android.gms.common.a;
import com.google.android.gms.common.api.Status;

public abstract interface ej
  extends IInterface
{
  public abstract void a(eq parameq);
  
  public abstract void a(a parama, ee paramee);
  
  public abstract void a(Status paramStatus);
  
  public abstract void a(Status paramStatus, GoogleSignInAccount paramGoogleSignInAccount);
  
  public abstract void b(Status paramStatus);
  
  public static abstract class a
    extends Binder
    implements ej
  {
    public a()
    {
      attachInterface(this, "com.google.android.gms.signin.internal.ISignInCallbacks");
    }
    
    public static ej a(IBinder paramIBinder)
    {
      if (paramIBinder == null) {
        return null;
      }
      IInterface localIInterface = paramIBinder.queryLocalInterface("com.google.android.gms.signin.internal.ISignInCallbacks");
      if ((localIInterface != null) && ((localIInterface instanceof ej))) {
        return (ej)localIInterface;
      }
      return new a(paramIBinder);
    }
    
    public IBinder asBinder()
    {
      return this;
    }
    
    public boolean onTransact(int paramInt1, Parcel paramParcel1, Parcel paramParcel2, int paramInt2)
    {
      Object localObject;
      switch (paramInt1)
      {
      default: 
        return super.onTransact(paramInt1, paramParcel1, paramParcel2, paramInt2);
      case 1598968902: 
        paramParcel2.writeString("com.google.android.gms.signin.internal.ISignInCallbacks");
        return true;
      case 3: 
        paramParcel1.enforceInterface("com.google.android.gms.signin.internal.ISignInCallbacks");
        if (paramParcel1.readInt() != 0)
        {
          localObject = (a)a.CREATOR.createFromParcel(paramParcel1);
          if (paramParcel1.readInt() == 0) {
            break label144;
          }
        }
        for (paramParcel1 = (ee)ee.CREATOR.createFromParcel(paramParcel1);; paramParcel1 = null)
        {
          a((a)localObject, paramParcel1);
          paramParcel2.writeNoException();
          return true;
          localObject = null;
          break;
        }
      case 4: 
        paramParcel1.enforceInterface("com.google.android.gms.signin.internal.ISignInCallbacks");
        if (paramParcel1.readInt() != 0) {}
        for (paramParcel1 = (Status)Status.CREATOR.createFromParcel(paramParcel1);; paramParcel1 = null)
        {
          a(paramParcel1);
          paramParcel2.writeNoException();
          return true;
        }
      case 6: 
        paramParcel1.enforceInterface("com.google.android.gms.signin.internal.ISignInCallbacks");
        if (paramParcel1.readInt() != 0) {}
        for (paramParcel1 = (Status)Status.CREATOR.createFromParcel(paramParcel1);; paramParcel1 = null)
        {
          b(paramParcel1);
          paramParcel2.writeNoException();
          return true;
        }
      case 7: 
        label144:
        paramParcel1.enforceInterface("com.google.android.gms.signin.internal.ISignInCallbacks");
        if (paramParcel1.readInt() != 0)
        {
          localObject = (Status)Status.CREATOR.createFromParcel(paramParcel1);
          if (paramParcel1.readInt() == 0) {
            break label299;
          }
        }
        label299:
        for (paramParcel1 = (GoogleSignInAccount)GoogleSignInAccount.CREATOR.createFromParcel(paramParcel1);; paramParcel1 = null)
        {
          a((Status)localObject, paramParcel1);
          paramParcel2.writeNoException();
          return true;
          localObject = null;
          break;
        }
      }
      paramParcel1.enforceInterface("com.google.android.gms.signin.internal.ISignInCallbacks");
      if (paramParcel1.readInt() != 0) {}
      for (paramParcel1 = (eq)eq.CREATOR.createFromParcel(paramParcel1);; paramParcel1 = null)
      {
        a(paramParcel1);
        paramParcel2.writeNoException();
        return true;
      }
    }
    
    private static final class a
      implements ej
    {
      private IBinder a;
      
      a(IBinder paramIBinder)
      {
        a = paramIBinder;
      }
      
      /* Error */
      public final void a(eq parameq)
      {
        // Byte code:
        //   0: invokestatic 25	android/os/Parcel:obtain	()Landroid/os/Parcel;
        //   3: astore_2
        //   4: invokestatic 25	android/os/Parcel:obtain	()Landroid/os/Parcel;
        //   7: astore_3
        //   8: aload_2
        //   9: ldc 27
        //   11: invokevirtual 31	android/os/Parcel:writeInterfaceToken	(Ljava/lang/String;)V
        //   14: aload_1
        //   15: ifnull +42 -> 57
        //   18: aload_2
        //   19: iconst_1
        //   20: invokevirtual 35	android/os/Parcel:writeInt	(I)V
        //   23: aload_1
        //   24: aload_2
        //   25: iconst_0
        //   26: invokevirtual 41	com/google/android/gms/b/eq:writeToParcel	(Landroid/os/Parcel;I)V
        //   29: aload_0
        //   30: getfield 17	com/google/android/gms/b/ej$a$a:a	Landroid/os/IBinder;
        //   33: bipush 8
        //   35: aload_2
        //   36: aload_3
        //   37: iconst_0
        //   38: invokeinterface 47 5 0
        //   43: pop
        //   44: aload_3
        //   45: invokevirtual 50	android/os/Parcel:readException	()V
        //   48: aload_3
        //   49: invokevirtual 53	android/os/Parcel:recycle	()V
        //   52: aload_2
        //   53: invokevirtual 53	android/os/Parcel:recycle	()V
        //   56: return
        //   57: aload_2
        //   58: iconst_0
        //   59: invokevirtual 35	android/os/Parcel:writeInt	(I)V
        //   62: goto -33 -> 29
        //   65: astore_1
        //   66: aload_3
        //   67: invokevirtual 53	android/os/Parcel:recycle	()V
        //   70: aload_2
        //   71: invokevirtual 53	android/os/Parcel:recycle	()V
        //   74: aload_1
        //   75: athrow
        // Local variable table:
        //   start	length	slot	name	signature
        //   0	76	0	this	a
        //   0	76	1	parameq	eq
        //   3	68	2	localParcel1	Parcel
        //   7	60	3	localParcel2	Parcel
        // Exception table:
        //   from	to	target	type
        //   8	14	65	finally
        //   18	29	65	finally
        //   29	48	65	finally
        //   57	62	65	finally
      }
      
      public final void a(a parama, ee paramee)
      {
        Parcel localParcel1 = Parcel.obtain();
        Parcel localParcel2 = Parcel.obtain();
        for (;;)
        {
          try
          {
            localParcel1.writeInterfaceToken("com.google.android.gms.signin.internal.ISignInCallbacks");
            if (parama != null)
            {
              localParcel1.writeInt(1);
              parama.writeToParcel(localParcel1, 0);
              if (paramee != null)
              {
                localParcel1.writeInt(1);
                paramee.writeToParcel(localParcel1, 0);
                a.transact(3, localParcel1, localParcel2, 0);
                localParcel2.readException();
              }
            }
            else
            {
              localParcel1.writeInt(0);
              continue;
            }
            localParcel1.writeInt(0);
          }
          finally
          {
            localParcel2.recycle();
            localParcel1.recycle();
          }
        }
      }
      
      /* Error */
      public final void a(Status paramStatus)
      {
        // Byte code:
        //   0: invokestatic 25	android/os/Parcel:obtain	()Landroid/os/Parcel;
        //   3: astore_2
        //   4: invokestatic 25	android/os/Parcel:obtain	()Landroid/os/Parcel;
        //   7: astore_3
        //   8: aload_2
        //   9: ldc 27
        //   11: invokevirtual 31	android/os/Parcel:writeInterfaceToken	(Ljava/lang/String;)V
        //   14: aload_1
        //   15: ifnull +41 -> 56
        //   18: aload_2
        //   19: iconst_1
        //   20: invokevirtual 35	android/os/Parcel:writeInt	(I)V
        //   23: aload_1
        //   24: aload_2
        //   25: iconst_0
        //   26: invokevirtual 64	com/google/android/gms/common/api/Status:writeToParcel	(Landroid/os/Parcel;I)V
        //   29: aload_0
        //   30: getfield 17	com/google/android/gms/b/ej$a$a:a	Landroid/os/IBinder;
        //   33: iconst_4
        //   34: aload_2
        //   35: aload_3
        //   36: iconst_0
        //   37: invokeinterface 47 5 0
        //   42: pop
        //   43: aload_3
        //   44: invokevirtual 50	android/os/Parcel:readException	()V
        //   47: aload_3
        //   48: invokevirtual 53	android/os/Parcel:recycle	()V
        //   51: aload_2
        //   52: invokevirtual 53	android/os/Parcel:recycle	()V
        //   55: return
        //   56: aload_2
        //   57: iconst_0
        //   58: invokevirtual 35	android/os/Parcel:writeInt	(I)V
        //   61: goto -32 -> 29
        //   64: astore_1
        //   65: aload_3
        //   66: invokevirtual 53	android/os/Parcel:recycle	()V
        //   69: aload_2
        //   70: invokevirtual 53	android/os/Parcel:recycle	()V
        //   73: aload_1
        //   74: athrow
        // Local variable table:
        //   start	length	slot	name	signature
        //   0	75	0	this	a
        //   0	75	1	paramStatus	Status
        //   3	67	2	localParcel1	Parcel
        //   7	59	3	localParcel2	Parcel
        // Exception table:
        //   from	to	target	type
        //   8	14	64	finally
        //   18	29	64	finally
        //   29	47	64	finally
        //   56	61	64	finally
      }
      
      public final void a(Status paramStatus, GoogleSignInAccount paramGoogleSignInAccount)
      {
        Parcel localParcel1 = Parcel.obtain();
        Parcel localParcel2 = Parcel.obtain();
        for (;;)
        {
          try
          {
            localParcel1.writeInterfaceToken("com.google.android.gms.signin.internal.ISignInCallbacks");
            if (paramStatus != null)
            {
              localParcel1.writeInt(1);
              paramStatus.writeToParcel(localParcel1, 0);
              if (paramGoogleSignInAccount != null)
              {
                localParcel1.writeInt(1);
                paramGoogleSignInAccount.writeToParcel(localParcel1, 0);
                a.transact(7, localParcel1, localParcel2, 0);
                localParcel2.readException();
              }
            }
            else
            {
              localParcel1.writeInt(0);
              continue;
            }
            localParcel1.writeInt(0);
          }
          finally
          {
            localParcel2.recycle();
            localParcel1.recycle();
          }
        }
      }
      
      public final IBinder asBinder()
      {
        return a;
      }
      
      /* Error */
      public final void b(Status paramStatus)
      {
        // Byte code:
        //   0: invokestatic 25	android/os/Parcel:obtain	()Landroid/os/Parcel;
        //   3: astore_2
        //   4: invokestatic 25	android/os/Parcel:obtain	()Landroid/os/Parcel;
        //   7: astore_3
        //   8: aload_2
        //   9: ldc 27
        //   11: invokevirtual 31	android/os/Parcel:writeInterfaceToken	(Ljava/lang/String;)V
        //   14: aload_1
        //   15: ifnull +42 -> 57
        //   18: aload_2
        //   19: iconst_1
        //   20: invokevirtual 35	android/os/Parcel:writeInt	(I)V
        //   23: aload_1
        //   24: aload_2
        //   25: iconst_0
        //   26: invokevirtual 64	com/google/android/gms/common/api/Status:writeToParcel	(Landroid/os/Parcel;I)V
        //   29: aload_0
        //   30: getfield 17	com/google/android/gms/b/ej$a$a:a	Landroid/os/IBinder;
        //   33: bipush 6
        //   35: aload_2
        //   36: aload_3
        //   37: iconst_0
        //   38: invokeinterface 47 5 0
        //   43: pop
        //   44: aload_3
        //   45: invokevirtual 50	android/os/Parcel:readException	()V
        //   48: aload_3
        //   49: invokevirtual 53	android/os/Parcel:recycle	()V
        //   52: aload_2
        //   53: invokevirtual 53	android/os/Parcel:recycle	()V
        //   56: return
        //   57: aload_2
        //   58: iconst_0
        //   59: invokevirtual 35	android/os/Parcel:writeInt	(I)V
        //   62: goto -33 -> 29
        //   65: astore_1
        //   66: aload_3
        //   67: invokevirtual 53	android/os/Parcel:recycle	()V
        //   70: aload_2
        //   71: invokevirtual 53	android/os/Parcel:recycle	()V
        //   74: aload_1
        //   75: athrow
        // Local variable table:
        //   start	length	slot	name	signature
        //   0	76	0	this	a
        //   0	76	1	paramStatus	Status
        //   3	68	2	localParcel1	Parcel
        //   7	60	3	localParcel2	Parcel
        // Exception table:
        //   from	to	target	type
        //   8	14	65	finally
        //   18	29	65	finally
        //   29	48	65	finally
        //   57	62	65	finally
      }
    }
  }
}


/* Location:              com/google/android/gms/b/ej.class
 * Java compiler version: 6 (50.0)
 * JD-Core Version:       0.7.1
 */