package com.google.android.gms.b;

import android.os.Binder;
import android.os.IBinder;
import android.os.IInterface;
import android.os.Parcel;

public abstract interface lt
  extends IInterface
{
  public abstract void a(lp paramlp);
  
  public static abstract class a
    extends Binder
    implements lt
  {
    public boolean onTransact(int paramInt1, Parcel paramParcel1, Parcel paramParcel2, int paramInt2)
    {
      switch (paramInt1)
      {
      default: 
        return super.onTransact(paramInt1, paramParcel1, paramParcel2, paramInt2);
      case 1598968902: 
        paramParcel2.writeString("com.google.android.gms.ads.internal.formats.client.IOnCustomTemplateAdLoadedListener");
        return true;
      }
      paramParcel1.enforceInterface("com.google.android.gms.ads.internal.formats.client.IOnCustomTemplateAdLoadedListener");
      a(lp.a.a(paramParcel1.readStrongBinder()));
      paramParcel2.writeNoException();
      return true;
    }
    
    private static final class a
      implements lt
    {
      private IBinder a;
      
      a(IBinder paramIBinder)
      {
        a = paramIBinder;
      }
      
      /* Error */
      public final void a(lp paramlp)
      {
        // Byte code:
        //   0: invokestatic 25	android/os/Parcel:obtain	()Landroid/os/Parcel;
        //   3: astore_2
        //   4: invokestatic 25	android/os/Parcel:obtain	()Landroid/os/Parcel;
        //   7: astore_3
        //   8: aload_2
        //   9: ldc 27
        //   11: invokevirtual 31	android/os/Parcel:writeInterfaceToken	(Ljava/lang/String;)V
        //   14: aload_1
        //   15: ifnull +42 -> 57
        //   18: aload_1
        //   19: invokeinterface 37 1 0
        //   24: astore_1
        //   25: aload_2
        //   26: aload_1
        //   27: invokevirtual 40	android/os/Parcel:writeStrongBinder	(Landroid/os/IBinder;)V
        //   30: aload_0
        //   31: getfield 17	com/google/android/gms/b/lt$a$a:a	Landroid/os/IBinder;
        //   34: iconst_1
        //   35: aload_2
        //   36: aload_3
        //   37: iconst_0
        //   38: invokeinterface 46 5 0
        //   43: pop
        //   44: aload_3
        //   45: invokevirtual 49	android/os/Parcel:readException	()V
        //   48: aload_3
        //   49: invokevirtual 52	android/os/Parcel:recycle	()V
        //   52: aload_2
        //   53: invokevirtual 52	android/os/Parcel:recycle	()V
        //   56: return
        //   57: aconst_null
        //   58: astore_1
        //   59: goto -34 -> 25
        //   62: astore_1
        //   63: aload_3
        //   64: invokevirtual 52	android/os/Parcel:recycle	()V
        //   67: aload_2
        //   68: invokevirtual 52	android/os/Parcel:recycle	()V
        //   71: aload_1
        //   72: athrow
        // Local variable table:
        //   start	length	slot	name	signature
        //   0	73	0	this	a
        //   0	73	1	paramlp	lp
        //   3	65	2	localParcel1	Parcel
        //   7	57	3	localParcel2	Parcel
        // Exception table:
        //   from	to	target	type
        //   8	14	62	finally
        //   18	25	62	finally
        //   25	48	62	finally
      }
      
      public final IBinder asBinder()
      {
        return a;
      }
    }
  }
}


/* Location:              com/google/android/gms/b/lt.class
 * Java compiler version: 6 (50.0)
 * JD-Core Version:       0.7.1
 */