package com.google.android.gms.b;

import android.os.Binder;
import android.os.Bundle;
import android.os.IBinder;
import android.os.IInterface;
import android.os.Parcel;
import android.os.Parcelable.Creator;
import com.google.android.gms.a.a;
import com.google.android.gms.a.a.a;
import java.util.List;

public abstract interface od
  extends IInterface
{
  public abstract a a();
  
  public abstract void a(a parama);
  
  public abstract void a(a parama, ih paramih, String paramString, oe paramoe);
  
  public abstract void a(a parama, ih paramih, String paramString1, sq paramsq, String paramString2);
  
  public abstract void a(a parama, ih paramih, String paramString1, String paramString2, oe paramoe);
  
  public abstract void a(a parama, ih paramih, String paramString1, String paramString2, oe paramoe, le paramle, List<String> paramList);
  
  public abstract void a(a parama, il paramil, ih paramih, String paramString, oe paramoe);
  
  public abstract void a(a parama, il paramil, ih paramih, String paramString1, String paramString2, oe paramoe);
  
  public abstract void a(a parama, sq paramsq, List<String> paramList);
  
  public abstract void a(ih paramih, String paramString);
  
  public abstract void a(ih paramih, String paramString1, String paramString2);
  
  public abstract void b();
  
  public abstract void c();
  
  public abstract void d();
  
  public abstract void e();
  
  public abstract void f();
  
  public abstract boolean g();
  
  public abstract og h();
  
  public abstract oh i();
  
  public abstract Bundle j();
  
  public abstract Bundle k();
  
  public abstract Bundle l();
  
  public abstract boolean m();
  
  public static abstract class a
    extends Binder
    implements od
  {
    public a()
    {
      attachInterface(this, "com.google.android.gms.ads.internal.mediation.client.IMediationAdapter");
    }
    
    public static od a(IBinder paramIBinder)
    {
      if (paramIBinder == null) {
        return null;
      }
      IInterface localIInterface = paramIBinder.queryLocalInterface("com.google.android.gms.ads.internal.mediation.client.IMediationAdapter");
      if ((localIInterface != null) && ((localIInterface instanceof od))) {
        return (od)localIInterface;
      }
      return new a(paramIBinder);
    }
    
    public IBinder asBinder()
    {
      return this;
    }
    
    public boolean onTransact(int paramInt1, Parcel paramParcel1, Parcel paramParcel2, int paramInt2)
    {
      int j = 0;
      int i = 0;
      Object localObject2 = null;
      a locala = null;
      String str1 = null;
      Object localObject1 = null;
      label328:
      label566:
      boolean bool;
      switch (paramInt1)
      {
      default: 
        return super.onTransact(paramInt1, paramParcel1, paramParcel2, paramInt2);
      case 1598968902: 
        paramParcel2.writeString("com.google.android.gms.ads.internal.mediation.client.IMediationAdapter");
        return true;
      case 1: 
        paramParcel1.enforceInterface("com.google.android.gms.ads.internal.mediation.client.IMediationAdapter");
        locala = a.a.a(paramParcel1.readStrongBinder());
        if (paramParcel1.readInt() != 0)
        {
          localObject1 = (il)il.CREATOR.createFromParcel(paramParcel1);
          if (paramParcel1.readInt() == 0) {
            break label328;
          }
        }
        for (localObject2 = (ih)ih.CREATOR.createFromParcel(paramParcel1);; localObject2 = null)
        {
          a(locala, (il)localObject1, (ih)localObject2, paramParcel1.readString(), oe.a.a(paramParcel1.readStrongBinder()));
          paramParcel2.writeNoException();
          return true;
          localObject1 = null;
          break;
        }
      case 2: 
        paramParcel1.enforceInterface("com.google.android.gms.ads.internal.mediation.client.IMediationAdapter");
        localObject2 = a();
        paramParcel2.writeNoException();
        paramParcel1 = (Parcel)localObject1;
        if (localObject2 != null) {
          paramParcel1 = ((a)localObject2).asBinder();
        }
        paramParcel2.writeStrongBinder(paramParcel1);
        return true;
      case 3: 
        paramParcel1.enforceInterface("com.google.android.gms.ads.internal.mediation.client.IMediationAdapter");
        localObject2 = a.a.a(paramParcel1.readStrongBinder());
        if (paramParcel1.readInt() != 0) {}
        for (localObject1 = (ih)ih.CREATOR.createFromParcel(paramParcel1);; localObject1 = null)
        {
          a((a)localObject2, (ih)localObject1, paramParcel1.readString(), oe.a.a(paramParcel1.readStrongBinder()));
          paramParcel2.writeNoException();
          return true;
        }
      case 4: 
        paramParcel1.enforceInterface("com.google.android.gms.ads.internal.mediation.client.IMediationAdapter");
        b();
        paramParcel2.writeNoException();
        return true;
      case 5: 
        paramParcel1.enforceInterface("com.google.android.gms.ads.internal.mediation.client.IMediationAdapter");
        c();
        paramParcel2.writeNoException();
        return true;
      case 6: 
        paramParcel1.enforceInterface("com.google.android.gms.ads.internal.mediation.client.IMediationAdapter");
        locala = a.a.a(paramParcel1.readStrongBinder());
        if (paramParcel1.readInt() != 0)
        {
          localObject1 = (il)il.CREATOR.createFromParcel(paramParcel1);
          if (paramParcel1.readInt() == 0) {
            break label566;
          }
        }
        for (localObject2 = (ih)ih.CREATOR.createFromParcel(paramParcel1);; localObject2 = null)
        {
          a(locala, (il)localObject1, (ih)localObject2, paramParcel1.readString(), paramParcel1.readString(), oe.a.a(paramParcel1.readStrongBinder()));
          paramParcel2.writeNoException();
          return true;
          localObject1 = null;
          break;
        }
      case 7: 
        paramParcel1.enforceInterface("com.google.android.gms.ads.internal.mediation.client.IMediationAdapter");
        localObject2 = a.a.a(paramParcel1.readStrongBinder());
        if (paramParcel1.readInt() != 0) {}
        for (localObject1 = (ih)ih.CREATOR.createFromParcel(paramParcel1);; localObject1 = null)
        {
          a((a)localObject2, (ih)localObject1, paramParcel1.readString(), paramParcel1.readString(), oe.a.a(paramParcel1.readStrongBinder()));
          paramParcel2.writeNoException();
          return true;
        }
      case 8: 
        paramParcel1.enforceInterface("com.google.android.gms.ads.internal.mediation.client.IMediationAdapter");
        d();
        paramParcel2.writeNoException();
        return true;
      case 9: 
        paramParcel1.enforceInterface("com.google.android.gms.ads.internal.mediation.client.IMediationAdapter");
        e();
        paramParcel2.writeNoException();
        return true;
      case 10: 
        paramParcel1.enforceInterface("com.google.android.gms.ads.internal.mediation.client.IMediationAdapter");
        localObject2 = a.a.a(paramParcel1.readStrongBinder());
        if (paramParcel1.readInt() != 0) {}
        for (localObject1 = (ih)ih.CREATOR.createFromParcel(paramParcel1);; localObject1 = null)
        {
          a((a)localObject2, (ih)localObject1, paramParcel1.readString(), sq.a.a(paramParcel1.readStrongBinder()), paramParcel1.readString());
          paramParcel2.writeNoException();
          return true;
        }
      case 11: 
        paramParcel1.enforceInterface("com.google.android.gms.ads.internal.mediation.client.IMediationAdapter");
        if (paramParcel1.readInt() != 0) {}
        for (localObject1 = (ih)ih.CREATOR.createFromParcel(paramParcel1);; localObject1 = null)
        {
          a((ih)localObject1, paramParcel1.readString());
          paramParcel2.writeNoException();
          return true;
        }
      case 12: 
        paramParcel1.enforceInterface("com.google.android.gms.ads.internal.mediation.client.IMediationAdapter");
        f();
        paramParcel2.writeNoException();
        return true;
      case 13: 
        paramParcel1.enforceInterface("com.google.android.gms.ads.internal.mediation.client.IMediationAdapter");
        bool = g();
        paramParcel2.writeNoException();
        paramInt1 = i;
        if (bool) {
          paramInt1 = 1;
        }
        paramParcel2.writeInt(paramInt1);
        return true;
      case 14: 
        paramParcel1.enforceInterface("com.google.android.gms.ads.internal.mediation.client.IMediationAdapter");
        locala = a.a.a(paramParcel1.readStrongBinder());
        if (paramParcel1.readInt() != 0) {}
        for (localObject1 = (ih)ih.CREATOR.createFromParcel(paramParcel1);; localObject1 = null)
        {
          str1 = paramParcel1.readString();
          String str2 = paramParcel1.readString();
          oe localoe = oe.a.a(paramParcel1.readStrongBinder());
          if (paramParcel1.readInt() != 0) {
            localObject2 = (le)le.CREATOR.createFromParcel(paramParcel1);
          }
          a(locala, (ih)localObject1, str1, str2, localoe, (le)localObject2, paramParcel1.createStringArrayList());
          paramParcel2.writeNoException();
          return true;
        }
      case 15: 
        paramParcel1.enforceInterface("com.google.android.gms.ads.internal.mediation.client.IMediationAdapter");
        localObject1 = h();
        paramParcel2.writeNoException();
        paramParcel1 = locala;
        if (localObject1 != null) {
          paramParcel1 = ((og)localObject1).asBinder();
        }
        paramParcel2.writeStrongBinder(paramParcel1);
        return true;
      case 16: 
        paramParcel1.enforceInterface("com.google.android.gms.ads.internal.mediation.client.IMediationAdapter");
        localObject1 = i();
        paramParcel2.writeNoException();
        paramParcel1 = str1;
        if (localObject1 != null) {
          paramParcel1 = ((oh)localObject1).asBinder();
        }
        paramParcel2.writeStrongBinder(paramParcel1);
        return true;
      case 17: 
        paramParcel1.enforceInterface("com.google.android.gms.ads.internal.mediation.client.IMediationAdapter");
        paramParcel1 = j();
        paramParcel2.writeNoException();
        if (paramParcel1 != null)
        {
          paramParcel2.writeInt(1);
          paramParcel1.writeToParcel(paramParcel2, 1);
          return true;
        }
        paramParcel2.writeInt(0);
        return true;
      case 18: 
        paramParcel1.enforceInterface("com.google.android.gms.ads.internal.mediation.client.IMediationAdapter");
        paramParcel1 = k();
        paramParcel2.writeNoException();
        if (paramParcel1 != null)
        {
          paramParcel2.writeInt(1);
          paramParcel1.writeToParcel(paramParcel2, 1);
          return true;
        }
        paramParcel2.writeInt(0);
        return true;
      case 19: 
        paramParcel1.enforceInterface("com.google.android.gms.ads.internal.mediation.client.IMediationAdapter");
        paramParcel1 = l();
        paramParcel2.writeNoException();
        if (paramParcel1 != null)
        {
          paramParcel2.writeInt(1);
          paramParcel1.writeToParcel(paramParcel2, 1);
          return true;
        }
        paramParcel2.writeInt(0);
        return true;
      case 20: 
        paramParcel1.enforceInterface("com.google.android.gms.ads.internal.mediation.client.IMediationAdapter");
        if (paramParcel1.readInt() != 0) {}
        for (localObject1 = (ih)ih.CREATOR.createFromParcel(paramParcel1);; localObject1 = null)
        {
          a((ih)localObject1, paramParcel1.readString(), paramParcel1.readString());
          paramParcel2.writeNoException();
          return true;
        }
      case 21: 
        paramParcel1.enforceInterface("com.google.android.gms.ads.internal.mediation.client.IMediationAdapter");
        a(a.a.a(paramParcel1.readStrongBinder()));
        paramParcel2.writeNoException();
        return true;
      case 22: 
        paramParcel1.enforceInterface("com.google.android.gms.ads.internal.mediation.client.IMediationAdapter");
        bool = m();
        paramParcel2.writeNoException();
        paramInt1 = j;
        if (bool) {
          paramInt1 = 1;
        }
        paramParcel2.writeInt(paramInt1);
        return true;
      }
      paramParcel1.enforceInterface("com.google.android.gms.ads.internal.mediation.client.IMediationAdapter");
      a(a.a.a(paramParcel1.readStrongBinder()), sq.a.a(paramParcel1.readStrongBinder()), paramParcel1.createStringArrayList());
      paramParcel2.writeNoException();
      return true;
    }
    
    private static final class a
      implements od
    {
      private IBinder a;
      
      a(IBinder paramIBinder)
      {
        a = paramIBinder;
      }
      
      public final a a()
      {
        Parcel localParcel1 = Parcel.obtain();
        Parcel localParcel2 = Parcel.obtain();
        try
        {
          localParcel1.writeInterfaceToken("com.google.android.gms.ads.internal.mediation.client.IMediationAdapter");
          a.transact(2, localParcel1, localParcel2, 0);
          localParcel2.readException();
          a locala = a.a.a(localParcel2.readStrongBinder());
          return locala;
        }
        finally
        {
          localParcel2.recycle();
          localParcel1.recycle();
        }
      }
      
      /* Error */
      public final void a(a parama)
      {
        // Byte code:
        //   0: invokestatic 25	android/os/Parcel:obtain	()Landroid/os/Parcel;
        //   3: astore_2
        //   4: invokestatic 25	android/os/Parcel:obtain	()Landroid/os/Parcel;
        //   7: astore_3
        //   8: aload_2
        //   9: ldc 27
        //   11: invokevirtual 31	android/os/Parcel:writeInterfaceToken	(Ljava/lang/String;)V
        //   14: aload_1
        //   15: ifnull +43 -> 58
        //   18: aload_1
        //   19: invokeinterface 58 1 0
        //   24: astore_1
        //   25: aload_2
        //   26: aload_1
        //   27: invokevirtual 61	android/os/Parcel:writeStrongBinder	(Landroid/os/IBinder;)V
        //   30: aload_0
        //   31: getfield 17	com/google/android/gms/b/od$a$a:a	Landroid/os/IBinder;
        //   34: bipush 21
        //   36: aload_2
        //   37: aload_3
        //   38: iconst_0
        //   39: invokeinterface 37 5 0
        //   44: pop
        //   45: aload_3
        //   46: invokevirtual 40	android/os/Parcel:readException	()V
        //   49: aload_3
        //   50: invokevirtual 52	android/os/Parcel:recycle	()V
        //   53: aload_2
        //   54: invokevirtual 52	android/os/Parcel:recycle	()V
        //   57: return
        //   58: aconst_null
        //   59: astore_1
        //   60: goto -35 -> 25
        //   63: astore_1
        //   64: aload_3
        //   65: invokevirtual 52	android/os/Parcel:recycle	()V
        //   68: aload_2
        //   69: invokevirtual 52	android/os/Parcel:recycle	()V
        //   72: aload_1
        //   73: athrow
        // Local variable table:
        //   start	length	slot	name	signature
        //   0	74	0	this	a
        //   0	74	1	parama	a
        //   3	66	2	localParcel1	Parcel
        //   7	58	3	localParcel2	Parcel
        // Exception table:
        //   from	to	target	type
        //   8	14	63	finally
        //   18	25	63	finally
        //   25	49	63	finally
      }
      
      /* Error */
      public final void a(a parama, ih paramih, String paramString, oe paramoe)
      {
        // Byte code:
        //   0: aconst_null
        //   1: astore 5
        //   3: invokestatic 25	android/os/Parcel:obtain	()Landroid/os/Parcel;
        //   6: astore 6
        //   8: invokestatic 25	android/os/Parcel:obtain	()Landroid/os/Parcel;
        //   11: astore 7
        //   13: aload 6
        //   15: ldc 27
        //   17: invokevirtual 31	android/os/Parcel:writeInterfaceToken	(Ljava/lang/String;)V
        //   20: aload_1
        //   21: ifnull +93 -> 114
        //   24: aload_1
        //   25: invokeinterface 58 1 0
        //   30: astore_1
        //   31: aload 6
        //   33: aload_1
        //   34: invokevirtual 61	android/os/Parcel:writeStrongBinder	(Landroid/os/IBinder;)V
        //   37: aload_2
        //   38: ifnull +81 -> 119
        //   41: aload 6
        //   43: iconst_1
        //   44: invokevirtual 66	android/os/Parcel:writeInt	(I)V
        //   47: aload_2
        //   48: aload 6
        //   50: iconst_0
        //   51: invokevirtual 72	com/google/android/gms/b/ih:writeToParcel	(Landroid/os/Parcel;I)V
        //   54: aload 6
        //   56: aload_3
        //   57: invokevirtual 75	android/os/Parcel:writeString	(Ljava/lang/String;)V
        //   60: aload 5
        //   62: astore_1
        //   63: aload 4
        //   65: ifnull +11 -> 76
        //   68: aload 4
        //   70: invokeinterface 78 1 0
        //   75: astore_1
        //   76: aload 6
        //   78: aload_1
        //   79: invokevirtual 61	android/os/Parcel:writeStrongBinder	(Landroid/os/IBinder;)V
        //   82: aload_0
        //   83: getfield 17	com/google/android/gms/b/od$a$a:a	Landroid/os/IBinder;
        //   86: iconst_3
        //   87: aload 6
        //   89: aload 7
        //   91: iconst_0
        //   92: invokeinterface 37 5 0
        //   97: pop
        //   98: aload 7
        //   100: invokevirtual 40	android/os/Parcel:readException	()V
        //   103: aload 7
        //   105: invokevirtual 52	android/os/Parcel:recycle	()V
        //   108: aload 6
        //   110: invokevirtual 52	android/os/Parcel:recycle	()V
        //   113: return
        //   114: aconst_null
        //   115: astore_1
        //   116: goto -85 -> 31
        //   119: aload 6
        //   121: iconst_0
        //   122: invokevirtual 66	android/os/Parcel:writeInt	(I)V
        //   125: goto -71 -> 54
        //   128: astore_1
        //   129: aload 7
        //   131: invokevirtual 52	android/os/Parcel:recycle	()V
        //   134: aload 6
        //   136: invokevirtual 52	android/os/Parcel:recycle	()V
        //   139: aload_1
        //   140: athrow
        // Local variable table:
        //   start	length	slot	name	signature
        //   0	141	0	this	a
        //   0	141	1	parama	a
        //   0	141	2	paramih	ih
        //   0	141	3	paramString	String
        //   0	141	4	paramoe	oe
        //   1	60	5	localObject	Object
        //   6	129	6	localParcel1	Parcel
        //   11	119	7	localParcel2	Parcel
        // Exception table:
        //   from	to	target	type
        //   13	20	128	finally
        //   24	31	128	finally
        //   31	37	128	finally
        //   41	54	128	finally
        //   54	60	128	finally
        //   68	76	128	finally
        //   76	103	128	finally
        //   119	125	128	finally
      }
      
      /* Error */
      public final void a(a parama, ih paramih, String paramString1, sq paramsq, String paramString2)
      {
        // Byte code:
        //   0: aconst_null
        //   1: astore 6
        //   3: invokestatic 25	android/os/Parcel:obtain	()Landroid/os/Parcel;
        //   6: astore 7
        //   8: invokestatic 25	android/os/Parcel:obtain	()Landroid/os/Parcel;
        //   11: astore 8
        //   13: aload 7
        //   15: ldc 27
        //   17: invokevirtual 31	android/os/Parcel:writeInterfaceToken	(Ljava/lang/String;)V
        //   20: aload_1
        //   21: ifnull +101 -> 122
        //   24: aload_1
        //   25: invokeinterface 58 1 0
        //   30: astore_1
        //   31: aload 7
        //   33: aload_1
        //   34: invokevirtual 61	android/os/Parcel:writeStrongBinder	(Landroid/os/IBinder;)V
        //   37: aload_2
        //   38: ifnull +89 -> 127
        //   41: aload 7
        //   43: iconst_1
        //   44: invokevirtual 66	android/os/Parcel:writeInt	(I)V
        //   47: aload_2
        //   48: aload 7
        //   50: iconst_0
        //   51: invokevirtual 72	com/google/android/gms/b/ih:writeToParcel	(Landroid/os/Parcel;I)V
        //   54: aload 7
        //   56: aload_3
        //   57: invokevirtual 75	android/os/Parcel:writeString	(Ljava/lang/String;)V
        //   60: aload 6
        //   62: astore_1
        //   63: aload 4
        //   65: ifnull +11 -> 76
        //   68: aload 4
        //   70: invokeinterface 82 1 0
        //   75: astore_1
        //   76: aload 7
        //   78: aload_1
        //   79: invokevirtual 61	android/os/Parcel:writeStrongBinder	(Landroid/os/IBinder;)V
        //   82: aload 7
        //   84: aload 5
        //   86: invokevirtual 75	android/os/Parcel:writeString	(Ljava/lang/String;)V
        //   89: aload_0
        //   90: getfield 17	com/google/android/gms/b/od$a$a:a	Landroid/os/IBinder;
        //   93: bipush 10
        //   95: aload 7
        //   97: aload 8
        //   99: iconst_0
        //   100: invokeinterface 37 5 0
        //   105: pop
        //   106: aload 8
        //   108: invokevirtual 40	android/os/Parcel:readException	()V
        //   111: aload 8
        //   113: invokevirtual 52	android/os/Parcel:recycle	()V
        //   116: aload 7
        //   118: invokevirtual 52	android/os/Parcel:recycle	()V
        //   121: return
        //   122: aconst_null
        //   123: astore_1
        //   124: goto -93 -> 31
        //   127: aload 7
        //   129: iconst_0
        //   130: invokevirtual 66	android/os/Parcel:writeInt	(I)V
        //   133: goto -79 -> 54
        //   136: astore_1
        //   137: aload 8
        //   139: invokevirtual 52	android/os/Parcel:recycle	()V
        //   142: aload 7
        //   144: invokevirtual 52	android/os/Parcel:recycle	()V
        //   147: aload_1
        //   148: athrow
        // Local variable table:
        //   start	length	slot	name	signature
        //   0	149	0	this	a
        //   0	149	1	parama	a
        //   0	149	2	paramih	ih
        //   0	149	3	paramString1	String
        //   0	149	4	paramsq	sq
        //   0	149	5	paramString2	String
        //   1	60	6	localObject	Object
        //   6	137	7	localParcel1	Parcel
        //   11	127	8	localParcel2	Parcel
        // Exception table:
        //   from	to	target	type
        //   13	20	136	finally
        //   24	31	136	finally
        //   31	37	136	finally
        //   41	54	136	finally
        //   54	60	136	finally
        //   68	76	136	finally
        //   76	111	136	finally
        //   127	133	136	finally
      }
      
      /* Error */
      public final void a(a parama, ih paramih, String paramString1, String paramString2, oe paramoe)
      {
        // Byte code:
        //   0: aconst_null
        //   1: astore 6
        //   3: invokestatic 25	android/os/Parcel:obtain	()Landroid/os/Parcel;
        //   6: astore 7
        //   8: invokestatic 25	android/os/Parcel:obtain	()Landroid/os/Parcel;
        //   11: astore 8
        //   13: aload 7
        //   15: ldc 27
        //   17: invokevirtual 31	android/os/Parcel:writeInterfaceToken	(Ljava/lang/String;)V
        //   20: aload_1
        //   21: ifnull +101 -> 122
        //   24: aload_1
        //   25: invokeinterface 58 1 0
        //   30: astore_1
        //   31: aload 7
        //   33: aload_1
        //   34: invokevirtual 61	android/os/Parcel:writeStrongBinder	(Landroid/os/IBinder;)V
        //   37: aload_2
        //   38: ifnull +89 -> 127
        //   41: aload 7
        //   43: iconst_1
        //   44: invokevirtual 66	android/os/Parcel:writeInt	(I)V
        //   47: aload_2
        //   48: aload 7
        //   50: iconst_0
        //   51: invokevirtual 72	com/google/android/gms/b/ih:writeToParcel	(Landroid/os/Parcel;I)V
        //   54: aload 7
        //   56: aload_3
        //   57: invokevirtual 75	android/os/Parcel:writeString	(Ljava/lang/String;)V
        //   60: aload 7
        //   62: aload 4
        //   64: invokevirtual 75	android/os/Parcel:writeString	(Ljava/lang/String;)V
        //   67: aload 6
        //   69: astore_1
        //   70: aload 5
        //   72: ifnull +11 -> 83
        //   75: aload 5
        //   77: invokeinterface 78 1 0
        //   82: astore_1
        //   83: aload 7
        //   85: aload_1
        //   86: invokevirtual 61	android/os/Parcel:writeStrongBinder	(Landroid/os/IBinder;)V
        //   89: aload_0
        //   90: getfield 17	com/google/android/gms/b/od$a$a:a	Landroid/os/IBinder;
        //   93: bipush 7
        //   95: aload 7
        //   97: aload 8
        //   99: iconst_0
        //   100: invokeinterface 37 5 0
        //   105: pop
        //   106: aload 8
        //   108: invokevirtual 40	android/os/Parcel:readException	()V
        //   111: aload 8
        //   113: invokevirtual 52	android/os/Parcel:recycle	()V
        //   116: aload 7
        //   118: invokevirtual 52	android/os/Parcel:recycle	()V
        //   121: return
        //   122: aconst_null
        //   123: astore_1
        //   124: goto -93 -> 31
        //   127: aload 7
        //   129: iconst_0
        //   130: invokevirtual 66	android/os/Parcel:writeInt	(I)V
        //   133: goto -79 -> 54
        //   136: astore_1
        //   137: aload 8
        //   139: invokevirtual 52	android/os/Parcel:recycle	()V
        //   142: aload 7
        //   144: invokevirtual 52	android/os/Parcel:recycle	()V
        //   147: aload_1
        //   148: athrow
        // Local variable table:
        //   start	length	slot	name	signature
        //   0	149	0	this	a
        //   0	149	1	parama	a
        //   0	149	2	paramih	ih
        //   0	149	3	paramString1	String
        //   0	149	4	paramString2	String
        //   0	149	5	paramoe	oe
        //   1	67	6	localObject	Object
        //   6	137	7	localParcel1	Parcel
        //   11	127	8	localParcel2	Parcel
        // Exception table:
        //   from	to	target	type
        //   13	20	136	finally
        //   24	31	136	finally
        //   31	37	136	finally
        //   41	54	136	finally
        //   54	67	136	finally
        //   75	83	136	finally
        //   83	111	136	finally
        //   127	133	136	finally
      }
      
      public final void a(a parama, ih paramih, String paramString1, String paramString2, oe paramoe, le paramle, List<String> paramList)
      {
        Object localObject = null;
        Parcel localParcel1 = Parcel.obtain();
        Parcel localParcel2 = Parcel.obtain();
        label175:
        for (;;)
        {
          try
          {
            localParcel1.writeInterfaceToken("com.google.android.gms.ads.internal.mediation.client.IMediationAdapter");
            if (parama != null)
            {
              parama = parama.asBinder();
              localParcel1.writeStrongBinder(parama);
              if (paramih != null)
              {
                localParcel1.writeInt(1);
                paramih.writeToParcel(localParcel1, 0);
                localParcel1.writeString(paramString1);
                localParcel1.writeString(paramString2);
                parama = (a)localObject;
                if (paramoe != null) {
                  parama = paramoe.asBinder();
                }
                localParcel1.writeStrongBinder(parama);
                if (paramle == null) {
                  break label175;
                }
                localParcel1.writeInt(1);
                paramle.writeToParcel(localParcel1, 0);
                localParcel1.writeStringList(paramList);
                a.transact(14, localParcel1, localParcel2, 0);
                localParcel2.readException();
              }
            }
            else
            {
              parama = null;
              continue;
            }
            localParcel1.writeInt(0);
            continue;
            localParcel1.writeInt(0);
          }
          finally
          {
            localParcel2.recycle();
            localParcel1.recycle();
          }
        }
      }
      
      public final void a(a parama, il paramil, ih paramih, String paramString, oe paramoe)
      {
        Object localObject = null;
        Parcel localParcel1 = Parcel.obtain();
        Parcel localParcel2 = Parcel.obtain();
        label159:
        for (;;)
        {
          try
          {
            localParcel1.writeInterfaceToken("com.google.android.gms.ads.internal.mediation.client.IMediationAdapter");
            if (parama != null)
            {
              parama = parama.asBinder();
              localParcel1.writeStrongBinder(parama);
              if (paramil != null)
              {
                localParcel1.writeInt(1);
                paramil.writeToParcel(localParcel1, 0);
                if (paramih == null) {
                  break label159;
                }
                localParcel1.writeInt(1);
                paramih.writeToParcel(localParcel1, 0);
                localParcel1.writeString(paramString);
                parama = (a)localObject;
                if (paramoe != null) {
                  parama = paramoe.asBinder();
                }
                localParcel1.writeStrongBinder(parama);
                a.transact(1, localParcel1, localParcel2, 0);
                localParcel2.readException();
              }
            }
            else
            {
              parama = null;
              continue;
            }
            localParcel1.writeInt(0);
            continue;
            localParcel1.writeInt(0);
          }
          finally
          {
            localParcel2.recycle();
            localParcel1.recycle();
          }
        }
      }
      
      public final void a(a parama, il paramil, ih paramih, String paramString1, String paramString2, oe paramoe)
      {
        Object localObject = null;
        Parcel localParcel1 = Parcel.obtain();
        Parcel localParcel2 = Parcel.obtain();
        label167:
        for (;;)
        {
          try
          {
            localParcel1.writeInterfaceToken("com.google.android.gms.ads.internal.mediation.client.IMediationAdapter");
            if (parama != null)
            {
              parama = parama.asBinder();
              localParcel1.writeStrongBinder(parama);
              if (paramil != null)
              {
                localParcel1.writeInt(1);
                paramil.writeToParcel(localParcel1, 0);
                if (paramih == null) {
                  break label167;
                }
                localParcel1.writeInt(1);
                paramih.writeToParcel(localParcel1, 0);
                localParcel1.writeString(paramString1);
                localParcel1.writeString(paramString2);
                parama = (a)localObject;
                if (paramoe != null) {
                  parama = paramoe.asBinder();
                }
                localParcel1.writeStrongBinder(parama);
                a.transact(6, localParcel1, localParcel2, 0);
                localParcel2.readException();
              }
            }
            else
            {
              parama = null;
              continue;
            }
            localParcel1.writeInt(0);
            continue;
            localParcel1.writeInt(0);
          }
          finally
          {
            localParcel2.recycle();
            localParcel1.recycle();
          }
        }
      }
      
      /* Error */
      public final void a(a parama, sq paramsq, List<String> paramList)
      {
        // Byte code:
        //   0: aconst_null
        //   1: astore 4
        //   3: invokestatic 25	android/os/Parcel:obtain	()Landroid/os/Parcel;
        //   6: astore 5
        //   8: invokestatic 25	android/os/Parcel:obtain	()Landroid/os/Parcel;
        //   11: astore 6
        //   13: aload 5
        //   15: ldc 27
        //   17: invokevirtual 31	android/os/Parcel:writeInterfaceToken	(Ljava/lang/String;)V
        //   20: aload_1
        //   21: ifnull +75 -> 96
        //   24: aload_1
        //   25: invokeinterface 58 1 0
        //   30: astore_1
        //   31: aload 5
        //   33: aload_1
        //   34: invokevirtual 61	android/os/Parcel:writeStrongBinder	(Landroid/os/IBinder;)V
        //   37: aload 4
        //   39: astore_1
        //   40: aload_2
        //   41: ifnull +10 -> 51
        //   44: aload_2
        //   45: invokeinterface 82 1 0
        //   50: astore_1
        //   51: aload 5
        //   53: aload_1
        //   54: invokevirtual 61	android/os/Parcel:writeStrongBinder	(Landroid/os/IBinder;)V
        //   57: aload 5
        //   59: aload_3
        //   60: invokevirtual 91	android/os/Parcel:writeStringList	(Ljava/util/List;)V
        //   63: aload_0
        //   64: getfield 17	com/google/android/gms/b/od$a$a:a	Landroid/os/IBinder;
        //   67: bipush 23
        //   69: aload 5
        //   71: aload 6
        //   73: iconst_0
        //   74: invokeinterface 37 5 0
        //   79: pop
        //   80: aload 6
        //   82: invokevirtual 40	android/os/Parcel:readException	()V
        //   85: aload 6
        //   87: invokevirtual 52	android/os/Parcel:recycle	()V
        //   90: aload 5
        //   92: invokevirtual 52	android/os/Parcel:recycle	()V
        //   95: return
        //   96: aconst_null
        //   97: astore_1
        //   98: goto -67 -> 31
        //   101: astore_1
        //   102: aload 6
        //   104: invokevirtual 52	android/os/Parcel:recycle	()V
        //   107: aload 5
        //   109: invokevirtual 52	android/os/Parcel:recycle	()V
        //   112: aload_1
        //   113: athrow
        // Local variable table:
        //   start	length	slot	name	signature
        //   0	114	0	this	a
        //   0	114	1	parama	a
        //   0	114	2	paramsq	sq
        //   0	114	3	paramList	List<String>
        //   1	37	4	localObject	Object
        //   6	102	5	localParcel1	Parcel
        //   11	92	6	localParcel2	Parcel
        // Exception table:
        //   from	to	target	type
        //   13	20	101	finally
        //   24	31	101	finally
        //   31	37	101	finally
        //   44	51	101	finally
        //   51	85	101	finally
      }
      
      /* Error */
      public final void a(ih paramih, String paramString)
      {
        // Byte code:
        //   0: invokestatic 25	android/os/Parcel:obtain	()Landroid/os/Parcel;
        //   3: astore_3
        //   4: invokestatic 25	android/os/Parcel:obtain	()Landroid/os/Parcel;
        //   7: astore 4
        //   9: aload_3
        //   10: ldc 27
        //   12: invokevirtual 31	android/os/Parcel:writeInterfaceToken	(Ljava/lang/String;)V
        //   15: aload_1
        //   16: ifnull +50 -> 66
        //   19: aload_3
        //   20: iconst_1
        //   21: invokevirtual 66	android/os/Parcel:writeInt	(I)V
        //   24: aload_1
        //   25: aload_3
        //   26: iconst_0
        //   27: invokevirtual 72	com/google/android/gms/b/ih:writeToParcel	(Landroid/os/Parcel;I)V
        //   30: aload_3
        //   31: aload_2
        //   32: invokevirtual 75	android/os/Parcel:writeString	(Ljava/lang/String;)V
        //   35: aload_0
        //   36: getfield 17	com/google/android/gms/b/od$a$a:a	Landroid/os/IBinder;
        //   39: bipush 11
        //   41: aload_3
        //   42: aload 4
        //   44: iconst_0
        //   45: invokeinterface 37 5 0
        //   50: pop
        //   51: aload 4
        //   53: invokevirtual 40	android/os/Parcel:readException	()V
        //   56: aload 4
        //   58: invokevirtual 52	android/os/Parcel:recycle	()V
        //   61: aload_3
        //   62: invokevirtual 52	android/os/Parcel:recycle	()V
        //   65: return
        //   66: aload_3
        //   67: iconst_0
        //   68: invokevirtual 66	android/os/Parcel:writeInt	(I)V
        //   71: goto -41 -> 30
        //   74: astore_1
        //   75: aload 4
        //   77: invokevirtual 52	android/os/Parcel:recycle	()V
        //   80: aload_3
        //   81: invokevirtual 52	android/os/Parcel:recycle	()V
        //   84: aload_1
        //   85: athrow
        // Local variable table:
        //   start	length	slot	name	signature
        //   0	86	0	this	a
        //   0	86	1	paramih	ih
        //   0	86	2	paramString	String
        //   3	78	3	localParcel1	Parcel
        //   7	69	4	localParcel2	Parcel
        // Exception table:
        //   from	to	target	type
        //   9	15	74	finally
        //   19	30	74	finally
        //   30	56	74	finally
        //   66	71	74	finally
      }
      
      /* Error */
      public final void a(ih paramih, String paramString1, String paramString2)
      {
        // Byte code:
        //   0: invokestatic 25	android/os/Parcel:obtain	()Landroid/os/Parcel;
        //   3: astore 4
        //   5: invokestatic 25	android/os/Parcel:obtain	()Landroid/os/Parcel;
        //   8: astore 5
        //   10: aload 4
        //   12: ldc 27
        //   14: invokevirtual 31	android/os/Parcel:writeInterfaceToken	(Ljava/lang/String;)V
        //   17: aload_1
        //   18: ifnull +61 -> 79
        //   21: aload 4
        //   23: iconst_1
        //   24: invokevirtual 66	android/os/Parcel:writeInt	(I)V
        //   27: aload_1
        //   28: aload 4
        //   30: iconst_0
        //   31: invokevirtual 72	com/google/android/gms/b/ih:writeToParcel	(Landroid/os/Parcel;I)V
        //   34: aload 4
        //   36: aload_2
        //   37: invokevirtual 75	android/os/Parcel:writeString	(Ljava/lang/String;)V
        //   40: aload 4
        //   42: aload_3
        //   43: invokevirtual 75	android/os/Parcel:writeString	(Ljava/lang/String;)V
        //   46: aload_0
        //   47: getfield 17	com/google/android/gms/b/od$a$a:a	Landroid/os/IBinder;
        //   50: bipush 20
        //   52: aload 4
        //   54: aload 5
        //   56: iconst_0
        //   57: invokeinterface 37 5 0
        //   62: pop
        //   63: aload 5
        //   65: invokevirtual 40	android/os/Parcel:readException	()V
        //   68: aload 5
        //   70: invokevirtual 52	android/os/Parcel:recycle	()V
        //   73: aload 4
        //   75: invokevirtual 52	android/os/Parcel:recycle	()V
        //   78: return
        //   79: aload 4
        //   81: iconst_0
        //   82: invokevirtual 66	android/os/Parcel:writeInt	(I)V
        //   85: goto -51 -> 34
        //   88: astore_1
        //   89: aload 5
        //   91: invokevirtual 52	android/os/Parcel:recycle	()V
        //   94: aload 4
        //   96: invokevirtual 52	android/os/Parcel:recycle	()V
        //   99: aload_1
        //   100: athrow
        // Local variable table:
        //   start	length	slot	name	signature
        //   0	101	0	this	a
        //   0	101	1	paramih	ih
        //   0	101	2	paramString1	String
        //   0	101	3	paramString2	String
        //   3	92	4	localParcel1	Parcel
        //   8	82	5	localParcel2	Parcel
        // Exception table:
        //   from	to	target	type
        //   10	17	88	finally
        //   21	34	88	finally
        //   34	68	88	finally
        //   79	85	88	finally
      }
      
      public final IBinder asBinder()
      {
        return a;
      }
      
      public final void b()
      {
        Parcel localParcel1 = Parcel.obtain();
        Parcel localParcel2 = Parcel.obtain();
        try
        {
          localParcel1.writeInterfaceToken("com.google.android.gms.ads.internal.mediation.client.IMediationAdapter");
          a.transact(4, localParcel1, localParcel2, 0);
          localParcel2.readException();
          return;
        }
        finally
        {
          localParcel2.recycle();
          localParcel1.recycle();
        }
      }
      
      public final void c()
      {
        Parcel localParcel1 = Parcel.obtain();
        Parcel localParcel2 = Parcel.obtain();
        try
        {
          localParcel1.writeInterfaceToken("com.google.android.gms.ads.internal.mediation.client.IMediationAdapter");
          a.transact(5, localParcel1, localParcel2, 0);
          localParcel2.readException();
          return;
        }
        finally
        {
          localParcel2.recycle();
          localParcel1.recycle();
        }
      }
      
      public final void d()
      {
        Parcel localParcel1 = Parcel.obtain();
        Parcel localParcel2 = Parcel.obtain();
        try
        {
          localParcel1.writeInterfaceToken("com.google.android.gms.ads.internal.mediation.client.IMediationAdapter");
          a.transact(8, localParcel1, localParcel2, 0);
          localParcel2.readException();
          return;
        }
        finally
        {
          localParcel2.recycle();
          localParcel1.recycle();
        }
      }
      
      public final void e()
      {
        Parcel localParcel1 = Parcel.obtain();
        Parcel localParcel2 = Parcel.obtain();
        try
        {
          localParcel1.writeInterfaceToken("com.google.android.gms.ads.internal.mediation.client.IMediationAdapter");
          a.transact(9, localParcel1, localParcel2, 0);
          localParcel2.readException();
          return;
        }
        finally
        {
          localParcel2.recycle();
          localParcel1.recycle();
        }
      }
      
      public final void f()
      {
        Parcel localParcel1 = Parcel.obtain();
        Parcel localParcel2 = Parcel.obtain();
        try
        {
          localParcel1.writeInterfaceToken("com.google.android.gms.ads.internal.mediation.client.IMediationAdapter");
          a.transact(12, localParcel1, localParcel2, 0);
          localParcel2.readException();
          return;
        }
        finally
        {
          localParcel2.recycle();
          localParcel1.recycle();
        }
      }
      
      public final boolean g()
      {
        boolean bool = false;
        Parcel localParcel1 = Parcel.obtain();
        Parcel localParcel2 = Parcel.obtain();
        try
        {
          localParcel1.writeInterfaceToken("com.google.android.gms.ads.internal.mediation.client.IMediationAdapter");
          a.transact(13, localParcel1, localParcel2, 0);
          localParcel2.readException();
          int i = localParcel2.readInt();
          if (i != 0) {
            bool = true;
          }
          return bool;
        }
        finally
        {
          localParcel2.recycle();
          localParcel1.recycle();
        }
      }
      
      public final og h()
      {
        Parcel localParcel1 = Parcel.obtain();
        Parcel localParcel2 = Parcel.obtain();
        try
        {
          localParcel1.writeInterfaceToken("com.google.android.gms.ads.internal.mediation.client.IMediationAdapter");
          a.transact(15, localParcel1, localParcel2, 0);
          localParcel2.readException();
          og localog = og.a.a(localParcel2.readStrongBinder());
          return localog;
        }
        finally
        {
          localParcel2.recycle();
          localParcel1.recycle();
        }
      }
      
      public final oh i()
      {
        Parcel localParcel1 = Parcel.obtain();
        Parcel localParcel2 = Parcel.obtain();
        try
        {
          localParcel1.writeInterfaceToken("com.google.android.gms.ads.internal.mediation.client.IMediationAdapter");
          a.transact(16, localParcel1, localParcel2, 0);
          localParcel2.readException();
          oh localoh = oh.a.a(localParcel2.readStrongBinder());
          return localoh;
        }
        finally
        {
          localParcel2.recycle();
          localParcel1.recycle();
        }
      }
      
      /* Error */
      public final Bundle j()
      {
        // Byte code:
        //   0: invokestatic 25	android/os/Parcel:obtain	()Landroid/os/Parcel;
        //   3: astore_2
        //   4: invokestatic 25	android/os/Parcel:obtain	()Landroid/os/Parcel;
        //   7: astore_3
        //   8: aload_2
        //   9: ldc 27
        //   11: invokevirtual 31	android/os/Parcel:writeInterfaceToken	(Ljava/lang/String;)V
        //   14: aload_0
        //   15: getfield 17	com/google/android/gms/b/od$a$a:a	Landroid/os/IBinder;
        //   18: bipush 17
        //   20: aload_2
        //   21: aload_3
        //   22: iconst_0
        //   23: invokeinterface 37 5 0
        //   28: pop
        //   29: aload_3
        //   30: invokevirtual 40	android/os/Parcel:readException	()V
        //   33: aload_3
        //   34: invokevirtual 113	android/os/Parcel:readInt	()I
        //   37: ifeq +26 -> 63
        //   40: getstatic 135	android/os/Bundle:CREATOR	Landroid/os/Parcelable$Creator;
        //   43: aload_3
        //   44: invokeinterface 141 2 0
        //   49: checkcast 131	android/os/Bundle
        //   52: astore_1
        //   53: aload_3
        //   54: invokevirtual 52	android/os/Parcel:recycle	()V
        //   57: aload_2
        //   58: invokevirtual 52	android/os/Parcel:recycle	()V
        //   61: aload_1
        //   62: areturn
        //   63: aconst_null
        //   64: astore_1
        //   65: goto -12 -> 53
        //   68: astore_1
        //   69: aload_3
        //   70: invokevirtual 52	android/os/Parcel:recycle	()V
        //   73: aload_2
        //   74: invokevirtual 52	android/os/Parcel:recycle	()V
        //   77: aload_1
        //   78: athrow
        // Local variable table:
        //   start	length	slot	name	signature
        //   0	79	0	this	a
        //   52	13	1	localBundle	Bundle
        //   68	10	1	localObject	Object
        //   3	71	2	localParcel1	Parcel
        //   7	63	3	localParcel2	Parcel
        // Exception table:
        //   from	to	target	type
        //   8	53	68	finally
      }
      
      /* Error */
      public final Bundle k()
      {
        // Byte code:
        //   0: invokestatic 25	android/os/Parcel:obtain	()Landroid/os/Parcel;
        //   3: astore_2
        //   4: invokestatic 25	android/os/Parcel:obtain	()Landroid/os/Parcel;
        //   7: astore_3
        //   8: aload_2
        //   9: ldc 27
        //   11: invokevirtual 31	android/os/Parcel:writeInterfaceToken	(Ljava/lang/String;)V
        //   14: aload_0
        //   15: getfield 17	com/google/android/gms/b/od$a$a:a	Landroid/os/IBinder;
        //   18: bipush 18
        //   20: aload_2
        //   21: aload_3
        //   22: iconst_0
        //   23: invokeinterface 37 5 0
        //   28: pop
        //   29: aload_3
        //   30: invokevirtual 40	android/os/Parcel:readException	()V
        //   33: aload_3
        //   34: invokevirtual 113	android/os/Parcel:readInt	()I
        //   37: ifeq +26 -> 63
        //   40: getstatic 135	android/os/Bundle:CREATOR	Landroid/os/Parcelable$Creator;
        //   43: aload_3
        //   44: invokeinterface 141 2 0
        //   49: checkcast 131	android/os/Bundle
        //   52: astore_1
        //   53: aload_3
        //   54: invokevirtual 52	android/os/Parcel:recycle	()V
        //   57: aload_2
        //   58: invokevirtual 52	android/os/Parcel:recycle	()V
        //   61: aload_1
        //   62: areturn
        //   63: aconst_null
        //   64: astore_1
        //   65: goto -12 -> 53
        //   68: astore_1
        //   69: aload_3
        //   70: invokevirtual 52	android/os/Parcel:recycle	()V
        //   73: aload_2
        //   74: invokevirtual 52	android/os/Parcel:recycle	()V
        //   77: aload_1
        //   78: athrow
        // Local variable table:
        //   start	length	slot	name	signature
        //   0	79	0	this	a
        //   52	13	1	localBundle	Bundle
        //   68	10	1	localObject	Object
        //   3	71	2	localParcel1	Parcel
        //   7	63	3	localParcel2	Parcel
        // Exception table:
        //   from	to	target	type
        //   8	53	68	finally
      }
      
      /* Error */
      public final Bundle l()
      {
        // Byte code:
        //   0: invokestatic 25	android/os/Parcel:obtain	()Landroid/os/Parcel;
        //   3: astore_2
        //   4: invokestatic 25	android/os/Parcel:obtain	()Landroid/os/Parcel;
        //   7: astore_3
        //   8: aload_2
        //   9: ldc 27
        //   11: invokevirtual 31	android/os/Parcel:writeInterfaceToken	(Ljava/lang/String;)V
        //   14: aload_0
        //   15: getfield 17	com/google/android/gms/b/od$a$a:a	Landroid/os/IBinder;
        //   18: bipush 19
        //   20: aload_2
        //   21: aload_3
        //   22: iconst_0
        //   23: invokeinterface 37 5 0
        //   28: pop
        //   29: aload_3
        //   30: invokevirtual 40	android/os/Parcel:readException	()V
        //   33: aload_3
        //   34: invokevirtual 113	android/os/Parcel:readInt	()I
        //   37: ifeq +26 -> 63
        //   40: getstatic 135	android/os/Bundle:CREATOR	Landroid/os/Parcelable$Creator;
        //   43: aload_3
        //   44: invokeinterface 141 2 0
        //   49: checkcast 131	android/os/Bundle
        //   52: astore_1
        //   53: aload_3
        //   54: invokevirtual 52	android/os/Parcel:recycle	()V
        //   57: aload_2
        //   58: invokevirtual 52	android/os/Parcel:recycle	()V
        //   61: aload_1
        //   62: areturn
        //   63: aconst_null
        //   64: astore_1
        //   65: goto -12 -> 53
        //   68: astore_1
        //   69: aload_3
        //   70: invokevirtual 52	android/os/Parcel:recycle	()V
        //   73: aload_2
        //   74: invokevirtual 52	android/os/Parcel:recycle	()V
        //   77: aload_1
        //   78: athrow
        // Local variable table:
        //   start	length	slot	name	signature
        //   0	79	0	this	a
        //   52	13	1	localBundle	Bundle
        //   68	10	1	localObject	Object
        //   3	71	2	localParcel1	Parcel
        //   7	63	3	localParcel2	Parcel
        // Exception table:
        //   from	to	target	type
        //   8	53	68	finally
      }
      
      public final boolean m()
      {
        boolean bool = false;
        Parcel localParcel1 = Parcel.obtain();
        Parcel localParcel2 = Parcel.obtain();
        try
        {
          localParcel1.writeInterfaceToken("com.google.android.gms.ads.internal.mediation.client.IMediationAdapter");
          a.transact(22, localParcel1, localParcel2, 0);
          localParcel2.readException();
          int i = localParcel2.readInt();
          if (i != 0) {
            bool = true;
          }
          return bool;
        }
        finally
        {
          localParcel2.recycle();
          localParcel1.recycle();
        }
      }
    }
  }
}


/* Location:              com/google/android/gms/b/od.class
 * Java compiler version: 6 (50.0)
 * JD-Core Version:       0.7.1
 */