package com.google.android.gms.b;

import android.os.Binder;
import android.os.IBinder;
import android.os.IInterface;
import android.os.Parcel;
import android.os.Parcelable.Creator;
import com.google.android.gms.a.a;
import com.google.android.gms.a.a.a;

public abstract interface rz
  extends IInterface
{
  public abstract void a();
  
  public abstract void a(a parama);
  
  public abstract void a(sb paramsb);
  
  public abstract void a(sg paramsg);
  
  public abstract void a(String paramString);
  
  public abstract void b(a parama);
  
  public abstract boolean b();
  
  public abstract void c();
  
  public abstract void c(a parama);
  
  public abstract void d();
  
  public abstract void e();
  
  public static abstract class a
    extends Binder
    implements rz
  {
    public a()
    {
      attachInterface(this, "com.google.android.gms.ads.internal.reward.client.IRewardedVideoAd");
    }
    
    public static rz a(IBinder paramIBinder)
    {
      if (paramIBinder == null) {
        return null;
      }
      IInterface localIInterface = paramIBinder.queryLocalInterface("com.google.android.gms.ads.internal.reward.client.IRewardedVideoAd");
      if ((localIInterface != null) && ((localIInterface instanceof rz))) {
        return (rz)localIInterface;
      }
      return new a(paramIBinder);
    }
    
    public IBinder asBinder()
    {
      return this;
    }
    
    public boolean onTransact(int paramInt1, Parcel paramParcel1, Parcel paramParcel2, int paramInt2)
    {
      switch (paramInt1)
      {
      default: 
        return super.onTransact(paramInt1, paramParcel1, paramParcel2, paramInt2);
      case 1598968902: 
        paramParcel2.writeString("com.google.android.gms.ads.internal.reward.client.IRewardedVideoAd");
        return true;
      case 1: 
        paramParcel1.enforceInterface("com.google.android.gms.ads.internal.reward.client.IRewardedVideoAd");
        if (paramParcel1.readInt() != 0) {}
        for (paramParcel1 = (sg)sg.CREATOR.createFromParcel(paramParcel1);; paramParcel1 = null)
        {
          a(paramParcel1);
          paramParcel2.writeNoException();
          return true;
        }
      case 2: 
        paramParcel1.enforceInterface("com.google.android.gms.ads.internal.reward.client.IRewardedVideoAd");
        a();
        paramParcel2.writeNoException();
        return true;
      case 3: 
        paramParcel1.enforceInterface("com.google.android.gms.ads.internal.reward.client.IRewardedVideoAd");
        a(sb.a.a(paramParcel1.readStrongBinder()));
        paramParcel2.writeNoException();
        return true;
      case 4: 
        paramParcel1.enforceInterface("com.google.android.gms.ads.internal.reward.client.IRewardedVideoAd");
        a(paramParcel1.readString());
        paramParcel2.writeNoException();
        return true;
      case 5: 
        paramParcel1.enforceInterface("com.google.android.gms.ads.internal.reward.client.IRewardedVideoAd");
        boolean bool = b();
        paramParcel2.writeNoException();
        if (bool) {}
        for (paramInt1 = 1;; paramInt1 = 0)
        {
          paramParcel2.writeInt(paramInt1);
          return true;
        }
      case 6: 
        paramParcel1.enforceInterface("com.google.android.gms.ads.internal.reward.client.IRewardedVideoAd");
        c();
        paramParcel2.writeNoException();
        return true;
      case 7: 
        paramParcel1.enforceInterface("com.google.android.gms.ads.internal.reward.client.IRewardedVideoAd");
        d();
        paramParcel2.writeNoException();
        return true;
      case 8: 
        paramParcel1.enforceInterface("com.google.android.gms.ads.internal.reward.client.IRewardedVideoAd");
        e();
        paramParcel2.writeNoException();
        return true;
      case 9: 
        paramParcel1.enforceInterface("com.google.android.gms.ads.internal.reward.client.IRewardedVideoAd");
        a(a.a.a(paramParcel1.readStrongBinder()));
        paramParcel2.writeNoException();
        return true;
      case 10: 
        paramParcel1.enforceInterface("com.google.android.gms.ads.internal.reward.client.IRewardedVideoAd");
        b(a.a.a(paramParcel1.readStrongBinder()));
        paramParcel2.writeNoException();
        return true;
      }
      paramParcel1.enforceInterface("com.google.android.gms.ads.internal.reward.client.IRewardedVideoAd");
      c(a.a.a(paramParcel1.readStrongBinder()));
      paramParcel2.writeNoException();
      return true;
    }
    
    private static final class a
      implements rz
    {
      private IBinder a;
      
      a(IBinder paramIBinder)
      {
        a = paramIBinder;
      }
      
      public final void a()
      {
        Parcel localParcel1 = Parcel.obtain();
        Parcel localParcel2 = Parcel.obtain();
        try
        {
          localParcel1.writeInterfaceToken("com.google.android.gms.ads.internal.reward.client.IRewardedVideoAd");
          a.transact(2, localParcel1, localParcel2, 0);
          localParcel2.readException();
          return;
        }
        finally
        {
          localParcel2.recycle();
          localParcel1.recycle();
        }
      }
      
      /* Error */
      public final void a(a parama)
      {
        // Byte code:
        //   0: invokestatic 24	android/os/Parcel:obtain	()Landroid/os/Parcel;
        //   3: astore_2
        //   4: invokestatic 24	android/os/Parcel:obtain	()Landroid/os/Parcel;
        //   7: astore_3
        //   8: aload_2
        //   9: ldc 26
        //   11: invokevirtual 30	android/os/Parcel:writeInterfaceToken	(Ljava/lang/String;)V
        //   14: aload_1
        //   15: ifnull +43 -> 58
        //   18: aload_1
        //   19: invokeinterface 49 1 0
        //   24: astore_1
        //   25: aload_2
        //   26: aload_1
        //   27: invokevirtual 52	android/os/Parcel:writeStrongBinder	(Landroid/os/IBinder;)V
        //   30: aload_0
        //   31: getfield 17	com/google/android/gms/b/rz$a$a:a	Landroid/os/IBinder;
        //   34: bipush 9
        //   36: aload_2
        //   37: aload_3
        //   38: iconst_0
        //   39: invokeinterface 36 5 0
        //   44: pop
        //   45: aload_3
        //   46: invokevirtual 39	android/os/Parcel:readException	()V
        //   49: aload_3
        //   50: invokevirtual 42	android/os/Parcel:recycle	()V
        //   53: aload_2
        //   54: invokevirtual 42	android/os/Parcel:recycle	()V
        //   57: return
        //   58: aconst_null
        //   59: astore_1
        //   60: goto -35 -> 25
        //   63: astore_1
        //   64: aload_3
        //   65: invokevirtual 42	android/os/Parcel:recycle	()V
        //   68: aload_2
        //   69: invokevirtual 42	android/os/Parcel:recycle	()V
        //   72: aload_1
        //   73: athrow
        // Local variable table:
        //   start	length	slot	name	signature
        //   0	74	0	this	a
        //   0	74	1	parama	a
        //   3	66	2	localParcel1	Parcel
        //   7	58	3	localParcel2	Parcel
        // Exception table:
        //   from	to	target	type
        //   8	14	63	finally
        //   18	25	63	finally
        //   25	49	63	finally
      }
      
      /* Error */
      public final void a(sb paramsb)
      {
        // Byte code:
        //   0: invokestatic 24	android/os/Parcel:obtain	()Landroid/os/Parcel;
        //   3: astore_2
        //   4: invokestatic 24	android/os/Parcel:obtain	()Landroid/os/Parcel;
        //   7: astore_3
        //   8: aload_2
        //   9: ldc 26
        //   11: invokevirtual 30	android/os/Parcel:writeInterfaceToken	(Ljava/lang/String;)V
        //   14: aload_1
        //   15: ifnull +42 -> 57
        //   18: aload_1
        //   19: invokeinterface 56 1 0
        //   24: astore_1
        //   25: aload_2
        //   26: aload_1
        //   27: invokevirtual 52	android/os/Parcel:writeStrongBinder	(Landroid/os/IBinder;)V
        //   30: aload_0
        //   31: getfield 17	com/google/android/gms/b/rz$a$a:a	Landroid/os/IBinder;
        //   34: iconst_3
        //   35: aload_2
        //   36: aload_3
        //   37: iconst_0
        //   38: invokeinterface 36 5 0
        //   43: pop
        //   44: aload_3
        //   45: invokevirtual 39	android/os/Parcel:readException	()V
        //   48: aload_3
        //   49: invokevirtual 42	android/os/Parcel:recycle	()V
        //   52: aload_2
        //   53: invokevirtual 42	android/os/Parcel:recycle	()V
        //   56: return
        //   57: aconst_null
        //   58: astore_1
        //   59: goto -34 -> 25
        //   62: astore_1
        //   63: aload_3
        //   64: invokevirtual 42	android/os/Parcel:recycle	()V
        //   67: aload_2
        //   68: invokevirtual 42	android/os/Parcel:recycle	()V
        //   71: aload_1
        //   72: athrow
        // Local variable table:
        //   start	length	slot	name	signature
        //   0	73	0	this	a
        //   0	73	1	paramsb	sb
        //   3	65	2	localParcel1	Parcel
        //   7	57	3	localParcel2	Parcel
        // Exception table:
        //   from	to	target	type
        //   8	14	62	finally
        //   18	25	62	finally
        //   25	48	62	finally
      }
      
      /* Error */
      public final void a(sg paramsg)
      {
        // Byte code:
        //   0: invokestatic 24	android/os/Parcel:obtain	()Landroid/os/Parcel;
        //   3: astore_2
        //   4: invokestatic 24	android/os/Parcel:obtain	()Landroid/os/Parcel;
        //   7: astore_3
        //   8: aload_2
        //   9: ldc 26
        //   11: invokevirtual 30	android/os/Parcel:writeInterfaceToken	(Ljava/lang/String;)V
        //   14: aload_1
        //   15: ifnull +41 -> 56
        //   18: aload_2
        //   19: iconst_1
        //   20: invokevirtual 61	android/os/Parcel:writeInt	(I)V
        //   23: aload_1
        //   24: aload_2
        //   25: iconst_0
        //   26: invokevirtual 67	com/google/android/gms/b/sg:writeToParcel	(Landroid/os/Parcel;I)V
        //   29: aload_0
        //   30: getfield 17	com/google/android/gms/b/rz$a$a:a	Landroid/os/IBinder;
        //   33: iconst_1
        //   34: aload_2
        //   35: aload_3
        //   36: iconst_0
        //   37: invokeinterface 36 5 0
        //   42: pop
        //   43: aload_3
        //   44: invokevirtual 39	android/os/Parcel:readException	()V
        //   47: aload_3
        //   48: invokevirtual 42	android/os/Parcel:recycle	()V
        //   51: aload_2
        //   52: invokevirtual 42	android/os/Parcel:recycle	()V
        //   55: return
        //   56: aload_2
        //   57: iconst_0
        //   58: invokevirtual 61	android/os/Parcel:writeInt	(I)V
        //   61: goto -32 -> 29
        //   64: astore_1
        //   65: aload_3
        //   66: invokevirtual 42	android/os/Parcel:recycle	()V
        //   69: aload_2
        //   70: invokevirtual 42	android/os/Parcel:recycle	()V
        //   73: aload_1
        //   74: athrow
        // Local variable table:
        //   start	length	slot	name	signature
        //   0	75	0	this	a
        //   0	75	1	paramsg	sg
        //   3	67	2	localParcel1	Parcel
        //   7	59	3	localParcel2	Parcel
        // Exception table:
        //   from	to	target	type
        //   8	14	64	finally
        //   18	29	64	finally
        //   29	47	64	finally
        //   56	61	64	finally
      }
      
      public final void a(String paramString)
      {
        Parcel localParcel1 = Parcel.obtain();
        Parcel localParcel2 = Parcel.obtain();
        try
        {
          localParcel1.writeInterfaceToken("com.google.android.gms.ads.internal.reward.client.IRewardedVideoAd");
          localParcel1.writeString(paramString);
          a.transact(4, localParcel1, localParcel2, 0);
          localParcel2.readException();
          return;
        }
        finally
        {
          localParcel2.recycle();
          localParcel1.recycle();
        }
      }
      
      public final IBinder asBinder()
      {
        return a;
      }
      
      /* Error */
      public final void b(a parama)
      {
        // Byte code:
        //   0: invokestatic 24	android/os/Parcel:obtain	()Landroid/os/Parcel;
        //   3: astore_2
        //   4: invokestatic 24	android/os/Parcel:obtain	()Landroid/os/Parcel;
        //   7: astore_3
        //   8: aload_2
        //   9: ldc 26
        //   11: invokevirtual 30	android/os/Parcel:writeInterfaceToken	(Ljava/lang/String;)V
        //   14: aload_1
        //   15: ifnull +43 -> 58
        //   18: aload_1
        //   19: invokeinterface 49 1 0
        //   24: astore_1
        //   25: aload_2
        //   26: aload_1
        //   27: invokevirtual 52	android/os/Parcel:writeStrongBinder	(Landroid/os/IBinder;)V
        //   30: aload_0
        //   31: getfield 17	com/google/android/gms/b/rz$a$a:a	Landroid/os/IBinder;
        //   34: bipush 10
        //   36: aload_2
        //   37: aload_3
        //   38: iconst_0
        //   39: invokeinterface 36 5 0
        //   44: pop
        //   45: aload_3
        //   46: invokevirtual 39	android/os/Parcel:readException	()V
        //   49: aload_3
        //   50: invokevirtual 42	android/os/Parcel:recycle	()V
        //   53: aload_2
        //   54: invokevirtual 42	android/os/Parcel:recycle	()V
        //   57: return
        //   58: aconst_null
        //   59: astore_1
        //   60: goto -35 -> 25
        //   63: astore_1
        //   64: aload_3
        //   65: invokevirtual 42	android/os/Parcel:recycle	()V
        //   68: aload_2
        //   69: invokevirtual 42	android/os/Parcel:recycle	()V
        //   72: aload_1
        //   73: athrow
        // Local variable table:
        //   start	length	slot	name	signature
        //   0	74	0	this	a
        //   0	74	1	parama	a
        //   3	66	2	localParcel1	Parcel
        //   7	58	3	localParcel2	Parcel
        // Exception table:
        //   from	to	target	type
        //   8	14	63	finally
        //   18	25	63	finally
        //   25	49	63	finally
      }
      
      public final boolean b()
      {
        boolean bool = false;
        Parcel localParcel1 = Parcel.obtain();
        Parcel localParcel2 = Parcel.obtain();
        try
        {
          localParcel1.writeInterfaceToken("com.google.android.gms.ads.internal.reward.client.IRewardedVideoAd");
          a.transact(5, localParcel1, localParcel2, 0);
          localParcel2.readException();
          int i = localParcel2.readInt();
          if (i != 0) {
            bool = true;
          }
          return bool;
        }
        finally
        {
          localParcel2.recycle();
          localParcel1.recycle();
        }
      }
      
      public final void c()
      {
        Parcel localParcel1 = Parcel.obtain();
        Parcel localParcel2 = Parcel.obtain();
        try
        {
          localParcel1.writeInterfaceToken("com.google.android.gms.ads.internal.reward.client.IRewardedVideoAd");
          a.transact(6, localParcel1, localParcel2, 0);
          localParcel2.readException();
          return;
        }
        finally
        {
          localParcel2.recycle();
          localParcel1.recycle();
        }
      }
      
      /* Error */
      public final void c(a parama)
      {
        // Byte code:
        //   0: invokestatic 24	android/os/Parcel:obtain	()Landroid/os/Parcel;
        //   3: astore_2
        //   4: invokestatic 24	android/os/Parcel:obtain	()Landroid/os/Parcel;
        //   7: astore_3
        //   8: aload_2
        //   9: ldc 26
        //   11: invokevirtual 30	android/os/Parcel:writeInterfaceToken	(Ljava/lang/String;)V
        //   14: aload_1
        //   15: ifnull +43 -> 58
        //   18: aload_1
        //   19: invokeinterface 49 1 0
        //   24: astore_1
        //   25: aload_2
        //   26: aload_1
        //   27: invokevirtual 52	android/os/Parcel:writeStrongBinder	(Landroid/os/IBinder;)V
        //   30: aload_0
        //   31: getfield 17	com/google/android/gms/b/rz$a$a:a	Landroid/os/IBinder;
        //   34: bipush 11
        //   36: aload_2
        //   37: aload_3
        //   38: iconst_0
        //   39: invokeinterface 36 5 0
        //   44: pop
        //   45: aload_3
        //   46: invokevirtual 39	android/os/Parcel:readException	()V
        //   49: aload_3
        //   50: invokevirtual 42	android/os/Parcel:recycle	()V
        //   53: aload_2
        //   54: invokevirtual 42	android/os/Parcel:recycle	()V
        //   57: return
        //   58: aconst_null
        //   59: astore_1
        //   60: goto -35 -> 25
        //   63: astore_1
        //   64: aload_3
        //   65: invokevirtual 42	android/os/Parcel:recycle	()V
        //   68: aload_2
        //   69: invokevirtual 42	android/os/Parcel:recycle	()V
        //   72: aload_1
        //   73: athrow
        // Local variable table:
        //   start	length	slot	name	signature
        //   0	74	0	this	a
        //   0	74	1	parama	a
        //   3	66	2	localParcel1	Parcel
        //   7	58	3	localParcel2	Parcel
        // Exception table:
        //   from	to	target	type
        //   8	14	63	finally
        //   18	25	63	finally
        //   25	49	63	finally
      }
      
      public final void d()
      {
        Parcel localParcel1 = Parcel.obtain();
        Parcel localParcel2 = Parcel.obtain();
        try
        {
          localParcel1.writeInterfaceToken("com.google.android.gms.ads.internal.reward.client.IRewardedVideoAd");
          a.transact(7, localParcel1, localParcel2, 0);
          localParcel2.readException();
          return;
        }
        finally
        {
          localParcel2.recycle();
          localParcel1.recycle();
        }
      }
      
      public final void e()
      {
        Parcel localParcel1 = Parcel.obtain();
        Parcel localParcel2 = Parcel.obtain();
        try
        {
          localParcel1.writeInterfaceToken("com.google.android.gms.ads.internal.reward.client.IRewardedVideoAd");
          a.transact(8, localParcel1, localParcel2, 0);
          localParcel2.readException();
          return;
        }
        finally
        {
          localParcel2.recycle();
          localParcel1.recycle();
        }
      }
    }
  }
}


/* Location:              com/google/android/gms/b/rz.class
 * Java compiler version: 6 (50.0)
 * JD-Core Version:       0.7.1
 */