package com.google.android.gms.b;

import com.google.android.gms.common.internal.c;
import java.net.URL;
import java.util.Map;

final class cv$c
  implements Runnable
{
  private final URL b;
  private final byte[] c;
  private final cv.a d;
  private final String e;
  private final Map f;
  
  public cv$c(cv paramcv, String paramString, URL paramURL, byte[] paramArrayOfByte, Map paramMap, cv.a parama)
  {
    c.a(paramString);
    c.a(paramURL);
    c.a(parama);
    b = paramURL;
    c = paramArrayOfByte;
    d = parama;
    e = paramString;
    f = paramMap;
  }
  
  /* Error */
  public final void run()
  {
    // Byte code:
    //   0: aload_0
    //   1: getfield 20	com/google/android/gms/b/cv$c:a	Lcom/google/android/gms/b/cv;
    //   4: astore_1
    //   5: aload_1
    //   6: invokevirtual 46	com/google/android/gms/b/cv:d	()V
    //   9: iconst_0
    //   10: istore_2
    //   11: aconst_null
    //   12: astore_3
    //   13: aconst_null
    //   14: astore 4
    //   16: iconst_0
    //   17: istore 5
    //   19: aconst_null
    //   20: astore 6
    //   22: aload_0
    //   23: getfield 34	com/google/android/gms/b/cv$c:b	Ljava/net/URL;
    //   26: astore_1
    //   27: aload_1
    //   28: invokevirtual 52	java/net/URL:openConnection	()Ljava/net/URLConnection;
    //   31: astore_1
    //   32: aload_1
    //   33: instanceof 54
    //   36: istore 7
    //   38: iload 7
    //   40: ifne +94 -> 134
    //   43: new 56	java/io/IOException
    //   46: astore_1
    //   47: ldc 58
    //   49: astore 8
    //   51: aload_1
    //   52: aload 8
    //   54: invokespecial 61	java/io/IOException:<init>	(Ljava/lang/String;)V
    //   57: aload_1
    //   58: athrow
    //   59: astore 9
    //   61: aconst_null
    //   62: astore_1
    //   63: aload_1
    //   64: ifnull +7 -> 71
    //   67: aload_1
    //   68: invokevirtual 66	java/io/OutputStream:close	()V
    //   71: aload_3
    //   72: ifnull +7 -> 79
    //   75: aload_3
    //   76: invokevirtual 69	java/net/HttpURLConnection:disconnect	()V
    //   79: aload_0
    //   80: getfield 20	com/google/android/gms/b/cv$c:a	Lcom/google/android/gms/b/cv;
    //   83: invokevirtual 73	com/google/android/gms/b/cv:t	()Lcom/google/android/gms/b/db;
    //   86: astore 10
    //   88: new 75	com/google/android/gms/b/cv$b
    //   91: astore_1
    //   92: aload_0
    //   93: getfield 40	com/google/android/gms/b/cv$c:e	Ljava/lang/String;
    //   96: astore_3
    //   97: aload_0
    //   98: getfield 38	com/google/android/gms/b/cv$c:d	Lcom/google/android/gms/b/cv$a;
    //   101: astore 8
    //   103: aconst_null
    //   104: astore 4
    //   106: iconst_0
    //   107: istore 11
    //   109: aconst_null
    //   110: astore 12
    //   112: aload_1
    //   113: aload_3
    //   114: aload 8
    //   116: iload 5
    //   118: aload 9
    //   120: aconst_null
    //   121: aload 6
    //   123: iconst_0
    //   124: invokespecial 78	com/google/android/gms/b/cv$b:<init>	(Ljava/lang/String;Lcom/google/android/gms/b/cv$a;ILjava/lang/Throwable;[BLjava/util/Map;B)V
    //   127: aload 10
    //   129: aload_1
    //   130: invokevirtual 83	com/google/android/gms/b/db:a	(Ljava/lang/Runnable;)V
    //   133: return
    //   134: aload_1
    //   135: checkcast 54	java/net/HttpURLConnection
    //   138: astore_1
    //   139: iconst_0
    //   140: istore 7
    //   142: aconst_null
    //   143: astore 8
    //   145: aload_1
    //   146: iconst_0
    //   147: invokevirtual 87	java/net/HttpURLConnection:setDefaultUseCaches	(Z)V
    //   150: invokestatic 93	com/google/android/gms/b/cf:Q	()J
    //   153: pop2
    //   154: ldc 94
    //   156: istore 7
    //   158: aload_1
    //   159: iload 7
    //   161: invokevirtual 99	java/net/HttpURLConnection:setConnectTimeout	(I)V
    //   164: invokestatic 102	com/google/android/gms/b/cf:R	()J
    //   167: pop2
    //   168: ldc 103
    //   170: istore 7
    //   172: aload_1
    //   173: iload 7
    //   175: invokevirtual 107	java/net/HttpURLConnection:setReadTimeout	(I)V
    //   178: iconst_0
    //   179: istore 7
    //   181: aconst_null
    //   182: astore 8
    //   184: aload_1
    //   185: iconst_0
    //   186: invokevirtual 110	java/net/HttpURLConnection:setInstanceFollowRedirects	(Z)V
    //   189: iconst_1
    //   190: istore 7
    //   192: aload_1
    //   193: iload 7
    //   195: invokevirtual 114	java/net/HttpURLConnection:setDoInput	(Z)V
    //   198: aload_0
    //   199: getfield 42	com/google/android/gms/b/cv$c:f	Ljava/util/Map;
    //   202: astore_3
    //   203: aload_3
    //   204: ifnull +104 -> 308
    //   207: aload_0
    //   208: getfield 42	com/google/android/gms/b/cv$c:f	Ljava/util/Map;
    //   211: astore_3
    //   212: aload_3
    //   213: invokeinterface 120 1 0
    //   218: astore_3
    //   219: aload_3
    //   220: invokeinterface 126 1 0
    //   225: astore 9
    //   227: aload 9
    //   229: invokeinterface 132 1 0
    //   234: istore_2
    //   235: iload_2
    //   236: ifeq +72 -> 308
    //   239: aload 9
    //   241: invokeinterface 136 1 0
    //   246: astore_3
    //   247: aload_3
    //   248: astore 13
    //   250: aload_3
    //   251: checkcast 138	java/util/Map$Entry
    //   254: astore 13
    //   256: aload 13
    //   258: astore 8
    //   260: aload 13
    //   262: invokeinterface 141 1 0
    //   267: astore_3
    //   268: aload_3
    //   269: checkcast 143	java/lang/String
    //   272: astore_3
    //   273: aload 13
    //   275: invokeinterface 146 1 0
    //   280: astore 8
    //   282: aload 8
    //   284: checkcast 143	java/lang/String
    //   287: astore 8
    //   289: aload_1
    //   290: aload_3
    //   291: aload 8
    //   293: invokevirtual 150	java/net/HttpURLConnection:addRequestProperty	(Ljava/lang/String;Ljava/lang/String;)V
    //   296: goto -69 -> 227
    //   299: astore 9
    //   301: aload_1
    //   302: astore_3
    //   303: aconst_null
    //   304: astore_1
    //   305: goto -242 -> 63
    //   308: aload_0
    //   309: getfield 36	com/google/android/gms/b/cv$c:c	[B
    //   312: astore_3
    //   313: aload_3
    //   314: ifnull +405 -> 719
    //   317: aload_0
    //   318: getfield 20	com/google/android/gms/b/cv$c:a	Lcom/google/android/gms/b/cv;
    //   321: astore_3
    //   322: aload_3
    //   323: invokevirtual 154	com/google/android/gms/b/cv:q	()Lcom/google/android/gms/b/dr;
    //   326: astore_3
    //   327: aload_0
    //   328: getfield 36	com/google/android/gms/b/cv$c:c	[B
    //   331: astore 8
    //   333: aload_3
    //   334: aload 8
    //   336: invokevirtual 159	com/google/android/gms/b/dr:a	([B)[B
    //   339: astore 8
    //   341: aload_0
    //   342: getfield 20	com/google/android/gms/b/cv$c:a	Lcom/google/android/gms/b/cv;
    //   345: astore_3
    //   346: aload_3
    //   347: invokevirtual 163	com/google/android/gms/b/cv:u	()Lcom/google/android/gms/b/cu;
    //   350: astore_3
    //   351: aload_3
    //   352: getfield 169	com/google/android/gms/b/cu:g	Lcom/google/android/gms/b/cu$a;
    //   355: astore_3
    //   356: ldc -85
    //   358: astore 9
    //   360: aload 8
    //   362: arraylength
    //   363: istore 11
    //   365: iload 11
    //   367: invokestatic 177	java/lang/Integer:valueOf	(I)Ljava/lang/Integer;
    //   370: astore 12
    //   372: aload_3
    //   373: aload 9
    //   375: aload 12
    //   377: invokevirtual 182	com/google/android/gms/b/cu$a:a	(Ljava/lang/String;Ljava/lang/Object;)V
    //   380: iconst_1
    //   381: istore_2
    //   382: aload_1
    //   383: iload_2
    //   384: invokevirtual 185	java/net/HttpURLConnection:setDoOutput	(Z)V
    //   387: ldc -69
    //   389: astore_3
    //   390: ldc -67
    //   392: astore 9
    //   394: aload_1
    //   395: aload_3
    //   396: aload 9
    //   398: invokevirtual 150	java/net/HttpURLConnection:addRequestProperty	(Ljava/lang/String;Ljava/lang/String;)V
    //   401: aload 8
    //   403: arraylength
    //   404: istore_2
    //   405: aload_1
    //   406: iload_2
    //   407: invokevirtual 192	java/net/HttpURLConnection:setFixedLengthStreamingMode	(I)V
    //   410: aload_1
    //   411: invokevirtual 195	java/net/HttpURLConnection:connect	()V
    //   414: aload_1
    //   415: invokevirtual 199	java/net/HttpURLConnection:getOutputStream	()Ljava/io/OutputStream;
    //   418: astore_3
    //   419: aload_3
    //   420: aload 8
    //   422: invokevirtual 203	java/io/OutputStream:write	([B)V
    //   425: aload_3
    //   426: invokevirtual 66	java/io/OutputStream:close	()V
    //   429: iconst_0
    //   430: istore_2
    //   431: aconst_null
    //   432: astore_3
    //   433: aload_1
    //   434: invokevirtual 207	java/net/HttpURLConnection:getResponseCode	()I
    //   437: istore 5
    //   439: aload_1
    //   440: invokevirtual 211	java/net/HttpURLConnection:getHeaderFields	()Ljava/util/Map;
    //   443: astore 6
    //   445: aload_1
    //   446: invokestatic 214	com/google/android/gms/b/cv:a	(Ljava/net/HttpURLConnection;)[B
    //   449: astore 4
    //   451: aload_1
    //   452: ifnull +7 -> 459
    //   455: aload_1
    //   456: invokevirtual 69	java/net/HttpURLConnection:disconnect	()V
    //   459: aload_0
    //   460: getfield 20	com/google/android/gms/b/cv$c:a	Lcom/google/android/gms/b/cv;
    //   463: invokevirtual 73	com/google/android/gms/b/cv:t	()Lcom/google/android/gms/b/db;
    //   466: astore 10
    //   468: new 75	com/google/android/gms/b/cv$b
    //   471: astore_1
    //   472: aload_0
    //   473: getfield 40	com/google/android/gms/b/cv$c:e	Ljava/lang/String;
    //   476: astore_3
    //   477: aload_0
    //   478: getfield 38	com/google/android/gms/b/cv$c:d	Lcom/google/android/gms/b/cv$a;
    //   481: astore 8
    //   483: aconst_null
    //   484: astore 9
    //   486: iconst_0
    //   487: istore 11
    //   489: aconst_null
    //   490: astore 12
    //   492: aload_1
    //   493: aload_3
    //   494: aload 8
    //   496: iload 5
    //   498: aconst_null
    //   499: aload 4
    //   501: aload 6
    //   503: iconst_0
    //   504: invokespecial 78	com/google/android/gms/b/cv$b:<init>	(Ljava/lang/String;Lcom/google/android/gms/b/cv$a;ILjava/lang/Throwable;[BLjava/util/Map;B)V
    //   507: aload 10
    //   509: aload_1
    //   510: invokevirtual 83	com/google/android/gms/b/db:a	(Ljava/lang/Runnable;)V
    //   513: goto -380 -> 133
    //   516: astore_1
    //   517: aload_0
    //   518: getfield 20	com/google/android/gms/b/cv$c:a	Lcom/google/android/gms/b/cv;
    //   521: invokevirtual 163	com/google/android/gms/b/cv:u	()Lcom/google/android/gms/b/cu;
    //   524: getfield 216	com/google/android/gms/b/cu:a	Lcom/google/android/gms/b/cu$a;
    //   527: astore 8
    //   529: ldc -38
    //   531: astore 4
    //   533: aload_0
    //   534: getfield 40	com/google/android/gms/b/cv$c:e	Ljava/lang/String;
    //   537: invokestatic 221	com/google/android/gms/b/cu:a	(Ljava/lang/String;)Ljava/lang/Object;
    //   540: astore 12
    //   542: aload 8
    //   544: aload 4
    //   546: aload 12
    //   548: aload_1
    //   549: invokevirtual 224	com/google/android/gms/b/cu$a:a	(Ljava/lang/String;Ljava/lang/Object;Ljava/lang/Object;)V
    //   552: goto -481 -> 71
    //   555: astore 10
    //   557: aconst_null
    //   558: astore_1
    //   559: aload 4
    //   561: ifnull +8 -> 569
    //   564: aload 4
    //   566: invokevirtual 66	java/io/OutputStream:close	()V
    //   569: aload_1
    //   570: ifnull +7 -> 577
    //   573: aload_1
    //   574: invokevirtual 69	java/net/HttpURLConnection:disconnect	()V
    //   577: aload_0
    //   578: getfield 20	com/google/android/gms/b/cv$c:a	Lcom/google/android/gms/b/cv;
    //   581: invokevirtual 73	com/google/android/gms/b/cv:t	()Lcom/google/android/gms/b/db;
    //   584: astore 14
    //   586: new 75	com/google/android/gms/b/cv$b
    //   589: astore_1
    //   590: aload_0
    //   591: getfield 40	com/google/android/gms/b/cv$c:e	Ljava/lang/String;
    //   594: astore_3
    //   595: aload_0
    //   596: getfield 38	com/google/android/gms/b/cv$c:d	Lcom/google/android/gms/b/cv$a;
    //   599: astore 8
    //   601: aload_1
    //   602: aload_3
    //   603: aload 8
    //   605: iload 5
    //   607: aconst_null
    //   608: aconst_null
    //   609: aload 6
    //   611: iconst_0
    //   612: invokespecial 78	com/google/android/gms/b/cv$b:<init>	(Ljava/lang/String;Lcom/google/android/gms/b/cv$a;ILjava/lang/Throwable;[BLjava/util/Map;B)V
    //   615: aload 14
    //   617: aload_1
    //   618: invokevirtual 83	com/google/android/gms/b/db:a	(Ljava/lang/Runnable;)V
    //   621: aload 10
    //   623: athrow
    //   624: astore_3
    //   625: aload_0
    //   626: getfield 20	com/google/android/gms/b/cv$c:a	Lcom/google/android/gms/b/cv;
    //   629: invokevirtual 163	com/google/android/gms/b/cv:u	()Lcom/google/android/gms/b/cu;
    //   632: getfield 216	com/google/android/gms/b/cu:a	Lcom/google/android/gms/b/cu$a;
    //   635: astore 8
    //   637: ldc -38
    //   639: astore 9
    //   641: aload_0
    //   642: getfield 40	com/google/android/gms/b/cv$c:e	Ljava/lang/String;
    //   645: invokestatic 221	com/google/android/gms/b/cu:a	(Ljava/lang/String;)Ljava/lang/Object;
    //   648: astore 4
    //   650: aload 8
    //   652: aload 9
    //   654: aload 4
    //   656: aload_3
    //   657: invokevirtual 224	com/google/android/gms/b/cu$a:a	(Ljava/lang/String;Ljava/lang/Object;Ljava/lang/Object;)V
    //   660: goto -91 -> 569
    //   663: astore_3
    //   664: aload_3
    //   665: astore 10
    //   667: goto -108 -> 559
    //   670: astore 8
    //   672: aload 8
    //   674: astore 10
    //   676: aload_3
    //   677: astore 4
    //   679: goto -120 -> 559
    //   682: astore 8
    //   684: aload 8
    //   686: astore 10
    //   688: aconst_null
    //   689: astore 4
    //   691: goto -132 -> 559
    //   694: astore 9
    //   696: aload_3
    //   697: astore 15
    //   699: aload_1
    //   700: astore_3
    //   701: aload 15
    //   703: astore_1
    //   704: goto -641 -> 63
    //   707: astore 9
    //   709: aconst_null
    //   710: astore 15
    //   712: aload_1
    //   713: astore_3
    //   714: aconst_null
    //   715: astore_1
    //   716: goto -653 -> 63
    //   719: iconst_0
    //   720: istore_2
    //   721: aconst_null
    //   722: astore_3
    //   723: goto -290 -> 433
    // Local variable table:
    //   start	length	slot	name	signature
    //   0	726	0	this	c
    //   4	506	1	localObject1	Object
    //   516	33	1	localIOException1	java.io.IOException
    //   558	158	1	localObject2	Object
    //   10	374	2	bool1	boolean
    //   404	317	2	i	int
    //   12	591	3	localObject3	Object
    //   624	33	3	localIOException2	java.io.IOException
    //   663	34	3	localObject4	Object
    //   700	23	3	localObject5	Object
    //   14	676	4	localObject6	Object
    //   17	589	5	j	int
    //   20	590	6	localMap	Map
    //   36	105	7	bool2	boolean
    //   156	38	7	k	int
    //   49	602	8	localObject7	Object
    //   670	3	8	localObject8	Object
    //   682	3	8	localObject9	Object
    //   59	60	9	localIOException3	java.io.IOException
    //   225	15	9	localIterator	java.util.Iterator
    //   299	1	9	localIOException4	java.io.IOException
    //   358	295	9	str	String
    //   694	1	9	localIOException5	java.io.IOException
    //   707	1	9	localIOException6	java.io.IOException
    //   86	422	10	localdb1	db
    //   555	67	10	localObject10	Object
    //   665	22	10	localObject11	Object
    //   107	381	11	m	int
    //   110	437	12	localObject12	Object
    //   248	26	13	localObject13	Object
    //   584	32	14	localdb2	db
    //   697	14	15	localObject14	Object
    // Exception table:
    //   from	to	target	type
    //   22	26	59	java/io/IOException
    //   27	31	59	java/io/IOException
    //   43	46	59	java/io/IOException
    //   52	57	59	java/io/IOException
    //   57	59	59	java/io/IOException
    //   134	138	59	java/io/IOException
    //   146	150	59	java/io/IOException
    //   150	154	59	java/io/IOException
    //   159	164	59	java/io/IOException
    //   164	168	59	java/io/IOException
    //   173	178	59	java/io/IOException
    //   185	189	59	java/io/IOException
    //   193	198	59	java/io/IOException
    //   198	202	299	java/io/IOException
    //   207	211	299	java/io/IOException
    //   212	218	299	java/io/IOException
    //   219	225	299	java/io/IOException
    //   227	234	299	java/io/IOException
    //   239	246	299	java/io/IOException
    //   250	254	299	java/io/IOException
    //   260	267	299	java/io/IOException
    //   268	272	299	java/io/IOException
    //   273	280	299	java/io/IOException
    //   282	287	299	java/io/IOException
    //   291	296	299	java/io/IOException
    //   308	312	299	java/io/IOException
    //   317	321	299	java/io/IOException
    //   322	326	299	java/io/IOException
    //   327	331	299	java/io/IOException
    //   334	339	299	java/io/IOException
    //   341	345	299	java/io/IOException
    //   346	350	299	java/io/IOException
    //   351	355	299	java/io/IOException
    //   360	363	299	java/io/IOException
    //   365	370	299	java/io/IOException
    //   375	380	299	java/io/IOException
    //   383	387	299	java/io/IOException
    //   396	401	299	java/io/IOException
    //   401	404	299	java/io/IOException
    //   406	410	299	java/io/IOException
    //   410	414	299	java/io/IOException
    //   414	418	299	java/io/IOException
    //   67	71	516	java/io/IOException
    //   22	26	555	finally
    //   27	31	555	finally
    //   43	46	555	finally
    //   52	57	555	finally
    //   57	59	555	finally
    //   134	138	555	finally
    //   146	150	555	finally
    //   150	154	555	finally
    //   159	164	555	finally
    //   164	168	555	finally
    //   173	178	555	finally
    //   185	189	555	finally
    //   193	198	555	finally
    //   564	569	624	java/io/IOException
    //   198	202	663	finally
    //   207	211	663	finally
    //   212	218	663	finally
    //   219	225	663	finally
    //   227	234	663	finally
    //   239	246	663	finally
    //   250	254	663	finally
    //   260	267	663	finally
    //   268	272	663	finally
    //   273	280	663	finally
    //   282	287	663	finally
    //   291	296	663	finally
    //   308	312	663	finally
    //   317	321	663	finally
    //   322	326	663	finally
    //   327	331	663	finally
    //   334	339	663	finally
    //   341	345	663	finally
    //   346	350	663	finally
    //   351	355	663	finally
    //   360	363	663	finally
    //   365	370	663	finally
    //   375	380	663	finally
    //   383	387	663	finally
    //   396	401	663	finally
    //   401	404	663	finally
    //   406	410	663	finally
    //   410	414	663	finally
    //   414	418	663	finally
    //   420	425	670	finally
    //   425	429	670	finally
    //   433	437	682	finally
    //   439	443	682	finally
    //   445	449	682	finally
    //   420	425	694	java/io/IOException
    //   425	429	694	java/io/IOException
    //   433	437	707	java/io/IOException
    //   439	443	707	java/io/IOException
    //   445	449	707	java/io/IOException
  }
}


/* Location:              com/google/android/gms/b/cv$c.class
 * Java compiler version: 5 (49.0)
 * JD-Core Version:       0.7.1
 */