package com.google.android.gms.b;

import com.google.android.gms.common.internal.c;
import java.util.concurrent.BlockingQueue;

final class db$d
  extends Thread
{
  private final Object b;
  private final BlockingQueue c;
  
  public db$d(db paramdb, String paramString, BlockingQueue paramBlockingQueue)
  {
    c.a(paramString);
    c.a(paramBlockingQueue);
    Object localObject = new java/lang/Object;
    localObject.<init>();
    b = localObject;
    c = paramBlockingQueue;
    setName(paramString);
  }
  
  private void a(InterruptedException paramInterruptedException)
  {
    cu.a locala = a.u().c;
    String str = String.valueOf(getName()).concat(" was interrupted");
    locala.a(str, paramInterruptedException);
  }
  
  public final void a()
  {
    synchronized (b)
    {
      Object localObject2 = b;
      localObject2.notifyAll();
      return;
    }
  }
  
  /* Error */
  public final void run()
  {
    // Byte code:
    //   0: iconst_0
    //   1: istore_1
    //   2: aconst_null
    //   3: astore_2
    //   4: iconst_0
    //   5: istore_3
    //   6: aconst_null
    //   7: astore 4
    //   9: iload_3
    //   10: ifne +33 -> 43
    //   13: aload_0
    //   14: getfield 12	com/google/android/gms/b/db$d:a	Lcom/google/android/gms/b/db;
    //   17: astore_2
    //   18: aload_2
    //   19: invokestatic 70	com/google/android/gms/b/db:a	(Lcom/google/android/gms/b/db;)Ljava/util/concurrent/Semaphore;
    //   22: astore_2
    //   23: aload_2
    //   24: invokevirtual 75	java/util/concurrent/Semaphore:acquire	()V
    //   27: iconst_1
    //   28: istore_1
    //   29: iload_1
    //   30: istore_3
    //   31: goto -22 -> 9
    //   34: astore_2
    //   35: aload_0
    //   36: aload_2
    //   37: invokespecial 79	com/google/android/gms/b/db$d:a	(Ljava/lang/InterruptedException;)V
    //   40: goto -31 -> 9
    //   43: aload_0
    //   44: getfield 28	com/google/android/gms/b/db$d:c	Ljava/util/concurrent/BlockingQueue;
    //   47: astore_2
    //   48: aload_2
    //   49: invokeinterface 85 1 0
    //   54: astore_2
    //   55: aload_2
    //   56: checkcast 87	java/util/concurrent/FutureTask
    //   59: astore_2
    //   60: aload_2
    //   61: ifnull +95 -> 156
    //   64: aload_2
    //   65: invokevirtual 90	java/util/concurrent/FutureTask:run	()V
    //   68: goto -25 -> 43
    //   71: astore_2
    //   72: aload_0
    //   73: getfield 12	com/google/android/gms/b/db$d:a	Lcom/google/android/gms/b/db;
    //   76: invokestatic 93	com/google/android/gms/b/db:c	(Lcom/google/android/gms/b/db;)Ljava/lang/Object;
    //   79: astore 4
    //   81: aload 4
    //   83: monitorenter
    //   84: aload_0
    //   85: getfield 12	com/google/android/gms/b/db$d:a	Lcom/google/android/gms/b/db;
    //   88: astore 5
    //   90: aload 5
    //   92: invokestatic 70	com/google/android/gms/b/db:a	(Lcom/google/android/gms/b/db;)Ljava/util/concurrent/Semaphore;
    //   95: astore 5
    //   97: aload 5
    //   99: invokevirtual 96	java/util/concurrent/Semaphore:release	()V
    //   102: aload_0
    //   103: getfield 12	com/google/android/gms/b/db$d:a	Lcom/google/android/gms/b/db;
    //   106: astore 5
    //   108: aload 5
    //   110: invokestatic 93	com/google/android/gms/b/db:c	(Lcom/google/android/gms/b/db;)Ljava/lang/Object;
    //   113: astore 5
    //   115: aload 5
    //   117: invokevirtual 67	java/lang/Object:notifyAll	()V
    //   120: aload_0
    //   121: getfield 12	com/google/android/gms/b/db$d:a	Lcom/google/android/gms/b/db;
    //   124: astore 5
    //   126: aload 5
    //   128: invokestatic 100	com/google/android/gms/b/db:d	(Lcom/google/android/gms/b/db;)Lcom/google/android/gms/b/db$d;
    //   131: astore 5
    //   133: aload_0
    //   134: aload 5
    //   136: if_acmpne +271 -> 407
    //   139: aload_0
    //   140: getfield 12	com/google/android/gms/b/db$d:a	Lcom/google/android/gms/b/db;
    //   143: astore 5
    //   145: aload 5
    //   147: invokestatic 103	com/google/android/gms/b/db:e	(Lcom/google/android/gms/b/db;)Lcom/google/android/gms/b/db$d;
    //   150: pop
    //   151: aload 4
    //   153: monitorexit
    //   154: aload_2
    //   155: athrow
    //   156: aload_0
    //   157: getfield 26	com/google/android/gms/b/db$d:b	Ljava/lang/Object;
    //   160: astore 4
    //   162: aload 4
    //   164: monitorenter
    //   165: aload_0
    //   166: getfield 28	com/google/android/gms/b/db$d:c	Ljava/util/concurrent/BlockingQueue;
    //   169: astore_2
    //   170: aload_2
    //   171: invokeinterface 106 1 0
    //   176: astore_2
    //   177: aload_2
    //   178: ifnonnull +33 -> 211
    //   181: aload_0
    //   182: getfield 12	com/google/android/gms/b/db$d:a	Lcom/google/android/gms/b/db;
    //   185: astore_2
    //   186: aload_2
    //   187: invokestatic 109	com/google/android/gms/b/db:b	(Lcom/google/android/gms/b/db;)Z
    //   190: istore_1
    //   191: iload_1
    //   192: ifne +19 -> 211
    //   195: aload_0
    //   196: getfield 26	com/google/android/gms/b/db$d:b	Ljava/lang/Object;
    //   199: astore_2
    //   200: ldc2_w 110
    //   203: lstore 6
    //   205: aload_2
    //   206: lload 6
    //   208: invokevirtual 117	java/lang/Object:wait	(J)V
    //   211: aload 4
    //   213: monitorexit
    //   214: aload_0
    //   215: getfield 12	com/google/android/gms/b/db$d:a	Lcom/google/android/gms/b/db;
    //   218: astore_2
    //   219: aload_2
    //   220: invokestatic 93	com/google/android/gms/b/db:c	(Lcom/google/android/gms/b/db;)Ljava/lang/Object;
    //   223: astore 4
    //   225: aload 4
    //   227: monitorenter
    //   228: aload_0
    //   229: getfield 28	com/google/android/gms/b/db$d:c	Ljava/util/concurrent/BlockingQueue;
    //   232: astore_2
    //   233: aload_2
    //   234: invokeinterface 106 1 0
    //   239: astore_2
    //   240: aload_2
    //   241: ifnonnull +154 -> 395
    //   244: aload 4
    //   246: monitorexit
    //   247: aload_0
    //   248: getfield 12	com/google/android/gms/b/db$d:a	Lcom/google/android/gms/b/db;
    //   251: astore_2
    //   252: aload_2
    //   253: invokestatic 93	com/google/android/gms/b/db:c	(Lcom/google/android/gms/b/db;)Ljava/lang/Object;
    //   256: astore 4
    //   258: aload 4
    //   260: monitorenter
    //   261: aload_0
    //   262: getfield 12	com/google/android/gms/b/db$d:a	Lcom/google/android/gms/b/db;
    //   265: astore_2
    //   266: aload_2
    //   267: invokestatic 70	com/google/android/gms/b/db:a	(Lcom/google/android/gms/b/db;)Ljava/util/concurrent/Semaphore;
    //   270: astore_2
    //   271: aload_2
    //   272: invokevirtual 96	java/util/concurrent/Semaphore:release	()V
    //   275: aload_0
    //   276: getfield 12	com/google/android/gms/b/db$d:a	Lcom/google/android/gms/b/db;
    //   279: astore_2
    //   280: aload_2
    //   281: invokestatic 93	com/google/android/gms/b/db:c	(Lcom/google/android/gms/b/db;)Ljava/lang/Object;
    //   284: astore_2
    //   285: aload_2
    //   286: invokevirtual 67	java/lang/Object:notifyAll	()V
    //   289: aload_0
    //   290: getfield 12	com/google/android/gms/b/db$d:a	Lcom/google/android/gms/b/db;
    //   293: astore_2
    //   294: aload_2
    //   295: invokestatic 100	com/google/android/gms/b/db:d	(Lcom/google/android/gms/b/db;)Lcom/google/android/gms/b/db$d;
    //   298: astore_2
    //   299: aload_0
    //   300: aload_2
    //   301: if_acmpne +32 -> 333
    //   304: aload_0
    //   305: getfield 12	com/google/android/gms/b/db$d:a	Lcom/google/android/gms/b/db;
    //   308: astore_2
    //   309: aload_2
    //   310: invokestatic 103	com/google/android/gms/b/db:e	(Lcom/google/android/gms/b/db;)Lcom/google/android/gms/b/db$d;
    //   313: pop
    //   314: aload 4
    //   316: monitorexit
    //   317: return
    //   318: astore_2
    //   319: aload_0
    //   320: aload_2
    //   321: invokespecial 79	com/google/android/gms/b/db$d:a	(Ljava/lang/InterruptedException;)V
    //   324: goto -113 -> 211
    //   327: astore_2
    //   328: aload 4
    //   330: monitorexit
    //   331: aload_2
    //   332: athrow
    //   333: aload_0
    //   334: getfield 12	com/google/android/gms/b/db$d:a	Lcom/google/android/gms/b/db;
    //   337: astore_2
    //   338: aload_2
    //   339: invokestatic 120	com/google/android/gms/b/db:f	(Lcom/google/android/gms/b/db;)Lcom/google/android/gms/b/db$d;
    //   342: astore_2
    //   343: aload_0
    //   344: aload_2
    //   345: if_acmpne +22 -> 367
    //   348: aload_0
    //   349: getfield 12	com/google/android/gms/b/db$d:a	Lcom/google/android/gms/b/db;
    //   352: astore_2
    //   353: aload_2
    //   354: invokestatic 123	com/google/android/gms/b/db:g	(Lcom/google/android/gms/b/db;)Lcom/google/android/gms/b/db$d;
    //   357: pop
    //   358: goto -44 -> 314
    //   361: astore_2
    //   362: aload 4
    //   364: monitorexit
    //   365: aload_2
    //   366: athrow
    //   367: aload_0
    //   368: getfield 12	com/google/android/gms/b/db$d:a	Lcom/google/android/gms/b/db;
    //   371: astore_2
    //   372: aload_2
    //   373: invokevirtual 38	com/google/android/gms/b/db:u	()Lcom/google/android/gms/b/cu;
    //   376: astore_2
    //   377: aload_2
    //   378: getfield 125	com/google/android/gms/b/cu:a	Lcom/google/android/gms/b/cu$a;
    //   381: astore_2
    //   382: ldc 127
    //   384: astore 5
    //   386: aload_2
    //   387: aload 5
    //   389: invokevirtual 129	com/google/android/gms/b/cu$a:a	(Ljava/lang/String;)V
    //   392: goto -78 -> 314
    //   395: aload 4
    //   397: monitorexit
    //   398: goto -355 -> 43
    //   401: astore_2
    //   402: aload 4
    //   404: monitorexit
    //   405: aload_2
    //   406: athrow
    //   407: aload_0
    //   408: getfield 12	com/google/android/gms/b/db$d:a	Lcom/google/android/gms/b/db;
    //   411: astore 5
    //   413: aload 5
    //   415: invokestatic 120	com/google/android/gms/b/db:f	(Lcom/google/android/gms/b/db;)Lcom/google/android/gms/b/db$d;
    //   418: astore 5
    //   420: aload_0
    //   421: aload 5
    //   423: if_acmpne +24 -> 447
    //   426: aload_0
    //   427: getfield 12	com/google/android/gms/b/db$d:a	Lcom/google/android/gms/b/db;
    //   430: astore 5
    //   432: aload 5
    //   434: invokestatic 123	com/google/android/gms/b/db:g	(Lcom/google/android/gms/b/db;)Lcom/google/android/gms/b/db$d;
    //   437: pop
    //   438: goto -287 -> 151
    //   441: astore_2
    //   442: aload 4
    //   444: monitorexit
    //   445: aload_2
    //   446: athrow
    //   447: aload_0
    //   448: getfield 12	com/google/android/gms/b/db$d:a	Lcom/google/android/gms/b/db;
    //   451: astore 5
    //   453: aload 5
    //   455: invokevirtual 38	com/google/android/gms/b/db:u	()Lcom/google/android/gms/b/cu;
    //   458: astore 5
    //   460: aload 5
    //   462: getfield 125	com/google/android/gms/b/cu:a	Lcom/google/android/gms/b/cu$a;
    //   465: astore 5
    //   467: ldc 127
    //   469: astore 8
    //   471: aload 5
    //   473: aload 8
    //   475: invokevirtual 129	com/google/android/gms/b/cu$a:a	(Ljava/lang/String;)V
    //   478: goto -327 -> 151
    // Local variable table:
    //   start	length	slot	name	signature
    //   0	481	0	this	d
    //   1	191	1	bool	boolean
    //   3	21	2	localObject1	Object
    //   34	3	2	localInterruptedException1	InterruptedException
    //   47	18	2	localObject2	Object
    //   71	84	2	localObject3	Object
    //   169	141	2	localObject4	Object
    //   318	3	2	localInterruptedException2	InterruptedException
    //   327	5	2	localObject5	Object
    //   337	17	2	localObject6	Object
    //   361	5	2	localObject7	Object
    //   371	16	2	localObject8	Object
    //   401	5	2	localObject9	Object
    //   441	5	2	localObject10	Object
    //   5	26	3	i	int
    //   88	384	5	localObject12	Object
    //   203	4	6	l	long
    //   469	5	8	str	String
    // Exception table:
    //   from	to	target	type
    //   13	17	34	java/lang/InterruptedException
    //   18	22	34	java/lang/InterruptedException
    //   23	27	34	java/lang/InterruptedException
    //   43	47	71	finally
    //   48	54	71	finally
    //   55	59	71	finally
    //   64	68	71	finally
    //   156	160	71	finally
    //   162	165	71	finally
    //   214	218	71	finally
    //   219	223	71	finally
    //   225	228	71	finally
    //   331	333	71	finally
    //   405	407	71	finally
    //   195	199	318	java/lang/InterruptedException
    //   206	211	318	java/lang/InterruptedException
    //   165	169	327	finally
    //   170	176	327	finally
    //   181	185	327	finally
    //   186	190	327	finally
    //   195	199	327	finally
    //   206	211	327	finally
    //   211	214	327	finally
    //   320	324	327	finally
    //   328	331	327	finally
    //   261	265	361	finally
    //   266	270	361	finally
    //   271	275	361	finally
    //   275	279	361	finally
    //   280	284	361	finally
    //   285	289	361	finally
    //   289	293	361	finally
    //   294	298	361	finally
    //   304	308	361	finally
    //   309	314	361	finally
    //   314	317	361	finally
    //   333	337	361	finally
    //   338	342	361	finally
    //   348	352	361	finally
    //   353	358	361	finally
    //   362	365	361	finally
    //   367	371	361	finally
    //   372	376	361	finally
    //   377	381	361	finally
    //   387	392	361	finally
    //   228	232	401	finally
    //   233	239	401	finally
    //   244	247	401	finally
    //   395	398	401	finally
    //   402	405	401	finally
    //   84	88	441	finally
    //   90	95	441	finally
    //   97	102	441	finally
    //   102	106	441	finally
    //   108	113	441	finally
    //   115	120	441	finally
    //   120	124	441	finally
    //   126	131	441	finally
    //   139	143	441	finally
    //   145	151	441	finally
    //   151	154	441	finally
    //   407	411	441	finally
    //   413	418	441	finally
    //   426	430	441	finally
    //   432	438	441	finally
    //   442	445	441	finally
    //   447	451	441	finally
    //   453	458	441	finally
    //   460	465	441	finally
    //   473	478	441	finally
  }
}


/* Location:              com/google/android/gms/b/db$d.class
 * Java compiler version: 5 (49.0)
 * JD-Core Version:       0.7.1
 */