package com.google.android.gms.b;

import android.os.IBinder;
import android.os.Parcel;
import com.google.android.gms.a.a;
import com.google.android.gms.a.a.a;

final class ix$a$a
  implements ix
{
  private IBinder a;
  
  ix$a$a(IBinder paramIBinder)
  {
    a = paramIBinder;
  }
  
  public final String F()
  {
    Parcel localParcel1 = Parcel.obtain();
    Parcel localParcel2 = Parcel.obtain();
    Object localObject1 = "com.google.android.gms.ads.internal.client.IAdManager";
    try
    {
      localParcel1.writeInterfaceToken((String)localObject1);
      localObject1 = a;
      int i = 18;
      ((IBinder)localObject1).transact(i, localParcel1, localParcel2, 0);
      localParcel2.readException();
      localObject1 = localParcel2.readString();
      return (String)localObject1;
    }
    finally
    {
      localParcel2.recycle();
      localParcel1.recycle();
    }
  }
  
  public final void G()
  {
    Parcel localParcel1 = Parcel.obtain();
    Parcel localParcel2 = Parcel.obtain();
    Object localObject1 = "com.google.android.gms.ads.internal.client.IAdManager";
    try
    {
      localParcel1.writeInterfaceToken((String)localObject1);
      localObject1 = a;
      int i = 9;
      ((IBinder)localObject1).transact(i, localParcel1, localParcel2, 0);
      localParcel2.readException();
      return;
    }
    finally
    {
      localParcel2.recycle();
      localParcel1.recycle();
    }
  }
  
  /* Error */
  public final void a(il paramil)
  {
    // Byte code:
    //   0: invokestatic 20	android/os/Parcel:obtain	()Landroid/os/Parcel;
    //   3: astore_2
    //   4: invokestatic 20	android/os/Parcel:obtain	()Landroid/os/Parcel;
    //   7: astore_3
    //   8: ldc 22
    //   10: astore 4
    //   12: aload_2
    //   13: aload 4
    //   15: invokevirtual 26	android/os/Parcel:writeInterfaceToken	(Ljava/lang/String;)V
    //   18: aload_1
    //   19: ifnull +60 -> 79
    //   22: iconst_1
    //   23: istore 5
    //   25: aload_2
    //   26: iload 5
    //   28: invokevirtual 49	android/os/Parcel:writeInt	(I)V
    //   31: iconst_0
    //   32: istore 5
    //   34: aconst_null
    //   35: astore 4
    //   37: aload_1
    //   38: aload_2
    //   39: iconst_0
    //   40: invokevirtual 55	com/google/android/gms/b/il:writeToParcel	(Landroid/os/Parcel;I)V
    //   43: aload_0
    //   44: getfield 14	com/google/android/gms/b/ix$a$a:a	Landroid/os/IBinder;
    //   47: astore 4
    //   49: bipush 13
    //   51: istore 6
    //   53: aload 4
    //   55: iload 6
    //   57: aload_2
    //   58: aload_3
    //   59: iconst_0
    //   60: invokeinterface 33 5 0
    //   65: pop
    //   66: aload_3
    //   67: invokevirtual 36	android/os/Parcel:readException	()V
    //   70: aload_3
    //   71: invokevirtual 43	android/os/Parcel:recycle	()V
    //   74: aload_2
    //   75: invokevirtual 43	android/os/Parcel:recycle	()V
    //   78: return
    //   79: iconst_0
    //   80: istore 5
    //   82: aconst_null
    //   83: astore 4
    //   85: aload_2
    //   86: iconst_0
    //   87: invokevirtual 49	android/os/Parcel:writeInt	(I)V
    //   90: goto -47 -> 43
    //   93: astore 4
    //   95: aload_3
    //   96: invokevirtual 43	android/os/Parcel:recycle	()V
    //   99: aload_2
    //   100: invokevirtual 43	android/os/Parcel:recycle	()V
    //   103: aload 4
    //   105: athrow
    // Local variable table:
    //   start	length	slot	name	signature
    //   0	106	0	this	a
    //   0	106	1	paramil	il
    //   3	97	2	localParcel1	Parcel
    //   7	89	3	localParcel2	Parcel
    //   10	74	4	localObject1	Object
    //   93	11	4	localObject2	Object
    //   23	58	5	i	int
    //   51	5	6	j	int
    // Exception table:
    //   from	to	target	type
    //   13	18	93	finally
    //   26	31	93	finally
    //   39	43	93	finally
    //   43	47	93	finally
    //   59	66	93	finally
    //   66	70	93	finally
    //   86	90	93	finally
  }
  
  /* Error */
  public final void a(is paramis)
  {
    // Byte code:
    //   0: invokestatic 20	android/os/Parcel:obtain	()Landroid/os/Parcel;
    //   3: astore_2
    //   4: invokestatic 20	android/os/Parcel:obtain	()Landroid/os/Parcel;
    //   7: astore_3
    //   8: ldc 22
    //   10: astore 4
    //   12: aload_2
    //   13: aload 4
    //   15: invokevirtual 26	android/os/Parcel:writeInterfaceToken	(Ljava/lang/String;)V
    //   18: aload_1
    //   19: ifnull +53 -> 72
    //   22: aload_1
    //   23: invokeinterface 62 1 0
    //   28: astore 4
    //   30: aload_2
    //   31: aload 4
    //   33: invokevirtual 66	android/os/Parcel:writeStrongBinder	(Landroid/os/IBinder;)V
    //   36: aload_0
    //   37: getfield 14	com/google/android/gms/b/ix$a$a:a	Landroid/os/IBinder;
    //   40: astore 4
    //   42: bipush 20
    //   44: istore 5
    //   46: aload 4
    //   48: iload 5
    //   50: aload_2
    //   51: aload_3
    //   52: iconst_0
    //   53: invokeinterface 33 5 0
    //   58: pop
    //   59: aload_3
    //   60: invokevirtual 36	android/os/Parcel:readException	()V
    //   63: aload_3
    //   64: invokevirtual 43	android/os/Parcel:recycle	()V
    //   67: aload_2
    //   68: invokevirtual 43	android/os/Parcel:recycle	()V
    //   71: return
    //   72: aconst_null
    //   73: astore 4
    //   75: goto -45 -> 30
    //   78: astore 4
    //   80: aload_3
    //   81: invokevirtual 43	android/os/Parcel:recycle	()V
    //   84: aload_2
    //   85: invokevirtual 43	android/os/Parcel:recycle	()V
    //   88: aload 4
    //   90: athrow
    // Local variable table:
    //   start	length	slot	name	signature
    //   0	91	0	this	a
    //   0	91	1	paramis	is
    //   3	82	2	localParcel1	Parcel
    //   7	74	3	localParcel2	Parcel
    //   10	64	4	localObject1	Object
    //   78	11	4	localObject2	Object
    //   44	5	5	i	int
    // Exception table:
    //   from	to	target	type
    //   13	18	78	finally
    //   22	28	78	finally
    //   31	36	78	finally
    //   36	40	78	finally
    //   52	59	78	finally
    //   59	63	78	finally
  }
  
  /* Error */
  public final void a(it paramit)
  {
    // Byte code:
    //   0: invokestatic 20	android/os/Parcel:obtain	()Landroid/os/Parcel;
    //   3: astore_2
    //   4: invokestatic 20	android/os/Parcel:obtain	()Landroid/os/Parcel;
    //   7: astore_3
    //   8: ldc 22
    //   10: astore 4
    //   12: aload_2
    //   13: aload 4
    //   15: invokevirtual 26	android/os/Parcel:writeInterfaceToken	(Ljava/lang/String;)V
    //   18: aload_1
    //   19: ifnull +53 -> 72
    //   22: aload_1
    //   23: invokeinterface 70 1 0
    //   28: astore 4
    //   30: aload_2
    //   31: aload 4
    //   33: invokevirtual 66	android/os/Parcel:writeStrongBinder	(Landroid/os/IBinder;)V
    //   36: aload_0
    //   37: getfield 14	com/google/android/gms/b/ix$a$a:a	Landroid/os/IBinder;
    //   40: astore 4
    //   42: bipush 7
    //   44: istore 5
    //   46: aload 4
    //   48: iload 5
    //   50: aload_2
    //   51: aload_3
    //   52: iconst_0
    //   53: invokeinterface 33 5 0
    //   58: pop
    //   59: aload_3
    //   60: invokevirtual 36	android/os/Parcel:readException	()V
    //   63: aload_3
    //   64: invokevirtual 43	android/os/Parcel:recycle	()V
    //   67: aload_2
    //   68: invokevirtual 43	android/os/Parcel:recycle	()V
    //   71: return
    //   72: aconst_null
    //   73: astore 4
    //   75: goto -45 -> 30
    //   78: astore 4
    //   80: aload_3
    //   81: invokevirtual 43	android/os/Parcel:recycle	()V
    //   84: aload_2
    //   85: invokevirtual 43	android/os/Parcel:recycle	()V
    //   88: aload 4
    //   90: athrow
    // Local variable table:
    //   start	length	slot	name	signature
    //   0	91	0	this	a
    //   0	91	1	paramit	it
    //   3	82	2	localParcel1	Parcel
    //   7	74	3	localParcel2	Parcel
    //   10	64	4	localObject1	Object
    //   78	11	4	localObject2	Object
    //   44	5	5	i	int
    // Exception table:
    //   from	to	target	type
    //   13	18	78	finally
    //   22	28	78	finally
    //   31	36	78	finally
    //   36	40	78	finally
    //   52	59	78	finally
    //   59	63	78	finally
  }
  
  /* Error */
  public final void a(iz paramiz)
  {
    // Byte code:
    //   0: invokestatic 20	android/os/Parcel:obtain	()Landroid/os/Parcel;
    //   3: astore_2
    //   4: invokestatic 20	android/os/Parcel:obtain	()Landroid/os/Parcel;
    //   7: astore_3
    //   8: ldc 22
    //   10: astore 4
    //   12: aload_2
    //   13: aload 4
    //   15: invokevirtual 26	android/os/Parcel:writeInterfaceToken	(Ljava/lang/String;)V
    //   18: aload_1
    //   19: ifnull +53 -> 72
    //   22: aload_1
    //   23: invokeinterface 74 1 0
    //   28: astore 4
    //   30: aload_2
    //   31: aload 4
    //   33: invokevirtual 66	android/os/Parcel:writeStrongBinder	(Landroid/os/IBinder;)V
    //   36: aload_0
    //   37: getfield 14	com/google/android/gms/b/ix$a$a:a	Landroid/os/IBinder;
    //   40: astore 4
    //   42: bipush 8
    //   44: istore 5
    //   46: aload 4
    //   48: iload 5
    //   50: aload_2
    //   51: aload_3
    //   52: iconst_0
    //   53: invokeinterface 33 5 0
    //   58: pop
    //   59: aload_3
    //   60: invokevirtual 36	android/os/Parcel:readException	()V
    //   63: aload_3
    //   64: invokevirtual 43	android/os/Parcel:recycle	()V
    //   67: aload_2
    //   68: invokevirtual 43	android/os/Parcel:recycle	()V
    //   71: return
    //   72: aconst_null
    //   73: astore 4
    //   75: goto -45 -> 30
    //   78: astore 4
    //   80: aload_3
    //   81: invokevirtual 43	android/os/Parcel:recycle	()V
    //   84: aload_2
    //   85: invokevirtual 43	android/os/Parcel:recycle	()V
    //   88: aload 4
    //   90: athrow
    // Local variable table:
    //   start	length	slot	name	signature
    //   0	91	0	this	a
    //   0	91	1	paramiz	iz
    //   3	82	2	localParcel1	Parcel
    //   7	74	3	localParcel2	Parcel
    //   10	64	4	localObject1	Object
    //   78	11	4	localObject2	Object
    //   44	5	5	i	int
    // Exception table:
    //   from	to	target	type
    //   13	18	78	finally
    //   22	28	78	finally
    //   31	36	78	finally
    //   36	40	78	finally
    //   52	59	78	finally
    //   59	63	78	finally
  }
  
  /* Error */
  public final void a(jb paramjb)
  {
    // Byte code:
    //   0: invokestatic 20	android/os/Parcel:obtain	()Landroid/os/Parcel;
    //   3: astore_2
    //   4: invokestatic 20	android/os/Parcel:obtain	()Landroid/os/Parcel;
    //   7: astore_3
    //   8: ldc 22
    //   10: astore 4
    //   12: aload_2
    //   13: aload 4
    //   15: invokevirtual 26	android/os/Parcel:writeInterfaceToken	(Ljava/lang/String;)V
    //   18: aload_1
    //   19: ifnull +53 -> 72
    //   22: aload_1
    //   23: invokeinterface 78 1 0
    //   28: astore 4
    //   30: aload_2
    //   31: aload 4
    //   33: invokevirtual 66	android/os/Parcel:writeStrongBinder	(Landroid/os/IBinder;)V
    //   36: aload_0
    //   37: getfield 14	com/google/android/gms/b/ix$a$a:a	Landroid/os/IBinder;
    //   40: astore 4
    //   42: bipush 21
    //   44: istore 5
    //   46: aload 4
    //   48: iload 5
    //   50: aload_2
    //   51: aload_3
    //   52: iconst_0
    //   53: invokeinterface 33 5 0
    //   58: pop
    //   59: aload_3
    //   60: invokevirtual 36	android/os/Parcel:readException	()V
    //   63: aload_3
    //   64: invokevirtual 43	android/os/Parcel:recycle	()V
    //   67: aload_2
    //   68: invokevirtual 43	android/os/Parcel:recycle	()V
    //   71: return
    //   72: aconst_null
    //   73: astore 4
    //   75: goto -45 -> 30
    //   78: astore 4
    //   80: aload_3
    //   81: invokevirtual 43	android/os/Parcel:recycle	()V
    //   84: aload_2
    //   85: invokevirtual 43	android/os/Parcel:recycle	()V
    //   88: aload 4
    //   90: athrow
    // Local variable table:
    //   start	length	slot	name	signature
    //   0	91	0	this	a
    //   0	91	1	paramjb	jb
    //   3	82	2	localParcel1	Parcel
    //   7	74	3	localParcel2	Parcel
    //   10	64	4	localObject1	Object
    //   78	11	4	localObject2	Object
    //   44	5	5	i	int
    // Exception table:
    //   from	to	target	type
    //   13	18	78	finally
    //   22	28	78	finally
    //   31	36	78	finally
    //   36	40	78	finally
    //   52	59	78	finally
    //   59	63	78	finally
  }
  
  /* Error */
  public final void a(jh paramjh)
  {
    // Byte code:
    //   0: invokestatic 20	android/os/Parcel:obtain	()Landroid/os/Parcel;
    //   3: astore_2
    //   4: invokestatic 20	android/os/Parcel:obtain	()Landroid/os/Parcel;
    //   7: astore_3
    //   8: ldc 22
    //   10: astore 4
    //   12: aload_2
    //   13: aload 4
    //   15: invokevirtual 26	android/os/Parcel:writeInterfaceToken	(Ljava/lang/String;)V
    //   18: aload_1
    //   19: ifnull +60 -> 79
    //   22: iconst_1
    //   23: istore 5
    //   25: aload_2
    //   26: iload 5
    //   28: invokevirtual 49	android/os/Parcel:writeInt	(I)V
    //   31: iconst_0
    //   32: istore 5
    //   34: aconst_null
    //   35: astore 4
    //   37: aload_1
    //   38: aload_2
    //   39: iconst_0
    //   40: invokevirtual 82	com/google/android/gms/b/jh:writeToParcel	(Landroid/os/Parcel;I)V
    //   43: aload_0
    //   44: getfield 14	com/google/android/gms/b/ix$a$a:a	Landroid/os/IBinder;
    //   47: astore 4
    //   49: bipush 30
    //   51: istore 6
    //   53: aload 4
    //   55: iload 6
    //   57: aload_2
    //   58: aload_3
    //   59: iconst_0
    //   60: invokeinterface 33 5 0
    //   65: pop
    //   66: aload_3
    //   67: invokevirtual 36	android/os/Parcel:readException	()V
    //   70: aload_3
    //   71: invokevirtual 43	android/os/Parcel:recycle	()V
    //   74: aload_2
    //   75: invokevirtual 43	android/os/Parcel:recycle	()V
    //   78: return
    //   79: iconst_0
    //   80: istore 5
    //   82: aconst_null
    //   83: astore 4
    //   85: aload_2
    //   86: iconst_0
    //   87: invokevirtual 49	android/os/Parcel:writeInt	(I)V
    //   90: goto -47 -> 43
    //   93: astore 4
    //   95: aload_3
    //   96: invokevirtual 43	android/os/Parcel:recycle	()V
    //   99: aload_2
    //   100: invokevirtual 43	android/os/Parcel:recycle	()V
    //   103: aload 4
    //   105: athrow
    // Local variable table:
    //   start	length	slot	name	signature
    //   0	106	0	this	a
    //   0	106	1	paramjh	jh
    //   3	97	2	localParcel1	Parcel
    //   7	89	3	localParcel2	Parcel
    //   10	74	4	localObject1	Object
    //   93	11	4	localObject2	Object
    //   23	58	5	i	int
    //   51	5	6	j	int
    // Exception table:
    //   from	to	target	type
    //   13	18	93	finally
    //   26	31	93	finally
    //   39	43	93	finally
    //   43	47	93	finally
    //   59	66	93	finally
    //   66	70	93	finally
    //   86	90	93	finally
  }
  
  /* Error */
  public final void a(jt paramjt)
  {
    // Byte code:
    //   0: invokestatic 20	android/os/Parcel:obtain	()Landroid/os/Parcel;
    //   3: astore_2
    //   4: invokestatic 20	android/os/Parcel:obtain	()Landroid/os/Parcel;
    //   7: astore_3
    //   8: ldc 22
    //   10: astore 4
    //   12: aload_2
    //   13: aload 4
    //   15: invokevirtual 26	android/os/Parcel:writeInterfaceToken	(Ljava/lang/String;)V
    //   18: aload_1
    //   19: ifnull +60 -> 79
    //   22: iconst_1
    //   23: istore 5
    //   25: aload_2
    //   26: iload 5
    //   28: invokevirtual 49	android/os/Parcel:writeInt	(I)V
    //   31: iconst_0
    //   32: istore 5
    //   34: aconst_null
    //   35: astore 4
    //   37: aload_1
    //   38: aload_2
    //   39: iconst_0
    //   40: invokevirtual 86	com/google/android/gms/b/jt:writeToParcel	(Landroid/os/Parcel;I)V
    //   43: aload_0
    //   44: getfield 14	com/google/android/gms/b/ix$a$a:a	Landroid/os/IBinder;
    //   47: astore 4
    //   49: bipush 29
    //   51: istore 6
    //   53: aload 4
    //   55: iload 6
    //   57: aload_2
    //   58: aload_3
    //   59: iconst_0
    //   60: invokeinterface 33 5 0
    //   65: pop
    //   66: aload_3
    //   67: invokevirtual 36	android/os/Parcel:readException	()V
    //   70: aload_3
    //   71: invokevirtual 43	android/os/Parcel:recycle	()V
    //   74: aload_2
    //   75: invokevirtual 43	android/os/Parcel:recycle	()V
    //   78: return
    //   79: iconst_0
    //   80: istore 5
    //   82: aconst_null
    //   83: astore 4
    //   85: aload_2
    //   86: iconst_0
    //   87: invokevirtual 49	android/os/Parcel:writeInt	(I)V
    //   90: goto -47 -> 43
    //   93: astore 4
    //   95: aload_3
    //   96: invokevirtual 43	android/os/Parcel:recycle	()V
    //   99: aload_2
    //   100: invokevirtual 43	android/os/Parcel:recycle	()V
    //   103: aload 4
    //   105: athrow
    // Local variable table:
    //   start	length	slot	name	signature
    //   0	106	0	this	a
    //   0	106	1	paramjt	jt
    //   3	97	2	localParcel1	Parcel
    //   7	89	3	localParcel2	Parcel
    //   10	74	4	localObject1	Object
    //   93	11	4	localObject2	Object
    //   23	58	5	i	int
    //   51	5	6	j	int
    // Exception table:
    //   from	to	target	type
    //   13	18	93	finally
    //   26	31	93	finally
    //   39	43	93	finally
    //   43	47	93	finally
    //   59	66	93	finally
    //   66	70	93	finally
    //   86	90	93	finally
  }
  
  /* Error */
  public final void a(kq paramkq)
  {
    // Byte code:
    //   0: invokestatic 20	android/os/Parcel:obtain	()Landroid/os/Parcel;
    //   3: astore_2
    //   4: invokestatic 20	android/os/Parcel:obtain	()Landroid/os/Parcel;
    //   7: astore_3
    //   8: ldc 22
    //   10: astore 4
    //   12: aload_2
    //   13: aload 4
    //   15: invokevirtual 26	android/os/Parcel:writeInterfaceToken	(Ljava/lang/String;)V
    //   18: aload_1
    //   19: ifnull +53 -> 72
    //   22: aload_1
    //   23: invokeinterface 90 1 0
    //   28: astore 4
    //   30: aload_2
    //   31: aload 4
    //   33: invokevirtual 66	android/os/Parcel:writeStrongBinder	(Landroid/os/IBinder;)V
    //   36: aload_0
    //   37: getfield 14	com/google/android/gms/b/ix$a$a:a	Landroid/os/IBinder;
    //   40: astore 4
    //   42: bipush 19
    //   44: istore 5
    //   46: aload 4
    //   48: iload 5
    //   50: aload_2
    //   51: aload_3
    //   52: iconst_0
    //   53: invokeinterface 33 5 0
    //   58: pop
    //   59: aload_3
    //   60: invokevirtual 36	android/os/Parcel:readException	()V
    //   63: aload_3
    //   64: invokevirtual 43	android/os/Parcel:recycle	()V
    //   67: aload_2
    //   68: invokevirtual 43	android/os/Parcel:recycle	()V
    //   71: return
    //   72: aconst_null
    //   73: astore 4
    //   75: goto -45 -> 30
    //   78: astore 4
    //   80: aload_3
    //   81: invokevirtual 43	android/os/Parcel:recycle	()V
    //   84: aload_2
    //   85: invokevirtual 43	android/os/Parcel:recycle	()V
    //   88: aload 4
    //   90: athrow
    // Local variable table:
    //   start	length	slot	name	signature
    //   0	91	0	this	a
    //   0	91	1	paramkq	kq
    //   3	82	2	localParcel1	Parcel
    //   7	74	3	localParcel2	Parcel
    //   10	64	4	localObject1	Object
    //   78	11	4	localObject2	Object
    //   44	5	5	i	int
    // Exception table:
    //   from	to	target	type
    //   13	18	78	finally
    //   22	28	78	finally
    //   31	36	78	finally
    //   36	40	78	finally
    //   52	59	78	finally
    //   59	63	78	finally
  }
  
  /* Error */
  public final void a(ph paramph)
  {
    // Byte code:
    //   0: invokestatic 20	android/os/Parcel:obtain	()Landroid/os/Parcel;
    //   3: astore_2
    //   4: invokestatic 20	android/os/Parcel:obtain	()Landroid/os/Parcel;
    //   7: astore_3
    //   8: ldc 22
    //   10: astore 4
    //   12: aload_2
    //   13: aload 4
    //   15: invokevirtual 26	android/os/Parcel:writeInterfaceToken	(Ljava/lang/String;)V
    //   18: aload_1
    //   19: ifnull +53 -> 72
    //   22: aload_1
    //   23: invokeinterface 94 1 0
    //   28: astore 4
    //   30: aload_2
    //   31: aload 4
    //   33: invokevirtual 66	android/os/Parcel:writeStrongBinder	(Landroid/os/IBinder;)V
    //   36: aload_0
    //   37: getfield 14	com/google/android/gms/b/ix$a$a:a	Landroid/os/IBinder;
    //   40: astore 4
    //   42: bipush 14
    //   44: istore 5
    //   46: aload 4
    //   48: iload 5
    //   50: aload_2
    //   51: aload_3
    //   52: iconst_0
    //   53: invokeinterface 33 5 0
    //   58: pop
    //   59: aload_3
    //   60: invokevirtual 36	android/os/Parcel:readException	()V
    //   63: aload_3
    //   64: invokevirtual 43	android/os/Parcel:recycle	()V
    //   67: aload_2
    //   68: invokevirtual 43	android/os/Parcel:recycle	()V
    //   71: return
    //   72: aconst_null
    //   73: astore 4
    //   75: goto -45 -> 30
    //   78: astore 4
    //   80: aload_3
    //   81: invokevirtual 43	android/os/Parcel:recycle	()V
    //   84: aload_2
    //   85: invokevirtual 43	android/os/Parcel:recycle	()V
    //   88: aload 4
    //   90: athrow
    // Local variable table:
    //   start	length	slot	name	signature
    //   0	91	0	this	a
    //   0	91	1	paramph	ph
    //   3	82	2	localParcel1	Parcel
    //   7	74	3	localParcel2	Parcel
    //   10	64	4	localObject1	Object
    //   78	11	4	localObject2	Object
    //   44	5	5	i	int
    // Exception table:
    //   from	to	target	type
    //   13	18	78	finally
    //   22	28	78	finally
    //   31	36	78	finally
    //   36	40	78	finally
    //   52	59	78	finally
    //   59	63	78	finally
  }
  
  /* Error */
  public final void a(pl parampl, String paramString)
  {
    // Byte code:
    //   0: invokestatic 20	android/os/Parcel:obtain	()Landroid/os/Parcel;
    //   3: astore_3
    //   4: invokestatic 20	android/os/Parcel:obtain	()Landroid/os/Parcel;
    //   7: astore 4
    //   9: ldc 22
    //   11: astore 5
    //   13: aload_3
    //   14: aload 5
    //   16: invokevirtual 26	android/os/Parcel:writeInterfaceToken	(Ljava/lang/String;)V
    //   19: aload_1
    //   20: ifnull +61 -> 81
    //   23: aload_1
    //   24: invokeinterface 98 1 0
    //   29: astore 5
    //   31: aload_3
    //   32: aload 5
    //   34: invokevirtual 66	android/os/Parcel:writeStrongBinder	(Landroid/os/IBinder;)V
    //   37: aload_3
    //   38: aload_2
    //   39: invokevirtual 101	android/os/Parcel:writeString	(Ljava/lang/String;)V
    //   42: aload_0
    //   43: getfield 14	com/google/android/gms/b/ix$a$a:a	Landroid/os/IBinder;
    //   46: astore 5
    //   48: bipush 15
    //   50: istore 6
    //   52: aload 5
    //   54: iload 6
    //   56: aload_3
    //   57: aload 4
    //   59: iconst_0
    //   60: invokeinterface 33 5 0
    //   65: pop
    //   66: aload 4
    //   68: invokevirtual 36	android/os/Parcel:readException	()V
    //   71: aload 4
    //   73: invokevirtual 43	android/os/Parcel:recycle	()V
    //   76: aload_3
    //   77: invokevirtual 43	android/os/Parcel:recycle	()V
    //   80: return
    //   81: aconst_null
    //   82: astore 5
    //   84: goto -53 -> 31
    //   87: astore 5
    //   89: aload 4
    //   91: invokevirtual 43	android/os/Parcel:recycle	()V
    //   94: aload_3
    //   95: invokevirtual 43	android/os/Parcel:recycle	()V
    //   98: aload 5
    //   100: athrow
    // Local variable table:
    //   start	length	slot	name	signature
    //   0	101	0	this	a
    //   0	101	1	parampl	pl
    //   0	101	2	paramString	String
    //   3	92	3	localParcel1	Parcel
    //   7	83	4	localParcel2	Parcel
    //   11	72	5	localObject1	Object
    //   87	12	5	localObject2	Object
    //   50	5	6	i	int
    // Exception table:
    //   from	to	target	type
    //   14	19	87	finally
    //   23	29	87	finally
    //   32	37	87	finally
    //   38	42	87	finally
    //   42	46	87	finally
    //   59	66	87	finally
    //   66	71	87	finally
  }
  
  /* Error */
  public final void a(sb paramsb)
  {
    // Byte code:
    //   0: invokestatic 20	android/os/Parcel:obtain	()Landroid/os/Parcel;
    //   3: astore_2
    //   4: invokestatic 20	android/os/Parcel:obtain	()Landroid/os/Parcel;
    //   7: astore_3
    //   8: ldc 22
    //   10: astore 4
    //   12: aload_2
    //   13: aload 4
    //   15: invokevirtual 26	android/os/Parcel:writeInterfaceToken	(Ljava/lang/String;)V
    //   18: aload_1
    //   19: ifnull +53 -> 72
    //   22: aload_1
    //   23: invokeinterface 105 1 0
    //   28: astore 4
    //   30: aload_2
    //   31: aload 4
    //   33: invokevirtual 66	android/os/Parcel:writeStrongBinder	(Landroid/os/IBinder;)V
    //   36: aload_0
    //   37: getfield 14	com/google/android/gms/b/ix$a$a:a	Landroid/os/IBinder;
    //   40: astore 4
    //   42: bipush 24
    //   44: istore 5
    //   46: aload 4
    //   48: iload 5
    //   50: aload_2
    //   51: aload_3
    //   52: iconst_0
    //   53: invokeinterface 33 5 0
    //   58: pop
    //   59: aload_3
    //   60: invokevirtual 36	android/os/Parcel:readException	()V
    //   63: aload_3
    //   64: invokevirtual 43	android/os/Parcel:recycle	()V
    //   67: aload_2
    //   68: invokevirtual 43	android/os/Parcel:recycle	()V
    //   71: return
    //   72: aconst_null
    //   73: astore 4
    //   75: goto -45 -> 30
    //   78: astore 4
    //   80: aload_3
    //   81: invokevirtual 43	android/os/Parcel:recycle	()V
    //   84: aload_2
    //   85: invokevirtual 43	android/os/Parcel:recycle	()V
    //   88: aload 4
    //   90: athrow
    // Local variable table:
    //   start	length	slot	name	signature
    //   0	91	0	this	a
    //   0	91	1	paramsb	sb
    //   3	82	2	localParcel1	Parcel
    //   7	74	3	localParcel2	Parcel
    //   10	64	4	localObject1	Object
    //   78	11	4	localObject2	Object
    //   44	5	5	i	int
    // Exception table:
    //   from	to	target	type
    //   13	18	78	finally
    //   22	28	78	finally
    //   31	36	78	finally
    //   36	40	78	finally
    //   52	59	78	finally
    //   59	63	78	finally
  }
  
  public final void a(String paramString)
  {
    Parcel localParcel1 = Parcel.obtain();
    Parcel localParcel2 = Parcel.obtain();
    Object localObject1 = "com.google.android.gms.ads.internal.client.IAdManager";
    try
    {
      localParcel1.writeInterfaceToken((String)localObject1);
      localParcel1.writeString(paramString);
      localObject1 = a;
      int i = 25;
      ((IBinder)localObject1).transact(i, localParcel1, localParcel2, 0);
      localParcel2.readException();
      return;
    }
    finally
    {
      localParcel2.recycle();
      localParcel1.recycle();
    }
  }
  
  public final void a(boolean paramBoolean)
  {
    int i = 0;
    IBinder localIBinder = null;
    Parcel localParcel1 = Parcel.obtain();
    Parcel localParcel2 = Parcel.obtain();
    String str = "com.google.android.gms.ads.internal.client.IAdManager";
    try
    {
      localParcel1.writeInterfaceToken(str);
      if (paramBoolean) {
        i = 1;
      }
      localParcel1.writeInt(i);
      localIBinder = a;
      int j = 22;
      localIBinder.transact(j, localParcel1, localParcel2, 0);
      localParcel2.readException();
      return;
    }
    finally
    {
      localParcel2.recycle();
      localParcel1.recycle();
    }
  }
  
  public final boolean a(ih paramih)
  {
    boolean bool = true;
    Parcel localParcel1 = Parcel.obtain();
    Parcel localParcel2 = Parcel.obtain();
    Object localObject1 = "com.google.android.gms.ads.internal.client.IAdManager";
    for (;;)
    {
      try
      {
        localParcel1.writeInterfaceToken((String)localObject1);
        int i;
        if (paramih != null)
        {
          i = 1;
          localParcel1.writeInt(i);
          i = 0;
          localObject1 = null;
          paramih.writeToParcel(localParcel1, 0);
          localObject1 = a;
          int j = 4;
          ((IBinder)localObject1).transact(j, localParcel1, localParcel2, 0);
          localParcel2.readException();
          i = localParcel2.readInt();
          if (i != 0) {
            return bool;
          }
        }
        else
        {
          i = 0;
          localObject1 = null;
          localParcel1.writeInt(0);
          continue;
        }
        bool = false;
      }
      finally
      {
        localParcel2.recycle();
        localParcel1.recycle();
      }
      Object localObject3 = null;
    }
  }
  
  public final IBinder asBinder()
  {
    return a;
  }
  
  public final void h()
  {
    Parcel localParcel1 = Parcel.obtain();
    Parcel localParcel2 = Parcel.obtain();
    Object localObject1 = "com.google.android.gms.ads.internal.client.IAdManager";
    try
    {
      localParcel1.writeInterfaceToken((String)localObject1);
      localObject1 = a;
      int i = 2;
      ((IBinder)localObject1).transact(i, localParcel1, localParcel2, 0);
      localParcel2.readException();
      return;
    }
    finally
    {
      localParcel2.recycle();
      localParcel1.recycle();
    }
  }
  
  public final a i()
  {
    Parcel localParcel1 = Parcel.obtain();
    Parcel localParcel2 = Parcel.obtain();
    Object localObject1 = "com.google.android.gms.ads.internal.client.IAdManager";
    try
    {
      localParcel1.writeInterfaceToken((String)localObject1);
      localObject1 = a;
      int i = 1;
      ((IBinder)localObject1).transact(i, localParcel1, localParcel2, 0);
      localParcel2.readException();
      localObject1 = localParcel2.readStrongBinder();
      localObject1 = a.a.a((IBinder)localObject1);
      return (a)localObject1;
    }
    finally
    {
      localParcel2.recycle();
      localParcel1.recycle();
    }
  }
  
  /* Error */
  public final il j()
  {
    // Byte code:
    //   0: invokestatic 20	android/os/Parcel:obtain	()Landroid/os/Parcel;
    //   3: astore_1
    //   4: invokestatic 20	android/os/Parcel:obtain	()Landroid/os/Parcel;
    //   7: astore_2
    //   8: ldc 22
    //   10: astore_3
    //   11: aload_1
    //   12: aload_3
    //   13: invokevirtual 26	android/os/Parcel:writeInterfaceToken	(Ljava/lang/String;)V
    //   16: aload_0
    //   17: getfield 14	com/google/android/gms/b/ix$a$a:a	Landroid/os/IBinder;
    //   20: astore_3
    //   21: bipush 12
    //   23: istore 4
    //   25: aload_3
    //   26: iload 4
    //   28: aload_1
    //   29: aload_2
    //   30: iconst_0
    //   31: invokeinterface 33 5 0
    //   36: pop
    //   37: aload_2
    //   38: invokevirtual 36	android/os/Parcel:readException	()V
    //   41: aload_2
    //   42: invokevirtual 116	android/os/Parcel:readInt	()I
    //   45: istore 5
    //   47: iload 5
    //   49: ifeq +30 -> 79
    //   52: getstatic 130	com/google/android/gms/b/il:CREATOR	Landroid/os/Parcelable$Creator;
    //   55: astore_3
    //   56: aload_3
    //   57: aload_2
    //   58: invokeinterface 136 2 0
    //   63: astore_3
    //   64: aload_3
    //   65: checkcast 51	com/google/android/gms/b/il
    //   68: astore_3
    //   69: aload_2
    //   70: invokevirtual 43	android/os/Parcel:recycle	()V
    //   73: aload_1
    //   74: invokevirtual 43	android/os/Parcel:recycle	()V
    //   77: aload_3
    //   78: areturn
    //   79: iconst_0
    //   80: istore 5
    //   82: aconst_null
    //   83: astore_3
    //   84: goto -15 -> 69
    //   87: astore_3
    //   88: aload_2
    //   89: invokevirtual 43	android/os/Parcel:recycle	()V
    //   92: aload_1
    //   93: invokevirtual 43	android/os/Parcel:recycle	()V
    //   96: aload_3
    //   97: athrow
    // Local variable table:
    //   start	length	slot	name	signature
    //   0	98	0	this	a
    //   3	90	1	localParcel1	Parcel
    //   7	82	2	localParcel2	Parcel
    //   10	74	3	localObject1	Object
    //   87	10	3	localObject2	Object
    //   23	4	4	i	int
    //   45	36	5	j	int
    // Exception table:
    //   from	to	target	type
    //   12	16	87	finally
    //   16	20	87	finally
    //   30	37	87	finally
    //   37	41	87	finally
    //   41	45	87	finally
    //   52	55	87	finally
    //   57	63	87	finally
    //   64	68	87	finally
  }
  
  public final boolean k()
  {
    boolean bool = false;
    Object localObject1 = null;
    Parcel localParcel1 = Parcel.obtain();
    Parcel localParcel2 = Parcel.obtain();
    Object localObject3 = "com.google.android.gms.ads.internal.client.IAdManager";
    try
    {
      localParcel1.writeInterfaceToken((String)localObject3);
      localObject3 = a;
      int i = 3;
      ((IBinder)localObject3).transact(i, localParcel1, localParcel2, 0);
      localParcel2.readException();
      int j = localParcel2.readInt();
      if (j != 0) {
        bool = true;
      }
      return bool;
    }
    finally
    {
      localParcel2.recycle();
      localParcel1.recycle();
    }
  }
  
  public final void l()
  {
    Parcel localParcel1 = Parcel.obtain();
    Parcel localParcel2 = Parcel.obtain();
    Object localObject1 = "com.google.android.gms.ads.internal.client.IAdManager";
    try
    {
      localParcel1.writeInterfaceToken((String)localObject1);
      localObject1 = a;
      int i = 11;
      ((IBinder)localObject1).transact(i, localParcel1, localParcel2, 0);
      localParcel2.readException();
      return;
    }
    finally
    {
      localParcel2.recycle();
      localParcel1.recycle();
    }
  }
  
  public final void m()
  {
    Parcel localParcel1 = Parcel.obtain();
    Parcel localParcel2 = Parcel.obtain();
    Object localObject1 = "com.google.android.gms.ads.internal.client.IAdManager";
    try
    {
      localParcel1.writeInterfaceToken((String)localObject1);
      localObject1 = a;
      int i = 5;
      ((IBinder)localObject1).transact(i, localParcel1, localParcel2, 0);
      localParcel2.readException();
      return;
    }
    finally
    {
      localParcel2.recycle();
      localParcel1.recycle();
    }
  }
  
  public final void n()
  {
    Parcel localParcel1 = Parcel.obtain();
    Parcel localParcel2 = Parcel.obtain();
    Object localObject1 = "com.google.android.gms.ads.internal.client.IAdManager";
    try
    {
      localParcel1.writeInterfaceToken((String)localObject1);
      localObject1 = a;
      int i = 6;
      ((IBinder)localObject1).transact(i, localParcel1, localParcel2, 0);
      localParcel2.readException();
      return;
    }
    finally
    {
      localParcel2.recycle();
      localParcel1.recycle();
    }
  }
  
  public final void o()
  {
    Parcel localParcel1 = Parcel.obtain();
    Parcel localParcel2 = Parcel.obtain();
    Object localObject1 = "com.google.android.gms.ads.internal.client.IAdManager";
    try
    {
      localParcel1.writeInterfaceToken((String)localObject1);
      localObject1 = a;
      int i = 10;
      ((IBinder)localObject1).transact(i, localParcel1, localParcel2, 0);
      localParcel2.readException();
      return;
    }
    finally
    {
      localParcel2.recycle();
      localParcel1.recycle();
    }
  }
  
  public final boolean p()
  {
    boolean bool = false;
    Object localObject1 = null;
    Parcel localParcel1 = Parcel.obtain();
    Parcel localParcel2 = Parcel.obtain();
    Object localObject3 = "com.google.android.gms.ads.internal.client.IAdManager";
    try
    {
      localParcel1.writeInterfaceToken((String)localObject3);
      localObject3 = a;
      int i = 23;
      ((IBinder)localObject3).transact(i, localParcel1, localParcel2, 0);
      localParcel2.readException();
      int j = localParcel2.readInt();
      if (j != 0) {
        bool = true;
      }
      return bool;
    }
    finally
    {
      localParcel2.recycle();
      localParcel1.recycle();
    }
  }
  
  public final jf q()
  {
    Parcel localParcel1 = Parcel.obtain();
    Parcel localParcel2 = Parcel.obtain();
    Object localObject1 = "com.google.android.gms.ads.internal.client.IAdManager";
    try
    {
      localParcel1.writeInterfaceToken((String)localObject1);
      localObject1 = a;
      int i = 26;
      ((IBinder)localObject1).transact(i, localParcel1, localParcel2, 0);
      localParcel2.readException();
      localObject1 = localParcel2.readStrongBinder();
      localObject1 = jf.a.a((IBinder)localObject1);
      return (jf)localObject1;
    }
    finally
    {
      localParcel2.recycle();
      localParcel1.recycle();
    }
  }
}


/* Location:              com/google/android/gms/b/ix$a$a.class
 * Java compiler version: 5 (49.0)
 * JD-Core Version:       0.7.1
 */