package com.google.android.gms.b;

import android.os.IBinder;

final class ja$a$a
  implements ja
{
  private IBinder a;
  
  ja$a$a(IBinder paramIBinder)
  {
    a = paramIBinder;
  }
  
  public final IBinder asBinder()
  {
    return a;
  }
  
  /* Error */
  public final iv createAdLoaderBuilder(com.google.android.gms.a.a parama, String paramString, oc paramoc, int paramInt)
  {
    // Byte code:
    //   0: aconst_null
    //   1: astore 5
    //   3: invokestatic 20	android/os/Parcel:obtain	()Landroid/os/Parcel;
    //   6: astore 6
    //   8: invokestatic 20	android/os/Parcel:obtain	()Landroid/os/Parcel;
    //   11: astore 7
    //   13: ldc 22
    //   15: astore 8
    //   17: aload 6
    //   19: aload 8
    //   21: invokevirtual 26	android/os/Parcel:writeInterfaceToken	(Ljava/lang/String;)V
    //   24: aload_1
    //   25: ifnull +106 -> 131
    //   28: aload_1
    //   29: invokeinterface 32 1 0
    //   34: astore 8
    //   36: aload 6
    //   38: aload 8
    //   40: invokevirtual 36	android/os/Parcel:writeStrongBinder	(Landroid/os/IBinder;)V
    //   43: aload 6
    //   45: aload_2
    //   46: invokevirtual 39	android/os/Parcel:writeString	(Ljava/lang/String;)V
    //   49: aload_3
    //   50: ifnull +11 -> 61
    //   53: aload_3
    //   54: invokeinterface 42 1 0
    //   59: astore 5
    //   61: aload 6
    //   63: aload 5
    //   65: invokevirtual 36	android/os/Parcel:writeStrongBinder	(Landroid/os/IBinder;)V
    //   68: aload 6
    //   70: iload 4
    //   72: invokevirtual 46	android/os/Parcel:writeInt	(I)V
    //   75: aload_0
    //   76: getfield 14	com/google/android/gms/b/ja$a$a:a	Landroid/os/IBinder;
    //   79: astore 5
    //   81: iconst_3
    //   82: istore 9
    //   84: aload 5
    //   86: iload 9
    //   88: aload 6
    //   90: aload 7
    //   92: iconst_0
    //   93: invokeinterface 53 5 0
    //   98: pop
    //   99: aload 7
    //   101: invokevirtual 56	android/os/Parcel:readException	()V
    //   104: aload 7
    //   106: invokevirtual 59	android/os/Parcel:readStrongBinder	()Landroid/os/IBinder;
    //   109: astore 5
    //   111: aload 5
    //   113: invokestatic 64	com/google/android/gms/b/iv$a:a	(Landroid/os/IBinder;)Lcom/google/android/gms/b/iv;
    //   116: astore 5
    //   118: aload 7
    //   120: invokevirtual 67	android/os/Parcel:recycle	()V
    //   123: aload 6
    //   125: invokevirtual 67	android/os/Parcel:recycle	()V
    //   128: aload 5
    //   130: areturn
    //   131: iconst_0
    //   132: istore 9
    //   134: aconst_null
    //   135: astore 8
    //   137: goto -101 -> 36
    //   140: astore 5
    //   142: aload 7
    //   144: invokevirtual 67	android/os/Parcel:recycle	()V
    //   147: aload 6
    //   149: invokevirtual 67	android/os/Parcel:recycle	()V
    //   152: aload 5
    //   154: athrow
    // Local variable table:
    //   start	length	slot	name	signature
    //   0	155	0	this	a
    //   0	155	1	parama	com.google.android.gms.a.a
    //   0	155	2	paramString	String
    //   0	155	3	paramoc	oc
    //   0	155	4	paramInt	int
    //   1	128	5	localObject1	Object
    //   140	13	5	localObject2	Object
    //   6	142	6	localParcel1	android.os.Parcel
    //   11	132	7	localParcel2	android.os.Parcel
    //   15	121	8	localObject3	Object
    //   82	51	9	i	int
    // Exception table:
    //   from	to	target	type
    //   19	24	140	finally
    //   28	34	140	finally
    //   38	43	140	finally
    //   45	49	140	finally
    //   53	59	140	finally
    //   63	68	140	finally
    //   70	75	140	finally
    //   75	79	140	finally
    //   92	99	140	finally
    //   99	104	140	finally
    //   104	109	140	finally
    //   111	116	140	finally
  }
  
  /* Error */
  public final pb createAdOverlay(com.google.android.gms.a.a parama)
  {
    // Byte code:
    //   0: invokestatic 20	android/os/Parcel:obtain	()Landroid/os/Parcel;
    //   3: astore_2
    //   4: invokestatic 20	android/os/Parcel:obtain	()Landroid/os/Parcel;
    //   7: astore_3
    //   8: ldc 22
    //   10: astore 4
    //   12: aload_2
    //   13: aload 4
    //   15: invokevirtual 26	android/os/Parcel:writeInterfaceToken	(Ljava/lang/String;)V
    //   18: aload_1
    //   19: ifnull +68 -> 87
    //   22: aload_1
    //   23: invokeinterface 32 1 0
    //   28: astore 4
    //   30: aload_2
    //   31: aload 4
    //   33: invokevirtual 36	android/os/Parcel:writeStrongBinder	(Landroid/os/IBinder;)V
    //   36: aload_0
    //   37: getfield 14	com/google/android/gms/b/ja$a$a:a	Landroid/os/IBinder;
    //   40: astore 4
    //   42: bipush 8
    //   44: istore 5
    //   46: aload 4
    //   48: iload 5
    //   50: aload_2
    //   51: aload_3
    //   52: iconst_0
    //   53: invokeinterface 53 5 0
    //   58: pop
    //   59: aload_3
    //   60: invokevirtual 56	android/os/Parcel:readException	()V
    //   63: aload_3
    //   64: invokevirtual 59	android/os/Parcel:readStrongBinder	()Landroid/os/IBinder;
    //   67: astore 4
    //   69: aload 4
    //   71: invokestatic 73	com/google/android/gms/b/pb$a:a	(Landroid/os/IBinder;)Lcom/google/android/gms/b/pb;
    //   74: astore 4
    //   76: aload_3
    //   77: invokevirtual 67	android/os/Parcel:recycle	()V
    //   80: aload_2
    //   81: invokevirtual 67	android/os/Parcel:recycle	()V
    //   84: aload 4
    //   86: areturn
    //   87: aconst_null
    //   88: astore 4
    //   90: goto -60 -> 30
    //   93: astore 4
    //   95: aload_3
    //   96: invokevirtual 67	android/os/Parcel:recycle	()V
    //   99: aload_2
    //   100: invokevirtual 67	android/os/Parcel:recycle	()V
    //   103: aload 4
    //   105: athrow
    // Local variable table:
    //   start	length	slot	name	signature
    //   0	106	0	this	a
    //   0	106	1	parama	com.google.android.gms.a.a
    //   3	97	2	localParcel1	android.os.Parcel
    //   7	89	3	localParcel2	android.os.Parcel
    //   10	79	4	localObject1	Object
    //   93	11	4	localObject2	Object
    //   44	5	5	i	int
    // Exception table:
    //   from	to	target	type
    //   13	18	93	finally
    //   22	28	93	finally
    //   31	36	93	finally
    //   36	40	93	finally
    //   52	59	93	finally
    //   59	63	93	finally
    //   63	67	93	finally
    //   69	74	93	finally
  }
  
  /* Error */
  public final ix createBannerAdManager(com.google.android.gms.a.a parama, il paramil, String paramString, oc paramoc, int paramInt)
  {
    // Byte code:
    //   0: aconst_null
    //   1: astore 6
    //   3: invokestatic 20	android/os/Parcel:obtain	()Landroid/os/Parcel;
    //   6: astore 7
    //   8: invokestatic 20	android/os/Parcel:obtain	()Landroid/os/Parcel;
    //   11: astore 8
    //   13: ldc 22
    //   15: astore 9
    //   17: aload 7
    //   19: aload 9
    //   21: invokevirtual 26	android/os/Parcel:writeInterfaceToken	(Ljava/lang/String;)V
    //   24: aload_1
    //   25: ifnull +135 -> 160
    //   28: aload_1
    //   29: invokeinterface 32 1 0
    //   34: astore 9
    //   36: aload 7
    //   38: aload 9
    //   40: invokevirtual 36	android/os/Parcel:writeStrongBinder	(Landroid/os/IBinder;)V
    //   43: aload_2
    //   44: ifnull +125 -> 169
    //   47: iconst_1
    //   48: istore 10
    //   50: aload 7
    //   52: iload 10
    //   54: invokevirtual 46	android/os/Parcel:writeInt	(I)V
    //   57: iconst_0
    //   58: istore 10
    //   60: aconst_null
    //   61: astore 9
    //   63: aload_2
    //   64: aload 7
    //   66: iconst_0
    //   67: invokevirtual 80	com/google/android/gms/b/il:writeToParcel	(Landroid/os/Parcel;I)V
    //   70: aload 7
    //   72: aload_3
    //   73: invokevirtual 39	android/os/Parcel:writeString	(Ljava/lang/String;)V
    //   76: aload 4
    //   78: ifnull +12 -> 90
    //   81: aload 4
    //   83: invokeinterface 42 1 0
    //   88: astore 6
    //   90: aload 7
    //   92: aload 6
    //   94: invokevirtual 36	android/os/Parcel:writeStrongBinder	(Landroid/os/IBinder;)V
    //   97: aload 7
    //   99: iload 5
    //   101: invokevirtual 46	android/os/Parcel:writeInt	(I)V
    //   104: aload_0
    //   105: getfield 14	com/google/android/gms/b/ja$a$a:a	Landroid/os/IBinder;
    //   108: astore 6
    //   110: iconst_1
    //   111: istore 10
    //   113: aload 6
    //   115: iload 10
    //   117: aload 7
    //   119: aload 8
    //   121: iconst_0
    //   122: invokeinterface 53 5 0
    //   127: pop
    //   128: aload 8
    //   130: invokevirtual 56	android/os/Parcel:readException	()V
    //   133: aload 8
    //   135: invokevirtual 59	android/os/Parcel:readStrongBinder	()Landroid/os/IBinder;
    //   138: astore 6
    //   140: aload 6
    //   142: invokestatic 85	com/google/android/gms/b/ix$a:a	(Landroid/os/IBinder;)Lcom/google/android/gms/b/ix;
    //   145: astore 6
    //   147: aload 8
    //   149: invokevirtual 67	android/os/Parcel:recycle	()V
    //   152: aload 7
    //   154: invokevirtual 67	android/os/Parcel:recycle	()V
    //   157: aload 6
    //   159: areturn
    //   160: iconst_0
    //   161: istore 10
    //   163: aconst_null
    //   164: astore 9
    //   166: goto -130 -> 36
    //   169: iconst_0
    //   170: istore 10
    //   172: aconst_null
    //   173: astore 9
    //   175: aload 7
    //   177: iconst_0
    //   178: invokevirtual 46	android/os/Parcel:writeInt	(I)V
    //   181: goto -111 -> 70
    //   184: astore 6
    //   186: aload 8
    //   188: invokevirtual 67	android/os/Parcel:recycle	()V
    //   191: aload 7
    //   193: invokevirtual 67	android/os/Parcel:recycle	()V
    //   196: aload 6
    //   198: athrow
    // Local variable table:
    //   start	length	slot	name	signature
    //   0	199	0	this	a
    //   0	199	1	parama	com.google.android.gms.a.a
    //   0	199	2	paramil	il
    //   0	199	3	paramString	String
    //   0	199	4	paramoc	oc
    //   0	199	5	paramInt	int
    //   1	157	6	localObject1	Object
    //   184	13	6	localObject2	Object
    //   6	186	7	localParcel1	android.os.Parcel
    //   11	176	8	localParcel2	android.os.Parcel
    //   15	159	9	localObject3	Object
    //   48	123	10	i	int
    // Exception table:
    //   from	to	target	type
    //   19	24	184	finally
    //   28	34	184	finally
    //   38	43	184	finally
    //   52	57	184	finally
    //   66	70	184	finally
    //   72	76	184	finally
    //   81	88	184	finally
    //   92	97	184	finally
    //   99	104	184	finally
    //   104	108	184	finally
    //   121	128	184	finally
    //   128	133	184	finally
    //   133	138	184	finally
    //   140	145	184	finally
    //   177	181	184	finally
  }
  
  /* Error */
  public final pi createInAppPurchaseManager(com.google.android.gms.a.a parama)
  {
    // Byte code:
    //   0: invokestatic 20	android/os/Parcel:obtain	()Landroid/os/Parcel;
    //   3: astore_2
    //   4: invokestatic 20	android/os/Parcel:obtain	()Landroid/os/Parcel;
    //   7: astore_3
    //   8: ldc 22
    //   10: astore 4
    //   12: aload_2
    //   13: aload 4
    //   15: invokevirtual 26	android/os/Parcel:writeInterfaceToken	(Ljava/lang/String;)V
    //   18: aload_1
    //   19: ifnull +68 -> 87
    //   22: aload_1
    //   23: invokeinterface 32 1 0
    //   28: astore 4
    //   30: aload_2
    //   31: aload 4
    //   33: invokevirtual 36	android/os/Parcel:writeStrongBinder	(Landroid/os/IBinder;)V
    //   36: aload_0
    //   37: getfield 14	com/google/android/gms/b/ja$a$a:a	Landroid/os/IBinder;
    //   40: astore 4
    //   42: bipush 7
    //   44: istore 5
    //   46: aload 4
    //   48: iload 5
    //   50: aload_2
    //   51: aload_3
    //   52: iconst_0
    //   53: invokeinterface 53 5 0
    //   58: pop
    //   59: aload_3
    //   60: invokevirtual 56	android/os/Parcel:readException	()V
    //   63: aload_3
    //   64: invokevirtual 59	android/os/Parcel:readStrongBinder	()Landroid/os/IBinder;
    //   67: astore 4
    //   69: aload 4
    //   71: invokestatic 91	com/google/android/gms/b/pi$a:a	(Landroid/os/IBinder;)Lcom/google/android/gms/b/pi;
    //   74: astore 4
    //   76: aload_3
    //   77: invokevirtual 67	android/os/Parcel:recycle	()V
    //   80: aload_2
    //   81: invokevirtual 67	android/os/Parcel:recycle	()V
    //   84: aload 4
    //   86: areturn
    //   87: aconst_null
    //   88: astore 4
    //   90: goto -60 -> 30
    //   93: astore 4
    //   95: aload_3
    //   96: invokevirtual 67	android/os/Parcel:recycle	()V
    //   99: aload_2
    //   100: invokevirtual 67	android/os/Parcel:recycle	()V
    //   103: aload 4
    //   105: athrow
    // Local variable table:
    //   start	length	slot	name	signature
    //   0	106	0	this	a
    //   0	106	1	parama	com.google.android.gms.a.a
    //   3	97	2	localParcel1	android.os.Parcel
    //   7	89	3	localParcel2	android.os.Parcel
    //   10	79	4	localObject1	Object
    //   93	11	4	localObject2	Object
    //   44	5	5	i	int
    // Exception table:
    //   from	to	target	type
    //   13	18	93	finally
    //   22	28	93	finally
    //   31	36	93	finally
    //   36	40	93	finally
    //   52	59	93	finally
    //   59	63	93	finally
    //   63	67	93	finally
    //   69	74	93	finally
  }
  
  /* Error */
  public final ix createInterstitialAdManager(com.google.android.gms.a.a parama, il paramil, String paramString, oc paramoc, int paramInt)
  {
    // Byte code:
    //   0: aconst_null
    //   1: astore 6
    //   3: invokestatic 20	android/os/Parcel:obtain	()Landroid/os/Parcel;
    //   6: astore 7
    //   8: invokestatic 20	android/os/Parcel:obtain	()Landroid/os/Parcel;
    //   11: astore 8
    //   13: ldc 22
    //   15: astore 9
    //   17: aload 7
    //   19: aload 9
    //   21: invokevirtual 26	android/os/Parcel:writeInterfaceToken	(Ljava/lang/String;)V
    //   24: aload_1
    //   25: ifnull +135 -> 160
    //   28: aload_1
    //   29: invokeinterface 32 1 0
    //   34: astore 9
    //   36: aload 7
    //   38: aload 9
    //   40: invokevirtual 36	android/os/Parcel:writeStrongBinder	(Landroid/os/IBinder;)V
    //   43: aload_2
    //   44: ifnull +125 -> 169
    //   47: iconst_1
    //   48: istore 10
    //   50: aload 7
    //   52: iload 10
    //   54: invokevirtual 46	android/os/Parcel:writeInt	(I)V
    //   57: iconst_0
    //   58: istore 10
    //   60: aconst_null
    //   61: astore 9
    //   63: aload_2
    //   64: aload 7
    //   66: iconst_0
    //   67: invokevirtual 80	com/google/android/gms/b/il:writeToParcel	(Landroid/os/Parcel;I)V
    //   70: aload 7
    //   72: aload_3
    //   73: invokevirtual 39	android/os/Parcel:writeString	(Ljava/lang/String;)V
    //   76: aload 4
    //   78: ifnull +12 -> 90
    //   81: aload 4
    //   83: invokeinterface 42 1 0
    //   88: astore 6
    //   90: aload 7
    //   92: aload 6
    //   94: invokevirtual 36	android/os/Parcel:writeStrongBinder	(Landroid/os/IBinder;)V
    //   97: aload 7
    //   99: iload 5
    //   101: invokevirtual 46	android/os/Parcel:writeInt	(I)V
    //   104: aload_0
    //   105: getfield 14	com/google/android/gms/b/ja$a$a:a	Landroid/os/IBinder;
    //   108: astore 6
    //   110: iconst_2
    //   111: istore 10
    //   113: aload 6
    //   115: iload 10
    //   117: aload 7
    //   119: aload 8
    //   121: iconst_0
    //   122: invokeinterface 53 5 0
    //   127: pop
    //   128: aload 8
    //   130: invokevirtual 56	android/os/Parcel:readException	()V
    //   133: aload 8
    //   135: invokevirtual 59	android/os/Parcel:readStrongBinder	()Landroid/os/IBinder;
    //   138: astore 6
    //   140: aload 6
    //   142: invokestatic 85	com/google/android/gms/b/ix$a:a	(Landroid/os/IBinder;)Lcom/google/android/gms/b/ix;
    //   145: astore 6
    //   147: aload 8
    //   149: invokevirtual 67	android/os/Parcel:recycle	()V
    //   152: aload 7
    //   154: invokevirtual 67	android/os/Parcel:recycle	()V
    //   157: aload 6
    //   159: areturn
    //   160: iconst_0
    //   161: istore 10
    //   163: aconst_null
    //   164: astore 9
    //   166: goto -130 -> 36
    //   169: iconst_0
    //   170: istore 10
    //   172: aconst_null
    //   173: astore 9
    //   175: aload 7
    //   177: iconst_0
    //   178: invokevirtual 46	android/os/Parcel:writeInt	(I)V
    //   181: goto -111 -> 70
    //   184: astore 6
    //   186: aload 8
    //   188: invokevirtual 67	android/os/Parcel:recycle	()V
    //   191: aload 7
    //   193: invokevirtual 67	android/os/Parcel:recycle	()V
    //   196: aload 6
    //   198: athrow
    // Local variable table:
    //   start	length	slot	name	signature
    //   0	199	0	this	a
    //   0	199	1	parama	com.google.android.gms.a.a
    //   0	199	2	paramil	il
    //   0	199	3	paramString	String
    //   0	199	4	paramoc	oc
    //   0	199	5	paramInt	int
    //   1	157	6	localObject1	Object
    //   184	13	6	localObject2	Object
    //   6	186	7	localParcel1	android.os.Parcel
    //   11	176	8	localParcel2	android.os.Parcel
    //   15	159	9	localObject3	Object
    //   48	123	10	i	int
    // Exception table:
    //   from	to	target	type
    //   19	24	184	finally
    //   28	34	184	finally
    //   38	43	184	finally
    //   52	57	184	finally
    //   66	70	184	finally
    //   72	76	184	finally
    //   81	88	184	finally
    //   92	97	184	finally
    //   99	104	184	finally
    //   104	108	184	finally
    //   121	128	184	finally
    //   128	133	184	finally
    //   133	138	184	finally
    //   140	145	184	finally
    //   177	181	184	finally
  }
  
  /* Error */
  public final lj createNativeAdViewDelegate(com.google.android.gms.a.a parama1, com.google.android.gms.a.a parama2)
  {
    // Byte code:
    //   0: aconst_null
    //   1: astore_3
    //   2: invokestatic 20	android/os/Parcel:obtain	()Landroid/os/Parcel;
    //   5: astore 4
    //   7: invokestatic 20	android/os/Parcel:obtain	()Landroid/os/Parcel;
    //   10: astore 5
    //   12: ldc 22
    //   14: astore 6
    //   16: aload 4
    //   18: aload 6
    //   20: invokevirtual 26	android/os/Parcel:writeInterfaceToken	(Ljava/lang/String;)V
    //   23: aload_1
    //   24: ifnull +85 -> 109
    //   27: aload_1
    //   28: invokeinterface 32 1 0
    //   33: astore 6
    //   35: aload 4
    //   37: aload 6
    //   39: invokevirtual 36	android/os/Parcel:writeStrongBinder	(Landroid/os/IBinder;)V
    //   42: aload_2
    //   43: ifnull +10 -> 53
    //   46: aload_2
    //   47: invokeinterface 32 1 0
    //   52: astore_3
    //   53: aload 4
    //   55: aload_3
    //   56: invokevirtual 36	android/os/Parcel:writeStrongBinder	(Landroid/os/IBinder;)V
    //   59: aload_0
    //   60: getfield 14	com/google/android/gms/b/ja$a$a:a	Landroid/os/IBinder;
    //   63: astore_3
    //   64: iconst_5
    //   65: istore 7
    //   67: aload_3
    //   68: iload 7
    //   70: aload 4
    //   72: aload 5
    //   74: iconst_0
    //   75: invokeinterface 53 5 0
    //   80: pop
    //   81: aload 5
    //   83: invokevirtual 56	android/os/Parcel:readException	()V
    //   86: aload 5
    //   88: invokevirtual 59	android/os/Parcel:readStrongBinder	()Landroid/os/IBinder;
    //   91: astore_3
    //   92: aload_3
    //   93: invokestatic 98	com/google/android/gms/b/lj$a:a	(Landroid/os/IBinder;)Lcom/google/android/gms/b/lj;
    //   96: astore_3
    //   97: aload 5
    //   99: invokevirtual 67	android/os/Parcel:recycle	()V
    //   102: aload 4
    //   104: invokevirtual 67	android/os/Parcel:recycle	()V
    //   107: aload_3
    //   108: areturn
    //   109: iconst_0
    //   110: istore 7
    //   112: aconst_null
    //   113: astore 6
    //   115: goto -80 -> 35
    //   118: astore_3
    //   119: aload 5
    //   121: invokevirtual 67	android/os/Parcel:recycle	()V
    //   124: aload 4
    //   126: invokevirtual 67	android/os/Parcel:recycle	()V
    //   129: aload_3
    //   130: athrow
    // Local variable table:
    //   start	length	slot	name	signature
    //   0	131	0	this	a
    //   0	131	1	parama1	com.google.android.gms.a.a
    //   0	131	2	parama2	com.google.android.gms.a.a
    //   1	107	3	localObject1	Object
    //   118	12	3	localObject2	Object
    //   5	120	4	localParcel1	android.os.Parcel
    //   10	110	5	localParcel2	android.os.Parcel
    //   14	100	6	localObject3	Object
    //   65	46	7	i	int
    // Exception table:
    //   from	to	target	type
    //   18	23	118	finally
    //   27	33	118	finally
    //   37	42	118	finally
    //   46	52	118	finally
    //   55	59	118	finally
    //   59	63	118	finally
    //   74	81	118	finally
    //   81	86	118	finally
    //   86	91	118	finally
    //   92	96	118	finally
  }
  
  /* Error */
  public final rz createRewardedVideoAd(com.google.android.gms.a.a parama, oc paramoc, int paramInt)
  {
    // Byte code:
    //   0: aconst_null
    //   1: astore 4
    //   3: invokestatic 20	android/os/Parcel:obtain	()Landroid/os/Parcel;
    //   6: astore 5
    //   8: invokestatic 20	android/os/Parcel:obtain	()Landroid/os/Parcel;
    //   11: astore 6
    //   13: ldc 22
    //   15: astore 7
    //   17: aload 5
    //   19: aload 7
    //   21: invokevirtual 26	android/os/Parcel:writeInterfaceToken	(Ljava/lang/String;)V
    //   24: aload_1
    //   25: ifnull +100 -> 125
    //   28: aload_1
    //   29: invokeinterface 32 1 0
    //   34: astore 7
    //   36: aload 5
    //   38: aload 7
    //   40: invokevirtual 36	android/os/Parcel:writeStrongBinder	(Landroid/os/IBinder;)V
    //   43: aload_2
    //   44: ifnull +11 -> 55
    //   47: aload_2
    //   48: invokeinterface 42 1 0
    //   53: astore 4
    //   55: aload 5
    //   57: aload 4
    //   59: invokevirtual 36	android/os/Parcel:writeStrongBinder	(Landroid/os/IBinder;)V
    //   62: aload 5
    //   64: iload_3
    //   65: invokevirtual 46	android/os/Parcel:writeInt	(I)V
    //   68: aload_0
    //   69: getfield 14	com/google/android/gms/b/ja$a$a:a	Landroid/os/IBinder;
    //   72: astore 4
    //   74: bipush 6
    //   76: istore 8
    //   78: aload 4
    //   80: iload 8
    //   82: aload 5
    //   84: aload 6
    //   86: iconst_0
    //   87: invokeinterface 53 5 0
    //   92: pop
    //   93: aload 6
    //   95: invokevirtual 56	android/os/Parcel:readException	()V
    //   98: aload 6
    //   100: invokevirtual 59	android/os/Parcel:readStrongBinder	()Landroid/os/IBinder;
    //   103: astore 4
    //   105: aload 4
    //   107: invokestatic 104	com/google/android/gms/b/rz$a:a	(Landroid/os/IBinder;)Lcom/google/android/gms/b/rz;
    //   110: astore 4
    //   112: aload 6
    //   114: invokevirtual 67	android/os/Parcel:recycle	()V
    //   117: aload 5
    //   119: invokevirtual 67	android/os/Parcel:recycle	()V
    //   122: aload 4
    //   124: areturn
    //   125: iconst_0
    //   126: istore 8
    //   128: aconst_null
    //   129: astore 7
    //   131: goto -95 -> 36
    //   134: astore 4
    //   136: aload 6
    //   138: invokevirtual 67	android/os/Parcel:recycle	()V
    //   141: aload 5
    //   143: invokevirtual 67	android/os/Parcel:recycle	()V
    //   146: aload 4
    //   148: athrow
    // Local variable table:
    //   start	length	slot	name	signature
    //   0	149	0	this	a
    //   0	149	1	parama	com.google.android.gms.a.a
    //   0	149	2	paramoc	oc
    //   0	149	3	paramInt	int
    //   1	122	4	localObject1	Object
    //   134	13	4	localObject2	Object
    //   6	136	5	localParcel1	android.os.Parcel
    //   11	126	6	localParcel2	android.os.Parcel
    //   15	115	7	localObject3	Object
    //   76	51	8	i	int
    // Exception table:
    //   from	to	target	type
    //   19	24	134	finally
    //   28	34	134	finally
    //   38	43	134	finally
    //   47	53	134	finally
    //   57	62	134	finally
    //   64	68	134	finally
    //   68	72	134	finally
    //   86	93	134	finally
    //   93	98	134	finally
    //   98	103	134	finally
    //   105	110	134	finally
  }
  
  /* Error */
  public final ix createSearchAdManager(com.google.android.gms.a.a parama, il paramil, String paramString, int paramInt)
  {
    // Byte code:
    //   0: invokestatic 20	android/os/Parcel:obtain	()Landroid/os/Parcel;
    //   3: astore 5
    //   5: invokestatic 20	android/os/Parcel:obtain	()Landroid/os/Parcel;
    //   8: astore 6
    //   10: ldc 22
    //   12: astore 7
    //   14: aload 5
    //   16: aload 7
    //   18: invokevirtual 26	android/os/Parcel:writeInterfaceToken	(Ljava/lang/String;)V
    //   21: aload_1
    //   22: ifnull +115 -> 137
    //   25: aload_1
    //   26: invokeinterface 32 1 0
    //   31: astore 7
    //   33: aload 5
    //   35: aload 7
    //   37: invokevirtual 36	android/os/Parcel:writeStrongBinder	(Landroid/os/IBinder;)V
    //   40: aload_2
    //   41: ifnull +105 -> 146
    //   44: iconst_1
    //   45: istore 8
    //   47: aload 5
    //   49: iload 8
    //   51: invokevirtual 46	android/os/Parcel:writeInt	(I)V
    //   54: iconst_0
    //   55: istore 8
    //   57: aconst_null
    //   58: astore 7
    //   60: aload_2
    //   61: aload 5
    //   63: iconst_0
    //   64: invokevirtual 80	com/google/android/gms/b/il:writeToParcel	(Landroid/os/Parcel;I)V
    //   67: aload 5
    //   69: aload_3
    //   70: invokevirtual 39	android/os/Parcel:writeString	(Ljava/lang/String;)V
    //   73: aload 5
    //   75: iload 4
    //   77: invokevirtual 46	android/os/Parcel:writeInt	(I)V
    //   80: aload_0
    //   81: getfield 14	com/google/android/gms/b/ja$a$a:a	Landroid/os/IBinder;
    //   84: astore 7
    //   86: bipush 10
    //   88: istore 9
    //   90: aload 7
    //   92: iload 9
    //   94: aload 5
    //   96: aload 6
    //   98: iconst_0
    //   99: invokeinterface 53 5 0
    //   104: pop
    //   105: aload 6
    //   107: invokevirtual 56	android/os/Parcel:readException	()V
    //   110: aload 6
    //   112: invokevirtual 59	android/os/Parcel:readStrongBinder	()Landroid/os/IBinder;
    //   115: astore 7
    //   117: aload 7
    //   119: invokestatic 85	com/google/android/gms/b/ix$a:a	(Landroid/os/IBinder;)Lcom/google/android/gms/b/ix;
    //   122: astore 7
    //   124: aload 6
    //   126: invokevirtual 67	android/os/Parcel:recycle	()V
    //   129: aload 5
    //   131: invokevirtual 67	android/os/Parcel:recycle	()V
    //   134: aload 7
    //   136: areturn
    //   137: iconst_0
    //   138: istore 8
    //   140: aconst_null
    //   141: astore 7
    //   143: goto -110 -> 33
    //   146: iconst_0
    //   147: istore 8
    //   149: aconst_null
    //   150: astore 7
    //   152: aload 5
    //   154: iconst_0
    //   155: invokevirtual 46	android/os/Parcel:writeInt	(I)V
    //   158: goto -91 -> 67
    //   161: astore 7
    //   163: aload 6
    //   165: invokevirtual 67	android/os/Parcel:recycle	()V
    //   168: aload 5
    //   170: invokevirtual 67	android/os/Parcel:recycle	()V
    //   173: aload 7
    //   175: athrow
    // Local variable table:
    //   start	length	slot	name	signature
    //   0	176	0	this	a
    //   0	176	1	parama	com.google.android.gms.a.a
    //   0	176	2	paramil	il
    //   0	176	3	paramString	String
    //   0	176	4	paramInt	int
    //   3	166	5	localParcel1	android.os.Parcel
    //   8	156	6	localParcel2	android.os.Parcel
    //   12	139	7	localObject1	Object
    //   161	13	7	localObject2	Object
    //   45	103	8	i	int
    //   88	5	9	j	int
    // Exception table:
    //   from	to	target	type
    //   16	21	161	finally
    //   25	31	161	finally
    //   35	40	161	finally
    //   49	54	161	finally
    //   63	67	161	finally
    //   69	73	161	finally
    //   75	80	161	finally
    //   80	84	161	finally
    //   98	105	161	finally
    //   105	110	161	finally
    //   110	115	161	finally
    //   117	122	161	finally
    //   154	158	161	finally
  }
  
  /* Error */
  public final jc getMobileAdsSettingsManager(com.google.android.gms.a.a parama)
  {
    // Byte code:
    //   0: invokestatic 20	android/os/Parcel:obtain	()Landroid/os/Parcel;
    //   3: astore_2
    //   4: invokestatic 20	android/os/Parcel:obtain	()Landroid/os/Parcel;
    //   7: astore_3
    //   8: ldc 22
    //   10: astore 4
    //   12: aload_2
    //   13: aload 4
    //   15: invokevirtual 26	android/os/Parcel:writeInterfaceToken	(Ljava/lang/String;)V
    //   18: aload_1
    //   19: ifnull +67 -> 86
    //   22: aload_1
    //   23: invokeinterface 32 1 0
    //   28: astore 4
    //   30: aload_2
    //   31: aload 4
    //   33: invokevirtual 36	android/os/Parcel:writeStrongBinder	(Landroid/os/IBinder;)V
    //   36: aload_0
    //   37: getfield 14	com/google/android/gms/b/ja$a$a:a	Landroid/os/IBinder;
    //   40: astore 4
    //   42: iconst_4
    //   43: istore 5
    //   45: aload 4
    //   47: iload 5
    //   49: aload_2
    //   50: aload_3
    //   51: iconst_0
    //   52: invokeinterface 53 5 0
    //   57: pop
    //   58: aload_3
    //   59: invokevirtual 56	android/os/Parcel:readException	()V
    //   62: aload_3
    //   63: invokevirtual 59	android/os/Parcel:readStrongBinder	()Landroid/os/IBinder;
    //   66: astore 4
    //   68: aload 4
    //   70: invokestatic 111	com/google/android/gms/b/jc$a:a	(Landroid/os/IBinder;)Lcom/google/android/gms/b/jc;
    //   73: astore 4
    //   75: aload_3
    //   76: invokevirtual 67	android/os/Parcel:recycle	()V
    //   79: aload_2
    //   80: invokevirtual 67	android/os/Parcel:recycle	()V
    //   83: aload 4
    //   85: areturn
    //   86: aconst_null
    //   87: astore 4
    //   89: goto -59 -> 30
    //   92: astore 4
    //   94: aload_3
    //   95: invokevirtual 67	android/os/Parcel:recycle	()V
    //   98: aload_2
    //   99: invokevirtual 67	android/os/Parcel:recycle	()V
    //   102: aload 4
    //   104: athrow
    // Local variable table:
    //   start	length	slot	name	signature
    //   0	105	0	this	a
    //   0	105	1	parama	com.google.android.gms.a.a
    //   3	96	2	localParcel1	android.os.Parcel
    //   7	88	3	localParcel2	android.os.Parcel
    //   10	78	4	localObject1	Object
    //   92	11	4	localObject2	Object
    //   43	5	5	i	int
    // Exception table:
    //   from	to	target	type
    //   13	18	92	finally
    //   22	28	92	finally
    //   31	36	92	finally
    //   36	40	92	finally
    //   51	58	92	finally
    //   58	62	92	finally
    //   62	66	92	finally
    //   68	73	92	finally
  }
  
  /* Error */
  public final jc getMobileAdsSettingsManagerWithClientJarVersion(com.google.android.gms.a.a parama, int paramInt)
  {
    // Byte code:
    //   0: invokestatic 20	android/os/Parcel:obtain	()Landroid/os/Parcel;
    //   3: astore_3
    //   4: invokestatic 20	android/os/Parcel:obtain	()Landroid/os/Parcel;
    //   7: astore 4
    //   9: ldc 22
    //   11: astore 5
    //   13: aload_3
    //   14: aload 5
    //   16: invokevirtual 26	android/os/Parcel:writeInterfaceToken	(Ljava/lang/String;)V
    //   19: aload_1
    //   20: ifnull +77 -> 97
    //   23: aload_1
    //   24: invokeinterface 32 1 0
    //   29: astore 5
    //   31: aload_3
    //   32: aload 5
    //   34: invokevirtual 36	android/os/Parcel:writeStrongBinder	(Landroid/os/IBinder;)V
    //   37: aload_3
    //   38: iload_2
    //   39: invokevirtual 46	android/os/Parcel:writeInt	(I)V
    //   42: aload_0
    //   43: getfield 14	com/google/android/gms/b/ja$a$a:a	Landroid/os/IBinder;
    //   46: astore 5
    //   48: bipush 9
    //   50: istore 6
    //   52: aload 5
    //   54: iload 6
    //   56: aload_3
    //   57: aload 4
    //   59: iconst_0
    //   60: invokeinterface 53 5 0
    //   65: pop
    //   66: aload 4
    //   68: invokevirtual 56	android/os/Parcel:readException	()V
    //   71: aload 4
    //   73: invokevirtual 59	android/os/Parcel:readStrongBinder	()Landroid/os/IBinder;
    //   76: astore 5
    //   78: aload 5
    //   80: invokestatic 111	com/google/android/gms/b/jc$a:a	(Landroid/os/IBinder;)Lcom/google/android/gms/b/jc;
    //   83: astore 5
    //   85: aload 4
    //   87: invokevirtual 67	android/os/Parcel:recycle	()V
    //   90: aload_3
    //   91: invokevirtual 67	android/os/Parcel:recycle	()V
    //   94: aload 5
    //   96: areturn
    //   97: aconst_null
    //   98: astore 5
    //   100: goto -69 -> 31
    //   103: astore 5
    //   105: aload 4
    //   107: invokevirtual 67	android/os/Parcel:recycle	()V
    //   110: aload_3
    //   111: invokevirtual 67	android/os/Parcel:recycle	()V
    //   114: aload 5
    //   116: athrow
    // Local variable table:
    //   start	length	slot	name	signature
    //   0	117	0	this	a
    //   0	117	1	parama	com.google.android.gms.a.a
    //   0	117	2	paramInt	int
    //   3	108	3	localParcel1	android.os.Parcel
    //   7	99	4	localParcel2	android.os.Parcel
    //   11	88	5	localObject1	Object
    //   103	12	5	localObject2	Object
    //   50	5	6	i	int
    // Exception table:
    //   from	to	target	type
    //   14	19	103	finally
    //   23	29	103	finally
    //   32	37	103	finally
    //   38	42	103	finally
    //   42	46	103	finally
    //   59	66	103	finally
    //   66	71	103	finally
    //   71	76	103	finally
    //   78	83	103	finally
  }
}


/* Location:              com/google/android/gms/b/ja$a$a.class
 * Java compiler version: 5 (49.0)
 * JD-Core Version:       0.7.1
 */