package com.google.android.gms.b;

final class kg$1
  implements Runnable
{
  kg$1(kg paramkg) {}
  
  /* Error */
  public final void run()
  {
    // Byte code:
    //   0: aload_0
    //   1: getfield 10	com/google/android/gms/b/kg$1:a	Lcom/google/android/gms/b/kg;
    //   4: astore_1
    //   5: aload_1
    //   6: getfield 19	com/google/android/gms/b/kg:a	Ljava/util/concurrent/BlockingQueue;
    //   9: astore_2
    //   10: aload_2
    //   11: invokeinterface 25 1 0
    //   16: astore_2
    //   17: aload_2
    //   18: checkcast 27	com/google/android/gms/b/km
    //   21: astore_2
    //   22: aload_2
    //   23: invokevirtual 31	com/google/android/gms/b/km:b	()Ljava/lang/String;
    //   26: astore_3
    //   27: aload_3
    //   28: invokestatic 37	android/text/TextUtils:isEmpty	(Ljava/lang/CharSequence;)Z
    //   31: istore 4
    //   33: iload 4
    //   35: ifne -30 -> 5
    //   38: aload_1
    //   39: getfield 41	com/google/android/gms/b/kg:c	Ljava/util/LinkedHashMap;
    //   42: astore 5
    //   44: aload_2
    //   45: invokevirtual 44	com/google/android/gms/b/km:c	()Ljava/util/Map;
    //   48: astore_2
    //   49: aload_1
    //   50: aload 5
    //   52: aload_2
    //   53: invokevirtual 47	com/google/android/gms/b/kg:a	(Ljava/util/Map;Ljava/util/Map;)Ljava/util/Map;
    //   56: astore_2
    //   57: aload_1
    //   58: getfield 51	com/google/android/gms/b/kg:e	Ljava/lang/String;
    //   61: invokestatic 57	android/net/Uri:parse	(Ljava/lang/String;)Landroid/net/Uri;
    //   64: astore 5
    //   66: aload 5
    //   68: invokevirtual 61	android/net/Uri:buildUpon	()Landroid/net/Uri$Builder;
    //   71: astore 6
    //   73: aload_2
    //   74: invokeinterface 67 1 0
    //   79: astore_2
    //   80: aload_2
    //   81: invokeinterface 73 1 0
    //   86: astore 7
    //   88: aload 7
    //   90: invokeinterface 79 1 0
    //   95: istore 8
    //   97: iload 8
    //   99: ifeq +55 -> 154
    //   102: aload 7
    //   104: invokeinterface 82 1 0
    //   109: checkcast 84	java/util/Map$Entry
    //   112: astore_2
    //   113: aload_2
    //   114: invokeinterface 87 1 0
    //   119: checkcast 89	java/lang/String
    //   122: astore 5
    //   124: aload_2
    //   125: invokeinterface 92 1 0
    //   130: checkcast 89	java/lang/String
    //   133: astore_2
    //   134: aload 6
    //   136: aload 5
    //   138: aload_2
    //   139: invokevirtual 98	android/net/Uri$Builder:appendQueryParameter	(Ljava/lang/String;Ljava/lang/String;)Landroid/net/Uri$Builder;
    //   142: pop
    //   143: goto -55 -> 88
    //   146: astore_2
    //   147: ldc 100
    //   149: aload_2
    //   150: invokestatic 105	com/google/android/gms/b/tp:c	(Ljava/lang/String;Ljava/lang/Throwable;)V
    //   153: return
    //   154: new 107	java/lang/StringBuilder
    //   157: astore_2
    //   158: aload 6
    //   160: invokevirtual 111	android/net/Uri$Builder:build	()Landroid/net/Uri;
    //   163: invokevirtual 114	android/net/Uri:toString	()Ljava/lang/String;
    //   166: astore 5
    //   168: aload_2
    //   169: aload 5
    //   171: invokespecial 117	java/lang/StringBuilder:<init>	(Ljava/lang/String;)V
    //   174: aload_2
    //   175: ldc 119
    //   177: invokevirtual 123	java/lang/StringBuilder:append	(Ljava/lang/String;)Ljava/lang/StringBuilder;
    //   180: aload_3
    //   181: invokevirtual 123	java/lang/StringBuilder:append	(Ljava/lang/String;)Ljava/lang/StringBuilder;
    //   184: pop
    //   185: aload_2
    //   186: invokevirtual 124	java/lang/StringBuilder:toString	()Ljava/lang/String;
    //   189: astore_2
    //   190: aload_1
    //   191: getfield 128	com/google/android/gms/b/kg:h	Ljava/util/concurrent/atomic/AtomicBoolean;
    //   194: astore 5
    //   196: aload 5
    //   198: invokevirtual 133	java/util/concurrent/atomic/AtomicBoolean:get	()Z
    //   201: istore 4
    //   203: iload 4
    //   205: ifeq +162 -> 367
    //   208: aload_1
    //   209: getfield 137	com/google/android/gms/b/kg:i	Ljava/io/File;
    //   212: astore 6
    //   214: aload 6
    //   216: ifnull +141 -> 357
    //   219: aconst_null
    //   220: astore_3
    //   221: new 139	java/io/FileOutputStream
    //   224: astore 5
    //   226: iconst_1
    //   227: istore 9
    //   229: aload 5
    //   231: aload 6
    //   233: iload 9
    //   235: invokespecial 143	java/io/FileOutputStream:<init>	(Ljava/io/File;Z)V
    //   238: aload_2
    //   239: invokevirtual 147	java/lang/String:getBytes	()[B
    //   242: astore_2
    //   243: aload 5
    //   245: aload_2
    //   246: invokevirtual 151	java/io/FileOutputStream:write	([B)V
    //   249: bipush 10
    //   251: istore 8
    //   253: aload 5
    //   255: iload 8
    //   257: invokevirtual 155	java/io/FileOutputStream:write	(I)V
    //   260: aload 5
    //   262: invokevirtual 158	java/io/FileOutputStream:close	()V
    //   265: goto -260 -> 5
    //   268: astore_2
    //   269: ldc -96
    //   271: astore 5
    //   273: aload 5
    //   275: aload_2
    //   276: invokestatic 105	com/google/android/gms/b/tp:c	(Ljava/lang/String;Ljava/lang/Throwable;)V
    //   279: goto -274 -> 5
    //   282: astore_2
    //   283: iconst_0
    //   284: istore 4
    //   286: aconst_null
    //   287: astore 5
    //   289: ldc -94
    //   291: astore_3
    //   292: aload_3
    //   293: aload_2
    //   294: invokestatic 105	com/google/android/gms/b/tp:c	(Ljava/lang/String;Ljava/lang/Throwable;)V
    //   297: aload 5
    //   299: ifnull -294 -> 5
    //   302: aload 5
    //   304: invokevirtual 158	java/io/FileOutputStream:close	()V
    //   307: goto -302 -> 5
    //   310: astore_2
    //   311: ldc -96
    //   313: astore 5
    //   315: aload 5
    //   317: aload_2
    //   318: invokestatic 105	com/google/android/gms/b/tp:c	(Ljava/lang/String;Ljava/lang/Throwable;)V
    //   321: goto -316 -> 5
    //   324: astore_2
    //   325: iconst_0
    //   326: istore 4
    //   328: aconst_null
    //   329: astore 5
    //   331: aload 5
    //   333: ifnull +8 -> 341
    //   336: aload 5
    //   338: invokevirtual 158	java/io/FileOutputStream:close	()V
    //   341: aload_2
    //   342: athrow
    //   343: astore 5
    //   345: ldc -96
    //   347: astore_3
    //   348: aload_3
    //   349: aload 5
    //   351: invokestatic 105	com/google/android/gms/b/tp:c	(Ljava/lang/String;Ljava/lang/Throwable;)V
    //   354: goto -13 -> 341
    //   357: ldc -92
    //   359: astore_2
    //   360: aload_2
    //   361: invokestatic 166	com/google/android/gms/b/tp:e	(Ljava/lang/String;)V
    //   364: goto -359 -> 5
    //   367: invokestatic 171	com/google/android/gms/ads/internal/w:e	()Lcom/google/android/gms/b/tt;
    //   370: pop
    //   371: aload_1
    //   372: getfield 175	com/google/android/gms/b/kg:f	Landroid/content/Context;
    //   375: astore 5
    //   377: aload_1
    //   378: getfield 178	com/google/android/gms/b/kg:g	Ljava/lang/String;
    //   381: astore_3
    //   382: aload 5
    //   384: aload_3
    //   385: aload_2
    //   386: invokestatic 183	com/google/android/gms/b/tt:b	(Landroid/content/Context;Ljava/lang/String;Ljava/lang/String;)V
    //   389: goto -384 -> 5
    //   392: astore_2
    //   393: goto -62 -> 331
    //   396: astore_2
    //   397: goto -108 -> 289
    // Local variable table:
    //   start	length	slot	name	signature
    //   0	400	0	this	1
    //   4	374	1	localkg	kg
    //   9	130	2	localObject1	Object
    //   146	4	2	localInterruptedException	InterruptedException
    //   157	89	2	localObject2	Object
    //   268	8	2	localIOException1	java.io.IOException
    //   282	12	2	localIOException2	java.io.IOException
    //   310	8	2	localIOException3	java.io.IOException
    //   324	18	2	localObject3	Object
    //   359	27	2	str1	String
    //   392	1	2	localObject4	Object
    //   396	1	2	localIOException4	java.io.IOException
    //   26	359	3	str2	String
    //   31	296	4	bool1	boolean
    //   42	295	5	localObject5	Object
    //   343	7	5	localIOException5	java.io.IOException
    //   375	8	5	localContext	android.content.Context
    //   71	161	6	localObject6	Object
    //   86	17	7	localIterator	java.util.Iterator
    //   95	3	8	bool2	boolean
    //   251	5	8	i	int
    //   227	7	9	bool3	boolean
    // Exception table:
    //   from	to	target	type
    //   5	9	146	java/lang/InterruptedException
    //   10	16	146	java/lang/InterruptedException
    //   17	21	146	java/lang/InterruptedException
    //   22	26	146	java/lang/InterruptedException
    //   260	265	268	java/io/IOException
    //   221	224	282	java/io/IOException
    //   233	238	282	java/io/IOException
    //   302	307	310	java/io/IOException
    //   221	224	324	finally
    //   233	238	324	finally
    //   336	341	343	java/io/IOException
    //   238	242	392	finally
    //   245	249	392	finally
    //   255	260	392	finally
    //   293	297	392	finally
    //   238	242	396	java/io/IOException
    //   245	249	396	java/io/IOException
    //   255	260	396	java/io/IOException
  }
}


/* Location:              com/google/android/gms/b/kg$1.class
 * Java compiler version: 5 (49.0)
 * JD-Core Version:       0.7.1
 */