package com.google.android.gms.b;

import java.util.concurrent.BlockingQueue;

public final class lb
  extends Thread
{
  volatile boolean a = false;
  private final BlockingQueue b;
  private final ka c;
  private final dz d;
  private final sf e;
  
  public lb(BlockingQueue paramBlockingQueue, ka paramka, dz paramdz, sf paramsf)
  {
    b = paramBlockingQueue;
    c = paramka;
    d = paramdz;
    e = paramsf;
  }
  
  /* Error */
  public final void run()
  {
    // Byte code:
    //   0: iconst_1
    //   1: istore_1
    //   2: bipush 10
    //   4: istore_2
    //   5: iload_2
    //   6: invokestatic 36	android/os/Process:setThreadPriority	(I)V
    //   9: invokestatic 42	android/os/SystemClock:elapsedRealtime	()J
    //   12: lstore_3
    //   13: aload_0
    //   14: getfield 22	com/google/android/gms/b/lb:b	Ljava/util/concurrent/BlockingQueue;
    //   17: astore 5
    //   19: aload 5
    //   21: invokeinterface 48 1 0
    //   26: astore 5
    //   28: aload 5
    //   30: checkcast 50	com/google/android/gms/b/pc
    //   33: astore 5
    //   35: ldc 52
    //   37: astore 6
    //   39: aload 5
    //   41: aload 6
    //   43: invokevirtual 55	com/google/android/gms/b/pc:a	(Ljava/lang/String;)V
    //   46: getstatic 61	android/os/Build$VERSION:SDK_INT	I
    //   49: istore 7
    //   51: aload 5
    //   53: getfield 63	com/google/android/gms/b/pc:c	I
    //   56: istore 7
    //   58: iload 7
    //   60: invokestatic 68	android/net/TrafficStats:setThreadStatsTag	(I)V
    //   63: aload_0
    //   64: getfield 24	com/google/android/gms/b/lb:c	Lcom/google/android/gms/b/ka;
    //   67: astore 6
    //   69: aload 6
    //   71: aload 5
    //   73: invokeinterface 73 2 0
    //   78: astore 6
    //   80: ldc 75
    //   82: astore 8
    //   84: aload 5
    //   86: aload 8
    //   88: invokevirtual 55	com/google/android/gms/b/pc:a	(Ljava/lang/String;)V
    //   91: aload 6
    //   93: getfield 79	com/google/android/gms/b/na:d	Z
    //   96: istore 9
    //   98: iload 9
    //   100: ifeq +86 -> 186
    //   103: aload 5
    //   105: getfield 82	com/google/android/gms/b/pc:h	Z
    //   108: istore 9
    //   110: iload 9
    //   112: ifeq +74 -> 186
    //   115: ldc 84
    //   117: astore 6
    //   119: aload 5
    //   121: aload 6
    //   123: invokevirtual 86	com/google/android/gms/b/pc:b	(Ljava/lang/String;)V
    //   126: goto -117 -> 9
    //   129: astore 6
    //   131: invokestatic 42	android/os/SystemClock:elapsedRealtime	()J
    //   134: lstore 10
    //   136: lload 10
    //   138: lload_3
    //   139: lsub
    //   140: lstore_3
    //   141: aload 6
    //   143: lload_3
    //   144: putfield 91	com/google/android/gms/b/vr:b	J
    //   147: aload 6
    //   149: invokestatic 94	com/google/android/gms/b/pc:a	(Lcom/google/android/gms/b/vr;)Lcom/google/android/gms/b/vr;
    //   152: astore 6
    //   154: aload_0
    //   155: getfield 28	com/google/android/gms/b/lb:e	Lcom/google/android/gms/b/sf;
    //   158: astore 12
    //   160: aload 12
    //   162: aload 5
    //   164: aload 6
    //   166: invokeinterface 99 3 0
    //   171: goto -162 -> 9
    //   174: astore 5
    //   176: aload_0
    //   177: getfield 20	com/google/android/gms/b/lb:a	Z
    //   180: istore_2
    //   181: iload_2
    //   182: ifeq -173 -> 9
    //   185: return
    //   186: aload 5
    //   188: aload 6
    //   190: invokevirtual 102	com/google/android/gms/b/pc:a	(Lcom/google/android/gms/b/na;)Lcom/google/android/gms/b/re;
    //   193: astore 6
    //   195: ldc 104
    //   197: astore 8
    //   199: aload 5
    //   201: aload 8
    //   203: invokevirtual 55	com/google/android/gms/b/pc:a	(Ljava/lang/String;)V
    //   206: aload 5
    //   208: getfield 107	com/google/android/gms/b/pc:g	Z
    //   211: istore 9
    //   213: iload 9
    //   215: ifeq +57 -> 272
    //   218: aload 6
    //   220: getfield 112	com/google/android/gms/b/re:b	Lcom/google/android/gms/b/dz$a;
    //   223: astore 8
    //   225: aload 8
    //   227: ifnull +45 -> 272
    //   230: aload_0
    //   231: getfield 26	com/google/android/gms/b/lb:d	Lcom/google/android/gms/b/dz;
    //   234: astore 8
    //   236: aload 5
    //   238: getfield 115	com/google/android/gms/b/pc:b	Ljava/lang/String;
    //   241: astore 13
    //   243: aload 6
    //   245: getfield 112	com/google/android/gms/b/re:b	Lcom/google/android/gms/b/dz$a;
    //   248: astore 14
    //   250: aload 8
    //   252: aload 13
    //   254: aload 14
    //   256: invokeinterface 120 3 0
    //   261: ldc 122
    //   263: astore 8
    //   265: aload 5
    //   267: aload 8
    //   269: invokevirtual 55	com/google/android/gms/b/pc:a	(Ljava/lang/String;)V
    //   272: iconst_1
    //   273: istore 9
    //   275: aload 5
    //   277: iload 9
    //   279: putfield 82	com/google/android/gms/b/pc:h	Z
    //   282: aload_0
    //   283: getfield 28	com/google/android/gms/b/lb:e	Lcom/google/android/gms/b/sf;
    //   286: astore 8
    //   288: aload 8
    //   290: aload 5
    //   292: aload 6
    //   294: invokeinterface 125 3 0
    //   299: goto -290 -> 9
    //   302: astore 6
    //   304: iload_1
    //   305: anewarray 129	java/lang/Object
    //   308: astore 13
    //   310: aconst_null
    //   311: astore 14
    //   313: aload 6
    //   315: invokevirtual 135	java/lang/Exception:toString	()Ljava/lang/String;
    //   318: astore 15
    //   320: aload 13
    //   322: iconst_0
    //   323: aload 15
    //   325: aastore
    //   326: aload 6
    //   328: ldc 127
    //   330: aload 13
    //   332: invokestatic 140	com/google/android/gms/b/vs:a	(Ljava/lang/Throwable;Ljava/lang/String;[Ljava/lang/Object;)V
    //   335: new 88	com/google/android/gms/b/vr
    //   338: astore 8
    //   340: aload 8
    //   342: aload 6
    //   344: invokespecial 143	com/google/android/gms/b/vr:<init>	(Ljava/lang/Throwable;)V
    //   347: invokestatic 42	android/os/SystemClock:elapsedRealtime	()J
    //   350: lstore 16
    //   352: lload 16
    //   354: lload_3
    //   355: lsub
    //   356: lstore_3
    //   357: aload 8
    //   359: lload_3
    //   360: putfield 91	com/google/android/gms/b/vr:b	J
    //   363: aload_0
    //   364: getfield 28	com/google/android/gms/b/lb:e	Lcom/google/android/gms/b/sf;
    //   367: astore 6
    //   369: aload 6
    //   371: aload 5
    //   373: aload 8
    //   375: invokeinterface 99 3 0
    //   380: goto -371 -> 9
    // Local variable table:
    //   start	length	slot	name	signature
    //   0	383	0	this	lb
    //   1	304	1	i	int
    //   4	2	2	j	int
    //   180	2	2	bool1	boolean
    //   12	348	3	l1	long
    //   17	146	5	localObject1	Object
    //   174	198	5	localInterruptedException	InterruptedException
    //   37	85	6	localObject2	Object
    //   129	19	6	localvr	vr
    //   152	141	6	localObject3	Object
    //   302	41	6	localException	Exception
    //   367	3	6	localsf1	sf
    //   49	10	7	k	int
    //   82	292	8	localObject4	Object
    //   96	182	9	bool2	boolean
    //   134	3	10	l2	long
    //   158	3	12	localsf2	sf
    //   241	90	13	localObject5	Object
    //   248	64	14	locala	dz.a
    //   318	6	15	str	String
    //   350	3	16	l3	long
    // Exception table:
    //   from	to	target	type
    //   41	46	129	com/google/android/gms/b/vr
    //   46	49	129	com/google/android/gms/b/vr
    //   51	56	129	com/google/android/gms/b/vr
    //   58	63	129	com/google/android/gms/b/vr
    //   63	67	129	com/google/android/gms/b/vr
    //   71	78	129	com/google/android/gms/b/vr
    //   86	91	129	com/google/android/gms/b/vr
    //   91	96	129	com/google/android/gms/b/vr
    //   103	108	129	com/google/android/gms/b/vr
    //   121	126	129	com/google/android/gms/b/vr
    //   188	193	129	com/google/android/gms/b/vr
    //   201	206	129	com/google/android/gms/b/vr
    //   206	211	129	com/google/android/gms/b/vr
    //   218	223	129	com/google/android/gms/b/vr
    //   230	234	129	com/google/android/gms/b/vr
    //   236	241	129	com/google/android/gms/b/vr
    //   243	248	129	com/google/android/gms/b/vr
    //   254	261	129	com/google/android/gms/b/vr
    //   267	272	129	com/google/android/gms/b/vr
    //   277	282	129	com/google/android/gms/b/vr
    //   282	286	129	com/google/android/gms/b/vr
    //   292	299	129	com/google/android/gms/b/vr
    //   13	17	174	java/lang/InterruptedException
    //   19	26	174	java/lang/InterruptedException
    //   28	33	174	java/lang/InterruptedException
    //   41	46	302	java/lang/Exception
    //   46	49	302	java/lang/Exception
    //   51	56	302	java/lang/Exception
    //   58	63	302	java/lang/Exception
    //   63	67	302	java/lang/Exception
    //   71	78	302	java/lang/Exception
    //   86	91	302	java/lang/Exception
    //   91	96	302	java/lang/Exception
    //   103	108	302	java/lang/Exception
    //   121	126	302	java/lang/Exception
    //   188	193	302	java/lang/Exception
    //   201	206	302	java/lang/Exception
    //   206	211	302	java/lang/Exception
    //   218	223	302	java/lang/Exception
    //   230	234	302	java/lang/Exception
    //   236	241	302	java/lang/Exception
    //   243	248	302	java/lang/Exception
    //   254	261	302	java/lang/Exception
    //   267	272	302	java/lang/Exception
    //   277	282	302	java/lang/Exception
    //   282	286	302	java/lang/Exception
    //   292	299	302	java/lang/Exception
  }
}


/* Location:              com/google/android/gms/b/lb.class
 * Java compiler version: 5 (49.0)
 * JD-Core Version:       0.7.1
 */