package com.google.android.gms.b;

import android.content.Context;
import java.io.File;
import java.text.DecimalFormat;
import java.util.Collections;
import java.util.HashSet;
import java.util.Set;

public final class mv
  extends ms
{
  private static final Set d;
  private static final DecimalFormat e;
  private File f;
  private boolean g;
  
  static
  {
    Object localObject = new java/util/HashSet;
    ((HashSet)localObject).<init>();
    d = Collections.synchronizedSet((Set)localObject);
    localObject = new java/text/DecimalFormat;
    ((DecimalFormat)localObject).<init>("#,###");
    e = (DecimalFormat)localObject;
  }
  
  public mv(vc paramvc)
  {
    super(paramvc);
    Object localObject1 = a.getCacheDir();
    if (localObject1 == null)
    {
      localObject1 = "Context.getCacheDir() returned null";
      tp.e((String)localObject1);
    }
    boolean bool2;
    do
    {
      return;
      localObject2 = new java/io/File;
      String str = "admobVideoStreams";
      ((File)localObject2).<init>((File)localObject1, str);
      f = ((File)localObject2);
      localObject1 = f;
      bool2 = ((File)localObject1).isDirectory();
      if (!bool2)
      {
        localObject1 = f;
        bool2 = ((File)localObject1).mkdirs();
        if (!bool2)
        {
          localObject2 = "Could not create preload cache directory at ";
          localObject1 = String.valueOf(f.getAbsolutePath());
          i = ((String)localObject1).length();
          if (i != 0) {
            localObject1 = ((String)localObject2).concat((String)localObject1);
          }
          for (;;)
          {
            tp.e((String)localObject1);
            f = null;
            break;
            localObject1 = new java/lang/String;
            ((String)localObject1).<init>((String)localObject2);
          }
        }
      }
      localObject1 = f;
      bool2 = ((File)localObject1).setReadable(bool1, false);
      if (!bool2) {
        break;
      }
      localObject1 = f;
      bool2 = ((File)localObject1).setExecutable(bool1, false);
    } while (bool2);
    Object localObject2 = "Could not set cache file permissions at ";
    localObject1 = String.valueOf(f.getAbsolutePath());
    int i = ((String)localObject1).length();
    if (i != 0) {
      localObject1 = ((String)localObject2).concat((String)localObject1);
    }
    for (;;)
    {
      tp.e((String)localObject1);
      f = null;
      break;
      localObject1 = new java/lang/String;
      ((String)localObject1).<init>((String)localObject2);
    }
  }
  
  private File a(File paramFile)
  {
    File localFile1 = new java/io/File;
    File localFile2 = f;
    String str = String.valueOf(paramFile.getName()).concat(".done");
    localFile1.<init>(localFile2, str);
    return localFile1;
  }
  
  public final void a()
  {
    g = true;
  }
  
  /* Error */
  public final boolean a(String paramString)
  {
    // Byte code:
    //   0: aload_0
    //   1: astore_2
    //   2: aload_0
    //   3: getfield 64	com/google/android/gms/b/mv:f	Ljava/io/File;
    //   6: astore_3
    //   7: aload_3
    //   8: ifnonnull +30 -> 38
    //   11: ldc 110
    //   13: astore 4
    //   15: iconst_0
    //   16: istore 5
    //   18: aconst_null
    //   19: astore 6
    //   21: aload_0
    //   22: aload_1
    //   23: aconst_null
    //   24: aload 4
    //   26: aconst_null
    //   27: invokevirtual 113	com/google/android/gms/b/mv:a	(Ljava/lang/String;Ljava/lang/String;Ljava/lang/String;Ljava/lang/String;)V
    //   30: iconst_0
    //   31: istore 7
    //   33: aconst_null
    //   34: astore_3
    //   35: iload 7
    //   37: ireturn
    //   38: aload_0
    //   39: astore_2
    //   40: aload_0
    //   41: getfield 64	com/google/android/gms/b/mv:f	Ljava/io/File;
    //   44: astore_3
    //   45: aload_3
    //   46: ifnonnull +101 -> 147
    //   49: iconst_0
    //   50: istore 7
    //   52: aconst_null
    //   53: astore_3
    //   54: iconst_0
    //   55: istore 8
    //   57: aconst_null
    //   58: astore 4
    //   60: getstatic 119	com/google/android/gms/b/ke:q	Lcom/google/android/gms/b/jz;
    //   63: astore_3
    //   64: invokestatic 124	com/google/android/gms/ads/internal/w:q	()Lcom/google/android/gms/b/kd;
    //   67: astore 6
    //   69: aload 6
    //   71: aload_3
    //   72: invokevirtual 129	com/google/android/gms/b/kd:a	(Lcom/google/android/gms/b/jz;)Ljava/lang/Object;
    //   75: checkcast 131	java/lang/Integer
    //   78: astore_3
    //   79: aload_3
    //   80: invokevirtual 134	java/lang/Integer:intValue	()I
    //   83: istore 7
    //   85: iload 8
    //   87: iload 7
    //   89: if_icmple +313 -> 402
    //   92: aload_0
    //   93: astore_2
    //   94: aload_0
    //   95: getfield 64	com/google/android/gms/b/mv:f	Ljava/io/File;
    //   98: astore_3
    //   99: aload_3
    //   100: ifnonnull +129 -> 229
    //   103: iconst_0
    //   104: istore 7
    //   106: aconst_null
    //   107: astore_3
    //   108: iload 7
    //   110: ifne -72 -> 38
    //   113: ldc -120
    //   115: invokestatic 55	com/google/android/gms/b/tp:e	(Ljava/lang/String;)V
    //   118: ldc -118
    //   120: astore 4
    //   122: iconst_0
    //   123: istore 5
    //   125: aconst_null
    //   126: astore 6
    //   128: aload_0
    //   129: astore_2
    //   130: aload_0
    //   131: aload_1
    //   132: aconst_null
    //   133: aload 4
    //   135: aconst_null
    //   136: invokevirtual 113	com/google/android/gms/b/mv:a	(Ljava/lang/String;Ljava/lang/String;Ljava/lang/String;Ljava/lang/String;)V
    //   139: iconst_0
    //   140: istore 7
    //   142: aconst_null
    //   143: astore_3
    //   144: goto -109 -> 35
    //   147: aload_0
    //   148: getfield 64	com/google/android/gms/b/mv:f	Ljava/io/File;
    //   151: invokevirtual 142	java/io/File:listFiles	()[Ljava/io/File;
    //   154: astore 6
    //   156: aload 6
    //   158: arraylength
    //   159: istore 9
    //   161: iconst_0
    //   162: istore 7
    //   164: aconst_null
    //   165: astore_3
    //   166: iconst_0
    //   167: istore 8
    //   169: aconst_null
    //   170: astore 4
    //   172: iload 8
    //   174: iload 9
    //   176: if_icmpge +46 -> 222
    //   179: aload 6
    //   181: iload 8
    //   183: aaload
    //   184: invokevirtual 104	java/io/File:getName	()Ljava/lang/String;
    //   187: astore 10
    //   189: ldc 106
    //   191: astore 11
    //   193: aload 10
    //   195: aload 11
    //   197: invokevirtual 146	java/lang/String:endsWith	(Ljava/lang/String;)Z
    //   200: istore 12
    //   202: iload 12
    //   204: ifne +9 -> 213
    //   207: iload 7
    //   209: iconst_1
    //   210: iadd
    //   211: istore 7
    //   213: iload 8
    //   215: iconst_1
    //   216: iadd
    //   217: istore 8
    //   219: goto -47 -> 172
    //   222: iload 7
    //   224: istore 8
    //   226: goto -166 -> 60
    //   229: iconst_0
    //   230: istore 13
    //   232: aconst_null
    //   233: astore 11
    //   235: ldc2_w 147
    //   238: lstore 14
    //   240: aload_0
    //   241: getfield 64	com/google/android/gms/b/mv:f	Ljava/io/File;
    //   244: invokevirtual 142	java/io/File:listFiles	()[Ljava/io/File;
    //   247: astore 16
    //   249: aload 16
    //   251: arraylength
    //   252: istore 17
    //   254: iconst_0
    //   255: istore 7
    //   257: aconst_null
    //   258: astore_3
    //   259: iconst_0
    //   260: istore 18
    //   262: aconst_null
    //   263: astore 19
    //   265: iload 18
    //   267: iload 17
    //   269: if_icmpge +77 -> 346
    //   272: aload 16
    //   274: iload 18
    //   276: aaload
    //   277: astore 10
    //   279: aload 10
    //   281: invokevirtual 104	java/io/File:getName	()Ljava/lang/String;
    //   284: astore_3
    //   285: ldc 106
    //   287: astore 4
    //   289: aload_3
    //   290: aload 4
    //   292: invokevirtual 146	java/lang/String:endsWith	(Ljava/lang/String;)Z
    //   295: istore 7
    //   297: iload 7
    //   299: ifne +2259 -> 2558
    //   302: aload 10
    //   304: invokevirtual 152	java/io/File:lastModified	()J
    //   307: lstore 20
    //   309: lload 20
    //   311: lload 14
    //   313: lcmp
    //   314: istore 22
    //   316: iload 22
    //   318: ifge +2240 -> 2558
    //   321: aload 10
    //   323: astore 6
    //   325: iload 18
    //   327: iconst_1
    //   328: iadd
    //   329: istore 9
    //   331: aload 6
    //   333: astore 11
    //   335: iload 9
    //   337: istore 18
    //   339: lload 20
    //   341: lstore 14
    //   343: goto -78 -> 265
    //   346: iconst_0
    //   347: istore 7
    //   349: aconst_null
    //   350: astore_3
    //   351: aload 11
    //   353: ifnull -245 -> 108
    //   356: aload 11
    //   358: invokevirtual 155	java/io/File:delete	()Z
    //   361: istore 7
    //   363: aload_0
    //   364: astore_2
    //   365: aload_0
    //   366: aload 11
    //   368: invokespecial 158	com/google/android/gms/b/mv:a	(Ljava/io/File;)Ljava/io/File;
    //   371: astore 4
    //   373: aload 4
    //   375: invokevirtual 161	java/io/File:isFile	()Z
    //   378: istore 5
    //   380: iload 5
    //   382: ifeq -274 -> 108
    //   385: aload 4
    //   387: invokevirtual 155	java/io/File:delete	()Z
    //   390: istore 8
    //   392: iload 7
    //   394: iload 8
    //   396: iand
    //   397: istore 7
    //   399: goto -291 -> 108
    //   402: invokestatic 166	com/google/android/gms/b/ip:a	()Lcom/google/android/gms/b/uk;
    //   405: pop
    //   406: aload_1
    //   407: invokestatic 170	com/google/android/gms/b/uk:a	(Ljava/lang/String;)Ljava/lang/String;
    //   410: astore_3
    //   411: new 57	java/io/File
    //   414: astore 23
    //   416: aload_0
    //   417: astore_2
    //   418: aload_0
    //   419: getfield 64	com/google/android/gms/b/mv:f	Ljava/io/File;
    //   422: astore 4
    //   424: aload 23
    //   426: aload 4
    //   428: aload_3
    //   429: invokespecial 62	java/io/File:<init>	(Ljava/io/File;Ljava/lang/String;)V
    //   432: aload_0
    //   433: aload 23
    //   435: invokespecial 158	com/google/android/gms/b/mv:a	(Ljava/io/File;)Ljava/io/File;
    //   438: astore 24
    //   440: aload 23
    //   442: invokevirtual 161	java/io/File:isFile	()Z
    //   445: istore 7
    //   447: iload 7
    //   449: ifeq +93 -> 542
    //   452: aload 24
    //   454: invokevirtual 161	java/io/File:isFile	()Z
    //   457: istore 7
    //   459: iload 7
    //   461: ifeq +81 -> 542
    //   464: aload 23
    //   466: invokevirtual 172	java/io/File:length	()J
    //   469: lstore 20
    //   471: lload 20
    //   473: l2i
    //   474: istore 8
    //   476: ldc -82
    //   478: astore 6
    //   480: aload_1
    //   481: invokestatic 83	java/lang/String:valueOf	(Ljava/lang/Object;)Ljava/lang/String;
    //   484: astore_3
    //   485: aload_3
    //   486: invokevirtual 87	java/lang/String:length	()I
    //   489: istore 9
    //   491: iload 9
    //   493: ifeq +36 -> 529
    //   496: aload 6
    //   498: aload_3
    //   499: invokevirtual 91	java/lang/String:concat	(Ljava/lang/String;)Ljava/lang/String;
    //   502: astore_3
    //   503: aload_3
    //   504: invokestatic 177	com/google/android/gms/b/tp:b	(Ljava/lang/String;)V
    //   507: aload 23
    //   509: invokevirtual 77	java/io/File:getAbsolutePath	()Ljava/lang/String;
    //   512: astore_3
    //   513: aload_0
    //   514: astore_2
    //   515: aload_0
    //   516: aload_1
    //   517: aload_3
    //   518: iload 8
    //   520: invokevirtual 180	com/google/android/gms/b/mv:a	(Ljava/lang/String;Ljava/lang/String;I)V
    //   523: iconst_1
    //   524: istore 7
    //   526: goto -491 -> 35
    //   529: new 79	java/lang/String
    //   532: astore_3
    //   533: aload_3
    //   534: aload 6
    //   536: invokespecial 92	java/lang/String:<init>	(Ljava/lang/String;)V
    //   539: goto -36 -> 503
    //   542: aload_0
    //   543: astore_2
    //   544: aload_0
    //   545: getfield 64	com/google/android/gms/b/mv:f	Ljava/io/File;
    //   548: invokevirtual 77	java/io/File:getAbsolutePath	()Ljava/lang/String;
    //   551: invokestatic 83	java/lang/String:valueOf	(Ljava/lang/Object;)Ljava/lang/String;
    //   554: astore 4
    //   556: aload_1
    //   557: invokestatic 83	java/lang/String:valueOf	(Ljava/lang/Object;)Ljava/lang/String;
    //   560: astore_3
    //   561: aload_3
    //   562: invokevirtual 87	java/lang/String:length	()I
    //   565: istore 5
    //   567: iload 5
    //   569: ifeq +115 -> 684
    //   572: aload 4
    //   574: aload_3
    //   575: invokevirtual 91	java/lang/String:concat	(Ljava/lang/String;)Ljava/lang/String;
    //   578: astore_3
    //   579: aload_3
    //   580: astore 19
    //   582: getstatic 26	com/google/android/gms/b/mv:d	Ljava/util/Set;
    //   585: astore 4
    //   587: aload 4
    //   589: monitorenter
    //   590: getstatic 26	com/google/android/gms/b/mv:d	Ljava/util/Set;
    //   593: astore_3
    //   594: aload_3
    //   595: aload 19
    //   597: invokeinterface 186 2 0
    //   602: istore 7
    //   604: iload 7
    //   606: ifeq +107 -> 713
    //   609: ldc -68
    //   611: astore 6
    //   613: aload_1
    //   614: invokestatic 83	java/lang/String:valueOf	(Ljava/lang/Object;)Ljava/lang/String;
    //   617: astore_3
    //   618: aload_3
    //   619: invokevirtual 87	java/lang/String:length	()I
    //   622: istore 9
    //   624: iload 9
    //   626: ifeq +74 -> 700
    //   629: aload 6
    //   631: aload_3
    //   632: invokevirtual 91	java/lang/String:concat	(Ljava/lang/String;)Ljava/lang/String;
    //   635: astore_3
    //   636: aload_3
    //   637: invokestatic 55	com/google/android/gms/b/tp:e	(Ljava/lang/String;)V
    //   640: aload 23
    //   642: invokevirtual 77	java/io/File:getAbsolutePath	()Ljava/lang/String;
    //   645: astore_3
    //   646: ldc -66
    //   648: astore 6
    //   650: iconst_0
    //   651: istore 9
    //   653: aconst_null
    //   654: astore 25
    //   656: aload_0
    //   657: astore_2
    //   658: aload_0
    //   659: aload_1
    //   660: aload_3
    //   661: aload 6
    //   663: aconst_null
    //   664: invokevirtual 113	com/google/android/gms/b/mv:a	(Ljava/lang/String;Ljava/lang/String;Ljava/lang/String;Ljava/lang/String;)V
    //   667: iconst_0
    //   668: istore 7
    //   670: aconst_null
    //   671: astore_3
    //   672: aload 4
    //   674: monitorexit
    //   675: goto -640 -> 35
    //   678: astore_3
    //   679: aload 4
    //   681: monitorexit
    //   682: aload_3
    //   683: athrow
    //   684: new 79	java/lang/String
    //   687: astore_3
    //   688: aload_3
    //   689: aload 4
    //   691: invokespecial 92	java/lang/String:<init>	(Ljava/lang/String;)V
    //   694: aload_3
    //   695: astore 19
    //   697: goto -115 -> 582
    //   700: new 79	java/lang/String
    //   703: astore_3
    //   704: aload_3
    //   705: aload 6
    //   707: invokespecial 92	java/lang/String:<init>	(Ljava/lang/String;)V
    //   710: goto -74 -> 636
    //   713: getstatic 26	com/google/android/gms/b/mv:d	Ljava/util/Set;
    //   716: astore_3
    //   717: aload_3
    //   718: aload 19
    //   720: invokeinterface 193 2 0
    //   725: pop
    //   726: aload 4
    //   728: monitorexit
    //   729: iconst_0
    //   730: istore 9
    //   732: aconst_null
    //   733: astore 25
    //   735: ldc -61
    //   737: astore 26
    //   739: aconst_null
    //   740: astore 16
    //   742: invokestatic 199	com/google/android/gms/ads/internal/w:r	()Lcom/google/android/gms/b/uu;
    //   745: pop
    //   746: getstatic 202	com/google/android/gms/b/ke:w	Lcom/google/android/gms/b/jz;
    //   749: astore_3
    //   750: invokestatic 124	com/google/android/gms/ads/internal/w:q	()Lcom/google/android/gms/b/kd;
    //   753: astore 4
    //   755: aload 4
    //   757: aload_3
    //   758: invokevirtual 129	com/google/android/gms/b/kd:a	(Lcom/google/android/gms/b/jz;)Ljava/lang/Object;
    //   761: astore_3
    //   762: aload_3
    //   763: checkcast 131	java/lang/Integer
    //   766: astore_3
    //   767: aload_3
    //   768: invokevirtual 134	java/lang/Integer:intValue	()I
    //   771: istore 7
    //   773: aload_1
    //   774: astore_2
    //   775: aload_1
    //   776: iload 7
    //   778: invokestatic 207	com/google/android/gms/b/uu:a	(Ljava/lang/String;I)Ljava/net/HttpURLConnection;
    //   781: astore 4
    //   783: aload 4
    //   785: instanceof 209
    //   788: istore 7
    //   790: iload 7
    //   792: ifeq +394 -> 1186
    //   795: aload 4
    //   797: astore_2
    //   798: aload 4
    //   800: checkcast 209	java/net/HttpURLConnection
    //   803: astore_2
    //   804: aload_2
    //   805: astore_3
    //   806: aload_2
    //   807: invokevirtual 212	java/net/HttpURLConnection:getResponseCode	()I
    //   810: istore 7
    //   812: sipush 400
    //   815: istore 5
    //   817: iload 7
    //   819: iload 5
    //   821: if_icmplt +365 -> 1186
    //   824: ldc -41
    //   826: astore 6
    //   828: ldc -39
    //   830: astore 10
    //   832: iload 7
    //   834: invokestatic 221	java/lang/Integer:toString	(I)Ljava/lang/String;
    //   837: astore 4
    //   839: aload 4
    //   841: invokestatic 83	java/lang/String:valueOf	(Ljava/lang/Object;)Ljava/lang/String;
    //   844: astore 4
    //   846: aload 4
    //   848: invokevirtual 87	java/lang/String:length	()I
    //   851: istore 13
    //   853: iload 13
    //   855: ifeq +306 -> 1161
    //   858: aload 10
    //   860: aload 4
    //   862: invokevirtual 91	java/lang/String:concat	(Ljava/lang/String;)Ljava/lang/String;
    //   865: astore 4
    //   867: new 223	java/io/IOException
    //   870: astore 10
    //   872: aload_1
    //   873: invokestatic 83	java/lang/String:valueOf	(Ljava/lang/Object;)Ljava/lang/String;
    //   876: astore 11
    //   878: aload 11
    //   880: invokevirtual 87	java/lang/String:length	()I
    //   883: bipush 32
    //   885: iadd
    //   886: istore 13
    //   888: new 225	java/lang/StringBuilder
    //   891: astore 16
    //   893: aload 16
    //   895: iload 13
    //   897: invokespecial 228	java/lang/StringBuilder:<init>	(I)V
    //   900: ldc -26
    //   902: astore 11
    //   904: aload 16
    //   906: aload 11
    //   908: invokevirtual 234	java/lang/StringBuilder:append	(Ljava/lang/String;)Ljava/lang/StringBuilder;
    //   911: astore 11
    //   913: aload 11
    //   915: iload 7
    //   917: invokevirtual 237	java/lang/StringBuilder:append	(I)Ljava/lang/StringBuilder;
    //   920: astore_3
    //   921: ldc -17
    //   923: astore 11
    //   925: aload_3
    //   926: aload 11
    //   928: invokevirtual 234	java/lang/StringBuilder:append	(Ljava/lang/String;)Ljava/lang/StringBuilder;
    //   931: astore_3
    //   932: aload_1
    //   933: astore_2
    //   934: aload_3
    //   935: aload_1
    //   936: invokevirtual 234	java/lang/StringBuilder:append	(Ljava/lang/String;)Ljava/lang/StringBuilder;
    //   939: astore_3
    //   940: aload_3
    //   941: invokevirtual 241	java/lang/StringBuilder:toString	()Ljava/lang/String;
    //   944: astore_3
    //   945: aload 10
    //   947: aload_3
    //   948: invokespecial 242	java/io/IOException:<init>	(Ljava/lang/String;)V
    //   951: aload 10
    //   953: athrow
    //   954: astore_3
    //   955: aload_3
    //   956: instanceof 244
    //   959: istore 12
    //   961: iload 12
    //   963: ifeq +23 -> 986
    //   966: invokestatic 248	com/google/android/gms/ads/internal/w:i	()Lcom/google/android/gms/b/tj;
    //   969: astore 10
    //   971: ldc -6
    //   973: astore 11
    //   975: aload 10
    //   977: aload_3
    //   978: checkcast 252	java/lang/Throwable
    //   981: aload 11
    //   983: invokevirtual 257	com/google/android/gms/b/tj:a	(Ljava/lang/Throwable;Ljava/lang/String;)V
    //   986: aload 25
    //   988: invokevirtual 262	java/io/FileOutputStream:close	()V
    //   991: aload_0
    //   992: astore_2
    //   993: aload_0
    //   994: getfield 108	com/google/android/gms/b/mv:g	Z
    //   997: istore 9
    //   999: iload 9
    //   1001: ifeq +1429 -> 2430
    //   1004: aload_1
    //   1005: invokestatic 83	java/lang/String:valueOf	(Ljava/lang/Object;)Ljava/lang/String;
    //   1008: invokevirtual 87	java/lang/String:length	()I
    //   1011: bipush 26
    //   1013: iadd
    //   1014: istore 7
    //   1016: new 225	java/lang/StringBuilder
    //   1019: astore 25
    //   1021: aload 25
    //   1023: iload 7
    //   1025: invokespecial 228	java/lang/StringBuilder:<init>	(I)V
    //   1028: aload 25
    //   1030: ldc_w 264
    //   1033: invokevirtual 234	java/lang/StringBuilder:append	(Ljava/lang/String;)Ljava/lang/StringBuilder;
    //   1036: astore_3
    //   1037: aload_1
    //   1038: astore_2
    //   1039: aload_3
    //   1040: aload_1
    //   1041: invokevirtual 234	java/lang/StringBuilder:append	(Ljava/lang/String;)Ljava/lang/StringBuilder;
    //   1044: astore_3
    //   1045: ldc_w 266
    //   1048: astore 25
    //   1050: aload_3
    //   1051: aload 25
    //   1053: invokevirtual 234	java/lang/StringBuilder:append	(Ljava/lang/String;)Ljava/lang/StringBuilder;
    //   1056: invokevirtual 241	java/lang/StringBuilder:toString	()Ljava/lang/String;
    //   1059: astore_3
    //   1060: aload_3
    //   1061: invokestatic 268	com/google/android/gms/b/tp:d	(Ljava/lang/String;)V
    //   1064: aload 23
    //   1066: invokevirtual 271	java/io/File:exists	()Z
    //   1069: istore 7
    //   1071: iload 7
    //   1073: ifeq +51 -> 1124
    //   1076: aload 23
    //   1078: invokevirtual 155	java/io/File:delete	()Z
    //   1081: istore 7
    //   1083: iload 7
    //   1085: ifne +39 -> 1124
    //   1088: ldc_w 273
    //   1091: astore 25
    //   1093: aload 23
    //   1095: invokevirtual 77	java/io/File:getAbsolutePath	()Ljava/lang/String;
    //   1098: invokestatic 83	java/lang/String:valueOf	(Ljava/lang/Object;)Ljava/lang/String;
    //   1101: astore_3
    //   1102: aload_3
    //   1103: invokevirtual 87	java/lang/String:length	()I
    //   1106: istore 12
    //   1108: iload 12
    //   1110: ifeq +1393 -> 2503
    //   1113: aload 25
    //   1115: aload_3
    //   1116: invokevirtual 91	java/lang/String:concat	(Ljava/lang/String;)Ljava/lang/String;
    //   1119: astore_3
    //   1120: aload_3
    //   1121: invokestatic 55	com/google/android/gms/b/tp:e	(Ljava/lang/String;)V
    //   1124: aload 23
    //   1126: invokevirtual 77	java/io/File:getAbsolutePath	()Ljava/lang/String;
    //   1129: astore_3
    //   1130: aload_0
    //   1131: astore_2
    //   1132: aload_0
    //   1133: aload_1
    //   1134: aload_3
    //   1135: aload 6
    //   1137: aload 4
    //   1139: invokevirtual 113	com/google/android/gms/b/mv:a	(Ljava/lang/String;Ljava/lang/String;Ljava/lang/String;Ljava/lang/String;)V
    //   1142: getstatic 26	com/google/android/gms/b/mv:d	Ljava/util/Set;
    //   1145: aload 19
    //   1147: invokeinterface 276 2 0
    //   1152: pop
    //   1153: iconst_0
    //   1154: istore 7
    //   1156: aconst_null
    //   1157: astore_3
    //   1158: goto -1123 -> 35
    //   1161: new 79	java/lang/String
    //   1164: astore 4
    //   1166: aload 4
    //   1168: aload 10
    //   1170: invokespecial 92	java/lang/String:<init>	(Ljava/lang/String;)V
    //   1173: goto -306 -> 867
    //   1176: astore_3
    //   1177: iconst_0
    //   1178: istore 8
    //   1180: aconst_null
    //   1181: astore 4
    //   1183: goto -228 -> 955
    //   1186: aload 4
    //   1188: checkcast 278	java/net/URLConnection
    //   1191: invokevirtual 281	java/net/URLConnection:getContentLength	()I
    //   1194: istore 13
    //   1196: iload 13
    //   1198: ifge +111 -> 1309
    //   1201: ldc_w 283
    //   1204: astore 4
    //   1206: aload_1
    //   1207: invokestatic 83	java/lang/String:valueOf	(Ljava/lang/Object;)Ljava/lang/String;
    //   1210: astore_3
    //   1211: aload_3
    //   1212: invokevirtual 87	java/lang/String:length	()I
    //   1215: istore 5
    //   1217: iload 5
    //   1219: ifeq +63 -> 1282
    //   1222: aload 4
    //   1224: aload_3
    //   1225: invokevirtual 91	java/lang/String:concat	(Ljava/lang/String;)Ljava/lang/String;
    //   1228: astore_3
    //   1229: aload_3
    //   1230: invokestatic 55	com/google/android/gms/b/tp:e	(Ljava/lang/String;)V
    //   1233: aload 23
    //   1235: invokevirtual 77	java/io/File:getAbsolutePath	()Ljava/lang/String;
    //   1238: astore_3
    //   1239: ldc_w 285
    //   1242: astore 4
    //   1244: iconst_0
    //   1245: istore 5
    //   1247: aconst_null
    //   1248: astore 6
    //   1250: aload_0
    //   1251: astore_2
    //   1252: aload_0
    //   1253: aload_1
    //   1254: aload_3
    //   1255: aload 4
    //   1257: aconst_null
    //   1258: invokevirtual 113	com/google/android/gms/b/mv:a	(Ljava/lang/String;Ljava/lang/String;Ljava/lang/String;Ljava/lang/String;)V
    //   1261: getstatic 26	com/google/android/gms/b/mv:d	Ljava/util/Set;
    //   1264: astore_3
    //   1265: aload_3
    //   1266: aload 19
    //   1268: invokeinterface 276 2 0
    //   1273: pop
    //   1274: iconst_0
    //   1275: istore 7
    //   1277: aconst_null
    //   1278: astore_3
    //   1279: goto -1244 -> 35
    //   1282: new 79	java/lang/String
    //   1285: astore_3
    //   1286: aload_3
    //   1287: aload 4
    //   1289: invokespecial 92	java/lang/String:<init>	(Ljava/lang/String;)V
    //   1292: goto -63 -> 1229
    //   1295: astore_3
    //   1296: iconst_0
    //   1297: istore 8
    //   1299: aconst_null
    //   1300: astore 4
    //   1302: aload 26
    //   1304: astore 6
    //   1306: goto -351 -> 955
    //   1309: getstatic 35	com/google/android/gms/b/mv:e	Ljava/text/DecimalFormat;
    //   1312: astore_3
    //   1313: iload 13
    //   1315: i2l
    //   1316: lstore 27
    //   1318: aload_3
    //   1319: lload 27
    //   1321: invokevirtual 289	java/text/DecimalFormat:format	(J)Ljava/lang/String;
    //   1324: astore 6
    //   1326: getstatic 291	com/google/android/gms/b/ke:r	Lcom/google/android/gms/b/jz;
    //   1329: astore_3
    //   1330: invokestatic 124	com/google/android/gms/ads/internal/w:q	()Lcom/google/android/gms/b/kd;
    //   1333: astore 10
    //   1335: aload 10
    //   1337: aload_3
    //   1338: invokevirtual 129	com/google/android/gms/b/kd:a	(Lcom/google/android/gms/b/jz;)Ljava/lang/Object;
    //   1341: astore_3
    //   1342: aload_3
    //   1343: checkcast 131	java/lang/Integer
    //   1346: astore_3
    //   1347: aload_3
    //   1348: invokevirtual 134	java/lang/Integer:intValue	()I
    //   1351: istore 29
    //   1353: iload 13
    //   1355: iload 29
    //   1357: if_icmple +198 -> 1555
    //   1360: aload 6
    //   1362: invokestatic 83	java/lang/String:valueOf	(Ljava/lang/Object;)Ljava/lang/String;
    //   1365: astore_3
    //   1366: aload_3
    //   1367: invokevirtual 87	java/lang/String:length	()I
    //   1370: bipush 33
    //   1372: iadd
    //   1373: istore 7
    //   1375: aload_1
    //   1376: invokestatic 83	java/lang/String:valueOf	(Ljava/lang/Object;)Ljava/lang/String;
    //   1379: astore 4
    //   1381: aload 4
    //   1383: invokevirtual 87	java/lang/String:length	()I
    //   1386: istore 8
    //   1388: iload 7
    //   1390: iload 8
    //   1392: iadd
    //   1393: istore 7
    //   1395: new 225	java/lang/StringBuilder
    //   1398: astore 4
    //   1400: aload 4
    //   1402: iload 7
    //   1404: invokespecial 228	java/lang/StringBuilder:<init>	(I)V
    //   1407: ldc_w 293
    //   1410: astore_3
    //   1411: aload 4
    //   1413: aload_3
    //   1414: invokevirtual 234	java/lang/StringBuilder:append	(Ljava/lang/String;)Ljava/lang/StringBuilder;
    //   1417: astore_3
    //   1418: aload_3
    //   1419: aload 6
    //   1421: invokevirtual 234	java/lang/StringBuilder:append	(Ljava/lang/String;)Ljava/lang/StringBuilder;
    //   1424: astore_3
    //   1425: ldc_w 295
    //   1428: astore 4
    //   1430: aload_3
    //   1431: aload 4
    //   1433: invokevirtual 234	java/lang/StringBuilder:append	(Ljava/lang/String;)Ljava/lang/StringBuilder;
    //   1436: astore_3
    //   1437: aload_1
    //   1438: astore_2
    //   1439: aload_3
    //   1440: aload_1
    //   1441: invokevirtual 234	java/lang/StringBuilder:append	(Ljava/lang/String;)Ljava/lang/StringBuilder;
    //   1444: astore_3
    //   1445: aload_3
    //   1446: invokevirtual 241	java/lang/StringBuilder:toString	()Ljava/lang/String;
    //   1449: astore_3
    //   1450: aload_3
    //   1451: invokestatic 55	com/google/android/gms/b/tp:e	(Ljava/lang/String;)V
    //   1454: ldc_w 297
    //   1457: astore 4
    //   1459: aload 6
    //   1461: invokestatic 83	java/lang/String:valueOf	(Ljava/lang/Object;)Ljava/lang/String;
    //   1464: astore_3
    //   1465: aload_3
    //   1466: invokevirtual 87	java/lang/String:length	()I
    //   1469: istore 5
    //   1471: iload 5
    //   1473: ifeq +55 -> 1528
    //   1476: aload 4
    //   1478: aload_3
    //   1479: invokevirtual 91	java/lang/String:concat	(Ljava/lang/String;)Ljava/lang/String;
    //   1482: astore_3
    //   1483: aload 23
    //   1485: invokevirtual 77	java/io/File:getAbsolutePath	()Ljava/lang/String;
    //   1488: astore 4
    //   1490: ldc_w 299
    //   1493: astore 6
    //   1495: aload_0
    //   1496: astore_2
    //   1497: aload_0
    //   1498: aload_1
    //   1499: aload 4
    //   1501: aload 6
    //   1503: aload_3
    //   1504: invokevirtual 113	com/google/android/gms/b/mv:a	(Ljava/lang/String;Ljava/lang/String;Ljava/lang/String;Ljava/lang/String;)V
    //   1507: getstatic 26	com/google/android/gms/b/mv:d	Ljava/util/Set;
    //   1510: astore_3
    //   1511: aload_3
    //   1512: aload 19
    //   1514: invokeinterface 276 2 0
    //   1519: pop
    //   1520: iconst_0
    //   1521: istore 7
    //   1523: aconst_null
    //   1524: astore_3
    //   1525: goto -1490 -> 35
    //   1528: new 79	java/lang/String
    //   1531: astore_3
    //   1532: aload_3
    //   1533: aload 4
    //   1535: invokespecial 92	java/lang/String:<init>	(Ljava/lang/String;)V
    //   1538: goto -55 -> 1483
    //   1541: astore_3
    //   1542: iconst_0
    //   1543: istore 8
    //   1545: aconst_null
    //   1546: astore 4
    //   1548: aload 26
    //   1550: astore 6
    //   1552: goto -597 -> 955
    //   1555: aload 6
    //   1557: invokestatic 83	java/lang/String:valueOf	(Ljava/lang/Object;)Ljava/lang/String;
    //   1560: astore_3
    //   1561: aload_3
    //   1562: invokevirtual 87	java/lang/String:length	()I
    //   1565: bipush 20
    //   1567: iadd
    //   1568: istore 7
    //   1570: aload_1
    //   1571: invokestatic 83	java/lang/String:valueOf	(Ljava/lang/Object;)Ljava/lang/String;
    //   1574: astore 10
    //   1576: aload 10
    //   1578: invokevirtual 87	java/lang/String:length	()I
    //   1581: istore 12
    //   1583: iload 7
    //   1585: iload 12
    //   1587: iadd
    //   1588: istore 7
    //   1590: new 225	java/lang/StringBuilder
    //   1593: astore 10
    //   1595: aload 10
    //   1597: iload 7
    //   1599: invokespecial 228	java/lang/StringBuilder:<init>	(I)V
    //   1602: ldc_w 301
    //   1605: astore_3
    //   1606: aload 10
    //   1608: aload_3
    //   1609: invokevirtual 234	java/lang/StringBuilder:append	(Ljava/lang/String;)Ljava/lang/StringBuilder;
    //   1612: astore_3
    //   1613: aload_3
    //   1614: aload 6
    //   1616: invokevirtual 234	java/lang/StringBuilder:append	(Ljava/lang/String;)Ljava/lang/StringBuilder;
    //   1619: astore_3
    //   1620: ldc_w 303
    //   1623: astore 6
    //   1625: aload_3
    //   1626: aload 6
    //   1628: invokevirtual 234	java/lang/StringBuilder:append	(Ljava/lang/String;)Ljava/lang/StringBuilder;
    //   1631: astore_3
    //   1632: aload_1
    //   1633: astore_2
    //   1634: aload_3
    //   1635: aload_1
    //   1636: invokevirtual 234	java/lang/StringBuilder:append	(Ljava/lang/String;)Ljava/lang/StringBuilder;
    //   1639: astore_3
    //   1640: aload_3
    //   1641: invokevirtual 241	java/lang/StringBuilder:toString	()Ljava/lang/String;
    //   1644: astore_3
    //   1645: aload_3
    //   1646: invokestatic 177	com/google/android/gms/b/tp:b	(Ljava/lang/String;)V
    //   1649: aload 4
    //   1651: checkcast 278	java/net/URLConnection
    //   1654: invokevirtual 307	java/net/URLConnection:getInputStream	()Ljava/io/InputStream;
    //   1657: astore_3
    //   1658: aload_3
    //   1659: invokestatic 313	java/nio/channels/Channels:newChannel	(Ljava/io/InputStream;)Ljava/nio/channels/ReadableByteChannel;
    //   1662: astore 30
    //   1664: new 259	java/io/FileOutputStream
    //   1667: astore 31
    //   1669: aload 31
    //   1671: aload 23
    //   1673: invokespecial 316	java/io/FileOutputStream:<init>	(Ljava/io/File;)V
    //   1676: aload 31
    //   1678: invokevirtual 320	java/io/FileOutputStream:getChannel	()Ljava/nio/channels/FileChannel;
    //   1681: astore 32
    //   1683: ldc_w 321
    //   1686: istore 7
    //   1688: iload 7
    //   1690: invokestatic 328	java/nio/ByteBuffer:allocate	(I)Ljava/nio/ByteBuffer;
    //   1693: astore 33
    //   1695: invokestatic 332	com/google/android/gms/ads/internal/w:k	()Lcom/google/android/gms/common/util/c;
    //   1698: astore 34
    //   1700: iconst_0
    //   1701: istore 12
    //   1703: aconst_null
    //   1704: astore 10
    //   1706: aload 34
    //   1708: invokeinterface 336 1 0
    //   1713: lstore 35
    //   1715: getstatic 339	com/google/android/gms/b/ke:v	Lcom/google/android/gms/b/jz;
    //   1718: astore_3
    //   1719: invokestatic 124	com/google/android/gms/ads/internal/w:q	()Lcom/google/android/gms/b/kd;
    //   1722: astore 4
    //   1724: aload 4
    //   1726: aload_3
    //   1727: invokevirtual 129	com/google/android/gms/b/kd:a	(Lcom/google/android/gms/b/jz;)Ljava/lang/Object;
    //   1730: astore_3
    //   1731: aload_3
    //   1732: checkcast 341	java/lang/Long
    //   1735: astore_3
    //   1736: aload_3
    //   1737: invokevirtual 344	java/lang/Long:longValue	()J
    //   1740: lstore 20
    //   1742: new 346	com/google/android/gms/b/ue
    //   1745: astore 37
    //   1747: aload 37
    //   1749: astore_2
    //   1750: aload 37
    //   1752: lload 20
    //   1754: invokespecial 349	com/google/android/gms/b/ue:<init>	(J)V
    //   1757: getstatic 352	com/google/android/gms/b/ke:u	Lcom/google/android/gms/b/jz;
    //   1760: astore_3
    //   1761: invokestatic 124	com/google/android/gms/ads/internal/w:q	()Lcom/google/android/gms/b/kd;
    //   1764: astore 4
    //   1766: aload 4
    //   1768: aload_3
    //   1769: invokevirtual 129	com/google/android/gms/b/kd:a	(Lcom/google/android/gms/b/jz;)Ljava/lang/Object;
    //   1772: astore_3
    //   1773: aload_3
    //   1774: checkcast 341	java/lang/Long
    //   1777: astore_3
    //   1778: aload_3
    //   1779: invokevirtual 344	java/lang/Long:longValue	()J
    //   1782: lstore 38
    //   1784: aload 33
    //   1786: astore_2
    //   1787: aload 30
    //   1789: aload 33
    //   1791: invokeinterface 358 2 0
    //   1796: istore 7
    //   1798: iload 7
    //   1800: iflt +405 -> 2205
    //   1803: iload 12
    //   1805: iload 7
    //   1807: iadd
    //   1808: istore 12
    //   1810: iload 12
    //   1812: iload 29
    //   1814: if_icmple +99 -> 1913
    //   1817: ldc_w 299
    //   1820: astore 6
    //   1822: ldc_w 297
    //   1825: astore_3
    //   1826: iload 12
    //   1828: invokestatic 221	java/lang/Integer:toString	(I)Ljava/lang/String;
    //   1831: astore 4
    //   1833: aload 4
    //   1835: invokestatic 83	java/lang/String:valueOf	(Ljava/lang/Object;)Ljava/lang/String;
    //   1838: astore 4
    //   1840: aload 4
    //   1842: invokevirtual 87	java/lang/String:length	()I
    //   1845: istore 9
    //   1847: iload 9
    //   1849: ifeq +36 -> 1885
    //   1852: aload_3
    //   1853: aload 4
    //   1855: invokevirtual 91	java/lang/String:concat	(Ljava/lang/String;)Ljava/lang/String;
    //   1858: astore 4
    //   1860: new 223	java/io/IOException
    //   1863: astore_3
    //   1864: ldc_w 360
    //   1867: astore 25
    //   1869: aload_3
    //   1870: aload 25
    //   1872: invokespecial 242	java/io/IOException:<init>	(Ljava/lang/String;)V
    //   1875: aload_3
    //   1876: athrow
    //   1877: astore_3
    //   1878: aload 31
    //   1880: astore 25
    //   1882: goto -927 -> 955
    //   1885: new 79	java/lang/String
    //   1888: astore 4
    //   1890: aload 4
    //   1892: aload_3
    //   1893: invokespecial 92	java/lang/String:<init>	(Ljava/lang/String;)V
    //   1896: goto -36 -> 1860
    //   1899: astore_3
    //   1900: iconst_0
    //   1901: istore 8
    //   1903: aconst_null
    //   1904: astore 4
    //   1906: aload 31
    //   1908: astore 25
    //   1910: goto -955 -> 955
    //   1913: aload 33
    //   1915: invokevirtual 364	java/nio/ByteBuffer:flip	()Ljava/nio/Buffer;
    //   1918: pop
    //   1919: aload 32
    //   1921: aload 33
    //   1923: invokevirtual 369	java/nio/channels/FileChannel:write	(Ljava/nio/ByteBuffer;)I
    //   1926: istore 7
    //   1928: iload 7
    //   1930: ifgt -11 -> 1919
    //   1933: aload 33
    //   1935: invokevirtual 372	java/nio/ByteBuffer:clear	()Ljava/nio/Buffer;
    //   1938: pop
    //   1939: aload 34
    //   1941: invokeinterface 336 1 0
    //   1946: lload 35
    //   1948: lsub
    //   1949: lstore 20
    //   1951: ldc2_w 373
    //   1954: lload 38
    //   1956: lmul
    //   1957: lstore 14
    //   1959: lload 20
    //   1961: lload 14
    //   1963: lcmp
    //   1964: istore 7
    //   1966: iload 7
    //   1968: ifle +111 -> 2079
    //   1971: ldc_w 378
    //   1974: astore 6
    //   1976: lload 38
    //   1978: invokestatic 380	java/lang/Long:toString	(J)Ljava/lang/String;
    //   1981: astore_3
    //   1982: aload_3
    //   1983: invokestatic 83	java/lang/String:valueOf	(Ljava/lang/Object;)Ljava/lang/String;
    //   1986: astore_3
    //   1987: aload_3
    //   1988: invokestatic 83	java/lang/String:valueOf	(Ljava/lang/Object;)Ljava/lang/String;
    //   1991: astore 4
    //   1993: aload 4
    //   1995: invokevirtual 87	java/lang/String:length	()I
    //   1998: bipush 29
    //   2000: iadd
    //   2001: istore 8
    //   2003: new 225	java/lang/StringBuilder
    //   2006: astore 25
    //   2008: aload 25
    //   2010: iload 8
    //   2012: invokespecial 228	java/lang/StringBuilder:<init>	(I)V
    //   2015: ldc_w 382
    //   2018: astore 4
    //   2020: aload 25
    //   2022: aload 4
    //   2024: invokevirtual 234	java/lang/StringBuilder:append	(Ljava/lang/String;)Ljava/lang/StringBuilder;
    //   2027: astore 4
    //   2029: aload 4
    //   2031: aload_3
    //   2032: invokevirtual 234	java/lang/StringBuilder:append	(Ljava/lang/String;)Ljava/lang/StringBuilder;
    //   2035: astore_3
    //   2036: ldc_w 384
    //   2039: astore 4
    //   2041: aload_3
    //   2042: aload 4
    //   2044: invokevirtual 234	java/lang/StringBuilder:append	(Ljava/lang/String;)Ljava/lang/StringBuilder;
    //   2047: astore_3
    //   2048: aload_3
    //   2049: invokevirtual 241	java/lang/StringBuilder:toString	()Ljava/lang/String;
    //   2052: astore 4
    //   2054: new 223	java/io/IOException
    //   2057: astore_3
    //   2058: ldc_w 386
    //   2061: astore 25
    //   2063: aload_3
    //   2064: aload 25
    //   2066: invokespecial 242	java/io/IOException:<init>	(Ljava/lang/String;)V
    //   2069: aload_3
    //   2070: athrow
    //   2071: astore_3
    //   2072: aload 31
    //   2074: astore 25
    //   2076: goto -1121 -> 955
    //   2079: aload_0
    //   2080: astore_2
    //   2081: aload_0
    //   2082: getfield 108	com/google/android/gms/b/mv:g	Z
    //   2085: istore 7
    //   2087: iload 7
    //   2089: ifeq +39 -> 2128
    //   2092: ldc_w 388
    //   2095: astore 6
    //   2097: new 223	java/io/IOException
    //   2100: astore_3
    //   2101: ldc_w 390
    //   2104: astore 4
    //   2106: aload_3
    //   2107: aload 4
    //   2109: invokespecial 242	java/io/IOException:<init>	(Ljava/lang/String;)V
    //   2112: aload_3
    //   2113: athrow
    //   2114: astore_3
    //   2115: iconst_0
    //   2116: istore 8
    //   2118: aconst_null
    //   2119: astore 4
    //   2121: aload 31
    //   2123: astore 25
    //   2125: goto -1170 -> 955
    //   2128: aload 37
    //   2130: invokevirtual 392	com/google/android/gms/b/ue:a	()Z
    //   2133: istore 7
    //   2135: iload 7
    //   2137: ifeq -353 -> 1784
    //   2140: aload 23
    //   2142: invokevirtual 77	java/io/File:getAbsolutePath	()Ljava/lang/String;
    //   2145: astore 25
    //   2147: getstatic 395	com/google/android/gms/b/uk:a	Landroid/os/Handler;
    //   2150: astore 40
    //   2152: new 397	com/google/android/gms/b/ms$1
    //   2155: astore_3
    //   2156: aload_0
    //   2157: astore 4
    //   2159: aload_1
    //   2160: astore 6
    //   2162: aload_3
    //   2163: aload_0
    //   2164: aload_1
    //   2165: aload 25
    //   2167: iload 12
    //   2169: iload 13
    //   2171: invokespecial 400	com/google/android/gms/b/ms$1:<init>	(Lcom/google/android/gms/b/ms;Ljava/lang/String;Ljava/lang/String;II)V
    //   2174: aload 40
    //   2176: astore_2
    //   2177: aload 40
    //   2179: aload_3
    //   2180: invokevirtual 406	android/os/Handler:post	(Ljava/lang/Runnable;)Z
    //   2183: pop
    //   2184: goto -400 -> 1784
    //   2187: astore_3
    //   2188: iconst_0
    //   2189: istore 8
    //   2191: aconst_null
    //   2192: astore 4
    //   2194: aload 26
    //   2196: astore 6
    //   2198: aload 31
    //   2200: astore 25
    //   2202: goto -1247 -> 955
    //   2205: aload 31
    //   2207: invokevirtual 262	java/io/FileOutputStream:close	()V
    //   2210: iconst_3
    //   2211: istore 7
    //   2213: iload 7
    //   2215: invokestatic 410	com/google/android/gms/b/tp:a	(I)Z
    //   2218: istore 7
    //   2220: iload 7
    //   2222: ifeq +117 -> 2339
    //   2225: getstatic 35	com/google/android/gms/b/mv:e	Ljava/text/DecimalFormat;
    //   2228: astore_3
    //   2229: iload 12
    //   2231: i2l
    //   2232: lstore 14
    //   2234: aload_3
    //   2235: lload 14
    //   2237: invokevirtual 289	java/text/DecimalFormat:format	(J)Ljava/lang/String;
    //   2240: astore_3
    //   2241: aload_3
    //   2242: invokestatic 83	java/lang/String:valueOf	(Ljava/lang/Object;)Ljava/lang/String;
    //   2245: astore 4
    //   2247: aload 4
    //   2249: invokevirtual 87	java/lang/String:length	()I
    //   2252: bipush 22
    //   2254: iadd
    //   2255: istore 8
    //   2257: aload_1
    //   2258: invokestatic 83	java/lang/String:valueOf	(Ljava/lang/Object;)Ljava/lang/String;
    //   2261: astore 6
    //   2263: aload 6
    //   2265: invokevirtual 87	java/lang/String:length	()I
    //   2268: istore 5
    //   2270: iload 8
    //   2272: iload 5
    //   2274: iadd
    //   2275: istore 8
    //   2277: new 225	java/lang/StringBuilder
    //   2280: astore 6
    //   2282: aload 6
    //   2284: iload 8
    //   2286: invokespecial 228	java/lang/StringBuilder:<init>	(I)V
    //   2289: ldc_w 412
    //   2292: astore 4
    //   2294: aload 6
    //   2296: aload 4
    //   2298: invokevirtual 234	java/lang/StringBuilder:append	(Ljava/lang/String;)Ljava/lang/StringBuilder;
    //   2301: astore 4
    //   2303: aload 4
    //   2305: aload_3
    //   2306: invokevirtual 234	java/lang/StringBuilder:append	(Ljava/lang/String;)Ljava/lang/StringBuilder;
    //   2309: astore_3
    //   2310: ldc_w 303
    //   2313: astore 4
    //   2315: aload_3
    //   2316: aload 4
    //   2318: invokevirtual 234	java/lang/StringBuilder:append	(Ljava/lang/String;)Ljava/lang/StringBuilder;
    //   2321: astore_3
    //   2322: aload_1
    //   2323: astore_2
    //   2324: aload_3
    //   2325: aload_1
    //   2326: invokevirtual 234	java/lang/StringBuilder:append	(Ljava/lang/String;)Ljava/lang/StringBuilder;
    //   2329: astore_3
    //   2330: aload_3
    //   2331: invokevirtual 241	java/lang/StringBuilder:toString	()Ljava/lang/String;
    //   2334: astore_3
    //   2335: aload_3
    //   2336: invokestatic 177	com/google/android/gms/b/tp:b	(Ljava/lang/String;)V
    //   2339: iconst_1
    //   2340: istore 7
    //   2342: iconst_0
    //   2343: istore 8
    //   2345: aconst_null
    //   2346: astore 4
    //   2348: aload 23
    //   2350: iload 7
    //   2352: iconst_0
    //   2353: invokevirtual 96	java/io/File:setReadable	(ZZ)Z
    //   2356: pop
    //   2357: aload 24
    //   2359: invokevirtual 161	java/io/File:isFile	()Z
    //   2362: istore 7
    //   2364: iload 7
    //   2366: ifeq +51 -> 2417
    //   2369: invokestatic 417	java/lang/System:currentTimeMillis	()J
    //   2372: lstore 20
    //   2374: aload 24
    //   2376: lload 20
    //   2378: invokevirtual 421	java/io/File:setLastModified	(J)Z
    //   2381: pop
    //   2382: aload 23
    //   2384: invokevirtual 77	java/io/File:getAbsolutePath	()Ljava/lang/String;
    //   2387: astore_3
    //   2388: aload_0
    //   2389: astore_2
    //   2390: aload_0
    //   2391: aload_1
    //   2392: aload_3
    //   2393: iload 12
    //   2395: invokevirtual 180	com/google/android/gms/b/mv:a	(Ljava/lang/String;Ljava/lang/String;I)V
    //   2398: getstatic 26	com/google/android/gms/b/mv:d	Ljava/util/Set;
    //   2401: astore_3
    //   2402: aload_3
    //   2403: aload 19
    //   2405: invokeinterface 276 2 0
    //   2410: pop
    //   2411: iconst_1
    //   2412: istore 7
    //   2414: goto -2379 -> 35
    //   2417: aload 24
    //   2419: invokevirtual 424	java/io/File:createNewFile	()Z
    //   2422: pop
    //   2423: goto -41 -> 2382
    //   2426: astore_3
    //   2427: goto -45 -> 2382
    //   2430: aload_1
    //   2431: invokestatic 83	java/lang/String:valueOf	(Ljava/lang/Object;)Ljava/lang/String;
    //   2434: invokevirtual 87	java/lang/String:length	()I
    //   2437: bipush 25
    //   2439: iadd
    //   2440: istore 9
    //   2442: new 225	java/lang/StringBuilder
    //   2445: astore 10
    //   2447: aload 10
    //   2449: iload 9
    //   2451: invokespecial 228	java/lang/StringBuilder:<init>	(I)V
    //   2454: aload 10
    //   2456: ldc_w 426
    //   2459: invokevirtual 234	java/lang/StringBuilder:append	(Ljava/lang/String;)Ljava/lang/StringBuilder;
    //   2462: astore 25
    //   2464: aload_1
    //   2465: astore_2
    //   2466: aload 25
    //   2468: aload_1
    //   2469: invokevirtual 234	java/lang/StringBuilder:append	(Ljava/lang/String;)Ljava/lang/StringBuilder;
    //   2472: astore 25
    //   2474: ldc_w 266
    //   2477: astore 10
    //   2479: aload 25
    //   2481: aload 10
    //   2483: invokevirtual 234	java/lang/StringBuilder:append	(Ljava/lang/String;)Ljava/lang/StringBuilder;
    //   2486: invokevirtual 241	java/lang/StringBuilder:toString	()Ljava/lang/String;
    //   2489: astore 25
    //   2491: aload 25
    //   2493: aload_3
    //   2494: checkcast 252	java/lang/Throwable
    //   2497: invokestatic 430	com/google/android/gms/b/tp:c	(Ljava/lang/String;Ljava/lang/Throwable;)V
    //   2500: goto -1436 -> 1064
    //   2503: new 79	java/lang/String
    //   2506: astore_3
    //   2507: aload_3
    //   2508: aload 25
    //   2510: invokespecial 92	java/lang/String:<init>	(Ljava/lang/String;)V
    //   2513: goto -1393 -> 1120
    //   2516: astore 25
    //   2518: goto -1527 -> 991
    //   2521: astore 25
    //   2523: goto -1532 -> 991
    //   2526: astore_3
    //   2527: iconst_0
    //   2528: istore 8
    //   2530: aconst_null
    //   2531: astore 4
    //   2533: goto -1578 -> 955
    //   2536: astore_3
    //   2537: goto -1582 -> 955
    //   2540: astore_3
    //   2541: iconst_0
    //   2542: istore 8
    //   2544: aconst_null
    //   2545: astore 4
    //   2547: aload 26
    //   2549: astore 6
    //   2551: aload 31
    //   2553: astore 25
    //   2555: goto -1600 -> 955
    //   2558: lload 14
    //   2560: lstore 20
    //   2562: aload 11
    //   2564: astore 6
    //   2566: goto -2241 -> 325
    // Local variable table:
    //   start	length	slot	name	signature
    //   0	2569	0	this	mv
    //   0	2569	1	paramString	String
    //   1	2465	2	localObject1	Object
    //   6	666	3	localObject2	Object
    //   678	5	3	localObject3	Object
    //   687	261	3	localObject4	Object
    //   954	24	3	localIOException1	java.io.IOException
    //   1036	122	3	localObject5	Object
    //   1176	1	3	localIOException2	java.io.IOException
    //   1210	77	3	localObject6	Object
    //   1295	1	3	localIOException3	java.io.IOException
    //   1312	221	3	localObject7	Object
    //   1541	1	3	localRuntimeException1	RuntimeException
    //   1560	316	3	localObject8	Object
    //   1877	16	3	localIOException4	java.io.IOException
    //   1899	1	3	localIOException5	java.io.IOException
    //   1981	89	3	localObject9	Object
    //   2071	1	3	localRuntimeException2	RuntimeException
    //   2100	13	3	localIOException6	java.io.IOException
    //   2114	1	3	localRuntimeException3	RuntimeException
    //   2155	25	3	local1	ms.1
    //   2187	1	3	localIOException7	java.io.IOException
    //   2228	175	3	localObject10	Object
    //   2426	68	3	localIOException8	java.io.IOException
    //   2506	2	3	str1	String
    //   2526	1	3	localRuntimeException4	RuntimeException
    //   2536	1	3	localRuntimeException5	RuntimeException
    //   2540	1	3	localRuntimeException6	RuntimeException
    //   13	2533	4	localObject11	Object
    //   16	365	5	bool1	boolean
    //   565	1710	5	i	int
    //   19	2546	6	localObject12	Object
    //   31	20	7	bool2	boolean
    //   83	173	7	j	int
    //   295	374	7	bool3	boolean
    //   771	6	7	k	int
    //   788	3	7	bool4	boolean
    //   810	214	7	m	int
    //   1069	207	7	bool5	boolean
    //   1373	556	7	n	int
    //   1964	172	7	bool6	boolean
    //   2211	3	7	i1	int
    //   2218	195	7	bool7	boolean
    //   55	170	8	i2	int
    //   390	7	8	bool8	boolean
    //   474	2069	8	i3	int
    //   159	572	9	i4	int
    //   997	3	9	bool9	boolean
    //   1845	605	9	i5	int
    //   187	2295	10	localObject13	Object
    //   191	2372	11	localObject14	Object
    //   200	762	12	bool10	boolean
    //   1106	1288	12	i6	int
    //   230	1940	13	i7	int
    //   238	2321	14	l1	long
    //   247	658	16	localObject15	Object
    //   252	18	17	i8	int
    //   260	78	18	i9	int
    //   263	2141	19	localObject16	Object
    //   307	2254	20	l2	long
    //   314	3	22	bool11	boolean
    //   414	1969	23	localFile1	File
    //   438	1980	24	localFile2	File
    //   654	1855	25	localObject17	Object
    //   2516	1	25	localIOException9	java.io.IOException
    //   2521	1	25	localNullPointerException	NullPointerException
    //   2553	1	25	localObject18	Object
    //   737	1811	26	str2	String
    //   1316	4	27	l3	long
    //   1351	464	29	i10	int
    //   1662	126	30	localReadableByteChannel	java.nio.channels.ReadableByteChannel
    //   1667	885	31	localFileOutputStream	java.io.FileOutputStream
    //   1681	239	32	localFileChannel	java.nio.channels.FileChannel
    //   1693	241	33	localByteBuffer	java.nio.ByteBuffer
    //   1698	242	34	localc	com.google.android.gms.common.util.c
    //   1713	234	35	l4	long
    //   1745	384	37	localue	ue
    //   1782	195	38	l5	long
    //   2150	28	40	localHandler	android.os.Handler
    // Exception table:
    //   from	to	target	type
    //   590	593	678	finally
    //   595	602	678	finally
    //   613	617	678	finally
    //   618	622	678	finally
    //   631	635	678	finally
    //   636	640	678	finally
    //   640	645	678	finally
    //   663	667	678	finally
    //   672	675	678	finally
    //   679	682	678	finally
    //   700	703	678	finally
    //   705	710	678	finally
    //   713	716	678	finally
    //   718	726	678	finally
    //   726	729	678	finally
    //   867	870	954	java/io/IOException
    //   872	876	954	java/io/IOException
    //   878	883	954	java/io/IOException
    //   888	891	954	java/io/IOException
    //   895	900	954	java/io/IOException
    //   906	911	954	java/io/IOException
    //   915	920	954	java/io/IOException
    //   926	931	954	java/io/IOException
    //   935	939	954	java/io/IOException
    //   940	944	954	java/io/IOException
    //   947	951	954	java/io/IOException
    //   951	954	954	java/io/IOException
    //   832	837	1176	java/io/IOException
    //   839	844	1176	java/io/IOException
    //   846	851	1176	java/io/IOException
    //   860	865	1176	java/io/IOException
    //   1161	1164	1176	java/io/IOException
    //   1168	1173	1176	java/io/IOException
    //   742	746	1295	java/io/IOException
    //   746	749	1295	java/io/IOException
    //   750	753	1295	java/io/IOException
    //   757	761	1295	java/io/IOException
    //   762	766	1295	java/io/IOException
    //   767	771	1295	java/io/IOException
    //   776	781	1295	java/io/IOException
    //   798	803	1295	java/io/IOException
    //   806	810	1295	java/io/IOException
    //   1186	1194	1295	java/io/IOException
    //   1206	1210	1295	java/io/IOException
    //   1211	1215	1295	java/io/IOException
    //   1224	1228	1295	java/io/IOException
    //   1229	1233	1295	java/io/IOException
    //   1233	1238	1295	java/io/IOException
    //   1257	1261	1295	java/io/IOException
    //   1261	1264	1295	java/io/IOException
    //   1266	1274	1295	java/io/IOException
    //   1282	1285	1295	java/io/IOException
    //   1287	1292	1295	java/io/IOException
    //   1309	1312	1295	java/io/IOException
    //   1319	1324	1295	java/io/IOException
    //   1326	1329	1295	java/io/IOException
    //   1330	1333	1295	java/io/IOException
    //   1337	1341	1295	java/io/IOException
    //   1342	1346	1295	java/io/IOException
    //   1347	1351	1295	java/io/IOException
    //   1360	1365	1295	java/io/IOException
    //   1366	1370	1295	java/io/IOException
    //   1375	1379	1295	java/io/IOException
    //   1381	1386	1295	java/io/IOException
    //   1395	1398	1295	java/io/IOException
    //   1402	1407	1295	java/io/IOException
    //   1413	1417	1295	java/io/IOException
    //   1419	1424	1295	java/io/IOException
    //   1431	1436	1295	java/io/IOException
    //   1440	1444	1295	java/io/IOException
    //   1445	1449	1295	java/io/IOException
    //   1450	1454	1295	java/io/IOException
    //   1459	1464	1295	java/io/IOException
    //   1465	1469	1295	java/io/IOException
    //   1478	1482	1295	java/io/IOException
    //   1483	1488	1295	java/io/IOException
    //   1503	1507	1295	java/io/IOException
    //   1507	1510	1295	java/io/IOException
    //   1512	1520	1295	java/io/IOException
    //   1528	1531	1295	java/io/IOException
    //   1533	1538	1295	java/io/IOException
    //   1555	1560	1295	java/io/IOException
    //   1561	1565	1295	java/io/IOException
    //   1570	1574	1295	java/io/IOException
    //   1576	1581	1295	java/io/IOException
    //   1590	1593	1295	java/io/IOException
    //   1597	1602	1295	java/io/IOException
    //   1608	1612	1295	java/io/IOException
    //   1614	1619	1295	java/io/IOException
    //   1626	1631	1295	java/io/IOException
    //   1635	1639	1295	java/io/IOException
    //   1640	1644	1295	java/io/IOException
    //   1645	1649	1295	java/io/IOException
    //   1649	1657	1295	java/io/IOException
    //   1658	1662	1295	java/io/IOException
    //   1664	1667	1295	java/io/IOException
    //   1671	1676	1295	java/io/IOException
    //   742	746	1541	java/lang/RuntimeException
    //   746	749	1541	java/lang/RuntimeException
    //   750	753	1541	java/lang/RuntimeException
    //   757	761	1541	java/lang/RuntimeException
    //   762	766	1541	java/lang/RuntimeException
    //   767	771	1541	java/lang/RuntimeException
    //   776	781	1541	java/lang/RuntimeException
    //   798	803	1541	java/lang/RuntimeException
    //   806	810	1541	java/lang/RuntimeException
    //   1186	1194	1541	java/lang/RuntimeException
    //   1206	1210	1541	java/lang/RuntimeException
    //   1211	1215	1541	java/lang/RuntimeException
    //   1224	1228	1541	java/lang/RuntimeException
    //   1229	1233	1541	java/lang/RuntimeException
    //   1233	1238	1541	java/lang/RuntimeException
    //   1257	1261	1541	java/lang/RuntimeException
    //   1261	1264	1541	java/lang/RuntimeException
    //   1266	1274	1541	java/lang/RuntimeException
    //   1282	1285	1541	java/lang/RuntimeException
    //   1287	1292	1541	java/lang/RuntimeException
    //   1309	1312	1541	java/lang/RuntimeException
    //   1319	1324	1541	java/lang/RuntimeException
    //   1326	1329	1541	java/lang/RuntimeException
    //   1330	1333	1541	java/lang/RuntimeException
    //   1337	1341	1541	java/lang/RuntimeException
    //   1342	1346	1541	java/lang/RuntimeException
    //   1347	1351	1541	java/lang/RuntimeException
    //   1360	1365	1541	java/lang/RuntimeException
    //   1366	1370	1541	java/lang/RuntimeException
    //   1375	1379	1541	java/lang/RuntimeException
    //   1381	1386	1541	java/lang/RuntimeException
    //   1395	1398	1541	java/lang/RuntimeException
    //   1402	1407	1541	java/lang/RuntimeException
    //   1413	1417	1541	java/lang/RuntimeException
    //   1419	1424	1541	java/lang/RuntimeException
    //   1431	1436	1541	java/lang/RuntimeException
    //   1440	1444	1541	java/lang/RuntimeException
    //   1445	1449	1541	java/lang/RuntimeException
    //   1450	1454	1541	java/lang/RuntimeException
    //   1459	1464	1541	java/lang/RuntimeException
    //   1465	1469	1541	java/lang/RuntimeException
    //   1478	1482	1541	java/lang/RuntimeException
    //   1483	1488	1541	java/lang/RuntimeException
    //   1503	1507	1541	java/lang/RuntimeException
    //   1507	1510	1541	java/lang/RuntimeException
    //   1512	1520	1541	java/lang/RuntimeException
    //   1528	1531	1541	java/lang/RuntimeException
    //   1533	1538	1541	java/lang/RuntimeException
    //   1555	1560	1541	java/lang/RuntimeException
    //   1561	1565	1541	java/lang/RuntimeException
    //   1570	1574	1541	java/lang/RuntimeException
    //   1576	1581	1541	java/lang/RuntimeException
    //   1590	1593	1541	java/lang/RuntimeException
    //   1597	1602	1541	java/lang/RuntimeException
    //   1608	1612	1541	java/lang/RuntimeException
    //   1614	1619	1541	java/lang/RuntimeException
    //   1626	1631	1541	java/lang/RuntimeException
    //   1635	1639	1541	java/lang/RuntimeException
    //   1640	1644	1541	java/lang/RuntimeException
    //   1645	1649	1541	java/lang/RuntimeException
    //   1649	1657	1541	java/lang/RuntimeException
    //   1658	1662	1541	java/lang/RuntimeException
    //   1664	1667	1541	java/lang/RuntimeException
    //   1671	1676	1541	java/lang/RuntimeException
    //   1860	1863	1877	java/io/IOException
    //   1870	1875	1877	java/io/IOException
    //   1875	1877	1877	java/io/IOException
    //   2054	2057	1877	java/io/IOException
    //   2064	2069	1877	java/io/IOException
    //   2069	2071	1877	java/io/IOException
    //   1826	1831	1899	java/io/IOException
    //   1833	1838	1899	java/io/IOException
    //   1840	1845	1899	java/io/IOException
    //   1853	1858	1899	java/io/IOException
    //   1885	1888	1899	java/io/IOException
    //   1892	1896	1899	java/io/IOException
    //   1976	1981	1899	java/io/IOException
    //   1982	1986	1899	java/io/IOException
    //   1987	1991	1899	java/io/IOException
    //   1993	1998	1899	java/io/IOException
    //   2003	2006	1899	java/io/IOException
    //   2010	2015	1899	java/io/IOException
    //   2022	2027	1899	java/io/IOException
    //   2031	2035	1899	java/io/IOException
    //   2042	2047	1899	java/io/IOException
    //   2048	2052	1899	java/io/IOException
    //   2097	2100	1899	java/io/IOException
    //   2107	2112	1899	java/io/IOException
    //   2112	2114	1899	java/io/IOException
    //   1860	1863	2071	java/lang/RuntimeException
    //   1870	1875	2071	java/lang/RuntimeException
    //   1875	1877	2071	java/lang/RuntimeException
    //   2054	2057	2071	java/lang/RuntimeException
    //   2064	2069	2071	java/lang/RuntimeException
    //   2069	2071	2071	java/lang/RuntimeException
    //   1826	1831	2114	java/lang/RuntimeException
    //   1833	1838	2114	java/lang/RuntimeException
    //   1840	1845	2114	java/lang/RuntimeException
    //   1853	1858	2114	java/lang/RuntimeException
    //   1885	1888	2114	java/lang/RuntimeException
    //   1892	1896	2114	java/lang/RuntimeException
    //   1976	1981	2114	java/lang/RuntimeException
    //   1982	1986	2114	java/lang/RuntimeException
    //   1987	1991	2114	java/lang/RuntimeException
    //   1993	1998	2114	java/lang/RuntimeException
    //   2003	2006	2114	java/lang/RuntimeException
    //   2010	2015	2114	java/lang/RuntimeException
    //   2022	2027	2114	java/lang/RuntimeException
    //   2031	2035	2114	java/lang/RuntimeException
    //   2042	2047	2114	java/lang/RuntimeException
    //   2048	2052	2114	java/lang/RuntimeException
    //   2097	2100	2114	java/lang/RuntimeException
    //   2107	2112	2114	java/lang/RuntimeException
    //   2112	2114	2114	java/lang/RuntimeException
    //   1676	1681	2187	java/io/IOException
    //   1688	1693	2187	java/io/IOException
    //   1695	1698	2187	java/io/IOException
    //   1706	1713	2187	java/io/IOException
    //   1715	1718	2187	java/io/IOException
    //   1719	1722	2187	java/io/IOException
    //   1726	1730	2187	java/io/IOException
    //   1731	1735	2187	java/io/IOException
    //   1736	1740	2187	java/io/IOException
    //   1742	1745	2187	java/io/IOException
    //   1752	1757	2187	java/io/IOException
    //   1757	1760	2187	java/io/IOException
    //   1761	1764	2187	java/io/IOException
    //   1768	1772	2187	java/io/IOException
    //   1773	1777	2187	java/io/IOException
    //   1778	1782	2187	java/io/IOException
    //   1789	1796	2187	java/io/IOException
    //   1913	1919	2187	java/io/IOException
    //   1921	1926	2187	java/io/IOException
    //   1933	1939	2187	java/io/IOException
    //   1939	1946	2187	java/io/IOException
    //   2081	2085	2187	java/io/IOException
    //   2128	2133	2187	java/io/IOException
    //   2140	2145	2187	java/io/IOException
    //   2147	2150	2187	java/io/IOException
    //   2152	2155	2187	java/io/IOException
    //   2169	2174	2187	java/io/IOException
    //   2179	2184	2187	java/io/IOException
    //   2205	2210	2187	java/io/IOException
    //   2213	2218	2187	java/io/IOException
    //   2225	2228	2187	java/io/IOException
    //   2235	2240	2187	java/io/IOException
    //   2241	2245	2187	java/io/IOException
    //   2247	2252	2187	java/io/IOException
    //   2257	2261	2187	java/io/IOException
    //   2263	2268	2187	java/io/IOException
    //   2277	2280	2187	java/io/IOException
    //   2284	2289	2187	java/io/IOException
    //   2296	2301	2187	java/io/IOException
    //   2305	2309	2187	java/io/IOException
    //   2316	2321	2187	java/io/IOException
    //   2325	2329	2187	java/io/IOException
    //   2330	2334	2187	java/io/IOException
    //   2335	2339	2187	java/io/IOException
    //   2352	2357	2187	java/io/IOException
    //   2357	2362	2187	java/io/IOException
    //   2369	2372	2187	java/io/IOException
    //   2376	2382	2187	java/io/IOException
    //   2382	2387	2187	java/io/IOException
    //   2393	2398	2187	java/io/IOException
    //   2398	2401	2187	java/io/IOException
    //   2403	2411	2187	java/io/IOException
    //   2417	2423	2426	java/io/IOException
    //   986	991	2516	java/io/IOException
    //   986	991	2521	java/lang/NullPointerException
    //   832	837	2526	java/lang/RuntimeException
    //   839	844	2526	java/lang/RuntimeException
    //   846	851	2526	java/lang/RuntimeException
    //   860	865	2526	java/lang/RuntimeException
    //   1161	1164	2526	java/lang/RuntimeException
    //   1168	1173	2526	java/lang/RuntimeException
    //   867	870	2536	java/lang/RuntimeException
    //   872	876	2536	java/lang/RuntimeException
    //   878	883	2536	java/lang/RuntimeException
    //   888	891	2536	java/lang/RuntimeException
    //   895	900	2536	java/lang/RuntimeException
    //   906	911	2536	java/lang/RuntimeException
    //   915	920	2536	java/lang/RuntimeException
    //   926	931	2536	java/lang/RuntimeException
    //   935	939	2536	java/lang/RuntimeException
    //   940	944	2536	java/lang/RuntimeException
    //   947	951	2536	java/lang/RuntimeException
    //   951	954	2536	java/lang/RuntimeException
    //   1676	1681	2540	java/lang/RuntimeException
    //   1688	1693	2540	java/lang/RuntimeException
    //   1695	1698	2540	java/lang/RuntimeException
    //   1706	1713	2540	java/lang/RuntimeException
    //   1715	1718	2540	java/lang/RuntimeException
    //   1719	1722	2540	java/lang/RuntimeException
    //   1726	1730	2540	java/lang/RuntimeException
    //   1731	1735	2540	java/lang/RuntimeException
    //   1736	1740	2540	java/lang/RuntimeException
    //   1742	1745	2540	java/lang/RuntimeException
    //   1752	1757	2540	java/lang/RuntimeException
    //   1757	1760	2540	java/lang/RuntimeException
    //   1761	1764	2540	java/lang/RuntimeException
    //   1768	1772	2540	java/lang/RuntimeException
    //   1773	1777	2540	java/lang/RuntimeException
    //   1778	1782	2540	java/lang/RuntimeException
    //   1789	1796	2540	java/lang/RuntimeException
    //   1913	1919	2540	java/lang/RuntimeException
    //   1921	1926	2540	java/lang/RuntimeException
    //   1933	1939	2540	java/lang/RuntimeException
    //   1939	1946	2540	java/lang/RuntimeException
    //   2081	2085	2540	java/lang/RuntimeException
    //   2128	2133	2540	java/lang/RuntimeException
    //   2140	2145	2540	java/lang/RuntimeException
    //   2147	2150	2540	java/lang/RuntimeException
    //   2152	2155	2540	java/lang/RuntimeException
    //   2169	2174	2540	java/lang/RuntimeException
    //   2179	2184	2540	java/lang/RuntimeException
    //   2205	2210	2540	java/lang/RuntimeException
    //   2213	2218	2540	java/lang/RuntimeException
    //   2225	2228	2540	java/lang/RuntimeException
    //   2235	2240	2540	java/lang/RuntimeException
    //   2241	2245	2540	java/lang/RuntimeException
    //   2247	2252	2540	java/lang/RuntimeException
    //   2257	2261	2540	java/lang/RuntimeException
    //   2263	2268	2540	java/lang/RuntimeException
    //   2277	2280	2540	java/lang/RuntimeException
    //   2284	2289	2540	java/lang/RuntimeException
    //   2296	2301	2540	java/lang/RuntimeException
    //   2305	2309	2540	java/lang/RuntimeException
    //   2316	2321	2540	java/lang/RuntimeException
    //   2325	2329	2540	java/lang/RuntimeException
    //   2330	2334	2540	java/lang/RuntimeException
    //   2335	2339	2540	java/lang/RuntimeException
    //   2352	2357	2540	java/lang/RuntimeException
    //   2357	2362	2540	java/lang/RuntimeException
    //   2369	2372	2540	java/lang/RuntimeException
    //   2376	2382	2540	java/lang/RuntimeException
    //   2382	2387	2540	java/lang/RuntimeException
    //   2393	2398	2540	java/lang/RuntimeException
    //   2398	2401	2540	java/lang/RuntimeException
    //   2403	2411	2540	java/lang/RuntimeException
    //   2417	2423	2540	java/lang/RuntimeException
  }
}


/* Location:              com/google/android/gms/b/mv.class
 * Java compiler version: 5 (49.0)
 * JD-Core Version:       0.7.1
 */