package com.google.android.gms.b;

import android.content.Context;
import com.google.android.gms.ads.internal.s;
import java.util.concurrent.Future;

public final class py
  extends to
{
  final pt.a a;
  private final qr b;
  private final tg.a c;
  private final qa d;
  private final Object e;
  private Future f;
  
  public py(Context paramContext, s params, tg.a parama, dw paramdw, pt.a parama1, km paramkm)
  {
    this(parama, parama1, localqa);
  }
  
  private py(tg.a parama, pt.a parama1, qa paramqa)
  {
    Object localObject = new java/lang/Object;
    localObject.<init>();
    e = localObject;
    c = parama;
    localObject = b;
    b = ((qr)localObject);
    a = parama1;
    d = paramqa;
  }
  
  /* Error */
  public final void a()
  {
    // Byte code:
    //   0: bipush -2
    //   2: istore_1
    //   3: aconst_null
    //   4: astore_2
    //   5: aload_0
    //   6: astore_3
    //   7: aload_0
    //   8: getfield 38	com/google/android/gms/b/py:e	Ljava/lang/Object;
    //   11: astore 4
    //   13: aload 4
    //   15: monitorenter
    //   16: aload_0
    //   17: getfield 49	com/google/android/gms/b/py:d	Lcom/google/android/gms/b/qa;
    //   20: astore 5
    //   22: aload 5
    //   24: invokestatic 54	com/google/android/gms/b/ts:a	(Ljava/util/concurrent/Callable;)Lcom/google/android/gms/b/us;
    //   27: astore 5
    //   29: aload_0
    //   30: aload 5
    //   32: putfield 56	com/google/android/gms/b/py:f	Ljava/util/concurrent/Future;
    //   35: aload 4
    //   37: monitorexit
    //   38: aload_0
    //   39: getfield 56	com/google/android/gms/b/py:f	Ljava/util/concurrent/Future;
    //   42: astore 5
    //   44: ldc2_w 57
    //   47: lstore 6
    //   49: getstatic 66	java/util/concurrent/TimeUnit:MILLISECONDS	Ljava/util/concurrent/TimeUnit;
    //   52: astore 8
    //   54: aload 5
    //   56: lload 6
    //   58: aload 8
    //   60: invokeinterface 72 4 0
    //   65: astore 5
    //   67: aload 5
    //   69: checkcast 74	com/google/android/gms/b/tg
    //   72: astore 5
    //   74: aload 5
    //   76: ifnull +104 -> 180
    //   79: getstatic 79	com/google/android/gms/b/tt:a	Landroid/os/Handler;
    //   82: astore_2
    //   83: new 81	com/google/android/gms/b/py$1
    //   86: astore 4
    //   88: aload_0
    //   89: astore_3
    //   90: aload 4
    //   92: aload_0
    //   93: aload 5
    //   95: invokespecial 84	com/google/android/gms/b/py$1:<init>	(Lcom/google/android/gms/b/py;Lcom/google/android/gms/b/tg;)V
    //   98: aload_2
    //   99: aload 4
    //   101: invokevirtual 90	android/os/Handler:post	(Ljava/lang/Runnable;)Z
    //   104: pop
    //   105: return
    //   106: astore 5
    //   108: aload 4
    //   110: monitorexit
    //   111: aload 5
    //   113: athrow
    //   114: astore 5
    //   116: ldc 92
    //   118: invokestatic 97	com/google/android/gms/b/tp:e	(Ljava/lang/String;)V
    //   121: iconst_2
    //   122: istore_1
    //   123: aload_0
    //   124: astore_3
    //   125: aload_0
    //   126: getfield 56	com/google/android/gms/b/py:f	Ljava/util/concurrent/Future;
    //   129: astore 5
    //   131: iconst_1
    //   132: istore 9
    //   134: aload 5
    //   136: iload 9
    //   138: invokeinterface 103 2 0
    //   143: pop
    //   144: aconst_null
    //   145: astore 5
    //   147: goto -73 -> 74
    //   150: astore 5
    //   152: iconst_0
    //   153: istore_1
    //   154: aconst_null
    //   155: astore 5
    //   157: goto -83 -> 74
    //   160: astore 5
    //   162: iconst_0
    //   163: istore_1
    //   164: aconst_null
    //   165: astore 5
    //   167: goto -93 -> 74
    //   170: astore 5
    //   172: iconst_0
    //   173: istore_1
    //   174: aconst_null
    //   175: astore 5
    //   177: goto -103 -> 74
    //   180: new 74	com/google/android/gms/b/tg
    //   183: astore 5
    //   185: aload_0
    //   186: astore_3
    //   187: aload_0
    //   188: getfield 40	com/google/android/gms/b/py:c	Lcom/google/android/gms/b/tg$a;
    //   191: getfield 106	com/google/android/gms/b/tg$a:a	Lcom/google/android/gms/b/qo;
    //   194: getfield 111	com/google/android/gms/b/qo:c	Lcom/google/android/gms/b/ih;
    //   197: astore_2
    //   198: iconst_0
    //   199: istore 9
    //   201: aconst_null
    //   202: astore 4
    //   204: aconst_null
    //   205: astore 8
    //   207: aload_0
    //   208: getfield 45	com/google/android/gms/b/py:b	Lcom/google/android/gms/b/qr;
    //   211: astore 10
    //   213: aload 10
    //   215: getfield 117	com/google/android/gms/b/qr:l	I
    //   218: istore 11
    //   220: aload_0
    //   221: getfield 45	com/google/android/gms/b/py:b	Lcom/google/android/gms/b/qr;
    //   224: astore 12
    //   226: aload 12
    //   228: getfield 121	com/google/android/gms/b/qr:k	J
    //   231: lstore 13
    //   233: aload_0
    //   234: getfield 40	com/google/android/gms/b/py:c	Lcom/google/android/gms/b/tg$a;
    //   237: getfield 106	com/google/android/gms/b/tg$a:a	Lcom/google/android/gms/b/qo;
    //   240: getfield 125	com/google/android/gms/b/qo:i	Ljava/lang/String;
    //   243: astore 15
    //   245: aload_0
    //   246: getfield 45	com/google/android/gms/b/py:b	Lcom/google/android/gms/b/qr;
    //   249: getfield 127	com/google/android/gms/b/qr:i	J
    //   252: lstore 16
    //   254: aload_0
    //   255: astore_3
    //   256: aload_0
    //   257: getfield 40	com/google/android/gms/b/py:c	Lcom/google/android/gms/b/tg$a;
    //   260: astore_3
    //   261: aload_3
    //   262: astore 18
    //   264: aload_3
    //   265: getfield 130	com/google/android/gms/b/tg$a:d	Lcom/google/android/gms/b/il;
    //   268: astore 18
    //   270: aload_0
    //   271: astore_3
    //   272: aload_0
    //   273: getfield 45	com/google/android/gms/b/py:b	Lcom/google/android/gms/b/qr;
    //   276: getfield 133	com/google/android/gms/b/qr:g	J
    //   279: lstore 19
    //   281: aload_0
    //   282: astore_3
    //   283: aload_0
    //   284: getfield 40	com/google/android/gms/b/py:c	Lcom/google/android/gms/b/tg$a;
    //   287: getfield 135	com/google/android/gms/b/tg$a:f	J
    //   290: lstore 21
    //   292: aload_0
    //   293: astore_3
    //   294: aload_0
    //   295: getfield 45	com/google/android/gms/b/py:b	Lcom/google/android/gms/b/qr;
    //   298: getfield 138	com/google/android/gms/b/qr:n	J
    //   301: lstore 23
    //   303: aload_0
    //   304: astore_3
    //   305: aload_0
    //   306: getfield 45	com/google/android/gms/b/py:b	Lcom/google/android/gms/b/qr;
    //   309: astore_3
    //   310: aload_3
    //   311: astore 25
    //   313: aload_3
    //   314: getfield 141	com/google/android/gms/b/qr:o	Ljava/lang/String;
    //   317: astore 25
    //   319: aload_0
    //   320: astore_3
    //   321: aload_0
    //   322: getfield 40	com/google/android/gms/b/py:c	Lcom/google/android/gms/b/tg$a;
    //   325: astore_3
    //   326: aload_3
    //   327: astore 26
    //   329: aload_3
    //   330: getfield 145	com/google/android/gms/b/tg$a:h	Lorg/json/JSONObject;
    //   333: astore 26
    //   335: aload_0
    //   336: astore_3
    //   337: aload_0
    //   338: getfield 40	com/google/android/gms/b/py:c	Lcom/google/android/gms/b/tg$a;
    //   341: getfield 44	com/google/android/gms/b/tg$a:b	Lcom/google/android/gms/b/qr;
    //   344: getfield 149	com/google/android/gms/b/qr:F	Z
    //   347: istore 27
    //   349: aload_0
    //   350: astore_3
    //   351: aload_0
    //   352: getfield 40	com/google/android/gms/b/py:c	Lcom/google/android/gms/b/tg$a;
    //   355: astore_3
    //   356: aload_3
    //   357: astore 28
    //   359: aload_3
    //   360: getfield 44	com/google/android/gms/b/tg$a:b	Lcom/google/android/gms/b/qr;
    //   363: astore_3
    //   364: aload_3
    //   365: astore 28
    //   367: aload_3
    //   368: getfield 153	com/google/android/gms/b/qr:G	Lcom/google/android/gms/b/qt;
    //   371: astore 28
    //   373: aload_0
    //   374: astore_3
    //   375: aload_0
    //   376: getfield 45	com/google/android/gms/b/py:b	Lcom/google/android/gms/b/qr;
    //   379: getfield 156	com/google/android/gms/b/qr:N	Ljava/lang/String;
    //   382: astore_3
    //   383: aload 5
    //   385: aload_2
    //   386: aconst_null
    //   387: aconst_null
    //   388: iload_1
    //   389: aconst_null
    //   390: aconst_null
    //   391: iload 11
    //   393: lload 13
    //   395: aload 15
    //   397: iconst_0
    //   398: aconst_null
    //   399: aconst_null
    //   400: aconst_null
    //   401: aconst_null
    //   402: aconst_null
    //   403: lload 16
    //   405: aload 18
    //   407: lload 19
    //   409: lload 21
    //   411: lload 23
    //   413: aload 25
    //   415: aload 26
    //   417: aconst_null
    //   418: aconst_null
    //   419: aconst_null
    //   420: aconst_null
    //   421: iload 27
    //   423: aload 28
    //   425: aconst_null
    //   426: aconst_null
    //   427: aload_3
    //   428: invokespecial 159	com/google/android/gms/b/tg:<init>	(Lcom/google/android/gms/b/ih;Lcom/google/android/gms/b/vc;Ljava/util/List;ILjava/util/List;Ljava/util/List;IJLjava/lang/String;ZLcom/google/android/gms/b/nr;Lcom/google/android/gms/b/od;Ljava/lang/String;Lcom/google/android/gms/b/ns;Lcom/google/android/gms/b/nu;JLcom/google/android/gms/b/il;JJJLjava/lang/String;Lorg/json/JSONObject;Lcom/google/android/gms/b/lc$a;Lcom/google/android/gms/b/ss;Ljava/util/List;Ljava/util/List;ZLcom/google/android/gms/b/qt;Ljava/lang/String;Ljava/util/List;Ljava/lang/String;)V
    //   431: goto -352 -> 79
    // Local variable table:
    //   start	length	slot	name	signature
    //   0	434	0	this	py
    //   2	387	1	i	int
    //   4	382	2	localObject1	Object
    //   6	422	3	localObject2	Object
    //   20	74	5	localObject4	Object
    //   106	6	5	localObject5	Object
    //   114	1	5	localTimeoutException	java.util.concurrent.TimeoutException
    //   129	17	5	localFuture	Future
    //   150	1	5	localExecutionException	java.util.concurrent.ExecutionException
    //   155	1	5	localObject6	Object
    //   160	1	5	localInterruptedException	InterruptedException
    //   165	1	5	localObject7	Object
    //   170	1	5	localCancellationException	java.util.concurrent.CancellationException
    //   175	209	5	localtg	tg
    //   47	10	6	l1	long
    //   52	154	8	localTimeUnit	java.util.concurrent.TimeUnit
    //   132	68	9	bool1	boolean
    //   211	3	10	localqr1	qr
    //   218	174	11	j	int
    //   224	3	12	localqr2	qr
    //   231	163	13	l2	long
    //   243	153	15	str	String
    //   252	152	16	l3	long
    //   262	144	18	localObject8	Object
    //   279	129	19	l4	long
    //   290	120	21	l5	long
    //   301	111	23	l6	long
    //   311	103	25	localObject9	Object
    //   327	89	26	localObject10	Object
    //   347	75	27	bool2	boolean
    //   357	67	28	localObject11	Object
    // Exception table:
    //   from	to	target	type
    //   16	20	106	finally
    //   22	27	106	finally
    //   30	35	106	finally
    //   35	38	106	finally
    //   108	111	106	finally
    //   7	11	114	java/util/concurrent/TimeoutException
    //   13	16	114	java/util/concurrent/TimeoutException
    //   38	42	114	java/util/concurrent/TimeoutException
    //   49	52	114	java/util/concurrent/TimeoutException
    //   58	65	114	java/util/concurrent/TimeoutException
    //   67	72	114	java/util/concurrent/TimeoutException
    //   111	114	114	java/util/concurrent/TimeoutException
    //   7	11	150	java/util/concurrent/ExecutionException
    //   13	16	150	java/util/concurrent/ExecutionException
    //   38	42	150	java/util/concurrent/ExecutionException
    //   49	52	150	java/util/concurrent/ExecutionException
    //   58	65	150	java/util/concurrent/ExecutionException
    //   67	72	150	java/util/concurrent/ExecutionException
    //   111	114	150	java/util/concurrent/ExecutionException
    //   7	11	160	java/lang/InterruptedException
    //   13	16	160	java/lang/InterruptedException
    //   38	42	160	java/lang/InterruptedException
    //   49	52	160	java/lang/InterruptedException
    //   58	65	160	java/lang/InterruptedException
    //   67	72	160	java/lang/InterruptedException
    //   111	114	160	java/lang/InterruptedException
    //   7	11	170	java/util/concurrent/CancellationException
    //   13	16	170	java/util/concurrent/CancellationException
    //   38	42	170	java/util/concurrent/CancellationException
    //   49	52	170	java/util/concurrent/CancellationException
    //   58	65	170	java/util/concurrent/CancellationException
    //   67	72	170	java/util/concurrent/CancellationException
    //   111	114	170	java/util/concurrent/CancellationException
  }
  
  public final void c_()
  {
    synchronized (e)
    {
      Future localFuture = f;
      if (localFuture != null)
      {
        localFuture = f;
        boolean bool = true;
        localFuture.cancel(bool);
      }
      return;
    }
  }
}


/* Location:              com/google/android/gms/b/py.class
 * Java compiler version: 5 (49.0)
 * JD-Core Version:       0.7.1
 */