package com.google.android.gms.b;

import android.content.Context;
import android.text.TextUtils;
import java.util.ArrayList;
import java.util.HashMap;
import java.util.HashSet;
import java.util.Iterator;
import java.util.List;
import org.json.JSONObject;

public final class so
  extends to
  implements sn
{
  final rx a;
  private final tg.a b;
  private final Context c;
  private final ArrayList d;
  private final ArrayList e;
  private final HashMap f;
  private final List g;
  private final HashSet h;
  private final Object i;
  private final long j;
  
  public so(Context paramContext, tg.a parama, rx paramrx)
  {
    this(paramContext, parama, paramrx, l);
  }
  
  private so(Context paramContext, tg.a parama, rx paramrx, long paramLong)
  {
    Object localObject = new java/util/ArrayList;
    ((ArrayList)localObject).<init>();
    d = ((ArrayList)localObject);
    localObject = new java/util/ArrayList;
    ((ArrayList)localObject).<init>();
    e = ((ArrayList)localObject);
    localObject = new java/util/HashMap;
    ((HashMap)localObject).<init>();
    f = ((HashMap)localObject);
    localObject = new java/util/ArrayList;
    ((ArrayList)localObject).<init>();
    g = ((List)localObject);
    localObject = new java/util/HashSet;
    ((HashSet)localObject).<init>();
    h = ((HashSet)localObject);
    localObject = new java/lang/Object;
    localObject.<init>();
    i = localObject;
    c = paramContext;
    b = parama;
    a = paramrx;
    j = paramLong;
  }
  
  private tg a(int paramInt, String paramString, nr paramnr)
  {
    tg localtg = new com/google/android/gms/b/tg;
    Object localObject = this;
    ih localih = b.a.c;
    List localList1 = b.b.d;
    List localList2 = b.b.f;
    List localList3 = b.b.j;
    int k = b.b.l;
    long l1 = b.b.k;
    String str1 = b.a.i;
    boolean bool1 = b.b.h;
    ns localns = b.c;
    localObject = this;
    long l2 = b.b.i;
    il localil = b.d;
    localObject = this;
    long l3 = b.b.g;
    long l4 = b.f;
    long l5 = b.b.n;
    String str2 = b.b.o;
    localObject = this;
    JSONObject localJSONObject = b.h;
    localObject = this;
    ss localss = b.b.C;
    localObject = this;
    List localList4 = b.b.D;
    localObject = this;
    List localList5 = b.b.E;
    localObject = this;
    boolean bool2 = b.b.F;
    qt localqt = b.b.G;
    String str3 = d();
    localObject = this;
    List localList6 = b.b.J;
    localObject = this;
    localObject = b.b.N;
    localtg.<init>(localih, null, localList1, paramInt, localList2, localList3, k, l1, str1, bool1, paramnr, null, paramString, localns, null, l2, localil, l3, l4, l5, str2, localJSONObject, null, localss, localList4, localList5, bool2, localqt, str3, localList6, (String)localObject);
    return localtg;
  }
  
  private String d()
  {
    StringBuilder localStringBuilder1 = new java/lang/StringBuilder;
    localStringBuilder1.<init>("");
    Object localObject = g;
    if (localObject == null) {}
    int k;
    for (localObject = localStringBuilder1.toString();; localObject = localStringBuilder1.substring(0, k))
    {
      return (String)localObject;
      localObject = g;
      Iterator localIterator = ((List)localObject).iterator();
      String str1;
      boolean bool2;
      do
      {
        do
        {
          boolean bool1 = localIterator.hasNext();
          if (!bool1) {
            break;
          }
          localObject = (sj)localIterator.next();
        } while (localObject == null);
        str1 = b;
        bool2 = TextUtils.isEmpty(str1);
      } while (bool2);
      String str2 = b;
      int m = c;
      switch (m)
      {
      default: 
        m = 6;
      }
      for (;;)
      {
        long l = d;
        k = String.valueOf(str2).length() + 33;
        StringBuilder localStringBuilder2 = new java/lang/StringBuilder;
        localStringBuilder2.<init>(k);
        localObject = localStringBuilder2.append(str2);
        str2 = ".";
        localObject = String.valueOf(str2 + m + "." + l);
        str1 = "_";
        localObject = ((String)localObject).concat(str1);
        localStringBuilder1.append((String)localObject);
        break;
        m = 0;
        str1 = null;
        continue;
        m = 1;
        continue;
        m = 2;
        continue;
        m = 3;
        continue;
        m = 4;
      }
      k = localStringBuilder1.length() + -1;
      k = Math.max(0, k);
    }
  }
  
  /* Error */
  public final void a()
  {
    // Byte code:
    //   0: aload_0
    //   1: getfield 83	com/google/android/gms/b/so:b	Lcom/google/android/gms/b/tg$a;
    //   4: getfield 126	com/google/android/gms/b/tg$a:c	Lcom/google/android/gms/b/ns;
    //   7: getfield 263	com/google/android/gms/b/ns:a	Ljava/util/List;
    //   10: astore_1
    //   11: aload_1
    //   12: invokeinterface 188 1 0
    //   17: astore_2
    //   18: aload_2
    //   19: invokeinterface 194 1 0
    //   24: istore_3
    //   25: iload_3
    //   26: ifeq +367 -> 393
    //   29: aload_2
    //   30: invokeinterface 198 1 0
    //   35: checkcast 265	com/google/android/gms/b/nr
    //   38: astore 4
    //   40: aload 4
    //   42: getfield 266	com/google/android/gms/b/nr:i	Ljava/lang/String;
    //   45: astore 5
    //   47: aload 4
    //   49: getfield 268	com/google/android/gms/b/nr:c	Ljava/util/List;
    //   52: astore_1
    //   53: aload_1
    //   54: invokeinterface 188 1 0
    //   59: astore 6
    //   61: aload 6
    //   63: invokeinterface 194 1 0
    //   68: istore_3
    //   69: iload_3
    //   70: ifeq -52 -> 18
    //   73: aload 6
    //   75: invokeinterface 198 1 0
    //   80: checkcast 215	java/lang/String
    //   83: astore_1
    //   84: ldc_w 270
    //   87: astore 7
    //   89: aload 7
    //   91: aload_1
    //   92: invokevirtual 274	java/lang/String:equals	(Ljava/lang/Object;)Z
    //   95: istore 8
    //   97: iload 8
    //   99: ifne +21 -> 120
    //   102: ldc_w 276
    //   105: astore 7
    //   107: aload 7
    //   109: aload_1
    //   110: invokevirtual 274	java/lang/String:equals	(Ljava/lang/Object;)Z
    //   113: istore 8
    //   115: iload 8
    //   117: ifeq +923 -> 1040
    //   120: new 278	org/json/JSONObject
    //   123: astore_1
    //   124: aload_1
    //   125: aload 5
    //   127: invokespecial 279	org/json/JSONObject:<init>	(Ljava/lang/String;)V
    //   130: ldc_w 281
    //   133: astore 7
    //   135: aload_1
    //   136: aload 7
    //   138: invokevirtual 284	org/json/JSONObject:getString	(Ljava/lang/String;)Ljava/lang/String;
    //   141: astore 9
    //   143: aload_0
    //   144: getfield 79	com/google/android/gms/b/so:i	Ljava/lang/Object;
    //   147: astore 10
    //   149: aload 10
    //   151: monitorenter
    //   152: aload_0
    //   153: getfield 85	com/google/android/gms/b/so:a	Lcom/google/android/gms/b/rx;
    //   156: astore_1
    //   157: aload_1
    //   158: aload 9
    //   160: invokevirtual 289	com/google/android/gms/b/rx:b	(Ljava/lang/String;)Lcom/google/android/gms/b/sp;
    //   163: astore 11
    //   165: aload 11
    //   167: ifnull +23 -> 190
    //   170: aload 11
    //   172: getfield 294	com/google/android/gms/b/sp:b	Lcom/google/android/gms/b/sm;
    //   175: astore_1
    //   176: aload_1
    //   177: ifnull +13 -> 190
    //   180: aload 11
    //   182: getfield 297	com/google/android/gms/b/sp:a	Lcom/google/android/gms/b/od;
    //   185: astore_1
    //   186: aload_1
    //   187: ifnonnull +103 -> 290
    //   190: aload_0
    //   191: getfield 69	com/google/android/gms/b/so:g	Ljava/util/List;
    //   194: astore_1
    //   195: new 299	com/google/android/gms/b/sj$a
    //   198: astore 7
    //   200: aload 7
    //   202: invokespecial 300	com/google/android/gms/b/sj$a:<init>	()V
    //   205: aload 4
    //   207: getfield 302	com/google/android/gms/b/nr:d	Ljava/lang/String;
    //   210: astore 12
    //   212: aload 7
    //   214: aload 12
    //   216: putfield 303	com/google/android/gms/b/sj$a:b	Ljava/lang/String;
    //   219: aload 7
    //   221: aload 9
    //   223: putfield 305	com/google/android/gms/b/sj$a:a	Ljava/lang/String;
    //   226: lconst_0
    //   227: lstore 13
    //   229: aload 7
    //   231: lload 13
    //   233: putfield 306	com/google/android/gms/b/sj$a:d	J
    //   236: bipush 7
    //   238: istore 15
    //   240: aload 7
    //   242: iload 15
    //   244: putfield 308	com/google/android/gms/b/sj$a:c	I
    //   247: aload 7
    //   249: invokevirtual 311	com/google/android/gms/b/sj$a:a	()Lcom/google/android/gms/b/sj;
    //   252: astore 7
    //   254: aload_1
    //   255: aload 7
    //   257: invokeinterface 314 2 0
    //   262: pop
    //   263: aload 10
    //   265: monitorexit
    //   266: goto -205 -> 61
    //   269: astore_1
    //   270: aload 10
    //   272: monitorexit
    //   273: aload_1
    //   274: athrow
    //   275: astore_1
    //   276: ldc_w 316
    //   279: astore 7
    //   281: aload 7
    //   283: aload_1
    //   284: invokestatic 321	com/google/android/gms/b/tp:b	(Ljava/lang/String;Ljava/lang/Throwable;)V
    //   287: goto -226 -> 61
    //   290: new 323	com/google/android/gms/b/si
    //   293: astore_1
    //   294: aload_0
    //   295: getfield 81	com/google/android/gms/b/so:c	Landroid/content/Context;
    //   298: astore 7
    //   300: aload_0
    //   301: getfield 83	com/google/android/gms/b/so:b	Lcom/google/android/gms/b/tg$a;
    //   304: astore 12
    //   306: aload_0
    //   307: getfield 87	com/google/android/gms/b/so:j	J
    //   310: lstore 16
    //   312: aload_1
    //   313: aload 7
    //   315: aload 9
    //   317: aload 5
    //   319: aload 4
    //   321: aload 12
    //   323: aload 11
    //   325: aload_0
    //   326: lload 16
    //   328: invokespecial 326	com/google/android/gms/b/si:<init>	(Landroid/content/Context;Ljava/lang/String;Ljava/lang/String;Lcom/google/android/gms/b/nr;Lcom/google/android/gms/b/tg$a;Lcom/google/android/gms/b/sp;Lcom/google/android/gms/b/sn;J)V
    //   331: aload_0
    //   332: getfield 60	com/google/android/gms/b/so:d	Ljava/util/ArrayList;
    //   335: astore 12
    //   337: aload_1
    //   338: invokevirtual 328	com/google/android/gms/b/to:c	()Ljava/lang/Object;
    //   341: astore 7
    //   343: aload 7
    //   345: checkcast 330	java/util/concurrent/Future
    //   348: astore 7
    //   350: aload 12
    //   352: aload 7
    //   354: invokevirtual 331	java/util/ArrayList:add	(Ljava/lang/Object;)Z
    //   357: pop
    //   358: aload_0
    //   359: getfield 62	com/google/android/gms/b/so:e	Ljava/util/ArrayList;
    //   362: astore 7
    //   364: aload 7
    //   366: aload 9
    //   368: invokevirtual 331	java/util/ArrayList:add	(Ljava/lang/Object;)Z
    //   371: pop
    //   372: aload_0
    //   373: getfield 67	com/google/android/gms/b/so:f	Ljava/util/HashMap;
    //   376: astore 7
    //   378: aload 7
    //   380: aload 9
    //   382: aload_1
    //   383: invokevirtual 335	java/util/HashMap:put	(Ljava/lang/Object;Ljava/lang/Object;)Ljava/lang/Object;
    //   386: pop
    //   387: aload 10
    //   389: monitorexit
    //   390: goto -329 -> 61
    //   393: iconst_0
    //   394: istore_3
    //   395: aconst_null
    //   396: astore_1
    //   397: iconst_0
    //   398: istore 8
    //   400: aconst_null
    //   401: astore 7
    //   403: aload_0
    //   404: getfield 60	com/google/android/gms/b/so:d	Ljava/util/ArrayList;
    //   407: astore_1
    //   408: aload_1
    //   409: invokevirtual 338	java/util/ArrayList:size	()I
    //   412: istore_3
    //   413: iload 8
    //   415: iload_3
    //   416: if_icmpge +353 -> 769
    //   419: aload_0
    //   420: getfield 60	com/google/android/gms/b/so:d	Ljava/util/ArrayList;
    //   423: astore_1
    //   424: aload_1
    //   425: iload 8
    //   427: invokevirtual 342	java/util/ArrayList:get	(I)Ljava/lang/Object;
    //   430: astore_1
    //   431: aload_1
    //   432: checkcast 330	java/util/concurrent/Future
    //   435: astore_1
    //   436: aload_1
    //   437: invokeinterface 344 1 0
    //   442: pop
    //   443: aload_0
    //   444: getfield 79	com/google/android/gms/b/so:i	Ljava/lang/Object;
    //   447: astore 9
    //   449: aload 9
    //   451: monitorenter
    //   452: aload_0
    //   453: getfield 62	com/google/android/gms/b/so:e	Ljava/util/ArrayList;
    //   456: astore_1
    //   457: aload_1
    //   458: iload 8
    //   460: invokevirtual 342	java/util/ArrayList:get	(I)Ljava/lang/Object;
    //   463: astore_1
    //   464: aload_1
    //   465: checkcast 215	java/lang/String
    //   468: astore_1
    //   469: aload_1
    //   470: invokestatic 208	android/text/TextUtils:isEmpty	(Ljava/lang/CharSequence;)Z
    //   473: istore 18
    //   475: iload 18
    //   477: ifne +45 -> 522
    //   480: aload_0
    //   481: getfield 67	com/google/android/gms/b/so:f	Ljava/util/HashMap;
    //   484: astore 5
    //   486: aload 5
    //   488: aload_1
    //   489: invokevirtual 347	java/util/HashMap:get	(Ljava/lang/Object;)Ljava/lang/Object;
    //   492: astore_1
    //   493: aload_1
    //   494: checkcast 323	com/google/android/gms/b/si
    //   497: astore_1
    //   498: aload_1
    //   499: ifnull +23 -> 522
    //   502: aload_0
    //   503: getfield 69	com/google/android/gms/b/so:g	Ljava/util/List;
    //   506: astore 5
    //   508: aload_1
    //   509: invokevirtual 349	com/google/android/gms/b/si:d	()Lcom/google/android/gms/b/sj;
    //   512: astore_1
    //   513: aload 5
    //   515: aload_1
    //   516: invokeinterface 314 2 0
    //   521: pop
    //   522: aload 9
    //   524: monitorexit
    //   525: aload_0
    //   526: getfield 79	com/google/android/gms/b/so:i	Ljava/lang/Object;
    //   529: astore 9
    //   531: aload 9
    //   533: monitorenter
    //   534: aload_0
    //   535: getfield 74	com/google/android/gms/b/so:h	Ljava/util/HashSet;
    //   538: astore_1
    //   539: aload_0
    //   540: getfield 62	com/google/android/gms/b/so:e	Ljava/util/ArrayList;
    //   543: astore 5
    //   545: aload 5
    //   547: iload 8
    //   549: invokevirtual 342	java/util/ArrayList:get	(I)Ljava/lang/Object;
    //   552: astore 5
    //   554: aload_1
    //   555: aload 5
    //   557: invokevirtual 352	java/util/HashSet:contains	(Ljava/lang/Object;)Z
    //   560: istore_3
    //   561: iload_3
    //   562: ifeq +466 -> 1028
    //   565: aload_0
    //   566: getfield 62	com/google/android/gms/b/so:e	Ljava/util/ArrayList;
    //   569: astore_1
    //   570: aload_1
    //   571: iload 8
    //   573: invokevirtual 342	java/util/ArrayList:get	(I)Ljava/lang/Object;
    //   576: astore_1
    //   577: aload_1
    //   578: checkcast 215	java/lang/String
    //   581: astore_1
    //   582: aload_0
    //   583: getfield 67	com/google/android/gms/b/so:f	Ljava/util/HashMap;
    //   586: astore 7
    //   588: aload 7
    //   590: aload_1
    //   591: invokevirtual 347	java/util/HashMap:get	(Ljava/lang/Object;)Ljava/lang/Object;
    //   594: astore 7
    //   596: aload 7
    //   598: ifnull +421 -> 1019
    //   601: aload_0
    //   602: getfield 67	com/google/android/gms/b/so:f	Ljava/util/HashMap;
    //   605: astore 7
    //   607: aload 7
    //   609: aload_1
    //   610: invokevirtual 347	java/util/HashMap:get	(Ljava/lang/Object;)Ljava/lang/Object;
    //   613: astore 7
    //   615: aload 7
    //   617: checkcast 323	com/google/android/gms/b/si
    //   620: astore 7
    //   622: aload 7
    //   624: getfield 355	com/google/android/gms/b/si:d	Lcom/google/android/gms/b/nr;
    //   627: astore 7
    //   629: bipush -2
    //   631: istore 18
    //   633: aload_0
    //   634: iload 18
    //   636: aload_1
    //   637: aload 7
    //   639: invokespecial 358	com/google/android/gms/b/so:a	(ILjava/lang/String;Lcom/google/android/gms/b/nr;)Lcom/google/android/gms/b/tg;
    //   642: astore_1
    //   643: getstatic 363	com/google/android/gms/b/uk:a	Landroid/os/Handler;
    //   646: astore 7
    //   648: new 365	com/google/android/gms/b/so$1
    //   651: astore 5
    //   653: aload 5
    //   655: aload_0
    //   656: aload_1
    //   657: invokespecial 368	com/google/android/gms/b/so$1:<init>	(Lcom/google/android/gms/b/so;Lcom/google/android/gms/b/tg;)V
    //   660: aload 7
    //   662: aload 5
    //   664: invokevirtual 374	android/os/Handler:post	(Ljava/lang/Runnable;)Z
    //   667: pop
    //   668: aload 9
    //   670: monitorexit
    //   671: return
    //   672: astore_1
    //   673: aload 9
    //   675: monitorexit
    //   676: aload_1
    //   677: athrow
    //   678: astore_1
    //   679: invokestatic 380	java/lang/Thread:currentThread	()Ljava/lang/Thread;
    //   682: astore_1
    //   683: aload_1
    //   684: invokevirtual 383	java/lang/Thread:interrupt	()V
    //   687: aload_0
    //   688: getfield 79	com/google/android/gms/b/so:i	Ljava/lang/Object;
    //   691: astore 9
    //   693: aload 9
    //   695: monitorenter
    //   696: aload_0
    //   697: getfield 62	com/google/android/gms/b/so:e	Ljava/util/ArrayList;
    //   700: astore_1
    //   701: aload_1
    //   702: iload 8
    //   704: invokevirtual 342	java/util/ArrayList:get	(I)Ljava/lang/Object;
    //   707: astore_1
    //   708: aload_1
    //   709: checkcast 215	java/lang/String
    //   712: astore_1
    //   713: aload_1
    //   714: invokestatic 208	android/text/TextUtils:isEmpty	(Ljava/lang/CharSequence;)Z
    //   717: istore 8
    //   719: iload 8
    //   721: ifne +45 -> 766
    //   724: aload_0
    //   725: getfield 67	com/google/android/gms/b/so:f	Ljava/util/HashMap;
    //   728: astore 7
    //   730: aload 7
    //   732: aload_1
    //   733: invokevirtual 347	java/util/HashMap:get	(Ljava/lang/Object;)Ljava/lang/Object;
    //   736: astore_1
    //   737: aload_1
    //   738: checkcast 323	com/google/android/gms/b/si
    //   741: astore_1
    //   742: aload_1
    //   743: ifnull +23 -> 766
    //   746: aload_0
    //   747: getfield 69	com/google/android/gms/b/so:g	Ljava/util/List;
    //   750: astore 7
    //   752: aload_1
    //   753: invokevirtual 349	com/google/android/gms/b/si:d	()Lcom/google/android/gms/b/sj;
    //   756: astore_1
    //   757: aload 7
    //   759: aload_1
    //   760: invokeinterface 314 2 0
    //   765: pop
    //   766: aload 9
    //   768: monitorexit
    //   769: iconst_3
    //   770: istore_3
    //   771: aload_0
    //   772: iload_3
    //   773: aconst_null
    //   774: aconst_null
    //   775: invokespecial 358	com/google/android/gms/b/so:a	(ILjava/lang/String;Lcom/google/android/gms/b/nr;)Lcom/google/android/gms/b/tg;
    //   778: astore_1
    //   779: getstatic 363	com/google/android/gms/b/uk:a	Landroid/os/Handler;
    //   782: astore 7
    //   784: new 385	com/google/android/gms/b/so$2
    //   787: astore 9
    //   789: aload 9
    //   791: aload_0
    //   792: aload_1
    //   793: invokespecial 386	com/google/android/gms/b/so$2:<init>	(Lcom/google/android/gms/b/so;Lcom/google/android/gms/b/tg;)V
    //   796: aload 7
    //   798: aload 9
    //   800: invokevirtual 374	android/os/Handler:post	(Ljava/lang/Runnable;)Z
    //   803: pop
    //   804: goto -133 -> 671
    //   807: astore_1
    //   808: aload 9
    //   810: monitorexit
    //   811: aload_1
    //   812: athrow
    //   813: astore_1
    //   814: ldc_w 388
    //   817: astore 9
    //   819: aload 9
    //   821: aload_1
    //   822: invokestatic 390	com/google/android/gms/b/tp:c	(Ljava/lang/String;Ljava/lang/Throwable;)V
    //   825: aload_0
    //   826: getfield 79	com/google/android/gms/b/so:i	Ljava/lang/Object;
    //   829: astore 9
    //   831: aload 9
    //   833: monitorenter
    //   834: aload_0
    //   835: getfield 62	com/google/android/gms/b/so:e	Ljava/util/ArrayList;
    //   838: astore_1
    //   839: aload_1
    //   840: iload 8
    //   842: invokevirtual 342	java/util/ArrayList:get	(I)Ljava/lang/Object;
    //   845: astore_1
    //   846: aload_1
    //   847: checkcast 215	java/lang/String
    //   850: astore_1
    //   851: aload_1
    //   852: invokestatic 208	android/text/TextUtils:isEmpty	(Ljava/lang/CharSequence;)Z
    //   855: istore 18
    //   857: iload 18
    //   859: ifne +45 -> 904
    //   862: aload_0
    //   863: getfield 67	com/google/android/gms/b/so:f	Ljava/util/HashMap;
    //   866: astore 5
    //   868: aload 5
    //   870: aload_1
    //   871: invokevirtual 347	java/util/HashMap:get	(Ljava/lang/Object;)Ljava/lang/Object;
    //   874: astore_1
    //   875: aload_1
    //   876: checkcast 323	com/google/android/gms/b/si
    //   879: astore_1
    //   880: aload_1
    //   881: ifnull +23 -> 904
    //   884: aload_0
    //   885: getfield 69	com/google/android/gms/b/so:g	Ljava/util/List;
    //   888: astore 5
    //   890: aload_1
    //   891: invokevirtual 349	com/google/android/gms/b/si:d	()Lcom/google/android/gms/b/sj;
    //   894: astore_1
    //   895: aload 5
    //   897: aload_1
    //   898: invokeinterface 314 2 0
    //   903: pop
    //   904: aload 9
    //   906: monitorexit
    //   907: iload 8
    //   909: iconst_1
    //   910: iadd
    //   911: istore_3
    //   912: iload_3
    //   913: istore 8
    //   915: goto -512 -> 403
    //   918: astore_1
    //   919: aload 9
    //   921: monitorexit
    //   922: aload_1
    //   923: athrow
    //   924: astore_1
    //   925: aload_1
    //   926: astore 9
    //   928: aload_0
    //   929: getfield 79	com/google/android/gms/b/so:i	Ljava/lang/Object;
    //   932: astore 5
    //   934: aload 5
    //   936: monitorenter
    //   937: aload_0
    //   938: getfield 62	com/google/android/gms/b/so:e	Ljava/util/ArrayList;
    //   941: astore_1
    //   942: aload_1
    //   943: iload 8
    //   945: invokevirtual 342	java/util/ArrayList:get	(I)Ljava/lang/Object;
    //   948: astore_1
    //   949: aload_1
    //   950: checkcast 215	java/lang/String
    //   953: astore_1
    //   954: aload_1
    //   955: invokestatic 208	android/text/TextUtils:isEmpty	(Ljava/lang/CharSequence;)Z
    //   958: istore 8
    //   960: iload 8
    //   962: ifne +45 -> 1007
    //   965: aload_0
    //   966: getfield 67	com/google/android/gms/b/so:f	Ljava/util/HashMap;
    //   969: astore 7
    //   971: aload 7
    //   973: aload_1
    //   974: invokevirtual 347	java/util/HashMap:get	(Ljava/lang/Object;)Ljava/lang/Object;
    //   977: astore_1
    //   978: aload_1
    //   979: checkcast 323	com/google/android/gms/b/si
    //   982: astore_1
    //   983: aload_1
    //   984: ifnull +23 -> 1007
    //   987: aload_0
    //   988: getfield 69	com/google/android/gms/b/so:g	Ljava/util/List;
    //   991: astore 7
    //   993: aload_1
    //   994: invokevirtual 349	com/google/android/gms/b/si:d	()Lcom/google/android/gms/b/sj;
    //   997: astore_1
    //   998: aload 7
    //   1000: aload_1
    //   1001: invokeinterface 314 2 0
    //   1006: pop
    //   1007: aload 5
    //   1009: monitorexit
    //   1010: aload 9
    //   1012: athrow
    //   1013: astore_1
    //   1014: aload 5
    //   1016: monitorexit
    //   1017: aload_1
    //   1018: athrow
    //   1019: iconst_0
    //   1020: istore 8
    //   1022: aconst_null
    //   1023: astore 7
    //   1025: goto -396 -> 629
    //   1028: aload 9
    //   1030: monitorexit
    //   1031: goto -124 -> 907
    //   1034: astore_1
    //   1035: aload 9
    //   1037: monitorexit
    //   1038: aload_1
    //   1039: athrow
    //   1040: aload_1
    //   1041: astore 9
    //   1043: goto -900 -> 143
    // Local variable table:
    //   start	length	slot	name	signature
    //   0	1046	0	this	so
    //   10	245	1	localObject1	Object
    //   269	5	1	localObject2	Object
    //   275	9	1	localJSONException	org.json.JSONException
    //   293	364	1	localObject3	Object
    //   672	5	1	localObject4	Object
    //   678	1	1	localInterruptedException	InterruptedException
    //   682	111	1	localObject5	Object
    //   807	5	1	localObject6	Object
    //   813	9	1	localException	Exception
    //   838	60	1	localObject7	Object
    //   918	5	1	localObject8	Object
    //   924	2	1	localObject9	Object
    //   941	60	1	localObject10	Object
    //   1013	5	1	localObject11	Object
    //   1034	7	1	localObject12	Object
    //   17	13	2	localIterator1	Iterator
    //   24	371	3	bool1	boolean
    //   412	5	3	k	int
    //   560	2	3	bool2	boolean
    //   770	143	3	m	int
    //   38	282	4	localnr	nr
    //   59	15	6	localIterator2	Iterator
    //   87	937	7	localObject14	Object
    //   95	608	8	n	int
    //   717	227	8	i1	int
    //   958	63	8	bool3	boolean
    //   147	241	10	localObject16	Object
    //   163	161	11	localsp	sp
    //   210	141	12	localObject17	Object
    //   227	5	13	l1	long
    //   238	5	15	i2	int
    //   310	17	16	l2	long
    //   473	3	18	bool4	boolean
    //   631	4	18	i3	int
    //   855	3	18	bool5	boolean
    // Exception table:
    //   from	to	target	type
    //   152	156	269	finally
    //   158	163	269	finally
    //   170	175	269	finally
    //   180	185	269	finally
    //   190	194	269	finally
    //   195	198	269	finally
    //   200	205	269	finally
    //   205	210	269	finally
    //   214	219	269	finally
    //   221	226	269	finally
    //   231	236	269	finally
    //   242	247	269	finally
    //   247	252	269	finally
    //   255	263	269	finally
    //   263	266	269	finally
    //   270	273	269	finally
    //   290	293	269	finally
    //   294	298	269	finally
    //   300	304	269	finally
    //   306	310	269	finally
    //   326	331	269	finally
    //   331	335	269	finally
    //   337	341	269	finally
    //   343	348	269	finally
    //   352	358	269	finally
    //   358	362	269	finally
    //   366	372	269	finally
    //   372	376	269	finally
    //   382	387	269	finally
    //   387	390	269	finally
    //   120	123	275	org/json/JSONException
    //   125	130	275	org/json/JSONException
    //   136	141	275	org/json/JSONException
    //   452	456	672	finally
    //   458	463	672	finally
    //   464	468	672	finally
    //   469	473	672	finally
    //   480	484	672	finally
    //   488	492	672	finally
    //   493	497	672	finally
    //   502	506	672	finally
    //   508	512	672	finally
    //   515	522	672	finally
    //   522	525	672	finally
    //   673	676	672	finally
    //   419	423	678	java/lang/InterruptedException
    //   425	430	678	java/lang/InterruptedException
    //   431	435	678	java/lang/InterruptedException
    //   436	443	678	java/lang/InterruptedException
    //   696	700	807	finally
    //   702	707	807	finally
    //   708	712	807	finally
    //   713	717	807	finally
    //   724	728	807	finally
    //   732	736	807	finally
    //   737	741	807	finally
    //   746	750	807	finally
    //   752	756	807	finally
    //   759	766	807	finally
    //   766	769	807	finally
    //   808	811	807	finally
    //   419	423	813	java/lang/Exception
    //   425	430	813	java/lang/Exception
    //   431	435	813	java/lang/Exception
    //   436	443	813	java/lang/Exception
    //   834	838	918	finally
    //   840	845	918	finally
    //   846	850	918	finally
    //   851	855	918	finally
    //   862	866	918	finally
    //   870	874	918	finally
    //   875	879	918	finally
    //   884	888	918	finally
    //   890	894	918	finally
    //   897	904	918	finally
    //   904	907	918	finally
    //   919	922	918	finally
    //   419	423	924	finally
    //   425	430	924	finally
    //   431	435	924	finally
    //   436	443	924	finally
    //   679	682	924	finally
    //   683	687	924	finally
    //   821	825	924	finally
    //   937	941	1013	finally
    //   943	948	1013	finally
    //   949	953	1013	finally
    //   954	958	1013	finally
    //   965	969	1013	finally
    //   973	977	1013	finally
    //   978	982	1013	finally
    //   987	991	1013	finally
    //   993	997	1013	finally
    //   1000	1007	1013	finally
    //   1007	1010	1013	finally
    //   1014	1017	1013	finally
    //   534	538	1034	finally
    //   539	543	1034	finally
    //   547	552	1034	finally
    //   555	560	1034	finally
    //   565	569	1034	finally
    //   571	576	1034	finally
    //   577	581	1034	finally
    //   582	586	1034	finally
    //   590	594	1034	finally
    //   601	605	1034	finally
    //   609	613	1034	finally
    //   615	620	1034	finally
    //   622	627	1034	finally
    //   637	642	1034	finally
    //   643	646	1034	finally
    //   648	651	1034	finally
    //   656	660	1034	finally
    //   662	668	1034	finally
    //   668	671	1034	finally
    //   1028	1031	1034	finally
    //   1035	1038	1034	finally
  }
  
  public final void a(int paramInt) {}
  
  public final void a(String paramString)
  {
    synchronized (i)
    {
      HashSet localHashSet = h;
      localHashSet.add(paramString);
      return;
    }
  }
  
  public final void c_() {}
}


/* Location:              com/google/android/gms/b/so.class
 * Java compiler version: 5 (49.0)
 * JD-Core Version:       0.7.1
 */