package com.google.android.gms.b;

import java.util.List;
import java.util.concurrent.atomic.AtomicInteger;

final class ur$2
  implements Runnable
{
  ur$2(AtomicInteger paramAtomicInteger, int paramInt, up paramup, List paramList) {}
  
  /* Error */
  public final void run()
  {
    // Byte code:
    //   0: aload_0
    //   1: getfield 16	com/google/android/gms/b/ur$2:a	Ljava/util/concurrent/atomic/AtomicInteger;
    //   4: astore_1
    //   5: aload_1
    //   6: invokevirtual 32	java/util/concurrent/atomic/AtomicInteger:incrementAndGet	()I
    //   9: istore_2
    //   10: aload_0
    //   11: getfield 18	com/google/android/gms/b/ur$2:b	I
    //   14: istore_3
    //   15: iload_2
    //   16: iload_3
    //   17: if_icmplt +91 -> 108
    //   20: aload_0
    //   21: getfield 20	com/google/android/gms/b/ur$2:c	Lcom/google/android/gms/b/up;
    //   24: astore 4
    //   26: aload_0
    //   27: getfield 22	com/google/android/gms/b/ur$2:d	Ljava/util/List;
    //   30: astore_1
    //   31: new 34	java/util/ArrayList
    //   34: astore 5
    //   36: aload 5
    //   38: invokespecial 35	java/util/ArrayList:<init>	()V
    //   41: aload_1
    //   42: invokeinterface 41 1 0
    //   47: astore 6
    //   49: aload 6
    //   51: invokeinterface 47 1 0
    //   56: istore_2
    //   57: iload_2
    //   58: ifeq +51 -> 109
    //   61: aload 6
    //   63: invokeinterface 51 1 0
    //   68: astore_1
    //   69: aload_1
    //   70: checkcast 53	com/google/android/gms/b/us
    //   73: astore_1
    //   74: aload_1
    //   75: invokeinterface 56 1 0
    //   80: astore_1
    //   81: aload_1
    //   82: ifnull -33 -> 49
    //   85: aload 5
    //   87: aload_1
    //   88: invokeinterface 60 2 0
    //   93: pop
    //   94: goto -45 -> 49
    //   97: astore_1
    //   98: ldc 62
    //   100: astore 4
    //   102: aload 4
    //   104: aload_1
    //   105: invokestatic 67	com/google/android/gms/b/tp:c	(Ljava/lang/String;Ljava/lang/Throwable;)V
    //   108: return
    //   109: aload 4
    //   111: aload 5
    //   113: invokevirtual 72	com/google/android/gms/b/up:b	(Ljava/lang/Object;)V
    //   116: goto -8 -> 108
    //   119: astore_1
    //   120: goto -22 -> 98
    // Local variable table:
    //   start	length	slot	name	signature
    //   0	123	0	this	2
    //   4	84	1	localObject1	Object
    //   97	8	1	localExecutionException	java.util.concurrent.ExecutionException
    //   119	1	1	localInterruptedException	InterruptedException
    //   9	9	2	i	int
    //   56	2	2	bool	boolean
    //   14	4	3	j	int
    //   24	86	4	localObject2	Object
    //   34	78	5	localArrayList	java.util.ArrayList
    //   47	15	6	localIterator	java.util.Iterator
    // Exception table:
    //   from	to	target	type
    //   20	24	97	java/util/concurrent/ExecutionException
    //   26	30	97	java/util/concurrent/ExecutionException
    //   31	34	97	java/util/concurrent/ExecutionException
    //   36	41	97	java/util/concurrent/ExecutionException
    //   41	47	97	java/util/concurrent/ExecutionException
    //   49	56	97	java/util/concurrent/ExecutionException
    //   61	68	97	java/util/concurrent/ExecutionException
    //   69	73	97	java/util/concurrent/ExecutionException
    //   74	80	97	java/util/concurrent/ExecutionException
    //   87	94	97	java/util/concurrent/ExecutionException
    //   111	116	97	java/util/concurrent/ExecutionException
    //   20	24	119	java/lang/InterruptedException
    //   26	30	119	java/lang/InterruptedException
    //   31	34	119	java/lang/InterruptedException
    //   36	41	119	java/lang/InterruptedException
    //   41	47	119	java/lang/InterruptedException
    //   49	56	119	java/lang/InterruptedException
    //   61	68	119	java/lang/InterruptedException
    //   69	73	119	java/lang/InterruptedException
    //   74	80	119	java/lang/InterruptedException
    //   87	94	119	java/lang/InterruptedException
    //   111	116	119	java/lang/InterruptedException
  }
}


/* Location:              com/google/android/gms/b/ur$2.class
 * Java compiler version: 5 (49.0)
 * JD-Core Version:       0.7.1
 */