package com.google.android.gms.b;

import java.io.IOException;
import java.io.InputStream;
import java.util.Comparator;
import java.util.Map;
import java.util.TreeMap;
import org.apache.http.Header;
import org.apache.http.HttpEntity;

public final class vt
  implements ka
{
  protected static final boolean a = vs.b;
  private static int d = 3000;
  private static int e = 4096;
  protected final vy b;
  protected final vu c;
  
  public vt(vy paramvy)
  {
    this(paramvy, localvu);
  }
  
  private vt(vy paramvy, vu paramvu)
  {
    b = paramvy;
    c = paramvu;
  }
  
  private static Map a(Header[] paramArrayOfHeader)
  {
    TreeMap localTreeMap = new java/util/TreeMap;
    Comparator localComparator = String.CASE_INSENSITIVE_ORDER;
    localTreeMap.<init>(localComparator);
    int i = 0;
    localComparator = null;
    for (;;)
    {
      int j = paramArrayOfHeader.length;
      if (i >= j) {
        break;
      }
      String str1 = paramArrayOfHeader[i].getName();
      String str2 = paramArrayOfHeader[i].getValue();
      localTreeMap.put(str1, str2);
      i += 1;
    }
    return localTreeMap;
  }
  
  private static void a(String paramString, pc parampc, vr paramvr)
  {
    int i = 2;
    int j = 1;
    Object localObject1 = i;
    int k = parampc.d();
    try
    {
      ((te)localObject1).a(paramvr);
      Object[] arrayOfObject1 = new Object[i];
      arrayOfObject1[0] = paramString;
      localObject2 = Integer.valueOf(k);
      arrayOfObject1[j] = localObject2;
      localObject1 = String.format("%s-retry [timeout=%s]", arrayOfObject1);
      parampc.a((String)localObject1);
      return;
    }
    catch (vr localvr)
    {
      Object[] arrayOfObject2 = new Object[i];
      arrayOfObject2[0] = paramString;
      Object localObject2 = Integer.valueOf(k);
      arrayOfObject2[j] = localObject2;
      localObject2 = String.format("%s-timeout-giveup [timeout=%s]", arrayOfObject2);
      parampc.a((String)localObject2);
      throw localvr;
    }
  }
  
  private byte[] a(HttpEntity paramHttpEntity)
  {
    aa localaa = new com/google/android/gms/b/aa;
    Object localObject1 = c;
    long l = paramHttpEntity.getContentLength();
    int i = (int)l;
    localaa.<init>((vu)localObject1, i);
    i = 0;
    byte[] arrayOfByte2 = null;
    try
    {
      localObject1 = paramHttpEntity.getContent();
      if (localObject1 == null)
      {
        localObject1 = new com/google/android/gms/b/uf;
        ((uf)localObject1).<init>();
        throw ((Throwable)localObject1);
      }
    }
    finally {}
    try
    {
      paramHttpEntity.consumeContent();
      c.a(arrayOfByte2);
      localaa.close();
      throw ((Throwable)localObject2);
      vu localvu = c;
      int j = 1024;
      arrayOfByte2 = localvu.a(j);
      for (;;)
      {
        int k = ((InputStream)localObject2).read(arrayOfByte2);
        j = -1;
        if (k == j) {
          break;
        }
        j = 0;
        arrayOfObject = null;
        localaa.write(arrayOfByte2, 0, k);
      }
      byte[] arrayOfByte1 = localaa.toByteArray();
      try
      {
        paramHttpEntity.consumeContent();
        c.a(arrayOfByte2);
        localaa.close();
        return arrayOfByte1;
      }
      catch (IOException localIOException1)
      {
        for (;;)
        {
          String str1 = "Error occured when calling consumingContent";
          arrayOfObject = new Object[0];
          vs.a(str1, arrayOfObject);
        }
      }
    }
    catch (IOException localIOException2)
    {
      for (;;)
      {
        String str2 = "Error occured when calling consumingContent";
        Object[] arrayOfObject = new Object[0];
        vs.a(str2, arrayOfObject);
      }
    }
  }
  
  /* Error */
  public final na a(pc parampc)
  {
    // Byte code:
    //   0: invokestatic 161	android/os/SystemClock:elapsedRealtime	()J
    //   3: lstore_2
    //   4: iconst_0
    //   5: istore 4
    //   7: aconst_null
    //   8: astore 5
    //   10: invokestatic 167	java/util/Collections:emptyMap	()Ljava/util/Map;
    //   13: astore 6
    //   15: new 169	java/util/HashMap
    //   18: astore 7
    //   20: aload 7
    //   22: invokespecial 170	java/util/HashMap:<init>	()V
    //   25: aload_1
    //   26: getfield 174	com/google/android/gms/b/pc:j	Lcom/google/android/gms/b/dz$a;
    //   29: astore 8
    //   31: aload 8
    //   33: ifnull +102 -> 135
    //   36: aload 8
    //   38: getfield 179	com/google/android/gms/b/dz$a:b	Ljava/lang/String;
    //   41: astore 9
    //   43: aload 9
    //   45: ifnull +26 -> 71
    //   48: ldc -75
    //   50: astore 9
    //   52: aload 8
    //   54: getfield 179	com/google/android/gms/b/dz$a:b	Ljava/lang/String;
    //   57: astore 10
    //   59: aload 7
    //   61: aload 9
    //   63: aload 10
    //   65: invokeinterface 69 3 0
    //   70: pop
    //   71: aload 8
    //   73: getfield 184	com/google/android/gms/b/dz$a:d	J
    //   76: lstore 11
    //   78: lconst_0
    //   79: lstore 13
    //   81: lload 11
    //   83: lload 13
    //   85: lcmp
    //   86: istore 15
    //   88: iload 15
    //   90: ifle +45 -> 135
    //   93: new 186	java/util/Date
    //   96: astore 9
    //   98: aload 8
    //   100: getfield 184	com/google/android/gms/b/dz$a:d	J
    //   103: lstore 11
    //   105: aload 9
    //   107: lload 11
    //   109: invokespecial 189	java/util/Date:<init>	(J)V
    //   112: ldc -65
    //   114: astore 8
    //   116: aload 9
    //   118: invokestatic 197	org/apache/http/impl/cookie/DateUtils:formatDate	(Ljava/util/Date;)Ljava/lang/String;
    //   121: astore 9
    //   123: aload 7
    //   125: aload 8
    //   127: aload 9
    //   129: invokeinterface 69 3 0
    //   134: pop
    //   135: aload_0
    //   136: getfield 41	com/google/android/gms/b/vt:b	Lcom/google/android/gms/b/vy;
    //   139: astore 8
    //   141: aload 8
    //   143: aload_1
    //   144: aload 7
    //   146: invokeinterface 202 3 0
    //   151: astore 16
    //   153: aload 16
    //   155: invokeinterface 208 1 0
    //   160: astore 5
    //   162: aload 5
    //   164: invokeinterface 213 1 0
    //   169: istore 17
    //   171: aload 16
    //   173: invokeinterface 217 1 0
    //   178: astore 7
    //   180: aload 7
    //   182: invokestatic 220	com/google/android/gms/b/vt:a	([Lorg/apache/http/Header;)Ljava/util/Map;
    //   185: astore 6
    //   187: sipush 304
    //   190: istore 18
    //   192: iload 17
    //   194: iload 18
    //   196: if_icmpne +133 -> 329
    //   199: aload_1
    //   200: getfield 174	com/google/android/gms/b/pc:j	Lcom/google/android/gms/b/dz$a;
    //   203: astore 7
    //   205: aload 7
    //   207: ifnonnull +46 -> 253
    //   210: new 223	com/google/android/gms/b/na
    //   213: astore 5
    //   215: sipush 304
    //   218: istore 17
    //   220: iconst_0
    //   221: istore 15
    //   223: aconst_null
    //   224: astore 9
    //   226: iconst_1
    //   227: istore 19
    //   229: invokestatic 161	android/os/SystemClock:elapsedRealtime	()J
    //   232: lload_2
    //   233: lsub
    //   234: lstore 11
    //   236: aload 5
    //   238: iload 17
    //   240: aconst_null
    //   241: aload 6
    //   243: iload 19
    //   245: lload 11
    //   247: invokespecial 226	com/google/android/gms/b/na:<init>	(I[BLjava/util/Map;ZJ)V
    //   250: aload 5
    //   252: areturn
    //   253: aload 7
    //   255: getfield 230	com/google/android/gms/b/dz$a:g	Ljava/util/Map;
    //   258: astore 5
    //   260: aload 5
    //   262: aload 6
    //   264: invokeinterface 234 2 0
    //   269: new 223	com/google/android/gms/b/na
    //   272: astore 10
    //   274: sipush 304
    //   277: istore 20
    //   279: aload 7
    //   281: getfield 237	com/google/android/gms/b/dz$a:a	[B
    //   284: astore 21
    //   286: aload 7
    //   288: getfield 230	com/google/android/gms/b/dz$a:g	Ljava/util/Map;
    //   291: astore 22
    //   293: iconst_1
    //   294: istore 23
    //   296: invokestatic 161	android/os/SystemClock:elapsedRealtime	()J
    //   299: lstore 24
    //   301: lload 24
    //   303: lload_2
    //   304: lsub
    //   305: lstore 26
    //   307: aload 10
    //   309: iload 20
    //   311: aload 21
    //   313: aload 22
    //   315: iload 23
    //   317: lload 26
    //   319: invokespecial 226	com/google/android/gms/b/na:<init>	(I[BLjava/util/Map;ZJ)V
    //   322: aload 10
    //   324: astore 5
    //   326: goto -76 -> 250
    //   329: aload 16
    //   331: invokeinterface 241 1 0
    //   336: astore 7
    //   338: aload 7
    //   340: ifnull +254 -> 594
    //   343: aload 16
    //   345: invokeinterface 241 1 0
    //   350: astore 7
    //   352: aload_0
    //   353: aload 7
    //   355: invokespecial 244	com/google/android/gms/b/vt:a	(Lorg/apache/http/HttpEntity;)[B
    //   358: astore 9
    //   360: invokestatic 161	android/os/SystemClock:elapsedRealtime	()J
    //   363: lload_2
    //   364: lsub
    //   365: lstore 11
    //   367: getstatic 21	com/google/android/gms/b/vt:a	Z
    //   370: istore 18
    //   372: iload 18
    //   374: ifne +21 -> 395
    //   377: getstatic 24	com/google/android/gms/b/vt:d	I
    //   380: i2l
    //   381: lstore 13
    //   383: lload 11
    //   385: lload 13
    //   387: lcmp
    //   388: istore 18
    //   390: iload 18
    //   392: ifle +137 -> 529
    //   395: ldc -10
    //   397: astore 10
    //   399: iconst_5
    //   400: istore 18
    //   402: iload 18
    //   404: anewarray 4	java/lang/Object
    //   407: astore 22
    //   409: iconst_0
    //   410: istore 18
    //   412: aconst_null
    //   413: astore 7
    //   415: aload 22
    //   417: iconst_0
    //   418: aload_1
    //   419: aastore
    //   420: iconst_1
    //   421: istore 18
    //   423: lload 11
    //   425: invokestatic 252	java/lang/Long:valueOf	(J)Ljava/lang/Long;
    //   428: astore 28
    //   430: aload 22
    //   432: iload 18
    //   434: aload 28
    //   436: aastore
    //   437: iconst_2
    //   438: istore 20
    //   440: aload 9
    //   442: ifnull +166 -> 608
    //   445: aload 9
    //   447: arraylength
    //   448: istore 18
    //   450: iload 18
    //   452: invokestatic 93	java/lang/Integer:valueOf	(I)Ljava/lang/Integer;
    //   455: astore 7
    //   457: aload 22
    //   459: iload 20
    //   461: aload 7
    //   463: aastore
    //   464: iconst_3
    //   465: istore 18
    //   467: aload 5
    //   469: invokeinterface 213 1 0
    //   474: istore 4
    //   476: iload 4
    //   478: invokestatic 93	java/lang/Integer:valueOf	(I)Ljava/lang/Integer;
    //   481: astore 5
    //   483: aload 22
    //   485: iload 18
    //   487: aload 5
    //   489: aastore
    //   490: iconst_4
    //   491: istore 18
    //   493: aload_1
    //   494: getfield 77	com/google/android/gms/b/pc:i	Lcom/google/android/gms/b/te;
    //   497: astore 5
    //   499: aload 5
    //   501: invokeinterface 256 1 0
    //   506: istore 4
    //   508: iload 4
    //   510: invokestatic 93	java/lang/Integer:valueOf	(I)Ljava/lang/Integer;
    //   513: astore 5
    //   515: aload 22
    //   517: iload 18
    //   519: aload 5
    //   521: aastore
    //   522: aload 10
    //   524: aload 22
    //   526: invokestatic 258	com/google/android/gms/b/vs:b	(Ljava/lang/String;[Ljava/lang/Object;)V
    //   529: sipush 200
    //   532: istore 18
    //   534: iload 17
    //   536: iload 18
    //   538: if_icmplt +15 -> 553
    //   541: sipush 299
    //   544: istore 18
    //   546: iload 17
    //   548: iload 18
    //   550: if_icmple +66 -> 616
    //   553: new 156	java/io/IOException
    //   556: astore 7
    //   558: aload 7
    //   560: invokespecial 261	java/io/IOException:<init>	()V
    //   563: aload 7
    //   565: athrow
    //   566: astore 7
    //   568: ldc_w 263
    //   571: astore 7
    //   573: new 265	com/google/android/gms/b/vg
    //   576: astore 5
    //   578: aload 5
    //   580: invokespecial 266	com/google/android/gms/b/vg:<init>	()V
    //   583: aload 7
    //   585: aload_1
    //   586: aload 5
    //   588: invokestatic 269	com/google/android/gms/b/vt:a	(Ljava/lang/String;Lcom/google/android/gms/b/pc;Lcom/google/android/gms/b/vr;)V
    //   591: goto -587 -> 4
    //   594: iconst_0
    //   595: istore 18
    //   597: aconst_null
    //   598: astore 7
    //   600: iconst_0
    //   601: newarray <illegal type>
    //   603: astore 9
    //   605: goto -245 -> 360
    //   608: ldc_w 271
    //   611: astore 7
    //   613: goto -156 -> 457
    //   616: new 223	com/google/android/gms/b/na
    //   619: astore 5
    //   621: iconst_0
    //   622: istore 19
    //   624: aconst_null
    //   625: astore 10
    //   627: invokestatic 161	android/os/SystemClock:elapsedRealtime	()J
    //   630: lload_2
    //   631: lsub
    //   632: lstore 11
    //   634: aload 5
    //   636: iload 17
    //   638: aload 9
    //   640: aload 6
    //   642: iconst_0
    //   643: lload 11
    //   645: invokespecial 226	com/google/android/gms/b/na:<init>	(I[BLjava/util/Map;ZJ)V
    //   648: goto -398 -> 250
    //   651: astore 7
    //   653: ldc_w 273
    //   656: astore 7
    //   658: new 265	com/google/android/gms/b/vg
    //   661: astore 5
    //   663: aload 5
    //   665: invokespecial 266	com/google/android/gms/b/vg:<init>	()V
    //   668: aload 7
    //   670: aload_1
    //   671: aload 5
    //   673: invokestatic 269	com/google/android/gms/b/vt:a	(Ljava/lang/String;Lcom/google/android/gms/b/pc;Lcom/google/android/gms/b/vr;)V
    //   676: goto -672 -> 4
    //   679: astore 7
    //   681: new 275	java/lang/RuntimeException
    //   684: astore 5
    //   686: new 277	java/lang/StringBuilder
    //   689: astore 8
    //   691: aload 8
    //   693: ldc_w 279
    //   696: invokespecial 281	java/lang/StringBuilder:<init>	(Ljava/lang/String;)V
    //   699: aload_1
    //   700: getfield 282	com/google/android/gms/b/pc:b	Ljava/lang/String;
    //   703: astore 9
    //   705: aload 8
    //   707: aload 9
    //   709: invokevirtual 286	java/lang/StringBuilder:append	(Ljava/lang/String;)Ljava/lang/StringBuilder;
    //   712: invokevirtual 289	java/lang/StringBuilder:toString	()Ljava/lang/String;
    //   715: astore 8
    //   717: aload 5
    //   719: aload 8
    //   721: aload 7
    //   723: invokespecial 292	java/lang/RuntimeException:<init>	(Ljava/lang/String;Ljava/lang/Throwable;)V
    //   726: aload 5
    //   728: athrow
    //   729: astore 7
    //   731: iconst_0
    //   732: istore 15
    //   734: aconst_null
    //   735: astore 9
    //   737: aload 5
    //   739: ifnull +160 -> 899
    //   742: aload 5
    //   744: invokeinterface 208 1 0
    //   749: invokeinterface 213 1 0
    //   754: istore 17
    //   756: ldc_w 294
    //   759: astore 7
    //   761: iconst_2
    //   762: istore 4
    //   764: iload 4
    //   766: anewarray 4	java/lang/Object
    //   769: astore 5
    //   771: aconst_null
    //   772: astore 10
    //   774: iload 17
    //   776: invokestatic 93	java/lang/Integer:valueOf	(I)Ljava/lang/Integer;
    //   779: astore 28
    //   781: aload 5
    //   783: iconst_0
    //   784: aload 28
    //   786: aastore
    //   787: iconst_1
    //   788: istore 19
    //   790: aload_1
    //   791: getfield 282	com/google/android/gms/b/pc:b	Ljava/lang/String;
    //   794: astore 28
    //   796: aload 5
    //   798: iload 19
    //   800: aload 28
    //   802: aastore
    //   803: aload 7
    //   805: aload 5
    //   807: invokestatic 296	com/google/android/gms/b/vs:c	(Ljava/lang/String;[Ljava/lang/Object;)V
    //   810: aload 9
    //   812: ifnull +195 -> 1007
    //   815: new 223	com/google/android/gms/b/na
    //   818: astore 5
    //   820: iconst_0
    //   821: istore 19
    //   823: aconst_null
    //   824: astore 10
    //   826: invokestatic 161	android/os/SystemClock:elapsedRealtime	()J
    //   829: lload_2
    //   830: lsub
    //   831: lstore 11
    //   833: aload 5
    //   835: iload 17
    //   837: aload 9
    //   839: aload 6
    //   841: iconst_0
    //   842: lload 11
    //   844: invokespecial 226	com/google/android/gms/b/na:<init>	(I[BLjava/util/Map;ZJ)V
    //   847: sipush 401
    //   850: istore 18
    //   852: iload 17
    //   854: iload 18
    //   856: if_icmpeq +15 -> 871
    //   859: sipush 403
    //   862: istore 18
    //   864: iload 17
    //   866: iload 18
    //   868: if_icmpne +46 -> 914
    //   871: ldc_w 300
    //   874: astore 7
    //   876: new 302	com/google/android/gms/b/a
    //   879: astore 8
    //   881: aload 8
    //   883: aload 5
    //   885: invokespecial 305	com/google/android/gms/b/a:<init>	(Lcom/google/android/gms/b/na;)V
    //   888: aload 7
    //   890: aload_1
    //   891: aload 8
    //   893: invokestatic 269	com/google/android/gms/b/vt:a	(Ljava/lang/String;Lcom/google/android/gms/b/pc;Lcom/google/android/gms/b/vr;)V
    //   896: goto -892 -> 4
    //   899: new 307	com/google/android/gms/b/ob
    //   902: astore 5
    //   904: aload 5
    //   906: aload 7
    //   908: invokespecial 310	com/google/android/gms/b/ob:<init>	(Ljava/lang/Throwable;)V
    //   911: aload 5
    //   913: athrow
    //   914: sipush 400
    //   917: istore 18
    //   919: iload 17
    //   921: iload 18
    //   923: if_icmplt +30 -> 953
    //   926: sipush 499
    //   929: istore 18
    //   931: iload 17
    //   933: iload 18
    //   935: if_icmpgt +18 -> 953
    //   938: new 314	com/google/android/gms/b/hd
    //   941: astore 7
    //   943: aload 7
    //   945: aload 5
    //   947: invokespecial 315	com/google/android/gms/b/hd:<init>	(Lcom/google/android/gms/b/na;)V
    //   950: aload 7
    //   952: athrow
    //   953: sipush 500
    //   956: istore 18
    //   958: iload 17
    //   960: iload 18
    //   962: if_icmplt +30 -> 992
    //   965: sipush 599
    //   968: istore 18
    //   970: iload 17
    //   972: iload 18
    //   974: if_icmpgt +18 -> 992
    //   977: new 121	com/google/android/gms/b/uf
    //   980: astore 7
    //   982: aload 7
    //   984: aload 5
    //   986: invokespecial 318	com/google/android/gms/b/uf:<init>	(Lcom/google/android/gms/b/na;)V
    //   989: aload 7
    //   991: athrow
    //   992: new 121	com/google/android/gms/b/uf
    //   995: astore 7
    //   997: aload 7
    //   999: aload 5
    //   1001: invokespecial 318	com/google/android/gms/b/uf:<init>	(Lcom/google/android/gms/b/na;)V
    //   1004: aload 7
    //   1006: athrow
    //   1007: ldc_w 320
    //   1010: astore 7
    //   1012: new 322	com/google/android/gms/b/lz
    //   1015: astore 5
    //   1017: aload 5
    //   1019: invokespecial 323	com/google/android/gms/b/lz:<init>	()V
    //   1022: aload 7
    //   1024: aload_1
    //   1025: aload 5
    //   1027: invokestatic 269	com/google/android/gms/b/vt:a	(Ljava/lang/String;Lcom/google/android/gms/b/pc;Lcom/google/android/gms/b/vr;)V
    //   1030: goto -1026 -> 4
    //   1033: astore 7
    //   1035: iconst_0
    //   1036: istore 15
    //   1038: aconst_null
    //   1039: astore 9
    //   1041: aload 16
    //   1043: astore 5
    //   1045: goto -308 -> 737
    //   1048: astore 7
    //   1050: aload 16
    //   1052: astore 5
    //   1054: goto -317 -> 737
    // Local variable table:
    //   start	length	slot	name	signature
    //   0	1057	0	this	vt
    //   0	1057	1	parampc	pc
    //   3	827	2	l1	long
    //   5	760	4	i	int
    //   8	1045	5	localObject1	Object
    //   13	827	6	localMap	Map
    //   18	546	7	localObject2	Object
    //   566	1	7	localSocketTimeoutException	java.net.SocketTimeoutException
    //   571	41	7	str1	String
    //   651	1	7	localConnectTimeoutException	org.apache.http.conn.ConnectTimeoutException
    //   656	13	7	str2	String
    //   679	43	7	localMalformedURLException	java.net.MalformedURLException
    //   729	1	7	localIOException1	IOException
    //   759	264	7	localObject3	Object
    //   1033	1	7	localIOException2	IOException
    //   1048	1	7	localIOException3	IOException
    //   29	863	8	localObject4	Object
    //   41	999	9	localObject5	Object
    //   57	768	10	localObject6	Object
    //   76	767	11	l2	long
    //   79	307	13	l3	long
    //   86	951	15	bool1	boolean
    //   151	900	16	localHttpResponse	org.apache.http.HttpResponse
    //   169	806	17	j	int
    //   190	7	18	k	int
    //   370	21	18	bool2	boolean
    //   400	575	18	m	int
    //   227	595	19	bool3	boolean
    //   277	183	20	n	int
    //   284	28	21	arrayOfByte	byte[]
    //   291	234	22	localObject7	Object
    //   294	22	23	bool4	boolean
    //   299	3	24	l4	long
    //   305	13	26	l5	long
    //   428	373	28	localObject8	Object
    // Exception table:
    //   from	to	target	type
    //   15	18	566	java/net/SocketTimeoutException
    //   20	25	566	java/net/SocketTimeoutException
    //   25	29	566	java/net/SocketTimeoutException
    //   36	41	566	java/net/SocketTimeoutException
    //   52	57	566	java/net/SocketTimeoutException
    //   63	71	566	java/net/SocketTimeoutException
    //   71	76	566	java/net/SocketTimeoutException
    //   93	96	566	java/net/SocketTimeoutException
    //   98	103	566	java/net/SocketTimeoutException
    //   107	112	566	java/net/SocketTimeoutException
    //   116	121	566	java/net/SocketTimeoutException
    //   127	135	566	java/net/SocketTimeoutException
    //   135	139	566	java/net/SocketTimeoutException
    //   144	151	566	java/net/SocketTimeoutException
    //   153	160	566	java/net/SocketTimeoutException
    //   162	169	566	java/net/SocketTimeoutException
    //   171	178	566	java/net/SocketTimeoutException
    //   180	185	566	java/net/SocketTimeoutException
    //   199	203	566	java/net/SocketTimeoutException
    //   210	213	566	java/net/SocketTimeoutException
    //   229	232	566	java/net/SocketTimeoutException
    //   245	250	566	java/net/SocketTimeoutException
    //   253	258	566	java/net/SocketTimeoutException
    //   262	269	566	java/net/SocketTimeoutException
    //   269	272	566	java/net/SocketTimeoutException
    //   279	284	566	java/net/SocketTimeoutException
    //   286	291	566	java/net/SocketTimeoutException
    //   296	299	566	java/net/SocketTimeoutException
    //   317	322	566	java/net/SocketTimeoutException
    //   329	336	566	java/net/SocketTimeoutException
    //   343	350	566	java/net/SocketTimeoutException
    //   353	358	566	java/net/SocketTimeoutException
    //   360	363	566	java/net/SocketTimeoutException
    //   367	370	566	java/net/SocketTimeoutException
    //   377	380	566	java/net/SocketTimeoutException
    //   402	407	566	java/net/SocketTimeoutException
    //   418	420	566	java/net/SocketTimeoutException
    //   423	428	566	java/net/SocketTimeoutException
    //   434	437	566	java/net/SocketTimeoutException
    //   445	448	566	java/net/SocketTimeoutException
    //   450	455	566	java/net/SocketTimeoutException
    //   461	464	566	java/net/SocketTimeoutException
    //   467	474	566	java/net/SocketTimeoutException
    //   476	481	566	java/net/SocketTimeoutException
    //   487	490	566	java/net/SocketTimeoutException
    //   493	497	566	java/net/SocketTimeoutException
    //   499	506	566	java/net/SocketTimeoutException
    //   508	513	566	java/net/SocketTimeoutException
    //   519	522	566	java/net/SocketTimeoutException
    //   524	529	566	java/net/SocketTimeoutException
    //   553	556	566	java/net/SocketTimeoutException
    //   558	563	566	java/net/SocketTimeoutException
    //   563	566	566	java/net/SocketTimeoutException
    //   600	603	566	java/net/SocketTimeoutException
    //   616	619	566	java/net/SocketTimeoutException
    //   627	630	566	java/net/SocketTimeoutException
    //   643	648	566	java/net/SocketTimeoutException
    //   15	18	651	org/apache/http/conn/ConnectTimeoutException
    //   20	25	651	org/apache/http/conn/ConnectTimeoutException
    //   25	29	651	org/apache/http/conn/ConnectTimeoutException
    //   36	41	651	org/apache/http/conn/ConnectTimeoutException
    //   52	57	651	org/apache/http/conn/ConnectTimeoutException
    //   63	71	651	org/apache/http/conn/ConnectTimeoutException
    //   71	76	651	org/apache/http/conn/ConnectTimeoutException
    //   93	96	651	org/apache/http/conn/ConnectTimeoutException
    //   98	103	651	org/apache/http/conn/ConnectTimeoutException
    //   107	112	651	org/apache/http/conn/ConnectTimeoutException
    //   116	121	651	org/apache/http/conn/ConnectTimeoutException
    //   127	135	651	org/apache/http/conn/ConnectTimeoutException
    //   135	139	651	org/apache/http/conn/ConnectTimeoutException
    //   144	151	651	org/apache/http/conn/ConnectTimeoutException
    //   153	160	651	org/apache/http/conn/ConnectTimeoutException
    //   162	169	651	org/apache/http/conn/ConnectTimeoutException
    //   171	178	651	org/apache/http/conn/ConnectTimeoutException
    //   180	185	651	org/apache/http/conn/ConnectTimeoutException
    //   199	203	651	org/apache/http/conn/ConnectTimeoutException
    //   210	213	651	org/apache/http/conn/ConnectTimeoutException
    //   229	232	651	org/apache/http/conn/ConnectTimeoutException
    //   245	250	651	org/apache/http/conn/ConnectTimeoutException
    //   253	258	651	org/apache/http/conn/ConnectTimeoutException
    //   262	269	651	org/apache/http/conn/ConnectTimeoutException
    //   269	272	651	org/apache/http/conn/ConnectTimeoutException
    //   279	284	651	org/apache/http/conn/ConnectTimeoutException
    //   286	291	651	org/apache/http/conn/ConnectTimeoutException
    //   296	299	651	org/apache/http/conn/ConnectTimeoutException
    //   317	322	651	org/apache/http/conn/ConnectTimeoutException
    //   329	336	651	org/apache/http/conn/ConnectTimeoutException
    //   343	350	651	org/apache/http/conn/ConnectTimeoutException
    //   353	358	651	org/apache/http/conn/ConnectTimeoutException
    //   360	363	651	org/apache/http/conn/ConnectTimeoutException
    //   367	370	651	org/apache/http/conn/ConnectTimeoutException
    //   377	380	651	org/apache/http/conn/ConnectTimeoutException
    //   402	407	651	org/apache/http/conn/ConnectTimeoutException
    //   418	420	651	org/apache/http/conn/ConnectTimeoutException
    //   423	428	651	org/apache/http/conn/ConnectTimeoutException
    //   434	437	651	org/apache/http/conn/ConnectTimeoutException
    //   445	448	651	org/apache/http/conn/ConnectTimeoutException
    //   450	455	651	org/apache/http/conn/ConnectTimeoutException
    //   461	464	651	org/apache/http/conn/ConnectTimeoutException
    //   467	474	651	org/apache/http/conn/ConnectTimeoutException
    //   476	481	651	org/apache/http/conn/ConnectTimeoutException
    //   487	490	651	org/apache/http/conn/ConnectTimeoutException
    //   493	497	651	org/apache/http/conn/ConnectTimeoutException
    //   499	506	651	org/apache/http/conn/ConnectTimeoutException
    //   508	513	651	org/apache/http/conn/ConnectTimeoutException
    //   519	522	651	org/apache/http/conn/ConnectTimeoutException
    //   524	529	651	org/apache/http/conn/ConnectTimeoutException
    //   553	556	651	org/apache/http/conn/ConnectTimeoutException
    //   558	563	651	org/apache/http/conn/ConnectTimeoutException
    //   563	566	651	org/apache/http/conn/ConnectTimeoutException
    //   600	603	651	org/apache/http/conn/ConnectTimeoutException
    //   616	619	651	org/apache/http/conn/ConnectTimeoutException
    //   627	630	651	org/apache/http/conn/ConnectTimeoutException
    //   643	648	651	org/apache/http/conn/ConnectTimeoutException
    //   15	18	679	java/net/MalformedURLException
    //   20	25	679	java/net/MalformedURLException
    //   25	29	679	java/net/MalformedURLException
    //   36	41	679	java/net/MalformedURLException
    //   52	57	679	java/net/MalformedURLException
    //   63	71	679	java/net/MalformedURLException
    //   71	76	679	java/net/MalformedURLException
    //   93	96	679	java/net/MalformedURLException
    //   98	103	679	java/net/MalformedURLException
    //   107	112	679	java/net/MalformedURLException
    //   116	121	679	java/net/MalformedURLException
    //   127	135	679	java/net/MalformedURLException
    //   135	139	679	java/net/MalformedURLException
    //   144	151	679	java/net/MalformedURLException
    //   153	160	679	java/net/MalformedURLException
    //   162	169	679	java/net/MalformedURLException
    //   171	178	679	java/net/MalformedURLException
    //   180	185	679	java/net/MalformedURLException
    //   199	203	679	java/net/MalformedURLException
    //   210	213	679	java/net/MalformedURLException
    //   229	232	679	java/net/MalformedURLException
    //   245	250	679	java/net/MalformedURLException
    //   253	258	679	java/net/MalformedURLException
    //   262	269	679	java/net/MalformedURLException
    //   269	272	679	java/net/MalformedURLException
    //   279	284	679	java/net/MalformedURLException
    //   286	291	679	java/net/MalformedURLException
    //   296	299	679	java/net/MalformedURLException
    //   317	322	679	java/net/MalformedURLException
    //   329	336	679	java/net/MalformedURLException
    //   343	350	679	java/net/MalformedURLException
    //   353	358	679	java/net/MalformedURLException
    //   360	363	679	java/net/MalformedURLException
    //   367	370	679	java/net/MalformedURLException
    //   377	380	679	java/net/MalformedURLException
    //   402	407	679	java/net/MalformedURLException
    //   418	420	679	java/net/MalformedURLException
    //   423	428	679	java/net/MalformedURLException
    //   434	437	679	java/net/MalformedURLException
    //   445	448	679	java/net/MalformedURLException
    //   450	455	679	java/net/MalformedURLException
    //   461	464	679	java/net/MalformedURLException
    //   467	474	679	java/net/MalformedURLException
    //   476	481	679	java/net/MalformedURLException
    //   487	490	679	java/net/MalformedURLException
    //   493	497	679	java/net/MalformedURLException
    //   499	506	679	java/net/MalformedURLException
    //   508	513	679	java/net/MalformedURLException
    //   519	522	679	java/net/MalformedURLException
    //   524	529	679	java/net/MalformedURLException
    //   553	556	679	java/net/MalformedURLException
    //   558	563	679	java/net/MalformedURLException
    //   563	566	679	java/net/MalformedURLException
    //   600	603	679	java/net/MalformedURLException
    //   616	619	679	java/net/MalformedURLException
    //   627	630	679	java/net/MalformedURLException
    //   643	648	679	java/net/MalformedURLException
    //   15	18	729	java/io/IOException
    //   20	25	729	java/io/IOException
    //   25	29	729	java/io/IOException
    //   36	41	729	java/io/IOException
    //   52	57	729	java/io/IOException
    //   63	71	729	java/io/IOException
    //   71	76	729	java/io/IOException
    //   93	96	729	java/io/IOException
    //   98	103	729	java/io/IOException
    //   107	112	729	java/io/IOException
    //   116	121	729	java/io/IOException
    //   127	135	729	java/io/IOException
    //   135	139	729	java/io/IOException
    //   144	151	729	java/io/IOException
    //   153	160	1033	java/io/IOException
    //   162	169	1033	java/io/IOException
    //   171	178	1033	java/io/IOException
    //   180	185	1033	java/io/IOException
    //   199	203	1033	java/io/IOException
    //   210	213	1033	java/io/IOException
    //   229	232	1033	java/io/IOException
    //   245	250	1033	java/io/IOException
    //   253	258	1033	java/io/IOException
    //   262	269	1033	java/io/IOException
    //   269	272	1033	java/io/IOException
    //   279	284	1033	java/io/IOException
    //   286	291	1033	java/io/IOException
    //   296	299	1033	java/io/IOException
    //   317	322	1033	java/io/IOException
    //   329	336	1033	java/io/IOException
    //   343	350	1033	java/io/IOException
    //   353	358	1033	java/io/IOException
    //   600	603	1033	java/io/IOException
    //   360	363	1048	java/io/IOException
    //   367	370	1048	java/io/IOException
    //   377	380	1048	java/io/IOException
    //   402	407	1048	java/io/IOException
    //   418	420	1048	java/io/IOException
    //   423	428	1048	java/io/IOException
    //   434	437	1048	java/io/IOException
    //   445	448	1048	java/io/IOException
    //   450	455	1048	java/io/IOException
    //   461	464	1048	java/io/IOException
    //   467	474	1048	java/io/IOException
    //   476	481	1048	java/io/IOException
    //   487	490	1048	java/io/IOException
    //   493	497	1048	java/io/IOException
    //   499	506	1048	java/io/IOException
    //   508	513	1048	java/io/IOException
    //   519	522	1048	java/io/IOException
    //   524	529	1048	java/io/IOException
    //   553	556	1048	java/io/IOException
    //   558	563	1048	java/io/IOException
    //   563	566	1048	java/io/IOException
    //   616	619	1048	java/io/IOException
    //   627	630	1048	java/io/IOException
    //   643	648	1048	java/io/IOException
  }
}


/* Location:              com/google/android/gms/b/vt.class
 * Java compiler version: 5 (49.0)
 * JD-Core Version:       0.7.1
 */