package com.google.android.gms.ads.internal;

final class q$1$1
  implements Runnable
{
  q$1$1(q.1 param1) {}
  
  /* Error */
  public final void run()
  {
    // Byte code:
    //   0: aload_0
    //   1: getfield 10	com/google/android/gms/ads/internal/q$1$1:a	Lcom/google/android/gms/ads/internal/q$1;
    //   4: getfield 20	com/google/android/gms/ads/internal/q$1:b	Lcom/google/android/gms/ads/internal/q;
    //   7: invokestatic 25	com/google/android/gms/ads/internal/q:a	(Lcom/google/android/gms/ads/internal/q;)Landroid/content/Context;
    //   10: astore_1
    //   11: aload_0
    //   12: getfield 10	com/google/android/gms/ads/internal/q$1$1:a	Lcom/google/android/gms/ads/internal/q$1;
    //   15: getfield 28	com/google/android/gms/ads/internal/q$1:a	Ljava/lang/Runnable;
    //   18: astore_2
    //   19: ldc 30
    //   21: invokestatic 35	com/google/android/gms/common/internal/c:b	(Ljava/lang/String;)V
    //   24: invokestatic 41	com/google/android/gms/ads/internal/w:i	()Lcom/google/android/gms/b/tj;
    //   27: invokevirtual 47	com/google/android/gms/b/tj:p	()Lcom/google/android/gms/b/ti;
    //   30: getfield 52	com/google/android/gms/b/ti:b	Ljava/util/Map;
    //   33: astore_3
    //   34: aload_3
    //   35: ifnull +16 -> 51
    //   38: aload_3
    //   39: invokeinterface 58 1 0
    //   44: istore 4
    //   46: iload 4
    //   48: ifeq +4 -> 52
    //   51: return
    //   52: aload_2
    //   53: ifnull +9 -> 62
    //   56: aload_2
    //   57: invokeinterface 61 1 0
    //   62: invokestatic 67	com/google/android/gms/b/rx:J	()Lcom/google/android/gms/b/rx;
    //   65: astore 5
    //   67: aload 5
    //   69: ifnull -18 -> 51
    //   72: aload_3
    //   73: invokeinterface 71 1 0
    //   78: astore_2
    //   79: new 73	java/util/HashMap
    //   82: astore_3
    //   83: aload_3
    //   84: invokespecial 74	java/util/HashMap:<init>	()V
    //   87: aload_1
    //   88: invokestatic 79	com/google/android/gms/a/b:a	(Ljava/lang/Object;)Lcom/google/android/gms/a/a;
    //   91: astore 6
    //   93: aload_2
    //   94: invokeinterface 85 1 0
    //   99: astore_2
    //   100: aload_2
    //   101: invokeinterface 90 1 0
    //   106: istore 7
    //   108: iload 7
    //   110: ifeq +167 -> 277
    //   113: aload_2
    //   114: invokeinterface 94 1 0
    //   119: checkcast 96	com/google/android/gms/b/ns
    //   122: getfield 99	com/google/android/gms/b/ns:a	Ljava/util/List;
    //   125: astore_1
    //   126: aload_1
    //   127: invokeinterface 102 1 0
    //   132: astore 8
    //   134: aload 8
    //   136: invokeinterface 90 1 0
    //   141: istore 7
    //   143: iload 7
    //   145: ifeq -45 -> 100
    //   148: aload 8
    //   150: invokeinterface 94 1 0
    //   155: checkcast 104	com/google/android/gms/b/nr
    //   158: astore_1
    //   159: aload_1
    //   160: getfield 107	com/google/android/gms/b/nr:i	Ljava/lang/String;
    //   163: astore 9
    //   165: aload_1
    //   166: getfield 110	com/google/android/gms/b/nr:c	Ljava/util/List;
    //   169: astore_1
    //   170: aload_1
    //   171: invokeinterface 102 1 0
    //   176: astore 10
    //   178: aload 10
    //   180: invokeinterface 90 1 0
    //   185: istore 7
    //   187: iload 7
    //   189: ifeq -55 -> 134
    //   192: aload 10
    //   194: invokeinterface 94 1 0
    //   199: checkcast 112	java/lang/String
    //   202: astore_1
    //   203: aload_3
    //   204: aload_1
    //   205: invokeinterface 116 2 0
    //   210: istore 11
    //   212: iload 11
    //   214: ifne +23 -> 237
    //   217: new 118	java/util/ArrayList
    //   220: astore 12
    //   222: aload 12
    //   224: invokespecial 119	java/util/ArrayList:<init>	()V
    //   227: aload_3
    //   228: aload_1
    //   229: aload 12
    //   231: invokeinterface 123 3 0
    //   236: pop
    //   237: aload 9
    //   239: ifnull -61 -> 178
    //   242: aload_3
    //   243: aload_1
    //   244: invokeinterface 127 2 0
    //   249: checkcast 81	java/util/Collection
    //   252: astore_1
    //   253: aload_1
    //   254: aload 9
    //   256: invokeinterface 130 2 0
    //   261: pop
    //   262: goto -84 -> 178
    //   265: astore_1
    //   266: ldc -124
    //   268: astore_2
    //   269: aload_2
    //   270: aload_1
    //   271: invokestatic 137	com/google/android/gms/b/tp:c	(Ljava/lang/String;Ljava/lang/Throwable;)V
    //   274: goto -223 -> 51
    //   277: aload_3
    //   278: invokeinterface 141 1 0
    //   283: astore_1
    //   284: aload_1
    //   285: invokeinterface 144 1 0
    //   290: astore_3
    //   291: aload_3
    //   292: invokeinterface 90 1 0
    //   297: istore 7
    //   299: iload 7
    //   301: ifeq -250 -> 51
    //   304: aload_3
    //   305: invokeinterface 94 1 0
    //   310: checkcast 146	java/util/Map$Entry
    //   313: astore_1
    //   314: aload_1
    //   315: invokeinterface 149 1 0
    //   320: checkcast 112	java/lang/String
    //   323: astore_2
    //   324: aload 5
    //   326: aload_2
    //   327: invokevirtual 152	com/google/android/gms/b/rx:b	(Ljava/lang/String;)Lcom/google/android/gms/b/sp;
    //   330: astore 8
    //   332: aload 8
    //   334: ifnull -43 -> 291
    //   337: aload 8
    //   339: getfield 157	com/google/android/gms/b/sp:a	Lcom/google/android/gms/b/od;
    //   342: astore 9
    //   344: aload 9
    //   346: invokeinterface 162 1 0
    //   351: istore 13
    //   353: iload 13
    //   355: ifne -64 -> 291
    //   358: aload 9
    //   360: invokeinterface 165 1 0
    //   365: istore 13
    //   367: iload 13
    //   369: ifeq -78 -> 291
    //   372: aload 8
    //   374: getfield 168	com/google/android/gms/b/sp:b	Lcom/google/android/gms/b/sm;
    //   377: astore 8
    //   379: aload_1
    //   380: invokeinterface 171 1 0
    //   385: astore_1
    //   386: aload_1
    //   387: checkcast 101	java/util/List
    //   390: astore_1
    //   391: aload 9
    //   393: aload 6
    //   395: aload 8
    //   397: aload_1
    //   398: invokeinterface 174 4 0
    //   403: ldc -80
    //   405: astore 8
    //   407: aload_2
    //   408: invokestatic 180	java/lang/String:valueOf	(Ljava/lang/Object;)Ljava/lang/String;
    //   411: astore_1
    //   412: aload_1
    //   413: invokevirtual 184	java/lang/String:length	()I
    //   416: istore 14
    //   418: iload 14
    //   420: ifeq +76 -> 496
    //   423: aload 8
    //   425: aload_1
    //   426: invokevirtual 188	java/lang/String:concat	(Ljava/lang/String;)Ljava/lang/String;
    //   429: astore_1
    //   430: aload_1
    //   431: invokestatic 189	com/google/android/gms/b/tp:b	(Ljava/lang/String;)V
    //   434: goto -143 -> 291
    //   437: astore_1
    //   438: aload_2
    //   439: invokestatic 180	java/lang/String:valueOf	(Ljava/lang/Object;)Ljava/lang/String;
    //   442: invokevirtual 184	java/lang/String:length	()I
    //   445: bipush 56
    //   447: iadd
    //   448: istore 15
    //   450: new 191	java/lang/StringBuilder
    //   453: astore 9
    //   455: aload 9
    //   457: iload 15
    //   459: invokespecial 194	java/lang/StringBuilder:<init>	(I)V
    //   462: aload 9
    //   464: ldc -60
    //   466: invokevirtual 200	java/lang/StringBuilder:append	(Ljava/lang/String;)Ljava/lang/StringBuilder;
    //   469: aload_2
    //   470: invokevirtual 200	java/lang/StringBuilder:append	(Ljava/lang/String;)Ljava/lang/StringBuilder;
    //   473: astore_2
    //   474: ldc -54
    //   476: astore 8
    //   478: aload_2
    //   479: aload 8
    //   481: invokevirtual 200	java/lang/StringBuilder:append	(Ljava/lang/String;)Ljava/lang/StringBuilder;
    //   484: invokevirtual 206	java/lang/StringBuilder:toString	()Ljava/lang/String;
    //   487: astore_2
    //   488: aload_2
    //   489: aload_1
    //   490: invokestatic 137	com/google/android/gms/b/tp:c	(Ljava/lang/String;Ljava/lang/Throwable;)V
    //   493: goto -202 -> 291
    //   496: new 112	java/lang/String
    //   499: astore_1
    //   500: aload_1
    //   501: aload 8
    //   503: invokespecial 208	java/lang/String:<init>	(Ljava/lang/String;)V
    //   506: goto -76 -> 430
    // Local variable table:
    //   start	length	slot	name	signature
    //   0	509	0	this	1
    //   10	244	1	localObject1	Object
    //   265	6	1	localThrowable1	Throwable
    //   283	148	1	localObject2	Object
    //   437	53	1	localThrowable2	Throwable
    //   499	2	1	str	String
    //   18	471	2	localObject3	Object
    //   33	272	3	localObject4	Object
    //   44	3	4	bool1	boolean
    //   65	260	5	localrx	com.google.android.gms.b.rx
    //   91	303	6	locala	com.google.android.gms.a.a
    //   106	194	7	bool2	boolean
    //   132	370	8	localObject5	Object
    //   163	300	9	localObject6	Object
    //   176	17	10	localIterator	java.util.Iterator
    //   210	3	11	bool3	boolean
    //   220	10	12	localArrayList	java.util.ArrayList
    //   351	17	13	bool4	boolean
    //   416	3	14	i	int
    //   448	10	15	j	int
    // Exception table:
    //   from	to	target	type
    //   56	62	265	finally
    //   326	330	437	finally
    //   337	342	437	finally
    //   344	351	437	finally
    //   358	365	437	finally
    //   372	377	437	finally
    //   379	385	437	finally
    //   386	390	437	finally
    //   397	403	437	finally
    //   407	411	437	finally
    //   412	416	437	finally
    //   425	429	437	finally
    //   430	434	437	finally
    //   496	499	437	finally
    //   501	506	437	finally
  }
}


/* Location:              com/google/android/gms/ads/internal/q$1$1.class
 * Java compiler version: 5 (49.0)
 * JD-Core Version:       0.7.1
 */