package com.google.android.gms.ads.internal.purchase;

import android.app.Activity;
import android.content.ComponentName;
import android.content.Context;
import android.content.Intent;
import android.content.ServiceConnection;
import android.content.res.Configuration;
import android.content.res.Resources;
import android.os.RemoteException;
import com.google.android.gms.ads.internal.w;
import com.google.android.gms.b.pg;
import com.google.android.gms.b.pi.a;
import com.google.android.gms.b.tp;
import com.google.android.gms.b.tu;
import com.google.android.gms.common.a.a;

public final class e
  extends pi.a
  implements ServiceConnection
{
  h a;
  private final Activity b;
  private Context c;
  private pg d;
  private b e;
  private f f;
  private j g;
  private k h;
  private String i = null;
  
  public e(Activity paramActivity)
  {
    b = paramActivity;
    h localh = h.a(b.getApplicationContext());
    a = localh;
  }
  
  private void a(String paramString, boolean paramBoolean, int paramInt, Intent paramIntent)
  {
    j localj = g;
    if (localj != null)
    {
      localj = g;
      f localf = f;
      localj.a(paramString, paramBoolean, paramInt, paramIntent, localf);
    }
  }
  
  public final void a()
  {
    Object localObject1 = GInAppPurchaseManagerInfoParcel.a(b.getIntent());
    Object localObject2 = d;
    g = ((j)localObject2);
    localObject2 = a;
    h = ((k)localObject2);
    localObject2 = b;
    d = ((pg)localObject2);
    localObject2 = new com/google/android/gms/ads/internal/purchase/b;
    Context localContext = b.getApplicationContext();
    ((b)localObject2).<init>(localContext);
    e = ((b)localObject2);
    localObject1 = c;
    c = ((Context)localObject1);
    localObject1 = b.getResources().getConfiguration();
    int j = orientation;
    int k = 2;
    if (j == k)
    {
      localObject1 = b;
      localObject2 = w.g();
      k = ((tu)localObject2).a();
      ((Activity)localObject1).setRequestedOrientation(k);
    }
    for (;;)
    {
      localObject1 = new android/content/Intent;
      ((Intent)localObject1).<init>("com.android.vending.billing.InAppBillingService.BIND");
      ((Intent)localObject1).setPackage("com.android.vending");
      a.a();
      a.b(b, (Intent)localObject1, this, 1);
      return;
      localObject1 = b;
      localObject2 = w.g();
      k = ((tu)localObject2).b();
      ((Activity)localObject1).setRequestedOrientation(k);
    }
  }
  
  public final void a(int paramInt1, int paramInt2, Intent paramIntent)
  {
    int j = 1001;
    if (paramInt1 == j)
    {
      j = 0;
      Object localObject1 = null;
    }
    for (;;)
    {
      try
      {
        w.s();
        int k = i.a(paramIntent);
        int m = -1;
        if (paramInt2 == m)
        {
          w.s();
          if (k == 0)
          {
            localObject4 = h;
            localObject5 = i;
            boolean bool = ((k)localObject4).a((String)localObject5, paramIntent);
            if (bool) {
              j = 1;
            }
            localObject4 = d;
            ((pg)localObject4).b(k);
            Object localObject6 = b;
            ((Activity)localObject6).finish();
            localObject6 = d;
            localObject6 = ((pg)localObject6).a();
            a((String)localObject6, j, paramInt2, paramIntent);
            return;
          }
        }
      }
      catch (RemoteException localRemoteException)
      {
        Object localObject4;
        Object localObject5;
        Object localObject2 = "Fail to process purchase result.";
        tp.e((String)localObject2);
        localObject2 = b;
        ((Activity)localObject2).finish();
        i = null;
        continue;
      }
      finally
      {
        i = null;
      }
      localObject4 = a;
      localObject5 = f;
      ((h)localObject4).a((f)localObject5);
    }
  }
  
  public final void b()
  {
    a.a();
    a.a(b, this);
    e.a = null;
  }
  
  /* Error */
  public final void onServiceConnected(ComponentName paramComponentName, android.os.IBinder paramIBinder)
  {
    // Byte code:
    //   0: aload_0
    //   1: astore_3
    //   2: aload_0
    //   3: getfield 80	com/google/android/gms/ads/internal/purchase/e:e	Lcom/google/android/gms/ads/internal/purchase/b;
    //   6: astore 4
    //   8: aload_2
    //   9: astore_3
    //   10: aload 4
    //   12: aload_2
    //   13: invokevirtual 186	com/google/android/gms/ads/internal/purchase/b:a	(Landroid/os/IBinder;)V
    //   16: invokestatic 189	com/google/android/gms/ads/internal/w:e	()Lcom/google/android/gms/b/tt;
    //   19: pop
    //   20: invokestatic 193	com/google/android/gms/b/tt:b	()Ljava/lang/String;
    //   23: astore 4
    //   25: aload_0
    //   26: astore_3
    //   27: aload_0
    //   28: aload 4
    //   30: putfield 30	com/google/android/gms/ads/internal/purchase/e:i	Ljava/lang/String;
    //   33: aload_0
    //   34: getfield 80	com/google/android/gms/ads/internal/purchase/e:e	Lcom/google/android/gms/ads/internal/purchase/b;
    //   37: astore 4
    //   39: aload_0
    //   40: getfield 32	com/google/android/gms/ads/internal/purchase/e:b	Landroid/app/Activity;
    //   43: astore 5
    //   45: aload 5
    //   47: invokevirtual 196	android/app/Activity:getPackageName	()Ljava/lang/String;
    //   50: astore 5
    //   52: aload_0
    //   53: getfield 73	com/google/android/gms/ads/internal/purchase/e:d	Lcom/google/android/gms/b/pg;
    //   56: astore 6
    //   58: aload 6
    //   60: invokeinterface 163 1 0
    //   65: astore 6
    //   67: aload_0
    //   68: getfield 30	com/google/android/gms/ads/internal/purchase/e:i	Ljava/lang/String;
    //   71: astore 7
    //   73: aload 4
    //   75: aload 5
    //   77: aload 6
    //   79: aload 7
    //   81: invokevirtual 199	com/google/android/gms/ads/internal/purchase/b:a	(Ljava/lang/String;Ljava/lang/String;Ljava/lang/String;)Landroid/os/Bundle;
    //   84: astore 5
    //   86: ldc -55
    //   88: astore 4
    //   90: aload 5
    //   92: aload 4
    //   94: invokevirtual 207	android/os/Bundle:getParcelable	(Ljava/lang/String;)Landroid/os/Parcelable;
    //   97: astore 4
    //   99: aload 4
    //   101: astore_3
    //   102: aload 4
    //   104: checkcast 209	android/app/PendingIntent
    //   107: astore_3
    //   108: aload_3
    //   109: astore 8
    //   111: aload_3
    //   112: ifnonnull +80 -> 192
    //   115: invokestatic 143	com/google/android/gms/ads/internal/w:s	()Lcom/google/android/gms/ads/internal/purchase/i;
    //   118: pop
    //   119: aload 5
    //   121: invokestatic 212	com/google/android/gms/ads/internal/purchase/i:a	(Landroid/os/Bundle;)I
    //   124: istore 9
    //   126: aload_0
    //   127: astore_3
    //   128: aload_0
    //   129: getfield 73	com/google/android/gms/ads/internal/purchase/e:d	Lcom/google/android/gms/b/pg;
    //   132: astore 5
    //   134: aload 5
    //   136: iload 9
    //   138: invokeinterface 157 2 0
    //   143: aload_0
    //   144: getfield 73	com/google/android/gms/ads/internal/purchase/e:d	Lcom/google/android/gms/b/pg;
    //   147: astore 5
    //   149: aload 5
    //   151: invokeinterface 163 1 0
    //   156: astore 5
    //   158: iconst_0
    //   159: istore 10
    //   161: aconst_null
    //   162: astore 6
    //   164: iconst_0
    //   165: istore 11
    //   167: aconst_null
    //   168: astore 7
    //   170: aload_0
    //   171: aload 5
    //   173: iconst_0
    //   174: iload 9
    //   176: aconst_null
    //   177: invokespecial 166	com/google/android/gms/ads/internal/purchase/e:a	(Ljava/lang/String;ZILandroid/content/Intent;)V
    //   180: aload_0
    //   181: getfield 32	com/google/android/gms/ads/internal/purchase/e:b	Landroid/app/Activity;
    //   184: astore 4
    //   186: aload 4
    //   188: invokevirtual 160	android/app/Activity:finish	()V
    //   191: return
    //   192: new 214	com/google/android/gms/ads/internal/purchase/f
    //   195: astore 4
    //   197: aload_0
    //   198: astore_3
    //   199: aload_0
    //   200: getfield 73	com/google/android/gms/ads/internal/purchase/e:d	Lcom/google/android/gms/b/pg;
    //   203: astore 5
    //   205: aload 5
    //   207: invokeinterface 163 1 0
    //   212: astore 5
    //   214: aload_0
    //   215: getfield 30	com/google/android/gms/ads/internal/purchase/e:i	Ljava/lang/String;
    //   218: astore 6
    //   220: aload 4
    //   222: aload 5
    //   224: aload 6
    //   226: invokespecial 217	com/google/android/gms/ads/internal/purchase/f:<init>	(Ljava/lang/String;Ljava/lang/String;)V
    //   229: aload_0
    //   230: aload 4
    //   232: putfield 49	com/google/android/gms/ads/internal/purchase/e:f	Lcom/google/android/gms/ads/internal/purchase/f;
    //   235: aload_0
    //   236: getfield 45	com/google/android/gms/ads/internal/purchase/e:a	Lcom/google/android/gms/ads/internal/purchase/h;
    //   239: astore 12
    //   241: aload_0
    //   242: getfield 49	com/google/android/gms/ads/internal/purchase/e:f	Lcom/google/android/gms/ads/internal/purchase/f;
    //   245: astore 4
    //   247: aload 4
    //   249: ifnull +26 -> 275
    //   252: getstatic 218	com/google/android/gms/ads/internal/purchase/h:a	Ljava/lang/Object;
    //   255: astore 13
    //   257: aload 13
    //   259: monitorenter
    //   260: aload 12
    //   262: invokevirtual 221	com/google/android/gms/ads/internal/purchase/h:a	()Landroid/database/sqlite/SQLiteDatabase;
    //   265: astore 5
    //   267: aload 5
    //   269: ifnonnull +142 -> 411
    //   272: aload 13
    //   274: monitorexit
    //   275: aload_0
    //   276: astore_3
    //   277: aload_0
    //   278: getfield 32	com/google/android/gms/ads/internal/purchase/e:b	Landroid/app/Activity;
    //   281: astore 4
    //   283: aload 8
    //   285: invokevirtual 225	android/app/PendingIntent:getIntentSender	()Landroid/content/IntentSender;
    //   288: astore 5
    //   290: sipush 1001
    //   293: istore 10
    //   295: new 116	android/content/Intent
    //   298: astore 7
    //   300: aload 7
    //   302: invokespecial 226	android/content/Intent:<init>	()V
    //   305: iconst_0
    //   306: istore 14
    //   308: aconst_null
    //   309: astore 15
    //   311: iconst_0
    //   312: invokestatic 232	java/lang/Integer:valueOf	(I)Ljava/lang/Integer;
    //   315: astore 15
    //   317: aload 15
    //   319: invokevirtual 235	java/lang/Integer:intValue	()I
    //   322: istore 14
    //   324: iconst_0
    //   325: istore 16
    //   327: aconst_null
    //   328: astore 17
    //   330: iconst_0
    //   331: invokestatic 232	java/lang/Integer:valueOf	(I)Ljava/lang/Integer;
    //   334: astore 17
    //   336: aload 17
    //   338: invokevirtual 235	java/lang/Integer:intValue	()I
    //   341: istore 16
    //   343: iconst_0
    //   344: istore 18
    //   346: aconst_null
    //   347: astore 19
    //   349: iconst_0
    //   350: invokestatic 232	java/lang/Integer:valueOf	(I)Ljava/lang/Integer;
    //   353: astore 19
    //   355: aload 19
    //   357: invokevirtual 235	java/lang/Integer:intValue	()I
    //   360: istore 18
    //   362: aload 4
    //   364: aload 5
    //   366: iload 10
    //   368: aload 7
    //   370: iload 14
    //   372: iload 16
    //   374: iload 18
    //   376: invokevirtual 239	android/app/Activity:startIntentSenderForResult	(Landroid/content/IntentSender;ILandroid/content/Intent;III)V
    //   379: goto -188 -> 191
    //   382: astore 4
    //   384: ldc -15
    //   386: astore 5
    //   388: aload 5
    //   390: aload 4
    //   392: invokestatic 244	com/google/android/gms/b/tp:c	(Ljava/lang/String;Ljava/lang/Throwable;)V
    //   395: aload_0
    //   396: astore_3
    //   397: aload_0
    //   398: getfield 32	com/google/android/gms/ads/internal/purchase/e:b	Landroid/app/Activity;
    //   401: astore 4
    //   403: aload 4
    //   405: invokevirtual 160	android/app/Activity:finish	()V
    //   408: goto -217 -> 191
    //   411: new 246	android/content/ContentValues
    //   414: astore 6
    //   416: aload 6
    //   418: invokespecial 247	android/content/ContentValues:<init>	()V
    //   421: ldc -7
    //   423: astore 7
    //   425: aload 4
    //   427: getfield 251	com/google/android/gms/ads/internal/purchase/f:c	Ljava/lang/String;
    //   430: astore 15
    //   432: aload 6
    //   434: aload 7
    //   436: aload 15
    //   438: invokevirtual 254	android/content/ContentValues:put	(Ljava/lang/String;Ljava/lang/String;)V
    //   441: ldc_w 256
    //   444: astore 7
    //   446: aload 4
    //   448: getfield 258	com/google/android/gms/ads/internal/purchase/f:b	Ljava/lang/String;
    //   451: astore 15
    //   453: aload 6
    //   455: aload 7
    //   457: aload 15
    //   459: invokevirtual 254	android/content/ContentValues:put	(Ljava/lang/String;Ljava/lang/String;)V
    //   462: ldc_w 260
    //   465: astore 7
    //   467: invokestatic 266	android/os/SystemClock:elapsedRealtime	()J
    //   470: lstore 20
    //   472: lload 20
    //   474: invokestatic 271	java/lang/Long:valueOf	(J)Ljava/lang/Long;
    //   477: astore 15
    //   479: aload 6
    //   481: aload 7
    //   483: aload 15
    //   485: invokevirtual 274	android/content/ContentValues:put	(Ljava/lang/String;Ljava/lang/Long;)V
    //   488: ldc_w 276
    //   491: astore 7
    //   493: iconst_0
    //   494: istore 14
    //   496: aconst_null
    //   497: astore 15
    //   499: aload 5
    //   501: aload 7
    //   503: aconst_null
    //   504: aload 6
    //   506: invokevirtual 282	android/database/sqlite/SQLiteDatabase:insert	(Ljava/lang/String;Ljava/lang/String;Landroid/content/ContentValues;)J
    //   509: lstore 22
    //   511: aload 4
    //   513: lload 22
    //   515: putfield 285	com/google/android/gms/ads/internal/purchase/f:a	J
    //   518: aload 12
    //   520: invokevirtual 287	com/google/android/gms/ads/internal/purchase/h:c	()I
    //   523: i2l
    //   524: lstore 24
    //   526: ldc2_w 288
    //   529: lstore 22
    //   531: lload 24
    //   533: lload 22
    //   535: lcmp
    //   536: istore 9
    //   538: iload 9
    //   540: ifle +26 -> 566
    //   543: getstatic 218	com/google/android/gms/ads/internal/purchase/h:a	Ljava/lang/Object;
    //   546: astore 26
    //   548: aload 26
    //   550: monitorenter
    //   551: aload 12
    //   553: invokevirtual 221	com/google/android/gms/ads/internal/purchase/h:a	()Landroid/database/sqlite/SQLiteDatabase;
    //   556: astore 4
    //   558: aload 4
    //   560: ifnonnull +25 -> 585
    //   563: aload 26
    //   565: monitorexit
    //   566: aload 13
    //   568: monitorexit
    //   569: goto -294 -> 275
    //   572: astore 4
    //   574: aload 13
    //   576: monitorexit
    //   577: aload 4
    //   579: athrow
    //   580: astore 4
    //   582: goto -198 -> 384
    //   585: ldc_w 293
    //   588: astore 27
    //   590: ldc_w 276
    //   593: astore 5
    //   595: iconst_0
    //   596: istore 10
    //   598: aconst_null
    //   599: astore 6
    //   601: iconst_0
    //   602: istore 11
    //   604: aconst_null
    //   605: astore 7
    //   607: iconst_0
    //   608: istore 14
    //   610: aconst_null
    //   611: astore 15
    //   613: iconst_0
    //   614: istore 16
    //   616: aconst_null
    //   617: astore 17
    //   619: iconst_0
    //   620: istore 18
    //   622: aconst_null
    //   623: astore 19
    //   625: ldc_w 295
    //   628: astore 28
    //   630: aload 4
    //   632: aload 5
    //   634: aconst_null
    //   635: aconst_null
    //   636: aconst_null
    //   637: aconst_null
    //   638: aconst_null
    //   639: aload 27
    //   641: aload 28
    //   643: invokevirtual 299	android/database/sqlite/SQLiteDatabase:query	(Ljava/lang/String;[Ljava/lang/String;Ljava/lang/String;[Ljava/lang/String;Ljava/lang/String;Ljava/lang/String;Ljava/lang/String;Ljava/lang/String;)Landroid/database/Cursor;
    //   646: astore 5
    //   648: aload 5
    //   650: ifnull +31 -> 681
    //   653: aload 5
    //   655: invokeinterface 305 1 0
    //   660: istore 9
    //   662: iload 9
    //   664: ifeq +17 -> 681
    //   667: aload 5
    //   669: invokestatic 308	com/google/android/gms/ads/internal/purchase/h:a	(Landroid/database/Cursor;)Lcom/google/android/gms/ads/internal/purchase/f;
    //   672: astore 4
    //   674: aload 12
    //   676: aload 4
    //   678: invokevirtual 169	com/google/android/gms/ads/internal/purchase/h:a	(Lcom/google/android/gms/ads/internal/purchase/f;)V
    //   681: aload 5
    //   683: ifnull +10 -> 693
    //   686: aload 5
    //   688: invokeinterface 311 1 0
    //   693: aload 26
    //   695: monitorexit
    //   696: goto -130 -> 566
    //   699: astore 4
    //   701: aload 26
    //   703: monitorexit
    //   704: aload 4
    //   706: athrow
    //   707: astore 4
    //   709: aconst_null
    //   710: astore 5
    //   712: ldc_w 313
    //   715: astore 6
    //   717: aload 4
    //   719: invokevirtual 318	android/database/sqlite/SQLiteException:getMessage	()Ljava/lang/String;
    //   722: astore 4
    //   724: aload 4
    //   726: invokestatic 323	java/lang/String:valueOf	(Ljava/lang/Object;)Ljava/lang/String;
    //   729: astore 4
    //   731: aload 4
    //   733: invokevirtual 326	java/lang/String:length	()I
    //   736: istore 11
    //   738: iload 11
    //   740: ifeq +32 -> 772
    //   743: aload 6
    //   745: aload 4
    //   747: invokevirtual 330	java/lang/String:concat	(Ljava/lang/String;)Ljava/lang/String;
    //   750: astore 4
    //   752: aload 4
    //   754: invokestatic 175	com/google/android/gms/b/tp:e	(Ljava/lang/String;)V
    //   757: aload 5
    //   759: ifnull -66 -> 693
    //   762: aload 5
    //   764: invokeinterface 311 1 0
    //   769: goto -76 -> 693
    //   772: new 320	java/lang/String
    //   775: astore 4
    //   777: aload 4
    //   779: aload 6
    //   781: invokespecial 331	java/lang/String:<init>	(Ljava/lang/String;)V
    //   784: goto -32 -> 752
    //   787: astore 4
    //   789: aload 5
    //   791: ifnull +10 -> 801
    //   794: aload 5
    //   796: invokeinterface 311 1 0
    //   801: aload 4
    //   803: athrow
    //   804: astore 4
    //   806: aconst_null
    //   807: astore 5
    //   809: goto -20 -> 789
    //   812: astore 4
    //   814: goto -102 -> 712
    // Local variable table:
    //   start	length	slot	name	signature
    //   0	817	0	this	e
    //   0	817	1	paramComponentName	ComponentName
    //   0	817	2	paramIBinder	android.os.IBinder
    //   1	396	3	localObject1	Object
    //   6	357	4	localObject2	Object
    //   382	9	4	localRemoteException	RemoteException
    //   401	158	4	localObject3	Object
    //   572	6	4	localObject4	Object
    //   580	51	4	localSendIntentException	android.content.IntentSender.SendIntentException
    //   672	5	4	localf	f
    //   699	6	4	localObject5	Object
    //   707	11	4	localSQLiteException1	android.database.sqlite.SQLiteException
    //   722	56	4	str1	String
    //   787	15	4	localObject6	Object
    //   804	1	4	localObject7	Object
    //   812	1	4	localSQLiteException2	android.database.sqlite.SQLiteException
    //   43	765	5	localObject8	Object
    //   56	724	6	localObject9	Object
    //   71	535	7	localObject10	Object
    //   109	175	8	localObject11	Object
    //   124	51	9	j	int
    //   536	127	9	bool	boolean
    //   159	438	10	k	int
    //   165	574	11	m	int
    //   239	436	12	localh	h
    //   255	320	13	localObject12	Object
    //   306	303	14	n	int
    //   309	303	15	localObject13	Object
    //   325	290	16	i1	int
    //   328	290	17	localInteger1	Integer
    //   344	277	18	i2	int
    //   347	277	19	localInteger2	Integer
    //   470	3	20	l1	long
    //   509	25	22	l2	long
    //   524	8	24	l3	long
    //   546	156	26	localObject14	Object
    //   588	52	27	str2	String
    //   628	14	28	str3	String
    // Exception table:
    //   from	to	target	type
    //   16	20	382	android/os/RemoteException
    //   20	23	382	android/os/RemoteException
    //   28	33	382	android/os/RemoteException
    //   33	37	382	android/os/RemoteException
    //   39	43	382	android/os/RemoteException
    //   45	50	382	android/os/RemoteException
    //   52	56	382	android/os/RemoteException
    //   58	65	382	android/os/RemoteException
    //   67	71	382	android/os/RemoteException
    //   79	84	382	android/os/RemoteException
    //   92	97	382	android/os/RemoteException
    //   102	107	382	android/os/RemoteException
    //   115	119	382	android/os/RemoteException
    //   119	124	382	android/os/RemoteException
    //   128	132	382	android/os/RemoteException
    //   136	143	382	android/os/RemoteException
    //   143	147	382	android/os/RemoteException
    //   149	156	382	android/os/RemoteException
    //   176	180	382	android/os/RemoteException
    //   180	184	382	android/os/RemoteException
    //   186	191	382	android/os/RemoteException
    //   192	195	382	android/os/RemoteException
    //   199	203	382	android/os/RemoteException
    //   205	212	382	android/os/RemoteException
    //   214	218	382	android/os/RemoteException
    //   224	229	382	android/os/RemoteException
    //   230	235	382	android/os/RemoteException
    //   235	239	382	android/os/RemoteException
    //   241	245	382	android/os/RemoteException
    //   252	255	382	android/os/RemoteException
    //   257	260	382	android/os/RemoteException
    //   277	281	382	android/os/RemoteException
    //   283	288	382	android/os/RemoteException
    //   295	298	382	android/os/RemoteException
    //   300	305	382	android/os/RemoteException
    //   311	315	382	android/os/RemoteException
    //   317	322	382	android/os/RemoteException
    //   330	334	382	android/os/RemoteException
    //   336	341	382	android/os/RemoteException
    //   349	353	382	android/os/RemoteException
    //   355	360	382	android/os/RemoteException
    //   374	379	382	android/os/RemoteException
    //   577	580	382	android/os/RemoteException
    //   260	265	572	finally
    //   272	275	572	finally
    //   411	414	572	finally
    //   416	421	572	finally
    //   425	430	572	finally
    //   436	441	572	finally
    //   446	451	572	finally
    //   457	462	572	finally
    //   467	470	572	finally
    //   472	477	572	finally
    //   483	488	572	finally
    //   504	509	572	finally
    //   513	518	572	finally
    //   518	523	572	finally
    //   543	546	572	finally
    //   548	551	572	finally
    //   566	569	572	finally
    //   574	577	572	finally
    //   704	707	572	finally
    //   16	20	580	android/content/IntentSender$SendIntentException
    //   20	23	580	android/content/IntentSender$SendIntentException
    //   28	33	580	android/content/IntentSender$SendIntentException
    //   33	37	580	android/content/IntentSender$SendIntentException
    //   39	43	580	android/content/IntentSender$SendIntentException
    //   45	50	580	android/content/IntentSender$SendIntentException
    //   52	56	580	android/content/IntentSender$SendIntentException
    //   58	65	580	android/content/IntentSender$SendIntentException
    //   67	71	580	android/content/IntentSender$SendIntentException
    //   79	84	580	android/content/IntentSender$SendIntentException
    //   92	97	580	android/content/IntentSender$SendIntentException
    //   102	107	580	android/content/IntentSender$SendIntentException
    //   115	119	580	android/content/IntentSender$SendIntentException
    //   119	124	580	android/content/IntentSender$SendIntentException
    //   128	132	580	android/content/IntentSender$SendIntentException
    //   136	143	580	android/content/IntentSender$SendIntentException
    //   143	147	580	android/content/IntentSender$SendIntentException
    //   149	156	580	android/content/IntentSender$SendIntentException
    //   176	180	580	android/content/IntentSender$SendIntentException
    //   180	184	580	android/content/IntentSender$SendIntentException
    //   186	191	580	android/content/IntentSender$SendIntentException
    //   192	195	580	android/content/IntentSender$SendIntentException
    //   199	203	580	android/content/IntentSender$SendIntentException
    //   205	212	580	android/content/IntentSender$SendIntentException
    //   214	218	580	android/content/IntentSender$SendIntentException
    //   224	229	580	android/content/IntentSender$SendIntentException
    //   230	235	580	android/content/IntentSender$SendIntentException
    //   235	239	580	android/content/IntentSender$SendIntentException
    //   241	245	580	android/content/IntentSender$SendIntentException
    //   252	255	580	android/content/IntentSender$SendIntentException
    //   257	260	580	android/content/IntentSender$SendIntentException
    //   277	281	580	android/content/IntentSender$SendIntentException
    //   283	288	580	android/content/IntentSender$SendIntentException
    //   295	298	580	android/content/IntentSender$SendIntentException
    //   300	305	580	android/content/IntentSender$SendIntentException
    //   311	315	580	android/content/IntentSender$SendIntentException
    //   317	322	580	android/content/IntentSender$SendIntentException
    //   330	334	580	android/content/IntentSender$SendIntentException
    //   336	341	580	android/content/IntentSender$SendIntentException
    //   349	353	580	android/content/IntentSender$SendIntentException
    //   355	360	580	android/content/IntentSender$SendIntentException
    //   374	379	580	android/content/IntentSender$SendIntentException
    //   577	580	580	android/content/IntentSender$SendIntentException
    //   551	556	699	finally
    //   563	566	699	finally
    //   686	693	699	finally
    //   693	696	699	finally
    //   701	704	699	finally
    //   762	769	699	finally
    //   794	801	699	finally
    //   801	804	699	finally
    //   641	646	707	android/database/sqlite/SQLiteException
    //   653	660	787	finally
    //   667	672	787	finally
    //   676	681	787	finally
    //   717	722	787	finally
    //   724	729	787	finally
    //   731	736	787	finally
    //   745	750	787	finally
    //   752	757	787	finally
    //   772	775	787	finally
    //   779	784	787	finally
    //   641	646	804	finally
    //   653	660	812	android/database/sqlite/SQLiteException
    //   667	672	812	android/database/sqlite/SQLiteException
    //   676	681	812	android/database/sqlite/SQLiteException
  }
  
  public final void onServiceDisconnected(ComponentName paramComponentName)
  {
    tp.d("In-app billing service disconnected.");
    e.a = null;
  }
}


/* Location:              com/google/android/gms/ads/internal/purchase/e.class
 * Java compiler version: 5 (49.0)
 * JD-Core Version:       0.7.1
 */